Workbook

Sheet Leeme
B1: Cobertura TIMSS de la malla de Ciencia y Tecnología — cómo se construyó y cómo leerla
B2: Versión 1 · 1 de octubre de 2026 · Elaborado con Claude (Cowork) a partir de las mallas compartidas por el equipo de Ciencias (MINED).
B4: Qué responde este libro
B5: 1. Balance: ¿el reparto de temas entre Vida / Física / Química / Tierra se parece al peso que TIMSS da a cada dominio? ¿Cuántos temas faltan o sobran para llegar a la meta?
B6: 2. Amplitud: ¿qué objetivos de contenido de TIMSS aparecen en la malla, en qué grado, con cuántos temas, y cuáles no aparecen?
B7: 3. Profundidad cognitiva: ¿la proporción Conocer / Aplicar / Razonar se parece a la de TIMSS?
B9: Proceso (de dónde salen los números)
B10: Paso 1 · Extracción. Se leyeron las 11 mallas (2.° a 9.° y Física, Química, Biología de 10.° y 11.°). Cada fila con «Procedimental» es un TEMA: 1.260 en total. Se conservan archivo, hoja y fila de origen (hoja Temas_TIMSS, columnas D-F) para poder volver a la malla.
B11: Paso 2 · Catálogo de referencia. Se armó la lista de objetivos de contenido de TIMSS 2023 (4.° grado: 32 objetivos; 8.° grado: 46) y de TIMSS Advanced 2015 Física (23), con su dominio y el % que TIMSS asigna a cada dominio (hoja Catalogo_TIMSS, en azul = valores tomados del marco).
B12: Paso 3 · Clasificación. Cada tema de 2.° a 9.° y de Física 10.°–11.° (889 temas) se asignó a UN objetivo principal y, si aplica, uno secundario, leyendo procedimental, contenido, indicador y evidencia. Lo hicieron agentes de IA con instrucciones fijas, tema por tema, dejando confianza (alta/media/baja) y una justificación corta. Los temas sin contenido TIMSS (medición general, método científico, tecnología/diseño, gestión de riesgos, electrónica digital, mecánica de fluidos en Bachillerato, etc.) se marcan «FUERA».
B13: Paso 4 · Reglas de grado. 2.°–4.° se comparan con TIMSS 4.°; 5.°–9.° con TIMSS 8.° (9.° solo como referencia, porque TIMSS 8.° evalúa hasta 8.°); Física 10.°–11.° con TIMSS Advanced. Química y Biología de Bachillerato no tienen marco TIMSS de contenido: solo entran en el análisis cognitivo.
B14: Paso 5 · Cálculo (todo con fórmulas). % actual = temas del dominio ÷ temas evaluables (sin FUERA). Temas esperados = meta × evaluables. Brecha = esperados − actuales (+ faltan, − sobran). «Temas a agregar sin quitar»: se busca el menor total que permite cumplir todas las metas sumando temas (lo fija el dominio más sobrerrepresentado: total = máx(actual ÷ meta)), y a cada dominio se le suma meta × total − actual, redondeado hacia arriba.
... B33: • 1.° grado no tiene malla, así que no entra en el ciclo 2.°–4.°.

Sheet Resumen
A1: Cobertura de la malla de Ciencias de El Salvador frente a TIMSS — resumen por grado
A2: Todo es fórmula sobre Temas_TIMSS. Balance = reparto de temas por dominio vs. metas TIMSS. Amplitud = objetivos TIMSS que aparecen. Profundidad cognitiva = Conocer/Aplicar/Razonar. Ver «Leeme» para el proceso completo.
A4: Grupo | B4: Marco de referencia | C4: Temas totales | D4: Temas fuera del marco | E4: % fuera del marco | F4: Dominio con mayor FALTANTE | G4: Faltan (temas) | H4: Dominio más SOBRErrepresentado | I4: Sobran (temas) | J4: Temas a agregar para cumplir todas las metas sin quitar | K4: Dominios en meta (±tolerancia) | L4: % Razonar actual | M4: % Razonar meta
A5: 2° | B5: TIMSS 2023 4.° | C5: =COUNTIFS(Temas_TIMSS!$V$5:$V$1264,$A5) -> 70 | D5: =Balance_grado!N6 -> 13 | E5: =IF(C5=0,0,D5/C5) -> 0.18571429 | F5: =INDEX(Balance_grado!$C$6:$C$8,MATCH(MAX(Balance_grado!$I$6:$I$8),Balance_grado!$I$6:$I$8,0)) -> Ciencias de la vida | G5: =ROUND(MAX(Balance_grado!$I$6:$I$8),0) -> 2 | H5: =INDEX(Balance_grado!$C$6:$C$8,MATCH(MIN(Balance_grado!$I$6:$I$8),Balance_grado!$I$6:$I$8,0)) -> Ciencias físicas | I5: =ROUND(-MIN(Balance_grado!$I$6:$I$8),0) -> 3 | J5: =Balance_grado!M9 -> 10 | K5: =COUNTIF(Balance_grado!$K$6:$K$8,"En meta")&" de "&ROWS(Balance_grado!$K$6:$K$8) -> 2 de 3 | L5: =Cognitivo_grado!I5 -> 0.27142857 | M5: =Cognitivo_grado!L5 -> 0.2
A6: 3° | B6: TIMSS 2023 4.° | C6: =COUNTIFS(Temas_TIMSS!$V$5:$V$1264,$A6) -> 66 | D6: =Balance_grado!N11 -> 9 | E6: =IF(C6=0,0,D6/C6) -> 0.13636364 | F6: =INDEX(Balance_grado!$C$11:$C$13,MATCH(MAX(Balance_grado!$I$11:$I$13),Balance_grado!$I$11:$I$13,0)) -> Ciencias físicas | G6: =ROUND(MAX(Balance_grado!$I$11:$I$13),0) -> 3 | H6: =INDEX(Balance_grado!$C$11:$C$13,MATCH(MIN(Balance_grado!$I$11:$I$13),Balance_grado!$I$11:$I$13,0)) -> Ciencias de la vida | I6: =ROUND(-MIN(Balance_grado!$I$11:$I$13),0) -> 5 | J6: =Balance_grado!M14 -> 13 | K6: =COUNTIF(Balance_grado!$K$11:$K$13,"En meta")&" de "&ROWS(Balance_grado!$K$11:$K$13) -> 1 de 3 | L6: =Cognitivo_grado!I6 -> 0.26515152 | M6: =Cognitivo_grado!L6 -> 0.2
A7: 4° | B7: TIMSS 2023 4.° | C7: =COUNTIFS(Temas_TIMSS!$V$5:$V$1264,$A7) -> 72 | D7: =Balance_grado!N16 -> 8 | E7: =IF(C7=0,0,D7/C7) -> 0.11111111 | F7: =INDEX(Balance_grado!$C$16:$C$18,MATCH(MAX(Balance_grado!$I$16:$I$18),Balance_grado!$I$16:$I$18,0)) -> Ciencias físicas | G7: =ROUND(MAX(Balance_grado!$I$16:$I$18),0) -> 13 | H7: =INDEX(Balance_grado!$C$16:$C$18,MATCH(MIN(Balance_grado!$I$16:$I$18),Balance_grado!$I$16:$I$18,0)) -> Ciencias de la vida | I7: =ROUND(-MIN(Balance_grado!$I$16:$I$18),0) -> 8 | J7: =Balance_grado!M19 -> 27 | K7: =COUNTIF(Balance_grado!$K$16:$K$18,"En meta")&" de "&ROWS(Balance_grado!$K$16:$K$18) -> 0 de 3 | L7: =Cognitivo_grado!I7 -> 0.20138889 | M7: =Cognitivo_grado!L7 -> 0.2
A8: 5° | B8: TIMSS 2023 8.° | C8: =COUNTIFS(Temas_TIMSS!$V$5:$V$1264,$A8) -> 72 | D8: =Balance_grado!N21 -> 14 | E8: =IF(C8=0,0,D8/C8) -> 0.19444444 | F8: =INDEX(Balance_grado!$C$21:$C$24,MATCH(MAX(Balance_grado!$I$21:$I$24),Balance_grado!$I$21:$I$24,0)) -> Biología | G8: =ROUND(MAX(Balance_grado!$I$21:$I$24),0) -> 19 | H8: =INDEX(Balance_grado!$C$21:$C$24,MATCH(MIN(Balance_grado!$I$21:$I$24),Balance_grado!$I$21:$I$24,0)) -> Ciencias de la Tierra | I8: =ROUND(-MIN(Balance_grado!$I$21:$I$24),0) -> 12 | J8: =Balance_grado!M25 -> 62 | K8: =COUNTIF(Balance_grado!$K$21:$K$24,"En meta")&" de "&ROWS(Balance_grado!$K$21:$K$24) -> 1 de 4 | L8: =Cognitivo_grado!I8 -> 0.24305556 | M8: =Cognitivo_grado!L8 -> 0.3
A9: 6° | B9: TIMSS 2023 8.° | C9: =COUNTIFS(Temas_TIMSS!$V$5:$V$1264,$A9) -> 68 | D9: =Balance_grado!N27 -> 0 | E9: =IF(C9=0,0,D9/C9) -> 0 | F9: =INDEX(Balance_grado!$C$27:$C$30,MATCH(MAX(Balance_grado!$I$27:$I$30),Balance_grado!$I$27:$I$30,0)) -> Ciencias de la Tierra | G9: =ROUND(MAX(Balance_grado!$I$27:$I$30),0) -> 14 | H9: =INDEX(Balance_grado!$C$27:$C$30,MATCH(MIN(Balance_grado!$I$27:$I$30),Balance_grado!$I$27:$I$30,0)) -> Biología | I9: =ROUND(-MIN(Balance_grado!$I$27:$I$30),0) -> 10 | J9: =Balance_grado!M31 -> 37 | K9: =COUNTIF(Balance_grado!$K$27:$K$30,"En meta")&" de "&ROWS(Balance_grado!$K$27:$K$30) -> 0 de 4 | L9: =Cognitivo_grado!I9 -> 0.19117647 | M9: =Cognitivo_grado!L9 -> 0.3
A10: 7° | B10: TIMSS 2023 8.° | C10: =COUNTIFS(Temas_TIMSS!$V$5:$V$1264,$A10) -> 91 | D10: =Balance_grado!N33 -> 6 | E10: =IF(C10=0,0,D10/C10) -> 0.065934066 | F10: =INDEX(Balance_grado!$C$33:$C$36,MATCH(MAX(Balance_grado!$I$33:$I$36),Balance_grado!$I$33:$I$36,0)) -> Física | G10: =ROUND(MAX(Balance_grado!$I$33:$I$36),0) -> 18 | H10: =INDEX(Balance_grado!$C$33:$C$36,MATCH(MIN(Balance_grado!$I$33:$I$36),Balance_grado!$I$33:$I$36,0)) -> Biología | I10: =ROUND(-MIN(Balance_grado!$I$33:$I$36),0) -> 18 | J10: =Balance_grado!M37 -> 54 | K10: =COUNTIF(Balance_grado!$K$33:$K$36,"En meta")&" de "&ROWS(Balance_grado!$K$33:$K$36) -> 0 de 4 | L10: =Cognitivo_grado!I10 -> 0.28571429 | M10: =Cognitivo_grado!L10 -> 0.3
A11: 8° | B11: TIMSS 2023 8.° | C11: =COUNTIFS(Temas_TIMSS!$V$5:$V$1264,$A11) -> 93 | D11: =Balance_grado!N39 -> 2 | E11: =IF(C11=0,0,D11/C11) -> 0.021505376 | F11: =INDEX(Balance_grado!$C$39:$C$42,MATCH(MAX(Balance_grado!$I$39:$I$42),Balance_grado!$I$39:$I$42,0)) -> Ciencias de la Tierra | G11: =ROUND(MAX(Balance_grado!$I$39:$I$42),0) -> 14 | H11: =INDEX(Balance_grado!$C$39:$C$42,MATCH(MIN(Balance_grado!$I$39:$I$42),Balance_grado!$I$39:$I$42,0)) -> Física | I11: =ROUND(-MIN(Balance_grado!$I$39:$I$42),0) -> 12 | J11: =Balance_grado!M43 -> 49 | K11: =COUNTIF(Balance_grado!$K$39:$K$42,"En meta")&" de "&ROWS(Balance_grado!$K$39:$K$42) -> 1 de 4 | L11: =Cognitivo_grado!I11 -> 0.20967742 | M11: =Cognitivo_grado!L11 -> 0.3
A12: 9° | B12: TIMSS 2023 8.° | C12: =COUNTIFS(Temas_TIMSS!$V$5:$V$1264,$A12) -> 90 | D12: =Balance_grado!N45 -> 8 | E12: =IF(C12=0,0,D12/C12) -> 0.088888889 | F12: =INDEX(Balance_grado!$C$45:$C$48,MATCH(MAX(Balance_grado!$I$45:$I$48),Balance_grado!$I$45:$I$48,0)) -> Biología | G12: =ROUND(MAX(Balance_grado!$I$45:$I$48),0) -> 25 | H12: =INDEX(Balance_grado!$C$45:$C$48,MATCH(MIN(Balance_grado!$I$45:$I$48),Balance_grado!$I$45:$I$48,0)) -> Física | I12: =ROUND(-MIN(Balance_grado!$I$45:$I$48),0) -> 18 | J12: =Balance_grado!M49 -> 72 | K12: =COUNTIF(Balance_grado!$K$45:$K$48,"En meta")&" de "&ROWS(Balance_grado!$K$45:$K$48) -> 2 de 4 | L12: =Cognitivo_grado!I12 -> 0.17777778 | M12: =Cognitivo_grado!L12 -> 0.3
A13: Física 10° | B13: TIMSS Advanced 2015 Física | C13: =COUNTIFS(Temas_TIMSS!$V$5:$V$1264,$A13) -> 121 | D13: =Balance_grado!N51 -> 41 | E13: =IF(C13=0,0,D13/C13) -> 0.33884298 | F13: =INDEX(Balance_grado!$C$51:$C$53,MATCH(MAX(Balance_grado!$I$51:$I$53),Balance_grado!$I$51:$I$53,0)) -> Electricidad y magnetismo | G13: =ROUND(MAX(Balance_grado!$I$51:$I$53),0) -> 20 | H13: =INDEX(Balance_grado!$C$51:$C$53,MATCH(MIN(Balance_grado!$I$51:$I$53),Balance_grado!$I$51:$I$53,0)) -> Mecánica y termodinámica | I13: =ROUND(-MIN(Balance_grado!$I$51:$I$53),0) -> 35 | J13: =Balance_grado!M54 -> 88 | K13: =COUNTIF(Balance_grado!$K$51:$K$53,"En meta")&" de "&ROWS(Balance_grado!$K$51:$K$53) -> 0 de 3 | L13: =Cognitivo_grado!I13 -> 0.48071625 | M13: =Cognitivo_grado!L13 -> 0.3
A14: Física 11° | B14: TIMSS Advanced 2015 Física | C14: =COUNTIFS(Temas_TIMSS!$V$5:$V$1264,$A14) -> 146 | D14: =Balance_grado!N56 -> 27 | E14: =IF(C14=0,0,D14/C14) -> 0.18493151 | F14: =INDEX(Balance_grado!$C$56:$C$58,MATCH(MAX(Balance_grado!$I$56:$I$58),Balance_grado!$I$56:$I$58,0)) -> Mecánica y termodinámica | G14: =ROUND(MAX(Balance_grado!$I$56:$I$58),0) -> 44 | H14: =INDEX(Balance_grado!$C$56:$C$58,MATCH(MIN(Balance_grado!$I$56:$I$58),Balance_grado!$I$56:$I$58,0)) -> Ondas y física atómica/nuclear | I14: =ROUND(-MIN(Balance_grado!$I$56:$I$58),0) -> 30 | J14: =Balance_grado!M59 -> 88 | K14: =COUNTIF(Balance_grado!$K$56:$K$58,"En meta")&" de "&ROWS(Balance_grado!$K$56:$K$58) -> 0 de 3 | L14: =Cognitivo_grado!I14 -> 0.46575342 | M14: =Cognitivo_grado!L14 -> 0.3
A16: Por ciclo (comparación acumulada)
A17: Ciclo | B17: Marco de referencia | C17: Temas evaluables | D17: Dominio con mayor FALTANTE | E17: Faltan (temas) | F17: Dominio más SOBRErrepresentado | G17: Sobran (temas) | H17: Temas a agregar sin quitar | I17: Dominios en meta | J17: Objetivos TIMSS del marco | K17: Objetivos cubiertos | L17: % amplitud | M17: Objetivos no cubiertos
A18: Ciclo 2°–4° | B18: TIMSS 2023 4.° | C18: =Balance_ciclo!E6 -> 178 | D18: =INDEX(Balance_ciclo!$C$6:$C$8,MATCH(MAX(Balance_ciclo!$I$6:$I$8),Balance_ciclo!$I$6:$I$8,0)) -> Ciencias físicas | E18: =ROUND(MAX(Balance_ciclo!$I$6:$I$8),0) -> 13 | F18: =INDEX(Balance_ciclo!$C$6:$C$8,MATCH(MIN(Balance_ciclo!$I$6:$I$8),Balance_ciclo!$I$6:$I$8,0)) -> Ciencias de la vida | G18: =ROUND(-MIN(Balance_ciclo!$I$6:$I$8),0) -> 12 | H18: =Balance_ciclo!M9 -> 27 | I18: =COUNTIF(Balance_ciclo!$K$6:$K$8,"En meta")&" de "&ROWS(Balance_ciclo!$K$6:$K$8) -> 1 de 3 | J18: =Cobertura_objetivos!C113 -> 32 | K18: =Cobertura_objetivos!D113 -> 31 | L18: =Cobertura_objetivos!E113 -> 0.96875 | M18: =Cobertura_objetivos!F113 -> 1
A19: Ciclo 5°–8° | B19: TIMSS 2023 8.° | C19: =Balance_ciclo!E11 -> 302 | D19: =INDEX(Balance_ciclo!$C$11:$C$14,MATCH(MAX(Balance_ciclo!$I$11:$I$14),Balance_ciclo!$I$11:$I$14,0)) -> Ciencias de la Tierra | E19: =ROUND(MAX(Balance_ciclo!$I$11:$I$14),0) -> 6 | F19: =INDEX(Balance_ciclo!$C$11:$C$14,MATCH(MIN(Balance_ciclo!$I$11:$I$14),Balance_ciclo!$I$11:$I$14,0)) -> Biología | G19: =ROUND(-MIN(Balance_ciclo!$I$11:$I$14),0) -> 5 | H19: =Balance_ciclo!M15 -> 17 | I19: =COUNTIF(Balance_ciclo!$K$11:$K$14,"En meta")&" de "&ROWS(Balance_ciclo!$K$11:$K$14) -> 4 de 4 | J19: =Cobertura_objetivos!C118 -> 46 | K19: =Cobertura_objetivos!D118 -> 43 | L19: =Cobertura_objetivos!E118 -> 0.93478261 | M19: =Cobertura_objetivos!F118 -> 3
A20: 9° | B20: TIMSS 2023 8.° | C20: =Balance_ciclo!E17 -> 82 | D20: =INDEX(Balance_ciclo!$C$17:$C$20,MATCH(MAX(Balance_ciclo!$I$17:$I$20),Balance_ciclo!$I$17:$I$20,0)) -> Biología | E20: =ROUND(MAX(Balance_ciclo!$I$17:$I$20),0) -> 25 | F20: =INDEX(Balance_ciclo!$C$17:$C$20,MATCH(MIN(Balance_ciclo!$I$17:$I$20),Balance_ciclo!$I$17:$I$20,0)) -> Física | G20: =ROUND(-MIN(Balance_ciclo!$I$17:$I$20),0) -> 18 | H20: =Balance_ciclo!M21 -> 72 | I20: =COUNTIF(Balance_ciclo!$K$17:$K$20,"En meta")&" de "&ROWS(Balance_ciclo!$K$17:$K$20) -> 2 de 4 | J20: — | K20: — | L20: — | M20: —
A21: Física 10°–11° | B21: TIMSS Advanced 2015 Física | C21: =Balance_ciclo!E23 -> 199 | D21: =INDEX(Balance_ciclo!$C$23:$C$25,MATCH(MAX(Balance_ciclo!$I$23:$I$25),Balance_ciclo!$I$23:$I$25,0)) -> Mecánica y termodinámica | E21: =ROUND(MAX(Balance_ciclo!$I$23:$I$25),0) -> 9 | F21: =INDEX(Balance_ciclo!$C$23:$C$25,MATCH(MIN(Balance_ciclo!$I$23:$I$25),Balance_ciclo!$I$23:$I$25,0)) -> Ondas y física atómica/nuclear | G21: =ROUND(-MIN(Balance_ciclo!$I$23:$I$25),0) -> 15 | H21: =Balance_ciclo!M26 -> 45 | I21: =COUNTIF(Balance_ciclo!$K$23:$K$25,"En meta")&" de "&ROWS(Balance_ciclo!$K$23:$K$25) -> 2 de 3 | J21: =Cobertura_objetivos!C122 -> 23 | K21: =Cobertura_objetivos!D122 -> 23 | L21: =Cobertura_objetivos!E122 -> 1 | M21: =Cobertura_objetivos!F122 -> 0

Sheet Balance_ciclo
A1: Balance de contenidos por ciclo (comparación acumulada, la más fiel a TIMSS)
A2: Tolerancia para considerar «en meta» (± puntos porcentuales): | H2: 0.05
A3: TIMSS 4.° evalúa lo aprendido hasta 4.° grado → se compara con el acumulado de 2.° a 4.° (1.° grado no tiene malla). TIMSS 8.° evalúa lo aprendido hasta 8.° → acumulado de 5.° a 8.°. 9.° se muestra contra TIMSS 8.° solo como referencia. Física de Bachillerato se compara con TIMSS Advanced 2015 (Física). Química y Biología de Bachillerato no tienen marco TIMSS de contenido.
A5: Grupo | B5: Marco de referencia | C5: Dominio | D5: Temas actuales en el dominio | E5: Temas evaluables del grupo (sin «fuera») | F5: % actual | G5: Meta TIMSS (%) | H5: Temas esperados según meta | I5: Brecha (temas): + faltan / − sobran | J5: Brecha (pp) | K5: Estado | L5: Escala para cumplir sin quitar temas (total evaluables) | M5: Temas a AGREGAR para llegar a la meta sin quitar | N5: Temas «fuera del marco» del grupo
A6: Ciclo 2°–4° | B6: TIMSS 2023 4.° | C6: Ciencias de la vida | D6: =COUNTIFS(Temas_TIMSS!$W$5:$W$1264,$A6,Temas_TIMSS!$M$5:$M$1264,$C6) -> 92 | E6: =COUNTIFS(Temas_TIMSS!$W$5:$W$1264,$A6)-COUNTIFS(Temas_TIMSS!$W$5:$W$1264,$A6,Temas_TIMSS!$K$5:$K$1264,"FUERA")-COUNTIFS(Temas_TIMSS!$W$5:$W$1264,$A6,Temas_TIMSS!$K$5:$K$1264,"PENDIENTE") -> 178 | F6: =IF(E6=0,0,D6/E6) -> 0.51685393 | G6: 0.45 | H6: =G6*E6 -> 80.1 | I6: =H6-D6 -> -11.9 | J6: =(G6-F6)*100 -> -6.6853933 | K6: =IF(ABS(G6-F6)<=$H$2,"En meta",IF(I6>0,"Faltan "&ROUND(I6,0)&" temas","Sobran "&ROUND(-I6,0)&" temas")) -> Sobran 12 temas | L6: =MAX(D6/G6,D7/G7,D8/G8) -> 204.44444 | M6: =MAX(0,ROUNDUP(G6*L6-D6,0)) -> 0 | N6: =COUNTIFS(Temas_TIMSS!$W$5:$W$1264,$A6,Temas_TIMSS!$K$5:$K$1264,"FUERA") -> 30
A7: Ciclo 2°–4° | B7: TIMSS 2023 4.° | C7: Ciencias físicas | D7: =COUNTIFS(Temas_TIMSS!$W$5:$W$1264,$A7,Temas_TIMSS!$M$5:$M$1264,$C7) -> 49 | E7: =COUNTIFS(Temas_TIMSS!$W$5:$W$1264,$A7)-COUNTIFS(Temas_TIMSS!$W$5:$W$1264,$A7,Temas_TIMSS!$K$5:$K$1264,"FUERA")-COUNTIFS(Temas_TIMSS!$W$5:$W$1264,$A7,Temas_TIMSS!$K$5:$K$1264,"PENDIENTE") -> 178 | F7: =IF(E7=0,0,D7/E7) -> 0.2752809 | G7: 0.35 | H7: =G7*E7 -> 62.3 | I7: =H7-D7 -> 13.3 | J7: =(G7-F7)*100 -> 7.4719101 | K7: =IF(ABS(G7-F7)<=$H$2,"En meta",IF(I7>0,"Faltan "&ROUND(I7,0)&" temas","Sobran "&ROUND(-I7,0)&" temas")) -> Faltan 13 temas | L7: =MAX(D6/G6,D7/G7,D8/G8) -> 204.44444 | M7: =MAX(0,ROUNDUP(G7*L7-D7,0)) -> 23 | N7: =COUNTIFS(Temas_TIMSS!$W$5:$W$1264,$A7,Temas_TIMSS!$K$5:$K$1264,"FUERA") -> 30
A8: Ciclo 2°–4° | B8: TIMSS 2023 4.° | C8: Ciencias de la Tierra | D8: =COUNTIFS(Temas_TIMSS!$W$5:$W$1264,$A8,Temas_TIMSS!$M$5:$M$1264,$C8) -> 37 | E8: =COUNTIFS(Temas_TIMSS!$W$5:$W$1264,$A8)-COUNTIFS(Temas_TIMSS!$W$5:$W$1264,$A8,Temas_TIMSS!$K$5:$K$1264,"FUERA")-COUNTIFS(Temas_TIMSS!$W$5:$W$1264,$A8,Temas_TIMSS!$K$5:$K$1264,"PENDIENTE") -> 178 | F8: =IF(E8=0,0,D8/E8) -> 0.20786517 | G8: 0.2 | H8: =G8*E8 -> 35.6 | I8: =H8-D8 -> -1.4 | J8: =(G8-F8)*100 -> -0.78651685 | K8: =IF(ABS(G8-F8)<=$H$2,"En meta",IF(I8>0,"Faltan "&ROUND(I8,0)&" temas","Sobran "&ROUND(-I8,0)&" temas")) -> En meta | L8: =MAX(D6/G6,D7/G7,D8/G8) -> 204.44444 | M8: =MAX(0,ROUNDUP(G8*L8-D8,0)) -> 4 | N8: =COUNTIFS(Temas_TIMSS!$W$5:$W$1264,$A8,Temas_TIMSS!$K$5:$K$1264,"FUERA") -> 30
C9: Total del grupo | D9: =SUM(D6:D8) -> 178 | G9: =SUM(G6:G8) -> 1 | M9: =SUM(M6:M8) -> 27
A11: Ciclo 5°–8° | B11: TIMSS 2023 8.° | C11: Biología | D11: =COUNTIFS(Temas_TIMSS!$W$5:$W$1264,$A11,Temas_TIMSS!$M$5:$M$1264,$C11) -> 111 | E11: =COUNTIFS(Temas_TIMSS!$W$5:$W$1264,$A11)-COUNTIFS(Temas_TIMSS!$W$5:$W$1264,$A11,Temas_TIMSS!$K$5:$K$1264,"FUERA")-COUNTIFS(Temas_TIMSS!$W$5:$W$1264,$A11,Temas_TIMSS!$K$5:$K$1264,"PENDIENTE") -> 302 | F11: =IF(E11=0,0,D11/E11) -> 0.36754967 | G11: 0.35 | H11: =G11*E11 -> 105.7 | I11: =H11-D11 -> -5.3 | J11: =(G11-F11)*100 -> -1.7549669 | K11: =IF(ABS(G11-F11)<=$H$2,"En meta",IF(I11>0,"Faltan "&ROUND(I11,0)&" temas","Sobran "&ROUND(-I11,0)&" temas")) -> En meta | L11: =MAX(D11/G11,D12/G12,D13/G13,D14/G14) -> 317.14286 | M11: =MAX(0,ROUNDUP(G11*L11-D11,0)) -> 0 | N11: =COUNTIFS(Temas_TIMSS!$W$5:$W$1264,$A11,Temas_TIMSS!$K$5:$K$1264,"FUERA") -> 22
A12: Ciclo 5°–8° | B12: TIMSS 2023 8.° | C12: Química | D12: =COUNTIFS(Temas_TIMSS!$W$5:$W$1264,$A12,Temas_TIMSS!$M$5:$M$1264,$C12) -> 58 | E12: =COUNTIFS(Temas_TIMSS!$W$5:$W$1264,$A12)-COUNTIFS(Temas_TIMSS!$W$5:$W$1264,$A12,Temas_TIMSS!$K$5:$K$1264,"FUERA")-COUNTIFS(Temas_TIMSS!$W$5:$W$1264,$A12,Temas_TIMSS!$K$5:$K$1264,"PENDIENTE") -> 302 | F12: =IF(E12=0,0,D12/E12) -> 0.19205298 | G12: 0.2 | H12: =G12*E12 -> 60.4 | I12: =H12-D12 -> 2.4 | J12: =(G12-F12)*100 -> 0.79470199 | K12: =IF(ABS(G12-F12)<=$H$2,"En meta",IF(I12>0,"Faltan "&ROUND(I12,0)&" temas","Sobran "&ROUND(-I12,0)&" temas")) -> En meta | L12: =MAX(D11/G11,D12/G12,D13/G13,D14/G14) -> 317.14286 | M12: =MAX(0,ROUNDUP(G12*L12-D12,0)) -> 6 | N12: =COUNTIFS(Temas_TIMSS!$W$5:$W$1264,$A12,Temas_TIMSS!$K$5:$K$1264,"FUERA") -> 22
A13: Ciclo 5°–8° | B13: TIMSS 2023 8.° | C13: Física | D13: =COUNTIFS(Temas_TIMSS!$W$5:$W$1264,$A13,Temas_TIMSS!$M$5:$M$1264,$C13) -> 79 | E13: =COUNTIFS(Temas_TIMSS!$W$5:$W$1264,$A13)-COUNTIFS(Temas_TIMSS!$W$5:$W$1264,$A13,Temas_TIMSS!$K$5:$K$1264,"FUERA")-COUNTIFS(Temas_TIMSS!$W$5:$W$1264,$A13,Temas_TIMSS!$K$5:$K$1264,"PENDIENTE") -> 302 | F13: =IF(E13=0,0,D13/E13) -> 0.2615894 | G13: 0.25 | H13: =G13*E13 -> 75.5 | I13: =H13-D13 -> -3.5 | J13: =(G13-F13)*100 -> -1.1589404 | K13: =IF(ABS(G13-F13)<=$H$2,"En meta",IF(I13>0,"Faltan "&ROUND(I13,0)&" temas","Sobran "&ROUND(-I13,0)&" temas")) -> En meta | L13: =MAX(D11/G11,D12/G12,D13/G13,D14/G14) -> 317.14286 | M13: =MAX(0,ROUNDUP(G13*L13-D13,0)) -> 1 | N13: =COUNTIFS(Temas_TIMSS!$W$5:$W$1264,$A13,Temas_TIMSS!$K$5:$K$1264,"FUERA") -> 22
A14: Ciclo 5°–8° | B14: TIMSS 2023 8.° | C14: Ciencias de la Tierra | D14: =COUNTIFS(Temas_TIMSS!$W$5:$W$1264,$A14,Temas_TIMSS!$M$5:$M$1264,$C14) -> 54 | E14: =COUNTIFS(Temas_TIMSS!$W$5:$W$1264,$A14)-COUNTIFS(Temas_TIMSS!$W$5:$W$1264,$A14,Temas_TIMSS!$K$5:$K$1264,"FUERA")-COUNTIFS(Temas_TIMSS!$W$5:$W$1264,$A14,Temas_TIMSS!$K$5:$K$1264,"PENDIENTE") -> 302 | F14: =IF(E14=0,0,D14/E14) -> 0.17880795 | G14: 0.2 | H14: =G14*E14 -> 60.4 | I14: =H14-D14 -> 6.4 | J14: =(G14-F14)*100 -> 2.1192053 | K14: =IF(ABS(G14-F14)<=$H$2,"En meta",IF(I14>0,"Faltan "&ROUND(I14,0)&" temas","Sobran "&ROUND(-I14,0)&" temas")) -> En meta | L14: =MAX(D11/G11,D12/G12,D13/G13,D14/G14) -> 317.14286 | M14: =MAX(0,ROUNDUP(G14*L14-D14,0)) -> 10 | N14: =COUNTIFS(Temas_TIMSS!$W$5:$W$1264,$A14,Temas_TIMSS!$K$5:$K$1264,"FUERA") -> 22
C15: Total del grupo | D15: =SUM(D11:D14) -> 302 | G15: =SUM(G11:G14) -> 1 | M15: =SUM(M11:M14) -> 17
A17: 9° | B17: TIMSS 2023 8.° | C17: Biología | D17: =COUNTIFS(Temas_TIMSS!$W$5:$W$1264,$A17,Temas_TIMSS!$M$5:$M$1264,$C17) -> 4 | E17: =COUNTIFS(Temas_TIMSS!$W$5:$W$1264,$A17)-COUNTIFS(Temas_TIMSS!$W$5:$W$1264,$A17,Temas_TIMSS!$K$5:$K$1264,"FUERA")-COUNTIFS(Temas_TIMSS!$W$5:$W$1264,$A17,Temas_TIMSS!$K$5:$K$1264,"PENDIENTE") -> 82 | F17: =IF(E17=0,0,D17/E17) -> 0.048780488 | G17: 0.35 | H17: =G17*E17 -> 28.7 | I17: =H17-D17 -> 24.7 | J17: =(G17-F17)*100 -> 30.121951 | K17: =IF(ABS(G17-F17)<=$H$2,"En meta",IF(I17>0,"Faltan "&ROUND(I17,0)&" temas","Sobran "&ROUND(-I17,0)&" temas")) -> Faltan 25 temas | L17: =MAX(D17/G17,D18/G18,D19/G19,D20/G20) -> 152 | M17: =MAX(0,ROUNDUP(G17*L17-D17,0)) -> 50 | N17: =COUNTIFS(Temas_TIMSS!$W$5:$W$1264,$A17,Temas_TIMSS!$K$5:$K$1264,"FUERA") -> 8
A18: 9° | B18: TIMSS 2023 8.° | C18: Química | D18: =COUNTIFS(Temas_TIMSS!$W$5:$W$1264,$A18,Temas_TIMSS!$M$5:$M$1264,$C18) -> 20 | E18: =COUNTIFS(Temas_TIMSS!$W$5:$W$1264,$A18)-COUNTIFS(Temas_TIMSS!$W$5:$W$1264,$A18,Temas_TIMSS!$K$5:$K$1264,"FUERA")-COUNTIFS(Temas_TIMSS!$W$5:$W$1264,$A18,Temas_TIMSS!$K$5:$K$1264,"PENDIENTE") -> 82 | F18: =IF(E18=0,0,D18/E18) -> 0.24390244 | G18: 0.2 | H18: =G18*E18 -> 16.4 | I18: =H18-D18 -> -3.6 | J18: =(G18-F18)*100 -> -4.3902439 | K18: =IF(ABS(G18-F18)<=$H$2,"En meta",IF(I18>0,"Faltan "&ROUND(I18,0)&" temas","Sobran "&ROUND(-I18,0)&" temas")) -> En meta | L18: =MAX(D17/G17,D18/G18,D19/G19,D20/G20) -> 152 | M18: =MAX(0,ROUNDUP(G18*L18-D18,0)) -> 11 | N18: =COUNTIFS(Temas_TIMSS!$W$5:$W$1264,$A18,Temas_TIMSS!$K$5:$K$1264,"FUERA") -> 8
A19: 9° | B19: TIMSS 2023 8.° | C19: Física | D19: =COUNTIFS(Temas_TIMSS!$W$5:$W$1264,$A19,Temas_TIMSS!$M$5:$M$1264,$C19) -> 38 | E19: =COUNTIFS(Temas_TIMSS!$W$5:$W$1264,$A19)-COUNTIFS(Temas_TIMSS!$W$5:$W$1264,$A19,Temas_TIMSS!$K$5:$K$1264,"FUERA")-COUNTIFS(Temas_TIMSS!$W$5:$W$1264,$A19,Temas_TIMSS!$K$5:$K$1264,"PENDIENTE") -> 82 | F19: =IF(E19=0,0,D19/E19) -> 0.46341463 | G19: 0.25 | H19: =G19*E19 -> 20.5 | I19: =H19-D19 -> -17.5 | J19: =(G19-F19)*100 -> -21.341463 | K19: =IF(ABS(G19-F19)<=$H$2,"En meta",IF(I19>0,"Faltan "&ROUND(I19,0)&" temas","Sobran "&ROUND(-I19,0)&" temas")) -> Sobran 18 temas | L19: =MAX(D17/G17,D18/G18,D19/G19,D20/G20) -> 152 | M19: =MAX(0,ROUNDUP(G19*L19-D19,0)) -> 0 | N19: =COUNTIFS(Temas_TIMSS!$W$5:$W$1264,$A19,Temas_TIMSS!$K$5:$K$1264,"FUERA") -> 8
A20: 9° | B20: TIMSS 2023 8.° | C20: Ciencias de la Tierra | D20: =COUNTIFS(Temas_TIMSS!$W$5:$W$1264,$A20,Temas_TIMSS!$M$5:$M$1264,$C20) -> 20 | E20: =COUNTIFS(Temas_TIMSS!$W$5:$W$1264,$A20)-COUNTIFS(Temas_TIMSS!$W$5:$W$1264,$A20,Temas_TIMSS!$K$5:$K$1264,"FUERA")-COUNTIFS(Temas_TIMSS!$W$5:$W$1264,$A20,Temas_TIMSS!$K$5:$K$1264,"PENDIENTE") -> 82 | F20: =IF(E20=0,0,D20/E20) -> 0.24390244 | G20: 0.2 | H20: =G20*E20 -> 16.4 | I20: =H20-D20 -> -3.6 | J20: =(G20-F20)*100 -> -4.3902439 | K20: =IF(ABS(G20-F20)<=$H$2,"En meta",IF(I20>0,"Faltan "&ROUND(I20,0)&" temas","Sobran "&ROUND(-I20,0)&" temas")) -> En meta | L20: =MAX(D17/G17,D18/G18,D19/G19,D20/G20) -> 152 | M20: =MAX(0,ROUNDUP(G20*L20-D20,0)) -> 11 | N20: =COUNTIFS(Temas_TIMSS!$W$5:$W$1264,$A20,Temas_TIMSS!$K$5:$K$1264,"FUERA") -> 8
C21: Total del grupo | D21: =SUM(D17:D20) -> 82 | G21: =SUM(G17:G20) -> 1 | M21: =SUM(M17:M20) -> 72
A23: Física 10°–11° | B23: TIMSS Advanced 2015 Física | C23: Mecánica y termodinámica | D23: =COUNTIFS(Temas_TIMSS!$W$5:$W$1264,$A23,Temas_TIMSS!$M$5:$M$1264,$C23) -> 71 | E23: =COUNTIFS(Temas_TIMSS!$W$5:$W$1264,$A23)-COUNTIFS(Temas_TIMSS!$W$5:$W$1264,$A23,Temas_TIMSS!$K$5:$K$1264,"FUERA")-COUNTIFS(Temas_TIMSS!$W$5:$W$1264,$A23,Temas_TIMSS!$K$5:$K$1264,"PENDIENTE") -> 199 | F23: =IF(E23=0,0,D23/E23) -> 0.35678392 | G23: 0.4 | H23: =G23*E23 -> 79.6 | I23: =H23-D23 -> 8.6 | J23: =(G23-F23)*100 -> 4.321608 | K23: =IF(ABS(G23-F23)<=$H$2,"En meta",IF(I23>0,"Faltan "&ROUND(I23,0)&" temas","Sobran "&ROUND(-I23,0)&" temas")) -> En meta | L23: =MAX(D23/G23,D24/G24,D25/G25) -> 242.85714 | M23: =MAX(0,ROUNDUP(G23*L23-D23,0)) -> 27 | N23: =COUNTIFS(Temas_TIMSS!$W$5:$W$1264,$A23,Temas_TIMSS!$K$5:$K$1264,"FUERA") -> 68
A24: Física 10°–11° | B24: TIMSS Advanced 2015 Física | C24: Electricidad y magnetismo | D24: =COUNTIFS(Temas_TIMSS!$W$5:$W$1264,$A24,Temas_TIMSS!$M$5:$M$1264,$C24) -> 43 | E24: =COUNTIFS(Temas_TIMSS!$W$5:$W$1264,$A24)-COUNTIFS(Temas_TIMSS!$W$5:$W$1264,$A24,Temas_TIMSS!$K$5:$K$1264,"FUERA")-COUNTIFS(Temas_TIMSS!$W$5:$W$1264,$A24,Temas_TIMSS!$K$5:$K$1264,"PENDIENTE") -> 199 | F24: =IF(E24=0,0,D24/E24) -> 0.2160804 | G24: 0.25 | H24: =G24*E24 -> 49.75 | I24: =H24-D24 -> 6.75 | J24: =(G24-F24)*100 -> 3.3919598 | K24: =IF(ABS(G24-F24)<=$H$2,"En meta",IF(I24>0,"Faltan "&ROUND(I24,0)&" temas","Sobran "&ROUND(-I24,0)&" temas")) -> En meta | L24: =MAX(D23/G23,D24/G24,D25/G25) -> 242.85714 | M24: =MAX(0,ROUNDUP(G24*L24-D24,0)) -> 18 | N24: =COUNTIFS(Temas_TIMSS!$W$5:$W$1264,$A24,Temas_TIMSS!$K$5:$K$1264,"FUERA") -> 68
A25: Física 10°–11° | B25: TIMSS Advanced 2015 Física | C25: Ondas y física atómica/nuclear | D25: =COUNTIFS(Temas_TIMSS!$W$5:$W$1264,$A25,Temas_TIMSS!$M$5:$M$1264,$C25) -> 85 | E25: =COUNTIFS(Temas_TIMSS!$W$5:$W$1264,$A25)-COUNTIFS(Temas_TIMSS!$W$5:$W$1264,$A25,Temas_TIMSS!$K$5:$K$1264,"FUERA")-COUNTIFS(Temas_TIMSS!$W$5:$W$1264,$A25,Temas_TIMSS!$K$5:$K$1264,"PENDIENTE") -> 199 | F25: =IF(E25=0,0,D25/E25) -> 0.42713568 | G25: 0.35 | H25: =G25*E25 -> 69.65 | I25: =H25-D25 -> -15.35 | J25: =(G25-F25)*100 -> -7.7135678 | K25: =IF(ABS(G25-F25)<=$H$2,"En meta",IF(I25>0,"Faltan "&ROUND(I25,0)&" temas","Sobran "&ROUND(-I25,0)&" temas")) -> Sobran 15 temas | L25: =MAX(D23/G23,D24/G24,D25/G25) -> 242.85714 | M25: =MAX(0,ROUNDUP(G25*L25-D25,0)) -> 0 | N25: =COUNTIFS(Temas_TIMSS!$W$5:$W$1264,$A25,Temas_TIMSS!$K$5:$K$1264,"FUERA") -> 68
C26: Total del grupo | D26: =SUM(D23:D25) -> 199 | G26: =SUM(G23:G25) -> 1 | M26: =SUM(M23:M25) -> 45

Sheet Balance_grado
A1: Balance de contenidos por grado frente a las metas de TIMSS
A2: Tolerancia para considerar «en meta» (± puntos porcentuales): | H2: 0.05
A3: Cómo leerlo: «% actual» = temas del dominio ÷ temas evaluables del grado (se excluyen los «fuera del marco»). «Brecha (temas)» = meta × evaluables − actuales: positivo = faltan temas en ese dominio si se redistribuye la misma carga; negativo = sobran. «Temas a AGREGAR» = cuántos temas habría que sumar a cada dominio para cumplir todas las metas SIN quitar ninguno (la escala la fija el dominio más sobrerrepresentado). Ojo: TIMSS fija pesos para la prueba acumulada (4.° y 8.°); aplicarlos a cada grado es una aproximación. La hoja Balance_ciclo hace la comparación acumulada.
A5: Grupo | B5: Marco de referencia | C5: Dominio | D5: Temas actuales en el dominio | E5: Temas evaluables del grupo (sin «fuera») | F5: % actual | G5: Meta TIMSS (%) | H5: Temas esperados según meta | I5: Brecha (temas): + faltan / − sobran | J5: Brecha (pp) | K5: Estado | L5: Escala para cumplir sin quitar temas (total evaluables) | M5: Temas a AGREGAR para llegar a la meta sin quitar | N5: Temas «fuera del marco» del grupo
A6: 2° | B6: TIMSS 2023 4.° | C6: Ciencias de la vida | D6: =COUNTIFS(Temas_TIMSS!$V$5:$V$1264,$A6,Temas_TIMSS!$M$5:$M$1264,$C6) -> 24 | E6: =COUNTIFS(Temas_TIMSS!$V$5:$V$1264,$A6)-COUNTIFS(Temas_TIMSS!$V$5:$V$1264,$A6,Temas_TIMSS!$K$5:$K$1264,"FUERA")-COUNTIFS(Temas_TIMSS!$V$5:$V$1264,$A6,Temas_TIMSS!$K$5:$K$1264,"PENDIENTE") -> 57 | F6: =IF(E6=0,0,D6/E6) -> 0.42105263 | G6: 0.45 | H6: =G6*E6 -> 25.65 | I6: =H6-D6 -> 1.65 | J6: =(G6-F6)*100 -> 2.8947368 | K6: =IF(ABS(G6-F6)<=$H$2,"En meta",IF(I6>0,"Faltan "&ROUND(I6,0)&" temas","Sobran "&ROUND(-I6,0)&" temas")) -> En meta | L6: =MAX(D6/G6,D7/G7,D8/G8) -> 65.714286 | M6: =MAX(0,ROUNDUP(G6*L6-D6,0)) -> 6 | N6: =COUNTIFS(Temas_TIMSS!$V$5:$V$1264,$A6,Temas_TIMSS!$K$5:$K$1264,"FUERA") -> 13
A7: 2° | B7: TIMSS 2023 4.° | C7: Ciencias físicas | D7: =COUNTIFS(Temas_TIMSS!$V$5:$V$1264,$A7,Temas_TIMSS!$M$5:$M$1264,$C7) -> 23 | E7: =COUNTIFS(Temas_TIMSS!$V$5:$V$1264,$A7)-COUNTIFS(Temas_TIMSS!$V$5:$V$1264,$A7,Temas_TIMSS!$K$5:$K$1264,"FUERA")-COUNTIFS(Temas_TIMSS!$V$5:$V$1264,$A7,Temas_TIMSS!$K$5:$K$1264,"PENDIENTE") -> 57 | F7: =IF(E7=0,0,D7/E7) -> 0.40350877 | G7: 0.35 | H7: =G7*E7 -> 19.95 | I7: =H7-D7 -> -3.05 | J7: =(G7-F7)*100 -> -5.3508772 | K7: =IF(ABS(G7-F7)<=$H$2,"En meta",IF(I7>0,"Faltan "&ROUND(I7,0)&" temas","Sobran "&ROUND(-I7,0)&" temas")) -> Sobran 3 temas | L7: =MAX(D6/G6,D7/G7,D8/G8) -> 65.714286 | M7: =MAX(0,ROUNDUP(G7*L7-D7,0)) -> 0 | N7: =COUNTIFS(Temas_TIMSS!$V$5:$V$1264,$A7,Temas_TIMSS!$K$5:$K$1264,"FUERA") -> 13
A8: 2° | B8: TIMSS 2023 4.° | C8: Ciencias de la Tierra | D8: =COUNTIFS(Temas_TIMSS!$V$5:$V$1264,$A8,Temas_TIMSS!$M$5:$M$1264,$C8) -> 10 | E8: =COUNTIFS(Temas_TIMSS!$V$5:$V$1264,$A8)-COUNTIFS(Temas_TIMSS!$V$5:$V$1264,$A8,Temas_TIMSS!$K$5:$K$1264,"FUERA")-COUNTIFS(Temas_TIMSS!$V$5:$V$1264,$A8,Temas_TIMSS!$K$5:$K$1264,"PENDIENTE") -> 57 | F8: =IF(E8=0,0,D8/E8) -> 0.1754386 | G8: 0.2 | H8: =G8*E8 -> 11.4 | I8: =H8-D8 -> 1.4 | J8: =(G8-F8)*100 -> 2.4561404 | K8: =IF(ABS(G8-F8)<=$H$2,"En meta",IF(I8>0,"Faltan "&ROUND(I8,0)&" temas","Sobran "&ROUND(-I8,0)&" temas")) -> En meta | L8: =MAX(D6/G6,D7/G7,D8/G8) -> 65.714286 | M8: =MAX(0,ROUNDUP(G8*L8-D8,0)) -> 4 | N8: =COUNTIFS(Temas_TIMSS!$V$5:$V$1264,$A8,Temas_TIMSS!$K$5:$K$1264,"FUERA") -> 13
C9: Total del grupo | D9: =SUM(D6:D8) -> 57 | G9: =SUM(G6:G8) -> 1 | M9: =SUM(M6:M8) -> 10
A11: 3° | B11: TIMSS 2023 4.° | C11: Ciencias de la vida | D11: =COUNTIFS(Temas_TIMSS!$V$5:$V$1264,$A11,Temas_TIMSS!$M$5:$M$1264,$C11) -> 31 | E11: =COUNTIFS(Temas_TIMSS!$V$5:$V$1264,$A11)-COUNTIFS(Temas_TIMSS!$V$5:$V$1264,$A11,Temas_TIMSS!$K$5:$K$1264,"FUERA")-COUNTIFS(Temas_TIMSS!$V$5:$V$1264,$A11,Temas_TIMSS!$K$5:$K$1264,"PENDIENTE") -> 57 | F11: =IF(E11=0,0,D11/E11) -> 0.54385965 | G11: 0.45 | H11: =G11*E11 -> 25.65 | I11: =H11-D11 -> -5.35 | J11: =(G11-F11)*100 -> -9.3859649 | K11: =IF(ABS(G11-F11)<=$H$2,"En meta",IF(I11>0,"Faltan "&ROUND(I11,0)&" temas","Sobran "&ROUND(-I11,0)&" temas")) -> Sobran 5 temas | L11: =MAX(D11/G11,D12/G12,D13/G13) -> 68.888889 | M11: =MAX(0,ROUNDUP(G11*L11-D11,0)) -> 0 | N11: =COUNTIFS(Temas_TIMSS!$V$5:$V$1264,$A11,Temas_TIMSS!$K$5:$K$1264,"FUERA") -> 9
A12: 3° | B12: TIMSS 2023 4.° | C12: Ciencias físicas | D12: =COUNTIFS(Temas_TIMSS!$V$5:$V$1264,$A12,Temas_TIMSS!$M$5:$M$1264,$C12) -> 17 | E12: =COUNTIFS(Temas_TIMSS!$V$5:$V$1264,$A12)-COUNTIFS(Temas_TIMSS!$V$5:$V$1264,$A12,Temas_TIMSS!$K$5:$K$1264,"FUERA")-COUNTIFS(Temas_TIMSS!$V$5:$V$1264,$A12,Temas_TIMSS!$K$5:$K$1264,"PENDIENTE") -> 57 | F12: =IF(E12=0,0,D12/E12) -> 0.29824561 | G12: 0.35 | H12: =G12*E12 -> 19.95 | I12: =H12-D12 -> 2.95 | J12: =(G12-F12)*100 -> 5.1754386 | K12: =IF(ABS(G12-F12)<=$H$2,"En meta",IF(I12>0,"Faltan "&ROUND(I12,0)&" temas","Sobran "&ROUND(-I12,0)&" temas")) -> Faltan 3 temas | L12: =MAX(D11/G11,D12/G12,D13/G13) -> 68.888889 | M12: =MAX(0,ROUNDUP(G12*L12-D12,0)) -> 8 | N12: =COUNTIFS(Temas_TIMSS!$V$5:$V$1264,$A12,Temas_TIMSS!$K$5:$K$1264,"FUERA") -> 9
A13: 3° | B13: TIMSS 2023 4.° | C13: Ciencias de la Tierra | D13: =COUNTIFS(Temas_TIMSS!$V$5:$V$1264,$A13,Temas_TIMSS!$M$5:$M$1264,$C13) -> 9 | E13: =COUNTIFS(Temas_TIMSS!$V$5:$V$1264,$A13)-COUNTIFS(Temas_TIMSS!$V$5:$V$1264,$A13,Temas_TIMSS!$K$5:$K$1264,"FUERA")-COUNTIFS(Temas_TIMSS!$V$5:$V$1264,$A13,Temas_TIMSS!$K$5:$K$1264,"PENDIENTE") -> 57 | F13: =IF(E13=0,0,D13/E13) -> 0.15789474 | G13: 0.2 | H13: =G13*E13 -> 11.4 | I13: =H13-D13 -> 2.4 | J13: =(G13-F13)*100 -> 4.2105263 | K13: =IF(ABS(G13-F13)<=$H$2,"En meta",IF(I13>0,"Faltan "&ROUND(I13,0)&" temas","Sobran "&ROUND(-I13,0)&" temas")) -> En meta | L13: =MAX(D11/G11,D12/G12,D13/G13) -> 68.888889 | M13: =MAX(0,ROUNDUP(G13*L13-D13,0)) -> 5 | N13: =COUNTIFS(Temas_TIMSS!$V$5:$V$1264,$A13,Temas_TIMSS!$K$5:$K$1264,"FUERA") -> 9
C14: Total del grupo | D14: =SUM(D11:D13) -> 57 | G14: =SUM(G11:G13) -> 1 | M14: =SUM(M11:M13) -> 13
A16: 4° | B16: TIMSS 2023 4.° | C16: Ciencias de la vida | D16: =COUNTIFS(Temas_TIMSS!$V$5:$V$1264,$A16,Temas_TIMSS!$M$5:$M$1264,$C16) -> 37 | E16: =COUNTIFS(Temas_TIMSS!$V$5:$V$1264,$A16)-COUNTIFS(Temas_TIMSS!$V$5:$V$1264,$A16,Temas_TIMSS!$K$5:$K$1264,"FUERA")-COUNTIFS(Temas_TIMSS!$V$5:$V$1264,$A16,Temas_TIMSS!$K$5:$K$1264,"PENDIENTE") -> 64 | F16: =IF(E16=0,0,D16/E16) -> 0.578125 | G16: 0.45 | H16: =G16*E16 -> 28.8 | I16: =H16-D16 -> -8.2 | J16: =(G16-F16)*100 -> -12.8125 | K16: =IF(ABS(G16-F16)<=$H$2,"En meta",IF(I16>0,"Faltan "&ROUND(I16,0)&" temas","Sobran "&ROUND(-I16,0)&" temas")) -> Sobran 8 temas | L16: =MAX(D16/G16,D17/G17,D18/G18) -> 90 | M16: =MAX(0,ROUNDUP(G16*L16-D16,0)) -> 4 | N16: =COUNTIFS(Temas_TIMSS!$V$5:$V$1264,$A16,Temas_TIMSS!$K$5:$K$1264,"FUERA") -> 8
A17: 4° | B17: TIMSS 2023 4.° | C17: Ciencias físicas | D17: =COUNTIFS(Temas_TIMSS!$V$5:$V$1264,$A17,Temas_TIMSS!$M$5:$M$1264,$C17) -> 9 | E17: =COUNTIFS(Temas_TIMSS!$V$5:$V$1264,$A17)-COUNTIFS(Temas_TIMSS!$V$5:$V$1264,$A17,Temas_TIMSS!$K$5:$K$1264,"FUERA")-COUNTIFS(Temas_TIMSS!$V$5:$V$1264,$A17,Temas_TIMSS!$K$5:$K$1264,"PENDIENTE") -> 64 | F17: =IF(E17=0,0,D17/E17) -> 0.140625 | G17: 0.35 | H17: =G17*E17 -> 22.4 | I17: =H17-D17 -> 13.4 | J17: =(G17-F17)*100 -> 20.9375 | K17: =IF(ABS(G17-F17)<=$H$2,"En meta",IF(I17>0,"Faltan "&ROUND(I17,0)&" temas","Sobran "&ROUND(-I17,0)&" temas")) -> Faltan 13 temas | L17: =MAX(D16/G16,D17/G17,D18/G18) -> 90 | M17: =MAX(0,ROUNDUP(G17*L17-D17,0)) -> 23 | N17: =COUNTIFS(Temas_TIMSS!$V$5:$V$1264,$A17,Temas_TIMSS!$K$5:$K$1264,"FUERA") -> 8
A18: 4° | B18: TIMSS 2023 4.° | C18: Ciencias de la Tierra | D18: =COUNTIFS(Temas_TIMSS!$V$5:$V$1264,$A18,Temas_TIMSS!$M$5:$M$1264,$C18) -> 18 | E18: =COUNTIFS(Temas_TIMSS!$V$5:$V$1264,$A18)-COUNTIFS(Temas_TIMSS!$V$5:$V$1264,$A18,Temas_TIMSS!$K$5:$K$1264,"FUERA")-COUNTIFS(Temas_TIMSS!$V$5:$V$1264,$A18,Temas_TIMSS!$K$5:$K$1264,"PENDIENTE") -> 64 | F18: =IF(E18=0,0,D18/E18) -> 0.28125 | G18: 0.2 | H18: =G18*E18 -> 12.8 | I18: =H18-D18 -> -5.2 | J18: =(G18-F18)*100 -> -8.125 | K18: =IF(ABS(G18-F18)<=$H$2,"En meta",IF(I18>0,"Faltan "&ROUND(I18,0)&" temas","Sobran "&ROUND(-I18,0)&" temas")) -> Sobran 5 temas | L18: =MAX(D16/G16,D17/G17,D18/G18) -> 90 | M18: =MAX(0,ROUNDUP(G18*L18-D18,0)) -> 0 | N18: =COUNTIFS(Temas_TIMSS!$V$5:$V$1264,$A18,Temas_TIMSS!$K$5:$K$1264,"FUERA") -> 8
C19: Total del grupo | D19: =SUM(D16:D18) -> 64 | G19: =SUM(G16:G18) -> 1 | M19: =SUM(M16:M18) -> 27
A21: 5° | B21: TIMSS 2023 8.° | C21: Biología | D21: =COUNTIFS(Temas_TIMSS!$V$5:$V$1264,$A21,Temas_TIMSS!$M$5:$M$1264,$C21) -> 1 | E21: =COUNTIFS(Temas_TIMSS!$V$5:$V$1264,$A21)-COUNTIFS(Temas_TIMSS!$V$5:$V$1264,$A21,Temas_TIMSS!$K$5:$K$1264,"FUERA")-COUNTIFS(Temas_TIMSS!$V$5:$V$1264,$A21,Temas_TIMSS!$K$5:$K$1264,"PENDIENTE") -> 58 | F21: =IF(E21=0,0,D21/E21) -> 0.017241379 | G21: 0.35 | H21: =G21*E21 -> 20.3 | I21: =H21-D21 -> 19.3 | J21: =(G21-F21)*100 -> 33.275862 | K21: =IF(ABS(G21-F21)<=$H$2,"En meta",IF(I21>0,"Faltan "&ROUND(I21,0)&" temas","Sobran "&ROUND(-I21,0)&" temas")) -> Faltan 19 temas | L21: =MAX(D21/G21,D22/G22,D23/G23,D24/G24) -> 120 | M21: =MAX(0,ROUNDUP(G21*L21-D21,0)) -> 41 | N21: =COUNTIFS(Temas_TIMSS!$V$5:$V$1264,$A21,Temas_TIMSS!$K$5:$K$1264,"FUERA") -> 14
A22: 5° | B22: TIMSS 2023 8.° | C22: Química | D22: =COUNTIFS(Temas_TIMSS!$V$5:$V$1264,$A22,Temas_TIMSS!$M$5:$M$1264,$C22) -> 18 | E22: =COUNTIFS(Temas_TIMSS!$V$5:$V$1264,$A22)-COUNTIFS(Temas_TIMSS!$V$5:$V$1264,$A22,Temas_TIMSS!$K$5:$K$1264,"FUERA")-COUNTIFS(Temas_TIMSS!$V$5:$V$1264,$A22,Temas_TIMSS!$K$5:$K$1264,"PENDIENTE") -> 58 | F22: =IF(E22=0,0,D22/E22) -> 0.31034483 | G22: 0.2 | H22: =G22*E22 -> 11.6 | I22: =H22-D22 -> -6.4 | J22: =(G22-F22)*100 -> -11.034483 | K22: =IF(ABS(G22-F22)<=$H$2,"En meta",IF(I22>0,"Faltan "&ROUND(I22,0)&" temas","Sobran "&ROUND(-I22,0)&" temas")) -> Sobran 6 temas | L22: =MAX(D21/G21,D22/G22,D23/G23,D24/G24) -> 120 | M22: =MAX(0,ROUNDUP(G22*L22-D22,0)) -> 6 | N22: =COUNTIFS(Temas_TIMSS!$V$5:$V$1264,$A22,Temas_TIMSS!$K$5:$K$1264,"FUERA") -> 14
A23: 5° | B23: TIMSS 2023 8.° | C23: Física | D23: =COUNTIFS(Temas_TIMSS!$V$5:$V$1264,$A23,Temas_TIMSS!$M$5:$M$1264,$C23) -> 15 | E23: =COUNTIFS(Temas_TIMSS!$V$5:$V$1264,$A23)-COUNTIFS(Temas_TIMSS!$V$5:$V$1264,$A23,Temas_TIMSS!$K$5:$K$1264,"FUERA")-COUNTIFS(Temas_TIMSS!$V$5:$V$1264,$A23,Temas_TIMSS!$K$5:$K$1264,"PENDIENTE") -> 58 | F23: =IF(E23=0,0,D23/E23) -> 0.25862069 | G23: 0.25 | H23: =G23*E23 -> 14.5 | I23: =H23-D23 -> -0.5 | J23: =(G23-F23)*100 -> -0.86206897 | K23: =IF(ABS(G23-F23)<=$H$2,"En meta",IF(I23>0,"Faltan "&ROUND(I23,0)&" temas","Sobran "&ROUND(-I23,0)&" temas")) -> En meta | L23: =MAX(D21/G21,D22/G22,D23/G23,D24/G24) -> 120 | M23: =MAX(0,ROUNDUP(G23*L23-D23,0)) -> 15 | N23: =COUNTIFS(Temas_TIMSS!$V$5:$V$1264,$A23,Temas_TIMSS!$K$5:$K$1264,"FUERA") -> 14
A24: 5° | B24: TIMSS 2023 8.° | C24: Ciencias de la Tierra | D24: =COUNTIFS(Temas_TIMSS!$V$5:$V$1264,$A24,Temas_TIMSS!$M$5:$M$1264,$C24) -> 24 | E24: =COUNTIFS(Temas_TIMSS!$V$5:$V$1264,$A24)-COUNTIFS(Temas_TIMSS!$V$5:$V$1264,$A24,Temas_TIMSS!$K$5:$K$1264,"FUERA")-COUNTIFS(Temas_TIMSS!$V$5:$V$1264,$A24,Temas_TIMSS!$K$5:$K$1264,"PENDIENTE") -> 58 | F24: =IF(E24=0,0,D24/E24) -> 0.4137931 | G24: 0.2 | H24: =G24*E24 -> 11.6 | I24: =H24-D24 -> -12.4 | J24: =(G24-F24)*100 -> -21.37931 | K24: =IF(ABS(G24-F24)<=$H$2,"En meta",IF(I24>0,"Faltan "&ROUND(I24,0)&" temas","Sobran "&ROUND(-I24,0)&" temas")) -> Sobran 12 temas | L24: =MAX(D21/G21,D22/G22,D23/G23,D24/G24) -> 120 | M24: =MAX(0,ROUNDUP(G24*L24-D24,0)) -> 0 | N24: =COUNTIFS(Temas_TIMSS!$V$5:$V$1264,$A24,Temas_TIMSS!$K$5:$K$1264,"FUERA") -> 14
C25: Total del grupo | D25: =SUM(D21:D24) -> 58 | G25: =SUM(G21:G24) -> 1 | M25: =SUM(M21:M24) -> 62
A27: 6° | B27: TIMSS 2023 8.° | C27: Biología | D27: =COUNTIFS(Temas_TIMSS!$V$5:$V$1264,$A27,Temas_TIMSS!$M$5:$M$1264,$C27) -> 34 | E27: =COUNTIFS(Temas_TIMSS!$V$5:$V$1264,$A27)-COUNTIFS(Temas_TIMSS!$V$5:$V$1264,$A27,Temas_TIMSS!$K$5:$K$1264,"FUERA")-COUNTIFS(Temas_TIMSS!$V$5:$V$1264,$A27,Temas_TIMSS!$K$5:$K$1264,"PENDIENTE") -> 68 | F27: =IF(E27=0,0,D27/E27) -> 0.5 | G27: 0.35 | H27: =G27*E27 -> 23.8 | I27: =H27-D27 -> -10.2 | J27: =(G27-F27)*100 -> -15 | K27: =IF(ABS(G27-F27)<=$H$2,"En meta",IF(I27>0,"Faltan "&ROUND(I27,0)&" temas","Sobran "&ROUND(-I27,0)&" temas")) -> Sobran 10 temas | L27: =MAX(D27/G27,D28/G28,D29/G29,D30/G30) -> 104 | M27: =MAX(0,ROUNDUP(G27*L27-D27,0)) -> 3 | N27: =COUNTIFS(Temas_TIMSS!$V$5:$V$1264,$A27,Temas_TIMSS!$K$5:$K$1264,"FUERA") -> 0
A28: 6° | B28: TIMSS 2023 8.° | C28: Química | D28: =COUNTIFS(Temas_TIMSS!$V$5:$V$1264,$A28,Temas_TIMSS!$M$5:$M$1264,$C28) -> 8 | E28: =COUNTIFS(Temas_TIMSS!$V$5:$V$1264,$A28)-COUNTIFS(Temas_TIMSS!$V$5:$V$1264,$A28,Temas_TIMSS!$K$5:$K$1264,"FUERA")-COUNTIFS(Temas_TIMSS!$V$5:$V$1264,$A28,Temas_TIMSS!$K$5:$K$1264,"PENDIENTE") -> 68 | F28: =IF(E28=0,0,D28/E28) -> 0.11764706 | G28: 0.2 | H28: =G28*E28 -> 13.6 | I28: =H28-D28 -> 5.6 | J28: =(G28-F28)*100 -> 8.2352941 | K28: =IF(ABS(G28-F28)<=$H$2,"En meta",IF(I28>0,"Faltan "&ROUND(I28,0)&" temas","Sobran "&ROUND(-I28,0)&" temas")) -> Faltan 6 temas | L28: =MAX(D27/G27,D28/G28,D29/G29,D30/G30) -> 104 | M28: =MAX(0,ROUNDUP(G28*L28-D28,0)) -> 13 | N28: =COUNTIFS(Temas_TIMSS!$V$5:$V$1264,$A28,Temas_TIMSS!$K$5:$K$1264,"FUERA") -> 0
A29: 6° | B29: TIMSS 2023 8.° | C29: Física | D29: =COUNTIFS(Temas_TIMSS!$V$5:$V$1264,$A29,Temas_TIMSS!$M$5:$M$1264,$C29) -> 26 | E29: =COUNTIFS(Temas_TIMSS!$V$5:$V$1264,$A29)-COUNTIFS(Temas_TIMSS!$V$5:$V$1264,$A29,Temas_TIMSS!$K$5:$K$1264,"FUERA")-COUNTIFS(Temas_TIMSS!$V$5:$V$1264,$A29,Temas_TIMSS!$K$5:$K$1264,"PENDIENTE") -> 68 | F29: =IF(E29=0,0,D29/E29) -> 0.38235294 | G29: 0.25 | H29: =G29*E29 -> 17 | I29: =H29-D29 -> -9 | J29: =(G29-F29)*100 -> -13.235294 | K29: =IF(ABS(G29-F29)<=$H$2,"En meta",IF(I29>0,"Faltan "&ROUND(I29,0)&" temas","Sobran "&ROUND(-I29,0)&" temas")) -> Sobran 9 temas | L29: =MAX(D27/G27,D28/G28,D29/G29,D30/G30) -> 104 | M29: =MAX(0,ROUNDUP(G29*L29-D29,0)) -> 0 | N29: =COUNTIFS(Temas_TIMSS!$V$5:$V$1264,$A29,Temas_TIMSS!$K$5:$K$1264,"FUERA") -> 0
A30: 6° | B30: TIMSS 2023 8.° | C30: Ciencias de la Tierra | D30: =COUNTIFS(Temas_TIMSS!$V$5:$V$1264,$A30,Temas_TIMSS!$M$5:$M$1264,$C30) -> 0 | E30: =COUNTIFS(Temas_TIMSS!$V$5:$V$1264,$A30)-COUNTIFS(Temas_TIMSS!$V$5:$V$1264,$A30,Temas_TIMSS!$K$5:$K$1264,"FUERA")-COUNTIFS(Temas_TIMSS!$V$5:$V$1264,$A30,Temas_TIMSS!$K$5:$K$1264,"PENDIENTE") -> 68 | F30: =IF(E30=0,0,D30/E30) -> 0 | G30: 0.2 | H30: =G30*E30 -> 13.6 | I30: =H30-D30 -> 13.6 | J30: =(G30-F30)*100 -> 20 | K30: =IF(ABS(G30-F30)<=$H$2,"En meta",IF(I30>0,"Faltan "&ROUND(I30,0)&" temas","Sobran "&ROUND(-I30,0)&" temas")) -> Faltan 14 temas | L30: =MAX(D27/G27,D28/G28,D29/G29,D30/G30) -> 104 | M30: =MAX(0,ROUNDUP(G30*L30-D30,0)) -> 21 | N30: =COUNTIFS(Temas_TIMSS!$V$5:$V$1264,$A30,Temas_TIMSS!$K$5:$K$1264,"FUERA") -> 0
C31: Total del grupo | D31: =SUM(D27:D30) -> 68 | G31: =SUM(G27:G30) -> 1 | M31: =SUM(M27:M30) -> 37
A33: 7° | B33: TIMSS 2023 8.° | C33: Biología | D33: =COUNTIFS(Temas_TIMSS!$V$5:$V$1264,$A33,Temas_TIMSS!$M$5:$M$1264,$C33) -> 48 | E33: =COUNTIFS(Temas_TIMSS!$V$5:$V$1264,$A33)-COUNTIFS(Temas_TIMSS!$V$5:$V$1264,$A33,Temas_TIMSS!$K$5:$K$1264,"FUERA")-COUNTIFS(Temas_TIMSS!$V$5:$V$1264,$A33,Temas_TIMSS!$K$5:$K$1264,"PENDIENTE") -> 85 | F33: =IF(E33=0,0,D33/E33) -> 0.56470588 | G33: 0.35 | H33: =G33*E33 -> 29.75 | I33: =H33-D33 -> -18.25 | J33: =(G33-F33)*100 -> -21.470588 | K33: =IF(ABS(G33-F33)<=$H$2,"En meta",IF(I33>0,"Faltan "&ROUND(I33,0)&" temas","Sobran "&ROUND(-I33,0)&" temas")) -> Sobran 18 temas | L33: =MAX(D33/G33,D34/G34,D35/G35,D36/G36) -> 137.14286 | M33: =MAX(0,ROUNDUP(G33*L33-D33,0)) -> 0 | N33: =COUNTIFS(Temas_TIMSS!$V$5:$V$1264,$A33,Temas_TIMSS!$K$5:$K$1264,"FUERA") -> 6
A34: 7° | B34: TIMSS 2023 8.° | C34: Química | D34: =COUNTIFS(Temas_TIMSS!$V$5:$V$1264,$A34,Temas_TIMSS!$M$5:$M$1264,$C34) -> 8 | E34: =COUNTIFS(Temas_TIMSS!$V$5:$V$1264,$A34)-COUNTIFS(Temas_TIMSS!$V$5:$V$1264,$A34,Temas_TIMSS!$K$5:$K$1264,"FUERA")-COUNTIFS(Temas_TIMSS!$V$5:$V$1264,$A34,Temas_TIMSS!$K$5:$K$1264,"PENDIENTE") -> 85 | F34: =IF(E34=0,0,D34/E34) -> 0.094117647 | G34: 0.2 | H34: =G34*E34 -> 17 | I34: =H34-D34 -> 9 | J34: =(G34-F34)*100 -> 10.588235 | K34: =IF(ABS(G34-F34)<=$H$2,"En meta",IF(I34>0,"Faltan "&ROUND(I34,0)&" temas","Sobran "&ROUND(-I34,0)&" temas")) -> Faltan 9 temas | L34: =MAX(D33/G33,D34/G34,D35/G35,D36/G36) -> 137.14286 | M34: =MAX(0,ROUNDUP(G34*L34-D34,0)) -> 20 | N34: =COUNTIFS(Temas_TIMSS!$V$5:$V$1264,$A34,Temas_TIMSS!$K$5:$K$1264,"FUERA") -> 6
A35: 7° | B35: TIMSS 2023 8.° | C35: Física | D35: =COUNTIFS(Temas_TIMSS!$V$5:$V$1264,$A35,Temas_TIMSS!$M$5:$M$1264,$C35) -> 3 | E35: =COUNTIFS(Temas_TIMSS!$V$5:$V$1264,$A35)-COUNTIFS(Temas_TIMSS!$V$5:$V$1264,$A35,Temas_TIMSS!$K$5:$K$1264,"FUERA")-COUNTIFS(Temas_TIMSS!$V$5:$V$1264,$A35,Temas_TIMSS!$K$5:$K$1264,"PENDIENTE") -> 85 | F35: =IF(E35=0,0,D35/E35) -> 0.035294118 | G35: 0.25 | H35: =G35*E35 -> 21.25 | I35: =H35-D35 -> 18.25 | J35: =(G35-F35)*100 -> 21.470588 | K35: =IF(ABS(G35-F35)<=$H$2,"En meta",IF(I35>0,"Faltan "&ROUND(I35,0)&" temas","Sobran "&ROUND(-I35,0)&" temas")) -> Faltan 18 temas | L35: =MAX(D33/G33,D34/G34,D35/G35,D36/G36) -> 137.14286 | M35: =MAX(0,ROUNDUP(G35*L35-D35,0)) -> 32 | N35: =COUNTIFS(Temas_TIMSS!$V$5:$V$1264,$A35,Temas_TIMSS!$K$5:$K$1264,"FUERA") -> 6
A36: 7° | B36: TIMSS 2023 8.° | C36: Ciencias de la Tierra | D36: =COUNTIFS(Temas_TIMSS!$V$5:$V$1264,$A36,Temas_TIMSS!$M$5:$M$1264,$C36) -> 26 | E36: =COUNTIFS(Temas_TIMSS!$V$5:$V$1264,$A36)-COUNTIFS(Temas_TIMSS!$V$5:$V$1264,$A36,Temas_TIMSS!$K$5:$K$1264,"FUERA")-COUNTIFS(Temas_TIMSS!$V$5:$V$1264,$A36,Temas_TIMSS!$K$5:$K$1264,"PENDIENTE") -> 85 | F36: =IF(E36=0,0,D36/E36) -> 0.30588235 | G36: 0.2 | H36: =G36*E36 -> 17 | I36: =H36-D36 -> -9 | J36: =(G36-F36)*100 -> -10.588235 | K36: =IF(ABS(G36-F36)<=$H$2,"En meta",IF(I36>0,"Faltan "&ROUND(I36,0)&" temas","Sobran "&ROUND(-I36,0)&" temas")) -> Sobran 9 temas | L36: =MAX(D33/G33,D34/G34,D35/G35,D36/G36) -> 137.14286 | M36: =MAX(0,ROUNDUP(G36*L36-D36,0)) -> 2 | N36: =COUNTIFS(Temas_TIMSS!$V$5:$V$1264,$A36,Temas_TIMSS!$K$5:$K$1264,"FUERA") -> 6
C37: Total del grupo | D37: =SUM(D33:D36) -> 85 | G37: =SUM(G33:G36) -> 1 | M37: =SUM(M33:M36) -> 54
A39: 8° | B39: TIMSS 2023 8.° | C39: Biología | D39: =COUNTIFS(Temas_TIMSS!$V$5:$V$1264,$A39,Temas_TIMSS!$M$5:$M$1264,$C39) -> 28 | E39: =COUNTIFS(Temas_TIMSS!$V$5:$V$1264,$A39)-COUNTIFS(Temas_TIMSS!$V$5:$V$1264,$A39,Temas_TIMSS!$K$5:$K$1264,"FUERA")-COUNTIFS(Temas_TIMSS!$V$5:$V$1264,$A39,Temas_TIMSS!$K$5:$K$1264,"PENDIENTE") -> 91 | F39: =IF(E39=0,0,D39/E39) -> 0.30769231 | G39: 0.35 | H39: =G39*E39 -> 31.85 | I39: =H39-D39 -> 3.85 | J39: =(G39-F39)*100 -> 4.2307692 | K39: =IF(ABS(G39-F39)<=$H$2,"En meta",IF(I39>0,"Faltan "&ROUND(I39,0)&" temas","Sobran "&ROUND(-I39,0)&" temas")) -> En meta | L39: =MAX(D39/G39,D40/G40,D41/G41,D42/G42) -> 140 | M39: =MAX(0,ROUNDUP(G39*L39-D39,0)) -> 21 | N39: =COUNTIFS(Temas_TIMSS!$V$5:$V$1264,$A39,Temas_TIMSS!$K$5:$K$1264,"FUERA") -> 2
A40: 8° | B40: TIMSS 2023 8.° | C40: Química | D40: =COUNTIFS(Temas_TIMSS!$V$5:$V$1264,$A40,Temas_TIMSS!$M$5:$M$1264,$C40) -> 24 | E40: =COUNTIFS(Temas_TIMSS!$V$5:$V$1264,$A40)-COUNTIFS(Temas_TIMSS!$V$5:$V$1264,$A40,Temas_TIMSS!$K$5:$K$1264,"FUERA")-COUNTIFS(Temas_TIMSS!$V$5:$V$1264,$A40,Temas_TIMSS!$K$5:$K$1264,"PENDIENTE") -> 91 | F40: =IF(E40=0,0,D40/E40) -> 0.26373626 | G40: 0.2 | H40: =G40*E40 -> 18.2 | I40: =H40-D40 -> -5.8 | J40: =(G40-F40)*100 -> -6.3736264 | K40: =IF(ABS(G40-F40)<=$H$2,"En meta",IF(I40>0,"Faltan "&ROUND(I40,0)&" temas","Sobran "&ROUND(-I40,0)&" temas")) -> Sobran 6 temas | L40: =MAX(D39/G39,D40/G40,D41/G41,D42/G42) -> 140 | M40: =MAX(0,ROUNDUP(G40*L40-D40,0)) -> 4 | N40: =COUNTIFS(Temas_TIMSS!$V$5:$V$1264,$A40,Temas_TIMSS!$K$5:$K$1264,"FUERA") -> 2
A41: 8° | B41: TIMSS 2023 8.° | C41: Física | D41: =COUNTIFS(Temas_TIMSS!$V$5:$V$1264,$A41,Temas_TIMSS!$M$5:$M$1264,$C41) -> 35 | E41: =COUNTIFS(Temas_TIMSS!$V$5:$V$1264,$A41)-COUNTIFS(Temas_TIMSS!$V$5:$V$1264,$A41,Temas_TIMSS!$K$5:$K$1264,"FUERA")-COUNTIFS(Temas_TIMSS!$V$5:$V$1264,$A41,Temas_TIMSS!$K$5:$K$1264,"PENDIENTE") -> 91 | F41: =IF(E41=0,0,D41/E41) -> 0.38461538 | G41: 0.25 | H41: =G41*E41 -> 22.75 | I41: =H41-D41 -> -12.25 | J41: =(G41-F41)*100 -> -13.461538 | K41: =IF(ABS(G41-F41)<=$H$2,"En meta",IF(I41>0,"Faltan "&ROUND(I41,0)&" temas","Sobran "&ROUND(-I41,0)&" temas")) -> Sobran 12 temas | L41: =MAX(D39/G39,D40/G40,D41/G41,D42/G42) -> 140 | M41: =MAX(0,ROUNDUP(G41*L41-D41,0)) -> 0 | N41: =COUNTIFS(Temas_TIMSS!$V$5:$V$1264,$A41,Temas_TIMSS!$K$5:$K$1264,"FUERA") -> 2
A42: 8° | B42: TIMSS 2023 8.° | C42: Ciencias de la Tierra | D42: =COUNTIFS(Temas_TIMSS!$V$5:$V$1264,$A42,Temas_TIMSS!$M$5:$M$1264,$C42) -> 4 | E42: =COUNTIFS(Temas_TIMSS!$V$5:$V$1264,$A42)-COUNTIFS(Temas_TIMSS!$V$5:$V$1264,$A42,Temas_TIMSS!$K$5:$K$1264,"FUERA")-COUNTIFS(Temas_TIMSS!$V$5:$V$1264,$A42,Temas_TIMSS!$K$5:$K$1264,"PENDIENTE") -> 91 | F42: =IF(E42=0,0,D42/E42) -> 0.043956044 | G42: 0.2 | H42: =G42*E42 -> 18.2 | I42: =H42-D42 -> 14.2 | J42: =(G42-F42)*100 -> 15.604396 | K42: =IF(ABS(G42-F42)<=$H$2,"En meta",IF(I42>0,"Faltan "&ROUND(I42,0)&" temas","Sobran "&ROUND(-I42,0)&" temas")) -> Faltan 14 temas | L42: =MAX(D39/G39,D40/G40,D41/G41,D42/G42) -> 140 | M42: =MAX(0,ROUNDUP(G42*L42-D42,0)) -> 24 | N42: =COUNTIFS(Temas_TIMSS!$V$5:$V$1264,$A42,Temas_TIMSS!$K$5:$K$1264,"FUERA") -> 2
C43: Total del grupo | D43: =SUM(D39:D42) -> 91 | G43: =SUM(G39:G42) -> 1 | M43: =SUM(M39:M42) -> 49
A45: 9° | B45: TIMSS 2023 8.° | C45: Biología | D45: =COUNTIFS(Temas_TIMSS!$V$5:$V$1264,$A45,Temas_TIMSS!$M$5:$M$1264,$C45) -> 4 | E45: =COUNTIFS(Temas_TIMSS!$V$5:$V$1264,$A45)-COUNTIFS(Temas_TIMSS!$V$5:$V$1264,$A45,Temas_TIMSS!$K$5:$K$1264,"FUERA")-COUNTIFS(Temas_TIMSS!$V$5:$V$1264,$A45,Temas_TIMSS!$K$5:$K$1264,"PENDIENTE") -> 82 | F45: =IF(E45=0,0,D45/E45) -> 0.048780488 | G45: 0.35 | H45: =G45*E45 -> 28.7 | I45: =H45-D45 -> 24.7 | J45: =(G45-F45)*100 -> 30.121951 | K45: =IF(ABS(G45-F45)<=$H$2,"En meta",IF(I45>0,"Faltan "&ROUND(I45,0)&" temas","Sobran "&ROUND(-I45,0)&" temas")) -> Faltan 25 temas | L45: =MAX(D45/G45,D46/G46,D47/G47,D48/G48) -> 152 | M45: =MAX(0,ROUNDUP(G45*L45-D45,0)) -> 50 | N45: =COUNTIFS(Temas_TIMSS!$V$5:$V$1264,$A45,Temas_TIMSS!$K$5:$K$1264,"FUERA") -> 8
A46: 9° | B46: TIMSS 2023 8.° | C46: Química | D46: =COUNTIFS(Temas_TIMSS!$V$5:$V$1264,$A46,Temas_TIMSS!$M$5:$M$1264,$C46) -> 20 | E46: =COUNTIFS(Temas_TIMSS!$V$5:$V$1264,$A46)-COUNTIFS(Temas_TIMSS!$V$5:$V$1264,$A46,Temas_TIMSS!$K$5:$K$1264,"FUERA")-COUNTIFS(Temas_TIMSS!$V$5:$V$1264,$A46,Temas_TIMSS!$K$5:$K$1264,"PENDIENTE") -> 82 | F46: =IF(E46=0,0,D46/E46) -> 0.24390244 | G46: 0.2 | H46: =G46*E46 -> 16.4 | I46: =H46-D46 -> -3.6 | J46: =(G46-F46)*100 -> -4.3902439 | K46: =IF(ABS(G46-F46)<=$H$2,"En meta",IF(I46>0,"Faltan "&ROUND(I46,0)&" temas","Sobran "&ROUND(-I46,0)&" temas")) -> En meta | L46: =MAX(D45/G45,D46/G46,D47/G47,D48/G48) -> 152 | M46: =MAX(0,ROUNDUP(G46*L46-D46,0)) -> 11 | N46: =COUNTIFS(Temas_TIMSS!$V$5:$V$1264,$A46,Temas_TIMSS!$K$5:$K$1264,"FUERA") -> 8
A47: 9° | B47: TIMSS 2023 8.° | C47: Física | D47: =COUNTIFS(Temas_TIMSS!$V$5:$V$1264,$A47,Temas_TIMSS!$M$5:$M$1264,$C47) -> 38 | E47: =COUNTIFS(Temas_TIMSS!$V$5:$V$1264,$A47)-COUNTIFS(Temas_TIMSS!$V$5:$V$1264,$A47,Temas_TIMSS!$K$5:$K$1264,"FUERA")-COUNTIFS(Temas_TIMSS!$V$5:$V$1264,$A47,Temas_TIMSS!$K$5:$K$1264,"PENDIENTE") -> 82 | F47: =IF(E47=0,0,D47/E47) -> 0.46341463 | G47: 0.25 | H47: =G47*E47 -> 20.5 | I47: =H47-D47 -> -17.5 | J47: =(G47-F47)*100 -> -21.341463 | K47: =IF(ABS(G47-F47)<=$H$2,"En meta",IF(I47>0,"Faltan "&ROUND(I47,0)&" temas","Sobran "&ROUND(-I47,0)&" temas")) -> Sobran 18 temas | L47: =MAX(D45/G45,D46/G46,D47/G47,D48/G48) -> 152 | M47: =MAX(0,ROUNDUP(G47*L47-D47,0)) -> 0 | N47: =COUNTIFS(Temas_TIMSS!$V$5:$V$1264,$A47,Temas_TIMSS!$K$5:$K$1264,"FUERA") -> 8
A48: 9° | B48: TIMSS 2023 8.° | C48: Ciencias de la Tierra | D48: =COUNTIFS(Temas_TIMSS!$V$5:$V$1264,$A48,Temas_TIMSS!$M$5:$M$1264,$C48) -> 20 | E48: =COUNTIFS(Temas_TIMSS!$V$5:$V$1264,$A48)-COUNTIFS(Temas_TIMSS!$V$5:$V$1264,$A48,Temas_TIMSS!$K$5:$K$1264,"FUERA")-COUNTIFS(Temas_TIMSS!$V$5:$V$1264,$A48,Temas_TIMSS!$K$5:$K$1264,"PENDIENTE") -> 82 | F48: =IF(E48=0,0,D48/E48) -> 0.24390244 | G48: 0.2 | H48: =G48*E48 -> 16.4 | I48: =H48-D48 -> -3.6 | J48: =(G48-F48)*100 -> -4.3902439 | K48: =IF(ABS(G48-F48)<=$H$2,"En meta",IF(I48>0,"Faltan "&ROUND(I48,0)&" temas","Sobran "&ROUND(-I48,0)&" temas")) -> En meta | L48: =MAX(D45/G45,D46/G46,D47/G47,D48/G48) -> 152 | M48: =MAX(0,ROUNDUP(G48*L48-D48,0)) -> 11 | N48: =COUNTIFS(Temas_TIMSS!$V$5:$V$1264,$A48,Temas_TIMSS!$K$5:$K$1264,"FUERA") -> 8
C49: Total del grupo | D49: =SUM(D45:D48) -> 82 | G49: =SUM(G45:G48) -> 1 | M49: =SUM(M45:M48) -> 72
A51: Física 10° | B51: TIMSS Advanced 2015 Física | C51: Mecánica y termodinámica | D51: =COUNTIFS(Temas_TIMSS!$V$5:$V$1264,$A51,Temas_TIMSS!$M$5:$M$1264,$C51) -> 67 | E51: =COUNTIFS(Temas_TIMSS!$V$5:$V$1264,$A51)-COUNTIFS(Temas_TIMSS!$V$5:$V$1264,$A51,Temas_TIMSS!$K$5:$K$1264,"FUERA")-COUNTIFS(Temas_TIMSS!$V$5:$V$1264,$A51,Temas_TIMSS!$K$5:$K$1264,"PENDIENTE") -> 80 | F51: =IF(E51=0,0,D51/E51) -> 0.8375 | G51: 0.4 | H51: =G51*E51 -> 32 | I51: =H51-D51 -> -35 | J51: =(G51-F51)*100 -> -43.75 | K51: =IF(ABS(G51-F51)<=$H$2,"En meta",IF(I51>0,"Faltan "&ROUND(I51,0)&" temas","Sobran "&ROUND(-I51,0)&" temas")) -> Sobran 35 temas | L51: =MAX(D51/G51,D52/G52,D53/G53) -> 167.5 | M51: =MAX(0,ROUNDUP(G51*L51-D51,0)) -> 0 | N51: =COUNTIFS(Temas_TIMSS!$V$5:$V$1264,$A51,Temas_TIMSS!$K$5:$K$1264,"FUERA") -> 41
A52: Física 10° | B52: TIMSS Advanced 2015 Física | C52: Electricidad y magnetismo | D52: =COUNTIFS(Temas_TIMSS!$V$5:$V$1264,$A52,Temas_TIMSS!$M$5:$M$1264,$C52) -> 0 | E52: =COUNTIFS(Temas_TIMSS!$V$5:$V$1264,$A52)-COUNTIFS(Temas_TIMSS!$V$5:$V$1264,$A52,Temas_TIMSS!$K$5:$K$1264,"FUERA")-COUNTIFS(Temas_TIMSS!$V$5:$V$1264,$A52,Temas_TIMSS!$K$5:$K$1264,"PENDIENTE") -> 80 | F52: =IF(E52=0,0,D52/E52) -> 0 | G52: 0.25 | H52: =G52*E52 -> 20 | I52: =H52-D52 -> 20 | J52: =(G52-F52)*100 -> 25 | K52: =IF(ABS(G52-F52)<=$H$2,"En meta",IF(I52>0,"Faltan "&ROUND(I52,0)&" temas","Sobran "&ROUND(-I52,0)&" temas")) -> Faltan 20 temas | L52: =MAX(D51/G51,D52/G52,D53/G53) -> 167.5 | M52: =MAX(0,ROUNDUP(G52*L52-D52,0)) -> 42 | N52: =COUNTIFS(Temas_TIMSS!$V$5:$V$1264,$A52,Temas_TIMSS!$K$5:$K$1264,"FUERA") -> 41
A53: Física 10° | B53: TIMSS Advanced 2015 Física | C53: Ondas y física atómica/nuclear | D53: =COUNTIFS(Temas_TIMSS!$V$5:$V$1264,$A53,Temas_TIMSS!$M$5:$M$1264,$C53) -> 13 | E53: =COUNTIFS(Temas_TIMSS!$V$5:$V$1264,$A53)-COUNTIFS(Temas_TIMSS!$V$5:$V$1264,$A53,Temas_TIMSS!$K$5:$K$1264,"FUERA")-COUNTIFS(Temas_TIMSS!$V$5:$V$1264,$A53,Temas_TIMSS!$K$5:$K$1264,"PENDIENTE") -> 80 | F53: =IF(E53=0,0,D53/E53) -> 0.1625 | G53: 0.35 | H53: =G53*E53 -> 28 | I53: =H53-D53 -> 15 | J53: =(G53-F53)*100 -> 18.75 | K53: =IF(ABS(G53-F53)<=$H$2,"En meta",IF(I53>0,"Faltan "&ROUND(I53,0)&" temas","Sobran "&ROUND(-I53,0)&" temas")) -> Faltan 15 temas | L53: =MAX(D51/G51,D52/G52,D53/G53) -> 167.5 | M53: =MAX(0,ROUNDUP(G53*L53-D53,0)) -> 46 | N53: =COUNTIFS(Temas_TIMSS!$V$5:$V$1264,$A53,Temas_TIMSS!$K$5:$K$1264,"FUERA") -> 41
C54: Total del grupo | D54: =SUM(D51:D53) -> 80 | G54: =SUM(G51:G53) -> 1 | M54: =SUM(M51:M53) -> 88
A56: Física 11° | B56: TIMSS Advanced 2015 Física | C56: Mecánica y termodinámica | D56: =COUNTIFS(Temas_TIMSS!$V$5:$V$1264,$A56,Temas_TIMSS!$M$5:$M$1264,$C56) -> 4 | E56: =COUNTIFS(Temas_TIMSS!$V$5:$V$1264,$A56)-COUNTIFS(Temas_TIMSS!$V$5:$V$1264,$A56,Temas_TIMSS!$K$5:$K$1264,"FUERA")-COUNTIFS(Temas_TIMSS!$V$5:$V$1264,$A56,Temas_TIMSS!$K$5:$K$1264,"PENDIENTE") -> 119 | F56: =IF(E56=0,0,D56/E56) -> 0.033613445 | G56: 0.4 | H56: =G56*E56 -> 47.6 | I56: =H56-D56 -> 43.6 | J56: =(G56-F56)*100 -> 36.638655 | K56: =IF(ABS(G56-F56)<=$H$2,"En meta",IF(I56>0,"Faltan "&ROUND(I56,0)&" temas","Sobran "&ROUND(-I56,0)&" temas")) -> Faltan 44 temas | L56: =MAX(D56/G56,D57/G57,D58/G58) -> 205.71429 | M56: =MAX(0,ROUNDUP(G56*L56-D56,0)) -> 79 | N56: =COUNTIFS(Temas_TIMSS!$V$5:$V$1264,$A56,Temas_TIMSS!$K$5:$K$1264,"FUERA") -> 27
A57: Física 11° | B57: TIMSS Advanced 2015 Física | C57: Electricidad y magnetismo | D57: =COUNTIFS(Temas_TIMSS!$V$5:$V$1264,$A57,Temas_TIMSS!$M$5:$M$1264,$C57) -> 43 | E57: =COUNTIFS(Temas_TIMSS!$V$5:$V$1264,$A57)-COUNTIFS(Temas_TIMSS!$V$5:$V$1264,$A57,Temas_TIMSS!$K$5:$K$1264,"FUERA")-COUNTIFS(Temas_TIMSS!$V$5:$V$1264,$A57,Temas_TIMSS!$K$5:$K$1264,"PENDIENTE") -> 119 | F57: =IF(E57=0,0,D57/E57) -> 0.36134454 | G57: 0.25 | H57: =G57*E57 -> 29.75 | I57: =H57-D57 -> -13.25 | J57: =(G57-F57)*100 -> -11.134454 | K57: =IF(ABS(G57-F57)<=$H$2,"En meta",IF(I57>0,"Faltan "&ROUND(I57,0)&" temas","Sobran "&ROUND(-I57,0)&" temas")) -> Sobran 13 temas | L57: =MAX(D56/G56,D57/G57,D58/G58) -> 205.71429 | M57: =MAX(0,ROUNDUP(G57*L57-D57,0)) -> 9 | N57: =COUNTIFS(Temas_TIMSS!$V$5:$V$1264,$A57,Temas_TIMSS!$K$5:$K$1264,"FUERA") -> 27
A58: Física 11° | B58: TIMSS Advanced 2015 Física | C58: Ondas y física atómica/nuclear | D58: =COUNTIFS(Temas_TIMSS!$V$5:$V$1264,$A58,Temas_TIMSS!$M$5:$M$1264,$C58) -> 72 | E58: =COUNTIFS(Temas_TIMSS!$V$5:$V$1264,$A58)-COUNTIFS(Temas_TIMSS!$V$5:$V$1264,$A58,Temas_TIMSS!$K$5:$K$1264,"FUERA")-COUNTIFS(Temas_TIMSS!$V$5:$V$1264,$A58,Temas_TIMSS!$K$5:$K$1264,"PENDIENTE") -> 119 | F58: =IF(E58=0,0,D58/E58) -> 0.60504202 | G58: 0.35 | H58: =G58*E58 -> 41.65 | I58: =H58-D58 -> -30.35 | J58: =(G58-F58)*100 -> -25.504202 | K58: =IF(ABS(G58-F58)<=$H$2,"En meta",IF(I58>0,"Faltan "&ROUND(I58,0)&" temas","Sobran "&ROUND(-I58,0)&" temas")) -> Sobran 30 temas | L58: =MAX(D56/G56,D57/G57,D58/G58) -> 205.71429 | M58: =MAX(0,ROUNDUP(G58*L58-D58,0)) -> 0 | N58: =COUNTIFS(Temas_TIMSS!$V$5:$V$1264,$A58,Temas_TIMSS!$K$5:$K$1264,"FUERA") -> 27
C59: Total del grupo | D59: =SUM(D56:D58) -> 119 | G59: =SUM(G56:G58) -> 1 | M59: =SUM(M56:M58) -> 88

Sheet Cobertura_objetivos
A1: Amplitud: ¿qué objetivos TIMSS cubre la malla y en qué grado?
A2: Cada celda de grado = n.º de temas de ese grado que trabajan el objetivo como principal o secundario (COUNTIFS sobre Temas_TIMSS). «Total en su ciclo» suma solo los grados que evalúa cada marco: TIMSS 4.° → 2.°–4.°; TIMSS 8.° → 5.°–8.° (la columna 9.° es referencia); TIMSS Advanced → Física 10.°–11.°. «Profundidad»: 0 = no cubierto; 1 = débil; 2–3 = básica; 4+ = sólida.
A4: Código | B4: Marco | C4: Dominio | D4: Área temática | E4: Objetivo | F4: 2° | G4: 3° | H4: 4° | I4: 5° | J4: 6° | K4: 7° | L4: 8° | M4: 9° | N4: Física 10° | O4: Física 11° | P4: Total temas en su ciclo | Q4: Como principal (todos los grados) | R4: Cubierto en su ciclo | S4: Profundidad en su ciclo | T4: Primer grado donde aparece
A5: T4-V1.1 | B5: T4 | C5: Ciencias de la vida | D5: Características y procesos vitales de los organismos | E5: Distinguir seres vivos de no vivos; reconocer lo que necesitan para vivir | F5: =COUNTIFS(Temas_TIMSS!$V$5:$V$1264,F$4,Temas_TIMSS!$K$5:$K$1264,$A5)+COUNTIFS(Temas_TIMSS!$V$5:$V$1264,F$4,Temas_TIMSS!$L$5:$L$1264,$A5) -> 5 | G5: =COUNTIFS(Temas_TIMSS!$V$5:$V$1264,G$4,Temas_TIMSS!$K$5:$K$1264,$A5)+COUNTIFS(Temas_TIMSS!$V$5:$V$1264,G$4,Temas_TIMSS!$L$5:$L$1264,$A5) -> 5 | H5: =COUNTIFS(Temas_TIMSS!$V$5:$V$1264,H$4,Temas_TIMSS!$K$5:$K$1264,$A5)+COUNTIFS(Temas_TIMSS!$V$5:$V$1264,H$4,Temas_TIMSS!$L$5:$L$1264,$A5) -> 3 | I5: =COUNTIFS(Temas_TIMSS!$V$5:$V$1264,I$4,Temas_TIMSS!$K$5:$K$1264,$A5)+COUNTIFS(Temas_TIMSS!$V$5:$V$1264,I$4,Temas_TIMSS!$L$5:$L$1264,$A5) -> 0 | J5: =COUNTIFS(Temas_TIMSS!$V$5:$V$1264,J$4,Temas_TIMSS!$K$5:$K$1264,$A5)+COUNTIFS(Temas_TIMSS!$V$5:$V$1264,J$4,Temas_TIMSS!$L$5:$L$1264,$A5) -> 0 | K5: =COUNTIFS(Temas_TIMSS!$V$5:$V$1264,K$4,Temas_TIMSS!$K$5:$K$1264,$A5)+COUNTIFS(Temas_TIMSS!$V$5:$V$1264,K$4,Temas_TIMSS!$L$5:$L$1264,$A5) -> 0 | L5: =COUNTIFS(Temas_TIMSS!$V$5:$V$1264,L$4,Temas_TIMSS!$K$5:$K$1264,$A5)+COUNTIFS(Temas_TIMSS!$V$5:$V$1264,L$4,Temas_TIMSS!$L$5:$L$1264,$A5) -> 0 | M5: =COUNTIFS(Temas_TIMSS!$V$5:$V$1264,M$4,Temas_TIMSS!$K$5:$K$1264,$A5)+COUNTIFS(Temas_TIMSS!$V$5:$V$1264,M$4,Temas_TIMSS!$L$5:$L$1264,$A5) -> 0 | ... O5: =COUNTIFS(Temas_TIMSS!$V$5:$V$1264,O$4,Temas_TIMSS!$K$5:$K$1264,$A5)+COUNTIFS(Temas_TIMSS!$V$5:$V$1264,O$4,Temas_TIMSS!$L$5:$L$1264,$A5) -> 0 | P5: =IF($B5="T4",SUM(F5:H5),IF($B5="T8",SUM(I5:L5),SUM(N5:O5))) -> 13 | Q5: =COUNTIFS(Temas_TIMSS!$K$5:$K$1264,$A5) -> 6 | R5: =IF(P5>0,"Sí","No") -> Sí | S5: =IF(P5=0,"No cubierto",IF(P5=1,"Débil (1 tema)",IF(P5<=3,"Básica (2–3)","Sólida (4+)"))) -> Sólida (4+) | T5: =IFERROR(INDEX($F$4:$O$4,MATCH(TRUE(),INDEX(F5:O5>0,0),0)),"—") -> 2°
A6: T4-V1.2 | B6: T4 | C6: Ciencias de la vida | D6: Características y procesos vitales de los organismos | E6: Comparar rasgos físicos y de conducta de grandes grupos de animales y plantas | F6: =COUNTIFS(Temas_TIMSS!$V$5:$V$1264,F$4,Temas_TIMSS!$K$5:$K$1264,$A6)+COUNTIFS(Temas_TIMSS!$V$5:$V$1264,F$4,Temas_TIMSS!$L$5:$L$1264,$A6) -> 6 | G6: =COUNTIFS(Temas_TIMSS!$V$5:$V$1264,G$4,Temas_TIMSS!$K$5:$K$1264,$A6)+COUNTIFS(Temas_TIMSS!$V$5:$V$1264,G$4,Temas_TIMSS!$L$5:$L$1264,$A6) -> 15 | H6: =COUNTIFS(Temas_TIMSS!$V$5:$V$1264,H$4,Temas_TIMSS!$K$5:$K$1264,$A6)+COUNTIFS(Temas_TIMSS!$V$5:$V$1264,H$4,Temas_TIMSS!$L$5:$L$1264,$A6) -> 0 | I6: =COUNTIFS(Temas_TIMSS!$V$5:$V$1264,I$4,Temas_TIMSS!$K$5:$K$1264,$A6)+COUNTIFS(Temas_TIMSS!$V$5:$V$1264,I$4,Temas_TIMSS!$L$5:$L$1264,$A6) -> 0 | J6: =COUNTIFS(Temas_TIMSS!$V$5:$V$1264,J$4,Temas_TIMSS!$K$5:$K$1264,$A6)+COUNTIFS(Temas_TIMSS!$V$5:$V$1264,J$4,Temas_TIMSS!$L$5:$L$1264,$A6) -> 0 | K6: =COUNTIFS(Temas_TIMSS!$V$5:$V$1264,K$4,Temas_TIMSS!$K$5:$K$1264,$A6)+COUNTIFS(Temas_TIMSS!$V$5:$V$1264,K$4,Temas_TIMSS!$L$5:$L$1264,$A6) -> 0 | L6: =COUNTIFS(Temas_TIMSS!$V$5:$V$1264,L$4,Temas_TIMSS!$K$5:$K$1264,$A6)+COUNTIFS(Temas_TIMSS!$V$5:$V$1264,L$4,Temas_TIMSS!$L$5:$L$1264,$A6) -> 0 | M6: =COUNTIFS(Temas_TIMSS!$V$5:$V$1264,M$4,Temas_TIMSS!$K$5:$K$1264,$A6)+COUNTIFS(Temas_TIMSS!$V$5:$V$1264,M$4,Temas_TIMSS!$L$5:$L$1264,$A6) -> 0 | ... O6: =COUNTIFS(Temas_TIMSS!$V$5:$V$1264,O$4,Temas_TIMSS!$K$5:$K$1264,$A6)+COUNTIFS(Temas_TIMSS!$V$5:$V$1264,O$4,Temas_TIMSS!$L$5:$L$1264,$A6) -> 0 | P6: =IF($B6="T4",SUM(F6:H6),IF($B6="T8",SUM(I6:L6),SUM(N6:O6))) -> 21 | Q6: =COUNTIFS(Temas_TIMSS!$K$5:$K$1264,$A6) -> 20 | R6: =IF(P6>0,"Sí","No") -> Sí | S6: =IF(P6=0,"No cubierto",IF(P6=1,"Débil (1 tema)",IF(P6<=3,"Básica (2–3)","Sólida (4+)"))) -> Sólida (4+) | T6: =IFERROR(INDEX($F$4:$O$4,MATCH(TRUE(),INDEX(F6:O6>0,0),0)),"—") -> 2°
A7: T4-V1.3 | B7: T4 | C7: Ciencias de la vida | D7: Características y procesos vitales de los organismos | E7: Relacionar estructuras principales de los organismos con su función | F7: =COUNTIFS(Temas_TIMSS!$V$5:$V$1264,F$4,Temas_TIMSS!$K$5:$K$1264,$A7)+COUNTIFS(Temas_TIMSS!$V$5:$V$1264,F$4,Temas_TIMSS!$L$5:$L$1264,$A7) -> 2 | G7: =COUNTIFS(Temas_TIMSS!$V$5:$V$1264,G$4,Temas_TIMSS!$K$5:$K$1264,$A7)+COUNTIFS(Temas_TIMSS!$V$5:$V$1264,G$4,Temas_TIMSS!$L$5:$L$1264,$A7) -> 4 | H7: =COUNTIFS(Temas_TIMSS!$V$5:$V$1264,H$4,Temas_TIMSS!$K$5:$K$1264,$A7)+COUNTIFS(Temas_TIMSS!$V$5:$V$1264,H$4,Temas_TIMSS!$L$5:$L$1264,$A7) -> 18 | I7: =COUNTIFS(Temas_TIMSS!$V$5:$V$1264,I$4,Temas_TIMSS!$K$5:$K$1264,$A7)+COUNTIFS(Temas_TIMSS!$V$5:$V$1264,I$4,Temas_TIMSS!$L$5:$L$1264,$A7) -> 0 | J7: =COUNTIFS(Temas_TIMSS!$V$5:$V$1264,J$4,Temas_TIMSS!$K$5:$K$1264,$A7)+COUNTIFS(Temas_TIMSS!$V$5:$V$1264,J$4,Temas_TIMSS!$L$5:$L$1264,$A7) -> 0 | K7: =COUNTIFS(Temas_TIMSS!$V$5:$V$1264,K$4,Temas_TIMSS!$K$5:$K$1264,$A7)+COUNTIFS(Temas_TIMSS!$V$5:$V$1264,K$4,Temas_TIMSS!$L$5:$L$1264,$A7) -> 0 | L7: =COUNTIFS(Temas_TIMSS!$V$5:$V$1264,L$4,Temas_TIMSS!$K$5:$K$1264,$A7)+COUNTIFS(Temas_TIMSS!$V$5:$V$1264,L$4,Temas_TIMSS!$L$5:$L$1264,$A7) -> 0 | M7: =COUNTIFS(Temas_TIMSS!$V$5:$V$1264,M$4,Temas_TIMSS!$K$5:$K$1264,$A7)+COUNTIFS(Temas_TIMSS!$V$5:$V$1264,M$4,Temas_TIMSS!$L$5:$L$1264,$A7) -> 0 | ... O7: =COUNTIFS(Temas_TIMSS!$V$5:$V$1264,O$4,Temas_TIMSS!$K$5:$K$1264,$A7)+COUNTIFS(Temas_TIMSS!$V$5:$V$1264,O$4,Temas_TIMSS!$L$5:$L$1264,$A7) -> 0 | P7: =IF($B7="T4",SUM(F7:H7),IF($B7="T8",SUM(I7:L7),SUM(N7:O7))) -> 24 | Q7: =COUNTIFS(Temas_TIMSS!$K$5:$K$1264,$A7) -> 21 | R7: =IF(P7>0,"Sí","No") -> Sí | S7: =IF(P7=0,"No cubierto",IF(P7=1,"Débil (1 tema)",IF(P7<=3,"Básica (2–3)","Sólida (4+)"))) -> Sólida (4+) | T7: =IFERROR(INDEX($F$4:$O$4,MATCH(TRUE(),INDEX(F7:O7>0,0),0)),"—") -> 2°
A8: T4-V2.1 | B8: T4 | C8: Ciencias de la vida | D8: Ciclos de vida, reproducción y herencia | E8: Etapas del ciclo de vida de plantas con flor; comparar ciclos de plantas y animales | F8: =COUNTIFS(Temas_TIMSS!$V$5:$V$1264,F$4,Temas_TIMSS!$K$5:$K$1264,$A8)+COUNTIFS(Temas_TIMSS!$V$5:$V$1264,F$4,Temas_TIMSS!$L$5:$L$1264,$A8) -> 1 | G8: =COUNTIFS(Temas_TIMSS!$V$5:$V$1264,G$4,Temas_TIMSS!$K$5:$K$1264,$A8)+COUNTIFS(Temas_TIMSS!$V$5:$V$1264,G$4,Temas_TIMSS!$L$5:$L$1264,$A8) -> 1 | H8: =COUNTIFS(Temas_TIMSS!$V$5:$V$1264,H$4,Temas_TIMSS!$K$5:$K$1264,$A8)+COUNTIFS(Temas_TIMSS!$V$5:$V$1264,H$4,Temas_TIMSS!$L$5:$L$1264,$A8) -> 0 | I8: =COUNTIFS(Temas_TIMSS!$V$5:$V$1264,I$4,Temas_TIMSS!$K$5:$K$1264,$A8)+COUNTIFS(Temas_TIMSS!$V$5:$V$1264,I$4,Temas_TIMSS!$L$5:$L$1264,$A8) -> 0 | J8: =COUNTIFS(Temas_TIMSS!$V$5:$V$1264,J$4,Temas_TIMSS!$K$5:$K$1264,$A8)+COUNTIFS(Temas_TIMSS!$V$5:$V$1264,J$4,Temas_TIMSS!$L$5:$L$1264,$A8) -> 0 | K8: =COUNTIFS(Temas_TIMSS!$V$5:$V$1264,K$4,Temas_TIMSS!$K$5:$K$1264,$A8)+COUNTIFS(Temas_TIMSS!$V$5:$V$1264,K$4,Temas_TIMSS!$L$5:$L$1264,$A8) -> 0 | L8: =COUNTIFS(Temas_TIMSS!$V$5:$V$1264,L$4,Temas_TIMSS!$K$5:$K$1264,$A8)+COUNTIFS(Temas_TIMSS!$V$5:$V$1264,L$4,Temas_TIMSS!$L$5:$L$1264,$A8) -> 0 | M8: =COUNTIFS(Temas_TIMSS!$V$5:$V$1264,M$4,Temas_TIMSS!$K$5:$K$1264,$A8)+COUNTIFS(Temas_TIMSS!$V$5:$V$1264,M$4,Temas_TIMSS!$L$5:$L$1264,$A8) -> 0 | ... O8: =COUNTIFS(Temas_TIMSS!$V$5:$V$1264,O$4,Temas_TIMSS!$K$5:$K$1264,$A8)+COUNTIFS(Temas_TIMSS!$V$5:$V$1264,O$4,Temas_TIMSS!$L$5:$L$1264,$A8) -> 0 | P8: =IF($B8="T4",SUM(F8:H8),IF($B8="T8",SUM(I8:L8),SUM(N8:O8))) -> 2 | Q8: =COUNTIFS(Temas_TIMSS!$K$5:$K$1264,$A8) -> 2 | R8: =IF(P8>0,"Sí","No") -> Sí | S8: =IF(P8=0,"No cubierto",IF(P8=1,"Débil (1 tema)",IF(P8<=3,"Básica (2–3)","Sólida (4+)"))) -> Básica (2–3) | T8: =IFERROR(INDEX($F$4:$O$4,MATCH(TRUE(),INDEX(F8:O8>0,0),0)),"—") -> 2°
A9: T4-V2.2 | B9: T4 | C9: Ciencias de la vida | D9: Ciclos de vida, reproducción y herencia | E9: Las crías se parecen a sus progenitores; rasgos heredados vs. adquiridos | F9: =COUNTIFS(Temas_TIMSS!$V$5:$V$1264,F$4,Temas_TIMSS!$K$5:$K$1264,$A9)+COUNTIFS(Temas_TIMSS!$V$5:$V$1264,F$4,Temas_TIMSS!$L$5:$L$1264,$A9) -> 0 | G9: =COUNTIFS(Temas_TIMSS!$V$5:$V$1264,G$4,Temas_TIMSS!$K$5:$K$1264,$A9)+COUNTIFS(Temas_TIMSS!$V$5:$V$1264,G$4,Temas_TIMSS!$L$5:$L$1264,$A9) -> 0 | H9: =COUNTIFS(Temas_TIMSS!$V$5:$V$1264,H$4,Temas_TIMSS!$K$5:$K$1264,$A9)+COUNTIFS(Temas_TIMSS!$V$5:$V$1264,H$4,Temas_TIMSS!$L$5:$L$1264,$A9) -> 0 | I9: =COUNTIFS(Temas_TIMSS!$V$5:$V$1264,I$4,Temas_TIMSS!$K$5:$K$1264,$A9)+COUNTIFS(Temas_TIMSS!$V$5:$V$1264,I$4,Temas_TIMSS!$L$5:$L$1264,$A9) -> 0 | J9: =COUNTIFS(Temas_TIMSS!$V$5:$V$1264,J$4,Temas_TIMSS!$K$5:$K$1264,$A9)+COUNTIFS(Temas_TIMSS!$V$5:$V$1264,J$4,Temas_TIMSS!$L$5:$L$1264,$A9) -> 0 | K9: =COUNTIFS(Temas_TIMSS!$V$5:$V$1264,K$4,Temas_TIMSS!$K$5:$K$1264,$A9)+COUNTIFS(Temas_TIMSS!$V$5:$V$1264,K$4,Temas_TIMSS!$L$5:$L$1264,$A9) -> 0 | L9: =COUNTIFS(Temas_TIMSS!$V$5:$V$1264,L$4,Temas_TIMSS!$K$5:$K$1264,$A9)+COUNTIFS(Temas_TIMSS!$V$5:$V$1264,L$4,Temas_TIMSS!$L$5:$L$1264,$A9) -> 0 | M9: =COUNTIFS(Temas_TIMSS!$V$5:$V$1264,M$4,Temas_TIMSS!$K$5:$K$1264,$A9)+COUNTIFS(Temas_TIMSS!$V$5:$V$1264,M$4,Temas_TIMSS!$L$5:$L$1264,$A9) -> 0 | ... O9: =COUNTIFS(Temas_TIMSS!$V$5:$V$1264,O$4,Temas_TIMSS!$K$5:$K$1264,$A9)+COUNTIFS(Temas_TIMSS!$V$5:$V$1264,O$4,Temas_TIMSS!$L$5:$L$1264,$A9) -> 0 | P9: =IF($B9="T4",SUM(F9:H9),IF($B9="T8",SUM(I9:L9),SUM(N9:O9))) -> 0 | Q9: =COUNTIFS(Temas_TIMSS!$K$5:$K$1264,$A9) -> 0 | R9: =IF(P9>0,"Sí","No") -> No | S9: =IF(P9=0,"No cubierto",IF(P9=1,"Débil (1 tema)",IF(P9<=3,"Básica (2–3)","Sólida (4+)"))) -> No cubierto | T9: =IFERROR(INDEX($F$4:$O$4,MATCH(TRUE(),INDEX(F9:O9>0,0),0)),"—") -> —
A10: T4-V3.1 | B10: T4 | C10: Ciencias de la vida | D10: Organismos, ambiente y sus interacciones | E10: Relacionar rasgos físicos y conductas con la supervivencia en un ambiente (adaptación) | F10: =COUNTIFS(Temas_TIMSS!$V$5:$V$1264,F$4,Temas_TIMSS!$K$5:$K$1264,$A10)+COUNTIFS(Temas_TIMSS!$V$5:$V$1264,F$4,Temas_TIMSS!$L$5:$L$1264,$A10) -> 1 | G10: =COUNTIFS(Temas_TIMSS!$V$5:$V$1264,G$4,Temas_TIMSS!$K$5:$K$1264,$A10)+COUNTIFS(Temas_TIMSS!$V$5:$V$1264,G$4,Temas_TIMSS!$L$5:$L$1264,$A10) -> 0 | H10: =COUNTIFS(Temas_TIMSS!$V$5:$V$1264,H$4,Temas_TIMSS!$K$5:$K$1264,$A10)+COUNTIFS(Temas_TIMSS!$V$5:$V$1264,H$4,Temas_TIMSS!$L$5:$L$1264,$A10) -> 1 | I10: =COUNTIFS(Temas_TIMSS!$V$5:$V$1264,I$4,Temas_TIMSS!$K$5:$K$1264,$A10)+COUNTIFS(Temas_TIMSS!$V$5:$V$1264,I$4,Temas_TIMSS!$L$5:$L$1264,$A10) -> 0 | J10: =COUNTIFS(Temas_TIMSS!$V$5:$V$1264,J$4,Temas_TIMSS!$K$5:$K$1264,$A10)+COUNTIFS(Temas_TIMSS!$V$5:$V$1264,J$4,Temas_TIMSS!$L$5:$L$1264,$A10) -> 0 | K10: =COUNTIFS(Temas_TIMSS!$V$5:$V$1264,K$4,Temas_TIMSS!$K$5:$K$1264,$A10)+COUNTIFS(Temas_TIMSS!$V$5:$V$1264,K$4,Temas_TIMSS!$L$5:$L$1264,$A10) -> 0 | L10: =COUNTIFS(Temas_TIMSS!$V$5:$V$1264,L$4,Temas_TIMSS!$K$5:$K$1264,$A10)+COUNTIFS(Temas_TIMSS!$V$5:$V$1264,L$4,Temas_TIMSS!$L$5:$L$1264,$A10) -> 0 | M10: =COUNTIFS(Temas_TIMSS!$V$5:$V$1264,M$4,Temas_TIMSS!$K$5:$K$1264,$A10)+COUNTIFS(Temas_TIMSS!$V$5:$V$1264,M$4,Temas_TIMSS!$L$5:$L$1264,$A10) -> 0 | ... O10: =COUNTIFS(Temas_TIMSS!$V$5:$V$1264,O$4,Temas_TIMSS!$K$5:$K$1264,$A10)+COUNTIFS(Temas_TIMSS!$V$5:$V$1264,O$4,Temas_TIMSS!$L$5:$L$1264,$A10) -> 0 | P10: =IF($B10="T4",SUM(F10:H10),IF($B10="T8",SUM(I10:L10),SUM(N10:O10))) -> 2 | Q10: =COUNTIFS(Temas_TIMSS!$K$5:$K$1264,$A10) -> 1 | R10: =IF(P10>0,"Sí","No") -> Sí | S10: =IF(P10=0,"No cubierto",IF(P10=1,"Débil (1 tema)",IF(P10<=3,"Básica (2–3)","Sólida (4+)"))) -> Básica (2–3) | T10: =IFERROR(INDEX($F$4:$O$4,MATCH(TRUE(),INDEX(F10:O10>0,0),0)),"—") -> 2°
A11: T4-V3.2 | B11: T4 | C11: Ciencias de la vida | D11: Organismos, ambiente y sus interacciones | E11: Cómo responden los organismos a cambios en su ambiente | F11: =COUNTIFS(Temas_TIMSS!$V$5:$V$1264,F$4,Temas_TIMSS!$K$5:$K$1264,$A11)+COUNTIFS(Temas_TIMSS!$V$5:$V$1264,F$4,Temas_TIMSS!$L$5:$L$1264,$A11) -> 1 | G11: =COUNTIFS(Temas_TIMSS!$V$5:$V$1264,G$4,Temas_TIMSS!$K$5:$K$1264,$A11)+COUNTIFS(Temas_TIMSS!$V$5:$V$1264,G$4,Temas_TIMSS!$L$5:$L$1264,$A11) -> 5 | H11: =COUNTIFS(Temas_TIMSS!$V$5:$V$1264,H$4,Temas_TIMSS!$K$5:$K$1264,$A11)+COUNTIFS(Temas_TIMSS!$V$5:$V$1264,H$4,Temas_TIMSS!$L$5:$L$1264,$A11) -> 0 | I11: =COUNTIFS(Temas_TIMSS!$V$5:$V$1264,I$4,Temas_TIMSS!$K$5:$K$1264,$A11)+COUNTIFS(Temas_TIMSS!$V$5:$V$1264,I$4,Temas_TIMSS!$L$5:$L$1264,$A11) -> 0 | J11: =COUNTIFS(Temas_TIMSS!$V$5:$V$1264,J$4,Temas_TIMSS!$K$5:$K$1264,$A11)+COUNTIFS(Temas_TIMSS!$V$5:$V$1264,J$4,Temas_TIMSS!$L$5:$L$1264,$A11) -> 0 | K11: =COUNTIFS(Temas_TIMSS!$V$5:$V$1264,K$4,Temas_TIMSS!$K$5:$K$1264,$A11)+COUNTIFS(Temas_TIMSS!$V$5:$V$1264,K$4,Temas_TIMSS!$L$5:$L$1264,$A11) -> 0 | L11: =COUNTIFS(Temas_TIMSS!$V$5:$V$1264,L$4,Temas_TIMSS!$K$5:$K$1264,$A11)+COUNTIFS(Temas_TIMSS!$V$5:$V$1264,L$4,Temas_TIMSS!$L$5:$L$1264,$A11) -> 0 | M11: =COUNTIFS(Temas_TIMSS!$V$5:$V$1264,M$4,Temas_TIMSS!$K$5:$K$1264,$A11)+COUNTIFS(Temas_TIMSS!$V$5:$V$1264,M$4,Temas_TIMSS!$L$5:$L$1264,$A11) -> 0 | ... O11: =COUNTIFS(Temas_TIMSS!$V$5:$V$1264,O$4,Temas_TIMSS!$K$5:$K$1264,$A11)+COUNTIFS(Temas_TIMSS!$V$5:$V$1264,O$4,Temas_TIMSS!$L$5:$L$1264,$A11) -> 0 | P11: =IF($B11="T4",SUM(F11:H11),IF($B11="T8",SUM(I11:L11),SUM(N11:O11))) -> 6 | Q11: =COUNTIFS(Temas_TIMSS!$K$5:$K$1264,$A11) -> 6 | R11: =IF(P11>0,"Sí","No") -> Sí | S11: =IF(P11=0,"No cubierto",IF(P11=1,"Débil (1 tema)",IF(P11<=3,"Básica (2–3)","Sólida (4+)"))) -> Sólida (4+) | T11: =IFERROR(INDEX($F$4:$O$4,MATCH(TRUE(),INDEX(F11:O11>0,0),0)),"—") -> 2°
A12: T4-V3.3 | B12: T4 | C12: Ciencias de la vida | D12: Organismos, ambiente y sus interacciones | E12: Impacto positivo y negativo del ser humano en el ambiente | F12: =COUNTIFS(Temas_TIMSS!$V$5:$V$1264,F$4,Temas_TIMSS!$K$5:$K$1264,$A12)+COUNTIFS(Temas_TIMSS!$V$5:$V$1264,F$4,Temas_TIMSS!$L$5:$L$1264,$A12) -> 5 | G12: =COUNTIFS(Temas_TIMSS!$V$5:$V$1264,G$4,Temas_TIMSS!$K$5:$K$1264,$A12)+COUNTIFS(Temas_TIMSS!$V$5:$V$1264,G$4,Temas_TIMSS!$L$5:$L$1264,$A12) -> 1 | H12: =COUNTIFS(Temas_TIMSS!$V$5:$V$1264,H$4,Temas_TIMSS!$K$5:$K$1264,$A12)+COUNTIFS(Temas_TIMSS!$V$5:$V$1264,H$4,Temas_TIMSS!$L$5:$L$1264,$A12) -> 0 | I12: =COUNTIFS(Temas_TIMSS!$V$5:$V$1264,I$4,Temas_TIMSS!$K$5:$K$1264,$A12)+COUNTIFS(Temas_TIMSS!$V$5:$V$1264,I$4,Temas_TIMSS!$L$5:$L$1264,$A12) -> 0 | J12: =COUNTIFS(Temas_TIMSS!$V$5:$V$1264,J$4,Temas_TIMSS!$K$5:$K$1264,$A12)+COUNTIFS(Temas_TIMSS!$V$5:$V$1264,J$4,Temas_TIMSS!$L$5:$L$1264,$A12) -> 0 | K12: =COUNTIFS(Temas_TIMSS!$V$5:$V$1264,K$4,Temas_TIMSS!$K$5:$K$1264,$A12)+COUNTIFS(Temas_TIMSS!$V$5:$V$1264,K$4,Temas_TIMSS!$L$5:$L$1264,$A12) -> 0 | L12: =COUNTIFS(Temas_TIMSS!$V$5:$V$1264,L$4,Temas_TIMSS!$K$5:$K$1264,$A12)+COUNTIFS(Temas_TIMSS!$V$5:$V$1264,L$4,Temas_TIMSS!$L$5:$L$1264,$A12) -> 0 | M12: =COUNTIFS(Temas_TIMSS!$V$5:$V$1264,M$4,Temas_TIMSS!$K$5:$K$1264,$A12)+COUNTIFS(Temas_TIMSS!$V$5:$V$1264,M$4,Temas_TIMSS!$L$5:$L$1264,$A12) -> 0 | ... O12: =COUNTIFS(Temas_TIMSS!$V$5:$V$1264,O$4,Temas_TIMSS!$K$5:$K$1264,$A12)+COUNTIFS(Temas_TIMSS!$V$5:$V$1264,O$4,Temas_TIMSS!$L$5:$L$1264,$A12) -> 0 | P12: =IF($B12="T4",SUM(F12:H12),IF($B12="T8",SUM(I12:L12),SUM(N12:O12))) -> 6 | Q12: =COUNTIFS(Temas_TIMSS!$K$5:$K$1264,$A12) -> 5 | R12: =IF(P12>0,"Sí","No") -> Sí | S12: =IF(P12=0,"No cubierto",IF(P12=1,"Débil (1 tema)",IF(P12<=3,"Básica (2–3)","Sólida (4+)"))) -> Sólida (4+) | T12: =IFERROR(INDEX($F$4:$O$4,MATCH(TRUE(),INDEX(F12:O12>0,0),0)),"—") -> 2°
A13: T4-V4.1 | B13: T4 | C13: Ciencias de la vida | D13: Ecosistemas | E13: Relacionar plantas y animales comunes con su ecosistema | F13: =COUNTIFS(Temas_TIMSS!$V$5:$V$1264,F$4,Temas_TIMSS!$K$5:$K$1264,$A13)+COUNTIFS(Temas_TIMSS!$V$5:$V$1264,F$4,Temas_TIMSS!$L$5:$L$1264,$A13) -> 5 | G13: =COUNTIFS(Temas_TIMSS!$V$5:$V$1264,G$4,Temas_TIMSS!$K$5:$K$1264,$A13)+COUNTIFS(Temas_TIMSS!$V$5:$V$1264,G$4,Temas_TIMSS!$L$5:$L$1264,$A13) -> 0 | H13: =COUNTIFS(Temas_TIMSS!$V$5:$V$1264,H$4,Temas_TIMSS!$K$5:$K$1264,$A13)+COUNTIFS(Temas_TIMSS!$V$5:$V$1264,H$4,Temas_TIMSS!$L$5:$L$1264,$A13) -> 6 | I13: =COUNTIFS(Temas_TIMSS!$V$5:$V$1264,I$4,Temas_TIMSS!$K$5:$K$1264,$A13)+COUNTIFS(Temas_TIMSS!$V$5:$V$1264,I$4,Temas_TIMSS!$L$5:$L$1264,$A13) -> 0 | J13: =COUNTIFS(Temas_TIMSS!$V$5:$V$1264,J$4,Temas_TIMSS!$K$5:$K$1264,$A13)+COUNTIFS(Temas_TIMSS!$V$5:$V$1264,J$4,Temas_TIMSS!$L$5:$L$1264,$A13) -> 0 | K13: =COUNTIFS(Temas_TIMSS!$V$5:$V$1264,K$4,Temas_TIMSS!$K$5:$K$1264,$A13)+COUNTIFS(Temas_TIMSS!$V$5:$V$1264,K$4,Temas_TIMSS!$L$5:$L$1264,$A13) -> 0 | L13: =COUNTIFS(Temas_TIMSS!$V$5:$V$1264,L$4,Temas_TIMSS!$K$5:$K$1264,$A13)+COUNTIFS(Temas_TIMSS!$V$5:$V$1264,L$4,Temas_TIMSS!$L$5:$L$1264,$A13) -> 0 | M13: =COUNTIFS(Temas_TIMSS!$V$5:$V$1264,M$4,Temas_TIMSS!$K$5:$K$1264,$A13)+COUNTIFS(Temas_TIMSS!$V$5:$V$1264,M$4,Temas_TIMSS!$L$5:$L$1264,$A13) -> 0 | ... O13: =COUNTIFS(Temas_TIMSS!$V$5:$V$1264,O$4,Temas_TIMSS!$K$5:$K$1264,$A13)+COUNTIFS(Temas_TIMSS!$V$5:$V$1264,O$4,Temas_TIMSS!$L$5:$L$1264,$A13) -> 0 | P13: =IF($B13="T4",SUM(F13:H13),IF($B13="T8",SUM(I13:L13),SUM(N13:O13))) -> 11 | Q13: =COUNTIFS(Temas_TIMSS!$K$5:$K$1264,$A13) -> 8 | R13: =IF(P13>0,"Sí","No") -> Sí | S13: =IF(P13=0,"No cubierto",IF(P13=1,"Débil (1 tema)",IF(P13<=3,"Básica (2–3)","Sólida (4+)"))) -> Sólida (4+) | T13: =IFERROR(INDEX($F$4:$O$4,MATCH(TRUE(),INDEX(F13:O13>0,0),0)),"—") -> 2°
A14: T4-V4.2 | B14: T4 | C14: Ciencias de la vida | D14: Ecosistemas | E14: Cadenas alimentarias; roles de organismos; depredador-presa | F14: =COUNTIFS(Temas_TIMSS!$V$5:$V$1264,F$4,Temas_TIMSS!$K$5:$K$1264,$A14)+COUNTIFS(Temas_TIMSS!$V$5:$V$1264,F$4,Temas_TIMSS!$L$5:$L$1264,$A14) -> 0 | G14: =COUNTIFS(Temas_TIMSS!$V$5:$V$1264,G$4,Temas_TIMSS!$K$5:$K$1264,$A14)+COUNTIFS(Temas_TIMSS!$V$5:$V$1264,G$4,Temas_TIMSS!$L$5:$L$1264,$A14) -> 1 | H14: =COUNTIFS(Temas_TIMSS!$V$5:$V$1264,H$4,Temas_TIMSS!$K$5:$K$1264,$A14)+COUNTIFS(Temas_TIMSS!$V$5:$V$1264,H$4,Temas_TIMSS!$L$5:$L$1264,$A14) -> 2 | I14: =COUNTIFS(Temas_TIMSS!$V$5:$V$1264,I$4,Temas_TIMSS!$K$5:$K$1264,$A14)+COUNTIFS(Temas_TIMSS!$V$5:$V$1264,I$4,Temas_TIMSS!$L$5:$L$1264,$A14) -> 0 | J14: =COUNTIFS(Temas_TIMSS!$V$5:$V$1264,J$4,Temas_TIMSS!$K$5:$K$1264,$A14)+COUNTIFS(Temas_TIMSS!$V$5:$V$1264,J$4,Temas_TIMSS!$L$5:$L$1264,$A14) -> 0 | K14: =COUNTIFS(Temas_TIMSS!$V$5:$V$1264,K$4,Temas_TIMSS!$K$5:$K$1264,$A14)+COUNTIFS(Temas_TIMSS!$V$5:$V$1264,K$4,Temas_TIMSS!$L$5:$L$1264,$A14) -> 0 | L14: =COUNTIFS(Temas_TIMSS!$V$5:$V$1264,L$4,Temas_TIMSS!$K$5:$K$1264,$A14)+COUNTIFS(Temas_TIMSS!$V$5:$V$1264,L$4,Temas_TIMSS!$L$5:$L$1264,$A14) -> 0 | M14: =COUNTIFS(Temas_TIMSS!$V$5:$V$1264,M$4,Temas_TIMSS!$K$5:$K$1264,$A14)+COUNTIFS(Temas_TIMSS!$V$5:$V$1264,M$4,Temas_TIMSS!$L$5:$L$1264,$A14) -> 0 | ... O14: =COUNTIFS(Temas_TIMSS!$V$5:$V$1264,O$4,Temas_TIMSS!$K$5:$K$1264,$A14)+COUNTIFS(Temas_TIMSS!$V$5:$V$1264,O$4,Temas_TIMSS!$L$5:$L$1264,$A14) -> 0 | P14: =IF($B14="T4",SUM(F14:H14),IF($B14="T8",SUM(I14:L14),SUM(N14:O14))) -> 3 | Q14: =COUNTIFS(Temas_TIMSS!$K$5:$K$1264,$A14) -> 3 | R14: =IF(P14>0,"Sí","No") -> Sí | S14: =IF(P14=0,"No cubierto",IF(P14=1,"Débil (1 tema)",IF(P14<=3,"Básica (2–3)","Sólida (4+)"))) -> Básica (2–3) | T14: =IFERROR(INDEX($F$4:$O$4,MATCH(TRUE(),INDEX(F14:O14>0,0),0)),"—") -> 3°
A15: T4-V4.3 | B15: T4 | C15: Ciencias de la vida | D15: Ecosistemas | E15: Competencia entre organismos por recursos del ecosistema | F15: =COUNTIFS(Temas_TIMSS!$V$5:$V$1264,F$4,Temas_TIMSS!$K$5:$K$1264,$A15)+COUNTIFS(Temas_TIMSS!$V$5:$V$1264,F$4,Temas_TIMSS!$L$5:$L$1264,$A15) -> 0 | G15: =COUNTIFS(Temas_TIMSS!$V$5:$V$1264,G$4,Temas_TIMSS!$K$5:$K$1264,$A15)+COUNTIFS(Temas_TIMSS!$V$5:$V$1264,G$4,Temas_TIMSS!$L$5:$L$1264,$A15) -> 0 | H15: =COUNTIFS(Temas_TIMSS!$V$5:$V$1264,H$4,Temas_TIMSS!$K$5:$K$1264,$A15)+COUNTIFS(Temas_TIMSS!$V$5:$V$1264,H$4,Temas_TIMSS!$L$5:$L$1264,$A15) -> 1 | I15: =COUNTIFS(Temas_TIMSS!$V$5:$V$1264,I$4,Temas_TIMSS!$K$5:$K$1264,$A15)+COUNTIFS(Temas_TIMSS!$V$5:$V$1264,I$4,Temas_TIMSS!$L$5:$L$1264,$A15) -> 0 | J15: =COUNTIFS(Temas_TIMSS!$V$5:$V$1264,J$4,Temas_TIMSS!$K$5:$K$1264,$A15)+COUNTIFS(Temas_TIMSS!$V$5:$V$1264,J$4,Temas_TIMSS!$L$5:$L$1264,$A15) -> 0 | K15: =COUNTIFS(Temas_TIMSS!$V$5:$V$1264,K$4,Temas_TIMSS!$K$5:$K$1264,$A15)+COUNTIFS(Temas_TIMSS!$V$5:$V$1264,K$4,Temas_TIMSS!$L$5:$L$1264,$A15) -> 0 | L15: =COUNTIFS(Temas_TIMSS!$V$5:$V$1264,L$4,Temas_TIMSS!$K$5:$K$1264,$A15)+COUNTIFS(Temas_TIMSS!$V$5:$V$1264,L$4,Temas_TIMSS!$L$5:$L$1264,$A15) -> 0 | M15: =COUNTIFS(Temas_TIMSS!$V$5:$V$1264,M$4,Temas_TIMSS!$K$5:$K$1264,$A15)+COUNTIFS(Temas_TIMSS!$V$5:$V$1264,M$4,Temas_TIMSS!$L$5:$L$1264,$A15) -> 0 | ... O15: =COUNTIFS(Temas_TIMSS!$V$5:$V$1264,O$4,Temas_TIMSS!$K$5:$K$1264,$A15)+COUNTIFS(Temas_TIMSS!$V$5:$V$1264,O$4,Temas_TIMSS!$L$5:$L$1264,$A15) -> 0 | P15: =IF($B15="T4",SUM(F15:H15),IF($B15="T8",SUM(I15:L15),SUM(N15:O15))) -> 1 | Q15: =COUNTIFS(Temas_TIMSS!$K$5:$K$1264,$A15) -> 0 | R15: =IF(P15>0,"Sí","No") -> Sí | S15: =IF(P15=0,"No cubierto",IF(P15=1,"Débil (1 tema)",IF(P15<=3,"Básica (2–3)","Sólida (4+)"))) -> Débil (1 tema) | T15: =IFERROR(INDEX($F$4:$O$4,MATCH(TRUE(),INDEX(F15:O15>0,0),0)),"—") -> 4°
A16: T4-V5.1 | B16: T4 | C16: Ciencias de la vida | D16: Salud humana | E16: Conductas saludables y componentes de una dieta balanceada | F16: =COUNTIFS(Temas_TIMSS!$V$5:$V$1264,F$4,Temas_TIMSS!$K$5:$K$1264,$A16)+COUNTIFS(Temas_TIMSS!$V$5:$V$1264,F$4,Temas_TIMSS!$L$5:$L$1264,$A16) -> 2 | G16: =COUNTIFS(Temas_TIMSS!$V$5:$V$1264,G$4,Temas_TIMSS!$K$5:$K$1264,$A16)+COUNTIFS(Temas_TIMSS!$V$5:$V$1264,G$4,Temas_TIMSS!$L$5:$L$1264,$A16) -> 0 | H16: =COUNTIFS(Temas_TIMSS!$V$5:$V$1264,H$4,Temas_TIMSS!$K$5:$K$1264,$A16)+COUNTIFS(Temas_TIMSS!$V$5:$V$1264,H$4,Temas_TIMSS!$L$5:$L$1264,$A16) -> 12 | I16: =COUNTIFS(Temas_TIMSS!$V$5:$V$1264,I$4,Temas_TIMSS!$K$5:$K$1264,$A16)+COUNTIFS(Temas_TIMSS!$V$5:$V$1264,I$4,Temas_TIMSS!$L$5:$L$1264,$A16) -> 0 | J16: =COUNTIFS(Temas_TIMSS!$V$5:$V$1264,J$4,Temas_TIMSS!$K$5:$K$1264,$A16)+COUNTIFS(Temas_TIMSS!$V$5:$V$1264,J$4,Temas_TIMSS!$L$5:$L$1264,$A16) -> 0 | K16: =COUNTIFS(Temas_TIMSS!$V$5:$V$1264,K$4,Temas_TIMSS!$K$5:$K$1264,$A16)+COUNTIFS(Temas_TIMSS!$V$5:$V$1264,K$4,Temas_TIMSS!$L$5:$L$1264,$A16) -> 0 | L16: =COUNTIFS(Temas_TIMSS!$V$5:$V$1264,L$4,Temas_TIMSS!$K$5:$K$1264,$A16)+COUNTIFS(Temas_TIMSS!$V$5:$V$1264,L$4,Temas_TIMSS!$L$5:$L$1264,$A16) -> 0 | M16: =COUNTIFS(Temas_TIMSS!$V$5:$V$1264,M$4,Temas_TIMSS!$K$5:$K$1264,$A16)+COUNTIFS(Temas_TIMSS!$V$5:$V$1264,M$4,Temas_TIMSS!$L$5:$L$1264,$A16) -> 0 | ... O16: =COUNTIFS(Temas_TIMSS!$V$5:$V$1264,O$4,Temas_TIMSS!$K$5:$K$1264,$A16)+COUNTIFS(Temas_TIMSS!$V$5:$V$1264,O$4,Temas_TIMSS!$L$5:$L$1264,$A16) -> 0 | P16: =IF($B16="T4",SUM(F16:H16),IF($B16="T8",SUM(I16:L16),SUM(N16:O16))) -> 14 | Q16: =COUNTIFS(Temas_TIMSS!$K$5:$K$1264,$A16) -> 12 | R16: =IF(P16>0,"Sí","No") -> Sí | S16: =IF(P16=0,"No cubierto",IF(P16=1,"Débil (1 tema)",IF(P16<=3,"Básica (2–3)","Sólida (4+)"))) -> Sólida (4+) | T16: =IFERROR(INDEX($F$4:$O$4,MATCH(TRUE(),INDEX(F16:O16>0,0),0)),"—") -> 2°
... A105: TA-O2.4 | B105: TA | C105: Ondas y física atómica/nuclear | D105: Física atómica y nuclear | E105: Equivalencia masa-energía | F105: =COUNTIFS(Temas_TIMSS!$V$5:$V$1264,F$4,Temas_TIMSS!$K$5:$K$1264,$A105)+COUNTIFS(Temas_TIMSS!$V$5:$V$1264,F$4,Temas_TIMSS!$L$5:$L$1264,$A105) -> 0 | G105: =COUNTIFS(Temas_TIMSS!$V$5:$V$1264,G$4,Temas_TIMSS!$K$5:$K$1264,$A105)+COUNTIFS(Temas_TIMSS!$V$5:$V$1264,G$4,Temas_TIMSS!$L$5:$L$1264,$A105) -> 0 | H105: =COUNTIFS(Temas_TIMSS!$V$5:$V$1264,H$4,Temas_TIMSS!$K$5:$K$1264,$A105)+COUNTIFS(Temas_TIMSS!$V$5:$V$1264,H$4,Temas_TIMSS!$L$5:$L$1264,$A105) -> 0 | I105: =COUNTIFS(Temas_TIMSS!$V$5:$V$1264,I$4,Temas_TIMSS!$K$5:$K$1264,$A105)+COUNTIFS(Temas_TIMSS!$V$5:$V$1264,I$4,Temas_TIMSS!$L$5:$L$1264,$A105) -> 0 | J105: =COUNTIFS(Temas_TIMSS!$V$5:$V$1264,J$4,Temas_TIMSS!$K$5:$K$1264,$A105)+COUNTIFS(Temas_TIMSS!$V$5:$V$1264,J$4,Temas_TIMSS!$L$5:$L$1264,$A105) -> 0 | K105: =COUNTIFS(Temas_TIMSS!$V$5:$V$1264,K$4,Temas_TIMSS!$K$5:$K$1264,$A105)+COUNTIFS(Temas_TIMSS!$V$5:$V$1264,K$4,Temas_TIMSS!$L$5:$L$1264,$A105) -> 0 | L105: =COUNTIFS(Temas_TIMSS!$V$5:$V$1264,L$4,Temas_TIMSS!$K$5:$K$1264,$A105)+COUNTIFS(Temas_TIMSS!$V$5:$V$1264,L$4,Temas_TIMSS!$L$5:$L$1264,$A105) -> 0 | M105: =COUNTIFS(Temas_TIMSS!$V$5:$V$1264,M$4,Temas_TIMSS!$K$5:$K$1264,$A105)+COUNTIFS(Temas_TIMSS!$V$5:$V$1264,M$4,Temas_TIMSS!$L$5:$L$1264,$A105) -> 0 | ... O105: =COUNTIFS(Temas_TIMSS!$V$5:$V$1264,O$4,Temas_TIMSS!$K$5:$K$1264,$A105)+COUNTIFS(Temas_TIMSS!$V$5:$V$1264,O$4,Temas_TIMSS!$L$5:$L$1264,$A105) -> 4 | P105: =IF($B105="T4",SUM(F105:H105),IF($B105="T8",SUM(I105:L105),SUM(N105:O105))) -> 4 | Q105: =COUNTIFS(Temas_TIMSS!$K$5:$K$1264,$A105) -> 2 | R105: =IF(P105>0,"Sí","No") -> Sí | S105: =IF(P105=0,"No cubierto",IF(P105=1,"Débil (1 tema)",IF(P105<=3,"Básica (2–3)","Sólida (4+)"))) -> Sólida (4+) | T105: =IFERROR(INDEX($F$4:$O$4,MATCH(TRUE(),INDEX(F105:O105>0,0),0)),"—") -> Física 11°
A108: Resumen de amplitud por marco y dominio
A109: Marco | B109: Dominio | C109: Objetivos en el marco | D109: Objetivos cubiertos | E109: % cubierto | F109: Objetivos no cubiertos | G109: Objetivos débiles (1 tema)
A110: T4 | B110: Ciencias de la vida | C110: =COUNTIFS($B$5:$B$105,$A110,$C$5:$C$105,$B110) -> 13 | D110: =COUNTIFS($B$5:$B$105,$A110,$C$5:$C$105,$B110,$R$5:$R$105,"Sí") -> 12 | E110: =IF(C110=0,0,D110/C110) -> 0.92307692 | F110: =C110-D110 -> 1 | G110: =COUNTIFS($B$5:$B$105,$A110,$C$5:$C$105,$B110,$S$5:$S$105,"Débil (1 tema)") -> 1
A111: T4 | B111: Ciencias físicas | C111: =COUNTIFS($B$5:$B$105,$A111,$C$5:$C$105,$B111) -> 11 | D111: =COUNTIFS($B$5:$B$105,$A111,$C$5:$C$105,$B111,$R$5:$R$105,"Sí") -> 11 | E111: =IF(C111=0,0,D111/C111) -> 1 | F111: =C111-D111 -> 0 | G111: =COUNTIFS($B$5:$B$105,$A111,$C$5:$C$105,$B111,$S$5:$S$105,"Débil (1 tema)") -> 2
A112: T4 | B112: Ciencias de la Tierra | C112: =COUNTIFS($B$5:$B$105,$A112,$C$5:$C$105,$B112) -> 8 | D112: =COUNTIFS($B$5:$B$105,$A112,$C$5:$C$105,$B112,$R$5:$R$105,"Sí") -> 8 | E112: =IF(C112=0,0,D112/C112) -> 1 | F112: =C112-D112 -> 0 | G112: =COUNTIFS($B$5:$B$105,$A112,$C$5:$C$105,$B112,$S$5:$S$105,"Débil (1 tema)") -> 0
A113: T4 | B113: (todos) | C113: =COUNTIFS($B$5:$B$105,$A113,$C$5:$C$105,"*") -> 32 | D113: =COUNTIFS($B$5:$B$105,$A113,$C$5:$C$105,"*",$R$5:$R$105,"Sí") -> 31 | E113: =IF(C113=0,0,D113/C113) -> 0.96875 | F113: =C113-D113 -> 1 | G113: =COUNTIFS($B$5:$B$105,$A113,$C$5:$C$105,"*",$S$5:$S$105,"Débil (1 tema)") -> 3
A114: T8 | B114: Biología | C114: =COUNTIFS($B$5:$B$105,$A114,$C$5:$C$105,$B114) -> 16 | D114: =COUNTIFS($B$5:$B$105,$A114,$C$5:$C$105,$B114,$R$5:$R$105,"Sí") -> 15 | E114: =IF(C114=0,0,D114/C114) -> 0.9375 | F114: =C114-D114 -> 1 | G114: =COUNTIFS($B$5:$B$105,$A114,$C$5:$C$105,$B114,$S$5:$S$105,"Débil (1 tema)") -> 1
A115: T8 | B115: Química | C115: =COUNTIFS($B$5:$B$105,$A115,$C$5:$C$105,$B115) -> 10 | D115: =COUNTIFS($B$5:$B$105,$A115,$C$5:$C$105,$B115,$R$5:$R$105,"Sí") -> 10 | E115: =IF(C115=0,0,D115/C115) -> 1 | F115: =C115-D115 -> 0 | G115: =COUNTIFS($B$5:$B$105,$A115,$C$5:$C$105,$B115,$S$5:$S$105,"Débil (1 tema)") -> 0
A116: T8 | B116: Física | C116: =COUNTIFS($B$5:$B$105,$A116,$C$5:$C$105,$B116) -> 11 | D116: =COUNTIFS($B$5:$B$105,$A116,$C$5:$C$105,$B116,$R$5:$R$105,"Sí") -> 10 | E116: =IF(C116=0,0,D116/C116) -> 0.90909091 | F116: =C116-D116 -> 1 | G116: =COUNTIFS($B$5:$B$105,$A116,$C$5:$C$105,$B116,$S$5:$S$105,"Débil (1 tema)") -> 0
A117: T8 | B117: Ciencias de la Tierra | C117: =COUNTIFS($B$5:$B$105,$A117,$C$5:$C$105,$B117) -> 9 | D117: =COUNTIFS($B$5:$B$105,$A117,$C$5:$C$105,$B117,$R$5:$R$105,"Sí") -> 8 | E117: =IF(C117=0,0,D117/C117) -> 0.88888889 | F117: =C117-D117 -> 1 | G117: =COUNTIFS($B$5:$B$105,$A117,$C$5:$C$105,$B117,$S$5:$S$105,"Débil (1 tema)") -> 0
A118: T8 | B118: (todos) | C118: =COUNTIFS($B$5:$B$105,$A118,$C$5:$C$105,"*") -> 46 | D118: =COUNTIFS($B$5:$B$105,$A118,$C$5:$C$105,"*",$R$5:$R$105,"Sí") -> 43 | E118: =IF(C118=0,0,D118/C118) -> 0.93478261 | F118: =C118-D118 -> 3 | G118: =COUNTIFS($B$5:$B$105,$A118,$C$5:$C$105,"*",$S$5:$S$105,"Débil (1 tema)") -> 1
A119: TA | B119: Mecánica y termodinámica | C119: =COUNTIFS($B$5:$B$105,$A119,$C$5:$C$105,$B119) -> 9 | D119: =COUNTIFS($B$5:$B$105,$A119,$C$5:$C$105,$B119,$R$5:$R$105,"Sí") -> 9 | E119: =IF(C119=0,0,D119/C119) -> 1 | F119: =C119-D119 -> 0 | G119: =COUNTIFS($B$5:$B$105,$A119,$C$5:$C$105,$B119,$S$5:$S$105,"Débil (1 tema)") -> 0
A120: TA | B120: Electricidad y magnetismo | C120: =COUNTIFS($B$5:$B$105,$A120,$C$5:$C$105,$B120) -> 6 | D120: =COUNTIFS($B$5:$B$105,$A120,$C$5:$C$105,$B120,$R$5:$R$105,"Sí") -> 6 | E120: =IF(C120=0,0,D120/C120) -> 1 | F120: =C120-D120 -> 0 | G120: =COUNTIFS($B$5:$B$105,$A120,$C$5:$C$105,$B120,$S$5:$S$105,"Débil (1 tema)") -> 0
A121: TA | B121: Ondas y física atómica/nuclear | C121: =COUNTIFS($B$5:$B$105,$A121,$C$5:$C$105,$B121) -> 8 | D121: =COUNTIFS($B$5:$B$105,$A121,$C$5:$C$105,$B121,$R$5:$R$105,"Sí") -> 8 | E121: =IF(C121=0,0,D121/C121) -> 1 | F121: =C121-D121 -> 0 | G121: =COUNTIFS($B$5:$B$105,$A121,$C$5:$C$105,$B121,$S$5:$S$105,"Débil (1 tema)") -> 0
A122: TA | B122: (todos) | C122: =COUNTIFS($B$5:$B$105,$A122,$C$5:$C$105,"*") -> 23 | D122: =COUNTIFS($B$5:$B$105,$A122,$C$5:$C$105,"*",$R$5:$R$105,"Sí") -> 23 | E122: =IF(C122=0,0,D122/C122) -> 1 | F122: =C122-D122 -> 0 | G122: =COUNTIFS($B$5:$B$105,$A122,$C$5:$C$105,"*",$S$5:$S$105,"Débil (1 tema)") -> 0

Sheet Faltantes
A1: Qué falta: objetivos TIMSS no cubiertos o débiles, y dónde podrían entrar
A2: Lista generada desde Cobertura_objetivos (profundidad «No cubierto» o «Débil»). La columna «Temas hoy» es fórmula y se actualiza si cambia la clasificación. La sugerencia de ubicación es una propuesta para discutir con el equipo de Ciencias, no una decisión.
A4: Código | B4: Marco | C4: Dominio | D4: Objetivo | E4: Temas hoy | F4: Profundidad hoy | G4: Dónde aparece hoy | H4: Sugerencia de ubicación en la malla
A5: T4-V2.2 | B5: T4 | C5: Ciencias de la vida | D5: Las crías se parecen a sus progenitores; rasgos heredados vs. adquiridos | E5: =Cobertura_objetivos!P9 -> 0 | F5: =Cobertura_objetivos!S9 -> No cubierto | G5: — | H5: Ciclo 2°–4°: agregar en 3.° U4 «Las plantas» o U5 «Los animales» un tema de semejanza crías-progenitores y rasgos heredados vs. adquiridos (antecede a Genética de 7.°).
A6: T4-V4.3 | B6: T4 | C6: Ciencias de la vida | D6: Competencia entre organismos por recursos del ecosistema | E6: =Cobertura_objetivos!P15 -> 1 | F6: =Cobertura_objetivos!S15 -> Débil (1 tema) | G6: 4.° U3 (1 tema) | H6: Reforzar en 4.° U3 «Naturaleza y sus interacciones»: competencia por agua, luz y alimento con una actividad de observación.
A7: T4-F1.1 | B7: T4 | C7: Ciencias físicas | D7: Tres estados de la materia y sus características | E7: =Cobertura_objetivos!P18 -> 1 | F7: =Cobertura_objetivos!S18 -> Débil (1 tema) | G7: 2.° U1 (1 tema) | H7: Reforzar en 2.° U1 «Materia» o 3.° U3 «El agua»: estados sólido, líquido y gaseoso con sus características (hoy solo aparece como cambio de estado del agua).
A8: T4-F2.3 | B8: T4 | C8: Ciencias físicas | D8: Cambios de temperatura al contacto entre objetos calientes y fríos | E8: =Cobertura_objetivos!P25 -> 1 | F8: =Cobertura_objetivos!S25 -> Débil (1 tema) | G8: 2.° U2 (1 tema) | H8: Reforzar en 4.° U1 «Máquinas y energía» o 2.° U2 «Energía»: transferencia de calor entre objetos calientes y fríos (hoy se ve recién en 6.°).
A9: T8-B5.2 | B9: T8 | C9: Biología | D9: Ciclos del agua, oxígeno y carbono en ecosistemas | E9: =Cobertura_objetivos!P47 -> 1 | F9: =Cobertura_objetivos!S47 -> Débil (1 tema) | G9: 7.° U4 (1 tema) | H9: Reforzar en 7.° U4 «Ecología» o U5 «Recurso hídrico»: ciclos del carbono y del oxígeno además del agua.
A10: T8-B6.1 | B10: T8 | C10: Biología | D10: Enfermedades: causas, transmisión, prevención; sistema inmune | E10: =Cobertura_objetivos!P51 -> 0 | F10: =Cobertura_objetivos!S51 -> No cubierto | G10: — | H10: Ciclo 5°–8°: agregar en 8.° U7 «Anatomía y fisiología animal» o 6.° U5 «Célula» un tema de enfermedades infecciosas, transmisión, prevención y sistema inmune (hoy aparece hasta 10.° Biología).
A11: T8-F3.1 | B11: T8 | C11: Física | D11: Propiedades de la luz; diagramas de rayos | E11: =Cobertura_objetivos!P67 -> 0 | F11: =Cobertura_objetivos!S67 -> No cubierto | G11: — | H11: Ciclo 5°–8°: agregar en 8.° U3 «Ondas mecánicas» temas de luz (propagación, reflexión, refracción, diagramas de rayos). Hoy la óptica aparece hasta 10.° Física.
A12: T8-T4.1 | B12: T8 | C12: Ciencias de la Tierra | D12: Fenómenos observables: traslación, mareas, fases lunares, eclipses | E12: =Cobertura_objetivos!P81 -> 0 | F12: =Cobertura_objetivos!S81 -> No cubierto | G12: Fuera del ciclo: fases de la Luna en 4.° (U4) y mareas en 9.° (U4) | H12: Agregar en 5.° U5 «Ciencias del espacio»: traslación y estaciones, mareas, fases lunares y eclipses dentro del ciclo 5°–8°.
A14: Además (balance): los faltantes/sobrantes por dominio están en Balance_ciclo (acumulado) y Balance_grado (por grado), columnas I, K y M.

Sheet Cognitivo_grado
A1: Profundidad cognitiva: Conocer / Aplicar / Razonar frente a TIMSS
A2: Fuente: columna «Habilidad TIMSS» de cada malla. Si un tema menciona varios dominios, se reparte en partes iguales (p. ej. «Conocer… Aplicar…» = 0,5 + 0,5). Columnas S-U de Temas_TIMSS. Química y Biología de Bachillerato se comparan con la meta de TIMSS Advanced Física solo como referencia aproximada.
A4: Grupo | B4: Referencia | C4: Temas | D4: Conocer (temas-eq.) | E4: Aplicar (temas-eq.) | F4: Razonar (temas-eq.) | G4: % Conocer | H4: % Aplicar | I4: % Razonar | J4: Meta Conocer | K4: Meta Aplicar | L4: Meta Razonar | M4: Brecha Razonar (pp) | N4: Lectura
A5: 2° | B5: TIMSS 2023 4.° | C5: =COUNTIFS(Temas_TIMSS!$V$5:$V$1264,$A5) -> 70 | D5: =SUMIFS(Temas_TIMSS!$S$5:$S$1264,Temas_TIMSS!$V$5:$V$1264,$A5) -> 12.5 | E5: =SUMIFS(Temas_TIMSS!$T$5:$T$1264,Temas_TIMSS!$V$5:$V$1264,$A5) -> 38.5 | F5: =SUMIFS(Temas_TIMSS!$U$5:$U$1264,Temas_TIMSS!$V$5:$V$1264,$A5) -> 19 | G5: =IF($C5=0,0,D5/$C5) -> 0.17857143 | H5: =IF($C5=0,0,E5/$C5) -> 0.55 | I5: =IF($C5=0,0,F5/$C5) -> 0.27142857 | J5: 0.4 | K5: 0.4 | L5: 0.2 | M5: =(I5-L5)*100 -> 7.1428571 | N5: =IF(ABS(M5)<=5,"Razonar en línea con la meta",IF(M5>0,"Más Razonar que la meta (revisar si la etiqueta está inflada)","Menos Razonar que la meta: faltan tareas de análisis y argumentación")) -> Más Razonar que la meta (revisar si la etiqueta está inflada)
A6: 3° | B6: TIMSS 2023 4.° | C6: =COUNTIFS(Temas_TIMSS!$V$5:$V$1264,$A6) -> 66 | D6: =SUMIFS(Temas_TIMSS!$S$5:$S$1264,Temas_TIMSS!$V$5:$V$1264,$A6) -> 14.5 | E6: =SUMIFS(Temas_TIMSS!$T$5:$T$1264,Temas_TIMSS!$V$5:$V$1264,$A6) -> 34 | F6: =SUMIFS(Temas_TIMSS!$U$5:$U$1264,Temas_TIMSS!$V$5:$V$1264,$A6) -> 17.5 | G6: =IF($C6=0,0,D6/$C6) -> 0.21969697 | H6: =IF($C6=0,0,E6/$C6) -> 0.51515152 | I6: =IF($C6=0,0,F6/$C6) -> 0.26515152 | J6: 0.4 | K6: 0.4 | L6: 0.2 | M6: =(I6-L6)*100 -> 6.5151515 | N6: =IF(ABS(M6)<=5,"Razonar en línea con la meta",IF(M6>0,"Más Razonar que la meta (revisar si la etiqueta está inflada)","Menos Razonar que la meta: faltan tareas de análisis y argumentación")) -> Más Razonar que la meta (revisar si la etiqueta está inflada)
A7: 4° | B7: TIMSS 2023 4.° | C7: =COUNTIFS(Temas_TIMSS!$V$5:$V$1264,$A7) -> 72 | D7: =SUMIFS(Temas_TIMSS!$S$5:$S$1264,Temas_TIMSS!$V$5:$V$1264,$A7) -> 17 | E7: =SUMIFS(Temas_TIMSS!$T$5:$T$1264,Temas_TIMSS!$V$5:$V$1264,$A7) -> 40.5 | F7: =SUMIFS(Temas_TIMSS!$U$5:$U$1264,Temas_TIMSS!$V$5:$V$1264,$A7) -> 14.5 | G7: =IF($C7=0,0,D7/$C7) -> 0.23611111 | H7: =IF($C7=0,0,E7/$C7) -> 0.5625 | I7: =IF($C7=0,0,F7/$C7) -> 0.20138889 | J7: 0.4 | K7: 0.4 | L7: 0.2 | M7: =(I7-L7)*100 -> 0.13888889 | N7: =IF(ABS(M7)<=5,"Razonar en línea con la meta",IF(M7>0,"Más Razonar que la meta (revisar si la etiqueta está inflada)","Menos Razonar que la meta: faltan tareas de análisis y argumentación")) -> Razonar en línea con la meta
A8: 5° | B8: TIMSS 2023 8.° | C8: =COUNTIFS(Temas_TIMSS!$V$5:$V$1264,$A8) -> 72 | D8: =SUMIFS(Temas_TIMSS!$S$5:$S$1264,Temas_TIMSS!$V$5:$V$1264,$A8) -> 7 | E8: =SUMIFS(Temas_TIMSS!$T$5:$T$1264,Temas_TIMSS!$V$5:$V$1264,$A8) -> 47.5 | F8: =SUMIFS(Temas_TIMSS!$U$5:$U$1264,Temas_TIMSS!$V$5:$V$1264,$A8) -> 17.5 | G8: =IF($C8=0,0,D8/$C8) -> 0.097222222 | H8: =IF($C8=0,0,E8/$C8) -> 0.65972222 | I8: =IF($C8=0,0,F8/$C8) -> 0.24305556 | J8: 0.35 | K8: 0.35 | L8: 0.3 | M8: =(I8-L8)*100 -> -5.6944444 | N8: =IF(ABS(M8)<=5,"Razonar en línea con la meta",IF(M8>0,"Más Razonar que la meta (revisar si la etiqueta está inflada)","Menos Razonar que la meta: faltan tareas de análisis y argumentación")) -> Menos Razonar que la meta: faltan tareas de análisis y argumentación
A9: 6° | B9: TIMSS 2023 8.° | C9: =COUNTIFS(Temas_TIMSS!$V$5:$V$1264,$A9) -> 68 | D9: =SUMIFS(Temas_TIMSS!$S$5:$S$1264,Temas_TIMSS!$V$5:$V$1264,$A9) -> 8.5 | E9: =SUMIFS(Temas_TIMSS!$T$5:$T$1264,Temas_TIMSS!$V$5:$V$1264,$A9) -> 46.5 | F9: =SUMIFS(Temas_TIMSS!$U$5:$U$1264,Temas_TIMSS!$V$5:$V$1264,$A9) -> 13 | G9: =IF($C9=0,0,D9/$C9) -> 0.125 | H9: =IF($C9=0,0,E9/$C9) -> 0.68382353 | I9: =IF($C9=0,0,F9/$C9) -> 0.19117647 | J9: 0.35 | K9: 0.35 | L9: 0.3 | M9: =(I9-L9)*100 -> -10.882353 | N9: =IF(ABS(M9)<=5,"Razonar en línea con la meta",IF(M9>0,"Más Razonar que la meta (revisar si la etiqueta está inflada)","Menos Razonar que la meta: faltan tareas de análisis y argumentación")) -> Menos Razonar que la meta: faltan tareas de análisis y argumentación
A10: 7° | B10: TIMSS 2023 8.° | C10: =COUNTIFS(Temas_TIMSS!$V$5:$V$1264,$A10) -> 91 | D10: =SUMIFS(Temas_TIMSS!$S$5:$S$1264,Temas_TIMSS!$V$5:$V$1264,$A10) -> 18 | E10: =SUMIFS(Temas_TIMSS!$T$5:$T$1264,Temas_TIMSS!$V$5:$V$1264,$A10) -> 47 | F10: =SUMIFS(Temas_TIMSS!$U$5:$U$1264,Temas_TIMSS!$V$5:$V$1264,$A10) -> 26 | G10: =IF($C10=0,0,D10/$C10) -> 0.1978022 | H10: =IF($C10=0,0,E10/$C10) -> 0.51648352 | I10: =IF($C10=0,0,F10/$C10) -> 0.28571429 | J10: 0.35 | K10: 0.35 | L10: 0.3 | M10: =(I10-L10)*100 -> -1.4285714 | N10: =IF(ABS(M10)<=5,"Razonar en línea con la meta",IF(M10>0,"Más Razonar que la meta (revisar si la etiqueta está inflada)","Menos Razonar que la meta: faltan tareas de análisis y argumentación")) -> Razonar en línea con la meta
A11: 8° | B11: TIMSS 2023 8.° | C11: =COUNTIFS(Temas_TIMSS!$V$5:$V$1264,$A11) -> 93 | D11: =SUMIFS(Temas_TIMSS!$S$5:$S$1264,Temas_TIMSS!$V$5:$V$1264,$A11) -> 14 | E11: =SUMIFS(Temas_TIMSS!$T$5:$T$1264,Temas_TIMSS!$V$5:$V$1264,$A11) -> 59.5 | F11: =SUMIFS(Temas_TIMSS!$U$5:$U$1264,Temas_TIMSS!$V$5:$V$1264,$A11) -> 19.5 | G11: =IF($C11=0,0,D11/$C11) -> 0.15053763 | H11: =IF($C11=0,0,E11/$C11) -> 0.63978495 | I11: =IF($C11=0,0,F11/$C11) -> 0.20967742 | J11: 0.35 | K11: 0.35 | L11: 0.3 | M11: =(I11-L11)*100 -> -9.0322581 | N11: =IF(ABS(M11)<=5,"Razonar en línea con la meta",IF(M11>0,"Más Razonar que la meta (revisar si la etiqueta está inflada)","Menos Razonar que la meta: faltan tareas de análisis y argumentación")) -> Menos Razonar que la meta: faltan tareas de análisis y argumentación
A12: 9° | B12: TIMSS 2023 8.° | C12: =COUNTIFS(Temas_TIMSS!$V$5:$V$1264,$A12) -> 90 | D12: =SUMIFS(Temas_TIMSS!$S$5:$S$1264,Temas_TIMSS!$V$5:$V$1264,$A12) -> 13.5 | E12: =SUMIFS(Temas_TIMSS!$T$5:$T$1264,Temas_TIMSS!$V$5:$V$1264,$A12) -> 60.5 | F12: =SUMIFS(Temas_TIMSS!$U$5:$U$1264,Temas_TIMSS!$V$5:$V$1264,$A12) -> 16 | G12: =IF($C12=0,0,D12/$C12) -> 0.15 | H12: =IF($C12=0,0,E12/$C12) -> 0.67222222 | I12: =IF($C12=0,0,F12/$C12) -> 0.17777778 | J12: 0.35 | K12: 0.35 | L12: 0.3 | M12: =(I12-L12)*100 -> -12.222222 | N12: =IF(ABS(M12)<=5,"Razonar en línea con la meta",IF(M12>0,"Más Razonar que la meta (revisar si la etiqueta está inflada)","Menos Razonar que la meta: faltan tareas de análisis y argumentación")) -> Menos Razonar que la meta: faltan tareas de análisis y argumentación
A13: Física 10° | B13: TIMSS Advanced 2015 Física | C13: =COUNTIFS(Temas_TIMSS!$V$5:$V$1264,$A13) -> 121 | D13: =SUMIFS(Temas_TIMSS!$S$5:$S$1264,Temas_TIMSS!$V$5:$V$1264,$A13) -> 8.1666667 | E13: =SUMIFS(Temas_TIMSS!$T$5:$T$1264,Temas_TIMSS!$V$5:$V$1264,$A13) -> 54.666667 | F13: =SUMIFS(Temas_TIMSS!$U$5:$U$1264,Temas_TIMSS!$V$5:$V$1264,$A13) -> 58.166667 | G13: =IF($C13=0,0,D13/$C13) -> 0.067493113 | H13: =IF($C13=0,0,E13/$C13) -> 0.45179063 | I13: =IF($C13=0,0,F13/$C13) -> 0.48071625 | J13: 0.3 | K13: 0.4 | L13: 0.3 | M13: =(I13-L13)*100 -> 18.071625 | N13: =IF(ABS(M13)<=5,"Razonar en línea con la meta",IF(M13>0,"Más Razonar que la meta (revisar si la etiqueta está inflada)","Menos Razonar que la meta: faltan tareas de análisis y argumentación")) -> Más Razonar que la meta (revisar si la etiqueta está inflada)
A14: Física 11° | B14: TIMSS Advanced 2015 Física | C14: =COUNTIFS(Temas_TIMSS!$V$5:$V$1264,$A14) -> 146 | D14: =SUMIFS(Temas_TIMSS!$S$5:$S$1264,Temas_TIMSS!$V$5:$V$1264,$A14) -> 14.5 | E14: =SUMIFS(Temas_TIMSS!$T$5:$T$1264,Temas_TIMSS!$V$5:$V$1264,$A14) -> 63.5 | F14: =SUMIFS(Temas_TIMSS!$U$5:$U$1264,Temas_TIMSS!$V$5:$V$1264,$A14) -> 68 | G14: =IF($C14=0,0,D14/$C14) -> 0.099315068 | H14: =IF($C14=0,0,E14/$C14) -> 0.43493151 | I14: =IF($C14=0,0,F14/$C14) -> 0.46575342 | J14: 0.3 | K14: 0.4 | L14: 0.3 | M14: =(I14-L14)*100 -> 16.575342 | N14: =IF(ABS(M14)<=5,"Razonar en línea con la meta",IF(M14>0,"Más Razonar que la meta (revisar si la etiqueta está inflada)","Menos Razonar que la meta: faltan tareas de análisis y argumentación")) -> Más Razonar que la meta (revisar si la etiqueta está inflada)
A15: Química 10° | B15: TIMSS Advanced Física (ref. aprox.) | C15: =COUNTIFS(Temas_TIMSS!$V$5:$V$1264,$A15) -> 112 | D15: =SUMIFS(Temas_TIMSS!$S$5:$S$1264,Temas_TIMSS!$V$5:$V$1264,$A15) -> 12.833333 | E15: =SUMIFS(Temas_TIMSS!$T$5:$T$1264,Temas_TIMSS!$V$5:$V$1264,$A15) -> 46.833333 | F15: =SUMIFS(Temas_TIMSS!$U$5:$U$1264,Temas_TIMSS!$V$5:$V$1264,$A15) -> 52.333333 | G15: =IF($C15=0,0,D15/$C15) -> 0.11458333 | H15: =IF($C15=0,0,E15/$C15) -> 0.41815476 | I15: =IF($C15=0,0,F15/$C15) -> 0.4672619 | J15: 0.3 | K15: 0.4 | L15: 0.3 | M15: =(I15-L15)*100 -> 16.72619 | N15: =IF(ABS(M15)<=5,"Razonar en línea con la meta",IF(M15>0,"Más Razonar que la meta (revisar si la etiqueta está inflada)","Menos Razonar que la meta: faltan tareas de análisis y argumentación")) -> Más Razonar que la meta (revisar si la etiqueta está inflada)
A16: Química 11° | B16: TIMSS Advanced Física (ref. aprox.) | C16: =COUNTIFS(Temas_TIMSS!$V$5:$V$1264,$A16) -> 97 | D16: =SUMIFS(Temas_TIMSS!$S$5:$S$1264,Temas_TIMSS!$V$5:$V$1264,$A16) -> 12.5 | E16: =SUMIFS(Temas_TIMSS!$T$5:$T$1264,Temas_TIMSS!$V$5:$V$1264,$A16) -> 39.5 | F16: =SUMIFS(Temas_TIMSS!$U$5:$U$1264,Temas_TIMSS!$V$5:$V$1264,$A16) -> 45 | G16: =IF($C16=0,0,D16/$C16) -> 0.12886598 | H16: =IF($C16=0,0,E16/$C16) -> 0.40721649 | I16: =IF($C16=0,0,F16/$C16) -> 0.46391753 | J16: 0.3 | K16: 0.4 | L16: 0.3 | M16: =(I16-L16)*100 -> 16.391753 | N16: =IF(ABS(M16)<=5,"Razonar en línea con la meta",IF(M16>0,"Más Razonar que la meta (revisar si la etiqueta está inflada)","Menos Razonar que la meta: faltan tareas de análisis y argumentación")) -> Más Razonar que la meta (revisar si la etiqueta está inflada)
... A18: Biología 11° | B18: TIMSS Advanced Física (ref. aprox.) | C18: =COUNTIFS(Temas_TIMSS!$V$5:$V$1264,$A18) -> 92 | D18: =SUMIFS(Temas_TIMSS!$S$5:$S$1264,Temas_TIMSS!$V$5:$V$1264,$A18) -> 19.333333 | E18: =SUMIFS(Temas_TIMSS!$T$5:$T$1264,Temas_TIMSS!$V$5:$V$1264,$A18) -> 32.833333 | F18: =SUMIFS(Temas_TIMSS!$U$5:$U$1264,Temas_TIMSS!$V$5:$V$1264,$A18) -> 39.833333 | G18: =IF($C18=0,0,D18/$C18) -> 0.21014493 | H18: =IF($C18=0,0,E18/$C18) -> 0.35688406 | I18: =IF($C18=0,0,F18/$C18) -> 0.43297101 | J18: 0.3 | K18: 0.4 | L18: 0.3 | M18: =(I18-L18)*100 -> 13.297101 | N18: =IF(ABS(M18)<=5,"Razonar en línea con la meta",IF(M18>0,"Más Razonar que la meta (revisar si la etiqueta está inflada)","Menos Razonar que la meta: faltan tareas de análisis y argumentación")) -> Más Razonar que la meta (revisar si la etiqueta está inflada)

Sheet Temas_TIMSS
A1: Trazabilidad: cada tema de las mallas y su clasificación contra TIMSS
A2: Una fila = un procedimental de la malla (un «tema»). Columnas K-L, P-Q: clasificación asistida por IA (revisable). M, N, O y S-U son fórmulas. Para auditar cualquier número del libro, filtra esta hoja por Grupo y Dominio.
A4: ID tema | B4: Grado | C4: Asignatura | D4: Archivo de origen | E4: Hoja | F4: Fila | G4: Unidad | H4: Contenido | I4: Procedimental (tema) | J4: Marco | K4: Objetivo TIMSS principal | L4: Objetivo TIMSS secundario | M4: Dominio (principal) | N4: Área temática (principal) | O4: Dominio (secundario) | P4: Confianza | Q4: Justificación de la clasificación | R4: Habilidad TIMSS (texto de la malla) | S4: Conocer (fracción) | T4: Aplicar (fracción) | U4: Razonar (fracción) | V4: Grupo | W4: Ciclo
A5: T0639-G02-CIE | B5: 2 | C5: Ciencias | D5: Matriz_Ciencias_2do_Grado_U1_U6_3.xlsx | E5: Unidad 1 - Materia | F5: 3 | G5: 1. Materia. | H5: ¿Qué es medir? | I5: 1.1. Manipulación de distintos instrumentos de medición. | J5: T4 | K5: FUERA | M5: =IF(K5="FUERA","Fuera del marco",IF(K5="N/A","Sin marco",IFERROR(INDEX(Catalogo_TIMSS!$C$5:$C$105,MATCH(K5,Catalogo_TIMSS!$A$5:$A$105,0)),"Pendiente de clasificar"))) -> Fuera del marco | N5: =IF(K5="FUERA","Fuera del marco",IF(K5="N/A","Sin marco",IFERROR(INDEX(Catalogo_TIMSS!$F$5:$F$105,MATCH(K5,Catalogo_TIMSS!$A$5:$A$105,0)),"Pendiente de clasificar"))) -> Fuera del marco | O5: =IF(L5="","",IFERROR(INDEX(Catalogo_TIMSS!$C$5:$C$105,MATCH(L5,Catalogo_TIMSS!$A$5:$A$105,0)),"?")) | P5: alta | Q5: Procedimiento general de medición con instrumentos, sin contenido disciplinar | R5: Conocer: reconocer instrumentos. Aplicar: usar instrumentos sencillos | S5: =IFERROR(ISNUMBER(SEARCH("Conocer",$R5))/(ISNUMBER(SEARCH("Conocer",$R5))+ISNUMBER(SEARCH("Aplicar",$R5))+ISNUMBER(SEARCH("Razonar",$R5))),0) -> 0.5 | T5: =IFERROR(ISNUMBER(SEARCH("Aplicar",$R5))/(ISNUMBER(SEARCH("Conocer",$R5))+ISNUMBER(SEARCH("Aplicar",$R5))+ISNUMBER(SEARCH("Razonar",$R5))),0) -> 0.5 | U5: =IFERROR(ISNUMBER(SEARCH("Razonar",$R5))/(ISNUMBER(SEARCH("Conocer",$R5))+ISNUMBER(SEARCH("Aplicar",$R5))+ISNUMBER(SEARCH("Razonar",$R5))),0) -> 0 | V5: 2° | W5: Ciclo 2°–4°
A6: T0640-G02-CIE | B6: 2 | C6: Ciencias | D6: Matriz_Ciencias_2do_Grado_U1_U6_3.xlsx | E6: Unidad 1 - Materia | F6: 4 | G6: 1. Materia. | H6: ¿Qué es medir? | I6: 1.2. Indagación de los conceptos de medición, magnitudes cuantitativas y cualitativas. | J6: T4 | K6: FUERA | M6: =IF(K6="FUERA","Fuera del marco",IF(K6="N/A","Sin marco",IFERROR(INDEX(Catalogo_TIMSS!$C$5:$C$105,MATCH(K6,Catalogo_TIMSS!$A$5:$A$105,0)),"Pendiente de clasificar"))) -> Fuera del marco | N6: =IF(K6="FUERA","Fuera del marco",IF(K6="N/A","Sin marco",IFERROR(INDEX(Catalogo_TIMSS!$F$5:$F$105,MATCH(K6,Catalogo_TIMSS!$A$5:$A$105,0)),"Pendiente de clasificar"))) -> Fuera del marco | O6: =IF(L6="","",IFERROR(INDEX(Catalogo_TIMSS!$C$5:$C$105,MATCH(L6,Catalogo_TIMSS!$A$5:$A$105,0)),"?")) | P6: alta | Q6: Concepto de medir y magnitudes; procedimiento de indagación general | R6: Conocer: describir. Aplicar: comparar | S6: =IFERROR(ISNUMBER(SEARCH("Conocer",$R6))/(ISNUMBER(SEARCH("Conocer",$R6))+ISNUMBER(SEARCH("Aplicar",$R6))+ISNUMBER(SEARCH("Razonar",$R6))),0) -> 0.5 | T6: =IFERROR(ISNUMBER(SEARCH("Aplicar",$R6))/(ISNUMBER(SEARCH("Conocer",$R6))+ISNUMBER(SEARCH("Aplicar",$R6))+ISNUMBER(SEARCH("Razonar",$R6))),0) -> 0.5 | U6: =IFERROR(ISNUMBER(SEARCH("Razonar",$R6))/(ISNUMBER(SEARCH("Conocer",$R6))+ISNUMBER(SEARCH("Aplicar",$R6))+ISNUMBER(SEARCH("Razonar",$R6))),0) -> 0 | V6: 2° | W6: Ciclo 2°–4°
A7: T0641-G02-CIE | B7: 2 | C7: Ciencias | D7: Matriz_Ciencias_2do_Grado_U1_U6_3.xlsx | E7: Unidad 1 - Materia | F7: 5 | G7: 1. Materia. | H7: La materia y sus propiedades. | I7: 1.3. Organización de materiales del entorno por sus propiedades físicas y procedencia. | J7: T4 | K7: T4-F1.2 | M7: =IF(K7="FUERA","Fuera del marco",IF(K7="N/A","Sin marco",IFERROR(INDEX(Catalogo_TIMSS!$C$5:$C$105,MATCH(K7,Catalogo_TIMSS!$A$5:$A$105,0)),"Pendiente de clasificar"))) -> Ciencias físicas | N7: =IF(K7="FUERA","Fuera del marco",IF(K7="N/A","Sin marco",IFERROR(INDEX(Catalogo_TIMSS!$F$5:$F$105,MATCH(K7,Catalogo_TIMSS!$A$5:$A$105,0)),"Pendiente de clasificar"))) -> Clasificación y propiedades de la materia y sus cambios | O7: =IF(L7="","",IFERROR(INDEX(Catalogo_TIMSS!$C$5:$C$105,MATCH(L7,Catalogo_TIMSS!$A$5:$A$105,0)),"?")) | P7: alta | Q7: Clasifica materiales por propiedades físicas y procedencia | R7: Aplicar: clasificar | S7: =IFERROR(ISNUMBER(SEARCH("Conocer",$R7))/(ISNUMBER(SEARCH("Conocer",$R7))+ISNUMBER(SEARCH("Aplicar",$R7))+ISNUMBER(SEARCH("Razonar",$R7))),0) -> 0 | T7: =IFERROR(ISNUMBER(SEARCH("Aplicar",$R7))/(ISNUMBER(SEARCH("Conocer",$R7))+ISNUMBER(SEARCH("Aplicar",$R7))+ISNUMBER(SEARCH("Razonar",$R7))),0) -> 1 | U7: =IFERROR(ISNUMBER(SEARCH("Razonar",$R7))/(ISNUMBER(SEARCH("Conocer",$R7))+ISNUMBER(SEARCH("Aplicar",$R7))+ISNUMBER(SEARCH("Razonar",$R7))),0) -> 0 | V7: 2° | W7: Ciclo 2°–4°
A8: T0642-G02-CIE | B8: 2 | C8: Ciencias | D8: Matriz_Ciencias_2do_Grado_U1_U6_3.xlsx | E8: Unidad 1 - Materia | F8: 6 | G8: 1. Materia. | H8: La materia y sus propiedades. | I8: 1.4. Manipulación de materiales del entorno para identificar sus propiedades físicas. | J8: T4 | K8: T4-F1.2 | M8: =IF(K8="FUERA","Fuera del marco",IF(K8="N/A","Sin marco",IFERROR(INDEX(Catalogo_TIMSS!$C$5:$C$105,MATCH(K8,Catalogo_TIMSS!$A$5:$A$105,0)),"Pendiente de clasificar"))) -> Ciencias físicas | N8: =IF(K8="FUERA","Fuera del marco",IF(K8="N/A","Sin marco",IFERROR(INDEX(Catalogo_TIMSS!$F$5:$F$105,MATCH(K8,Catalogo_TIMSS!$A$5:$A$105,0)),"Pendiente de clasificar"))) -> Clasificación y propiedades de la materia y sus cambios | O8: =IF(L8="","",IFERROR(INDEX(Catalogo_TIMSS!$C$5:$C$105,MATCH(L8,Catalogo_TIMSS!$A$5:$A$105,0)),"?")) | P8: alta | Q8: Identifica propiedades físicas de materiales mediante pruebas sencillas | R8: Conocer: identificar. Aplicar: comparar | S8: =IFERROR(ISNUMBER(SEARCH("Conocer",$R8))/(ISNUMBER(SEARCH("Conocer",$R8))+ISNUMBER(SEARCH("Aplicar",$R8))+ISNUMBER(SEARCH("Razonar",$R8))),0) -> 0.5 | T8: =IFERROR(ISNUMBER(SEARCH("Aplicar",$R8))/(ISNUMBER(SEARCH("Conocer",$R8))+ISNUMBER(SEARCH("Aplicar",$R8))+ISNUMBER(SEARCH("Razonar",$R8))),0) -> 0.5 | U8: =IFERROR(ISNUMBER(SEARCH("Razonar",$R8))/(ISNUMBER(SEARCH("Conocer",$R8))+ISNUMBER(SEARCH("Aplicar",$R8))+ISNUMBER(SEARCH("Razonar",$R8))),0) -> 0 | V8: 2° | W8: Ciclo 2°–4°
A9: T0643-G02-CIE | B9: 2 | C9: Ciencias | D9: Matriz_Ciencias_2do_Grado_U1_U6_3.xlsx | E9: Unidad 1 - Materia | F9: 7 | G9: 1. Materia. | H9: La materia y sus propiedades. | I9: 1.5. Relación entre las propiedades físicas y la utilidad de los materiales. | J9: T4 | K9: T4-F1.2 | M9: =IF(K9="FUERA","Fuera del marco",IF(K9="N/A","Sin marco",IFERROR(INDEX(Catalogo_TIMSS!$C$5:$C$105,MATCH(K9,Catalogo_TIMSS!$A$5:$A$105,0)),"Pendiente de clasificar"))) -> Ciencias físicas | N9: =IF(K9="FUERA","Fuera del marco",IF(K9="N/A","Sin marco",IFERROR(INDEX(Catalogo_TIMSS!$F$5:$F$105,MATCH(K9,Catalogo_TIMSS!$A$5:$A$105,0)),"Pendiente de clasificar"))) -> Clasificación y propiedades de la materia y sus cambios | O9: =IF(L9="","",IFERROR(INDEX(Catalogo_TIMSS!$C$5:$C$105,MATCH(L9,Catalogo_TIMSS!$A$5:$A$105,0)),"?")) | P9: alta | Q9: Relaciona propiedades físicas de materiales con su utilidad | R9: Aplicar: relacionar. Razonar: justificar con sus palabras | S9: =IFERROR(ISNUMBER(SEARCH("Conocer",$R9))/(ISNUMBER(SEARCH("Conocer",$R9))+ISNUMBER(SEARCH("Aplicar",$R9))+ISNUMBER(SEARCH("Razonar",$R9))),0) -> 0 | T9: =IFERROR(ISNUMBER(SEARCH("Aplicar",$R9))/(ISNUMBER(SEARCH("Conocer",$R9))+ISNUMBER(SEARCH("Aplicar",$R9))+ISNUMBER(SEARCH("Razonar",$R9))),0) -> 0.5 | U9: =IFERROR(ISNUMBER(SEARCH("Razonar",$R9))/(ISNUMBER(SEARCH("Conocer",$R9))+ISNUMBER(SEARCH("Aplicar",$R9))+ISNUMBER(SEARCH("Razonar",$R9))),0) -> 0.5 | V9: 2° | W9: Ciclo 2°–4°
A10: T0644-G02-CIE | B10: 2 | C10: Ciencias | D10: Matriz_Ciencias_2do_Grado_U1_U6_3.xlsx | E10: Unidad 1 - Materia | F10: 8 | G10: 1. Materia. | H10: Transformaciones de la materia. | I10: 1.6. Reconocimiento de las propiedades químicas de la materia. | J10: T4 | K10: T4-F1.5 | M10: =IF(K10="FUERA","Fuera del marco",IF(K10="N/A","Sin marco",IFERROR(INDEX(Catalogo_TIMSS!$C$5:$C$105,MATCH(K10,Catalogo_TIMSS!$A$5:$A$105,0)),"Pendiente de clasificar"))) -> Ciencias físicas | N10: =IF(K10="FUERA","Fuera del marco",IF(K10="N/A","Sin marco",IFERROR(INDEX(Catalogo_TIMSS!$F$5:$F$105,MATCH(K10,Catalogo_TIMSS!$A$5:$A$105,0)),"Pendiente de clasificar"))) -> Clasificación y propiedades de la materia y sus cambios | O10: =IF(L10="","",IFERROR(INDEX(Catalogo_TIMSS!$C$5:$C$105,MATCH(L10,Catalogo_TIMSS!$A$5:$A$105,0)),"?")) | P10: alta | Q10: Reconoce cambios químicos observables e irreversibles en materiales cotidianos | R10: Conocer: reconocer y dar ejemplos | S10: =IFERROR(ISNUMBER(SEARCH("Conocer",$R10))/(ISNUMBER(SEARCH("Conocer",$R10))+ISNUMBER(SEARCH("Aplicar",$R10))+ISNUMBER(SEARCH("Razonar",$R10))),0) -> 1 | T10: =IFERROR(ISNUMBER(SEARCH("Aplicar",$R10))/(ISNUMBER(SEARCH("Conocer",$R10))+ISNUMBER(SEARCH("Aplicar",$R10))+ISNUMBER(SEARCH("Razonar",$R10))),0) -> 0 | U10: =IFERROR(ISNUMBER(SEARCH("Razonar",$R10))/(ISNUMBER(SEARCH("Conocer",$R10))+ISNUMBER(SEARCH("Aplicar",$R10))+ISNUMBER(SEARCH("Razonar",$R10))),0) -> 0 | V10: 2° | W10: Ciclo 2°–4°
A11: T0645-G02-CIE | B11: 2 | C11: Ciencias | D11: Matriz_Ciencias_2do_Grado_U1_U6_3.xlsx | E11: Unidad 1 - Materia | F11: 9 | G11: 1. Materia. | H11: Transformaciones de la materia. | I11: 1.7. Experimentación con las propiedades químicas de la materia. | J11: T4 | K11: T4-F1.5 | M11: =IF(K11="FUERA","Fuera del marco",IF(K11="N/A","Sin marco",IFERROR(INDEX(Catalogo_TIMSS!$C$5:$C$105,MATCH(K11,Catalogo_TIMSS!$A$5:$A$105,0)),"Pendiente de clasificar"))) -> Ciencias físicas | N11: =IF(K11="FUERA","Fuera del marco",IF(K11="N/A","Sin marco",IFERROR(INDEX(Catalogo_TIMSS!$F$5:$F$105,MATCH(K11,Catalogo_TIMSS!$A$5:$A$105,0)),"Pendiente de clasificar"))) -> Clasificación y propiedades de la materia y sus cambios | O11: =IF(L11="","",IFERROR(INDEX(Catalogo_TIMSS!$C$5:$C$105,MATCH(L11,Catalogo_TIMSS!$A$5:$A$105,0)),"?")) | P11: alta | Q11: Experimenta un cambio químico (bicarbonato y vinagre) | R11: Razonar: predecir y extraer conclusiones sencillas | S11: =IFERROR(ISNUMBER(SEARCH("Conocer",$R11))/(ISNUMBER(SEARCH("Conocer",$R11))+ISNUMBER(SEARCH("Aplicar",$R11))+ISNUMBER(SEARCH("Razonar",$R11))),0) -> 0 | T11: =IFERROR(ISNUMBER(SEARCH("Aplicar",$R11))/(ISNUMBER(SEARCH("Conocer",$R11))+ISNUMBER(SEARCH("Aplicar",$R11))+ISNUMBER(SEARCH("Razonar",$R11))),0) -> 0 | U11: =IFERROR(ISNUMBER(SEARCH("Razonar",$R11))/(ISNUMBER(SEARCH("Conocer",$R11))+ISNUMBER(SEARCH("Aplicar",$R11))+ISNUMBER(SEARCH("Razonar",$R11))),0) -> 1 | V11: 2° | W11: Ciclo 2°–4°
A12: T0646-G02-CIE | B12: 2 | C12: Ciencias | D12: Matriz_Ciencias_2do_Grado_U1_U6_3.xlsx | E12: Unidad 1 - Materia | F12: 10 | G12: 1. Materia. | H12: Estados de la materia y sus cambios. | I12: 1.8. Observación de los cambios de estado del agua al calentarla o enfriarla. | J12: T4 | K12: T4-F1.4 | L12: T4-F1.1 | M12: =IF(K12="FUERA","Fuera del marco",IF(K12="N/A","Sin marco",IFERROR(INDEX(Catalogo_TIMSS!$C$5:$C$105,MATCH(K12,Catalogo_TIMSS!$A$5:$A$105,0)),"Pendiente de clasificar"))) -> Ciencias físicas | N12: =IF(K12="FUERA","Fuera del marco",IF(K12="N/A","Sin marco",IFERROR(INDEX(Catalogo_TIMSS!$F$5:$F$105,MATCH(K12,Catalogo_TIMSS!$A$5:$A$105,0)),"Pendiente de clasificar"))) -> Clasificación y propiedades de la materia y sus cambios | O12: =IF(L12="","",IFERROR(INDEX(Catalogo_TIMSS!$C$5:$C$105,MATCH(L12,Catalogo_TIMSS!$A$5:$A$105,0)),"?")) -> Ciencias físicas | P12: alta | Q12: Cambios de estado del agua por calentamiento o enfriamiento | R12: Aplicar: relacionar | S12: =IFERROR(ISNUMBER(SEARCH("Conocer",$R12))/(ISNUMBER(SEARCH("Conocer",$R12))+ISNUMBER(SEARCH("Aplicar",$R12))+ISNUMBER(SEARCH("Razonar",$R12))),0) -> 0 | T12: =IFERROR(ISNUMBER(SEARCH("Aplicar",$R12))/(ISNUMBER(SEARCH("Conocer",$R12))+ISNUMBER(SEARCH("Aplicar",$R12))+ISNUMBER(SEARCH("Razonar",$R12))),0) -> 1 | U12: =IFERROR(ISNUMBER(SEARCH("Razonar",$R12))/(ISNUMBER(SEARCH("Conocer",$R12))+ISNUMBER(SEARCH("Aplicar",$R12))+ISNUMBER(SEARCH("Razonar",$R12))),0) -> 0 | V12: 2° | W12: Ciclo 2°–4°
A13: T0647-G02-CIE | B13: 2 | C13: Ciencias | D13: Matriz_Ciencias_2do_Grado_U1_U6_3.xlsx | E13: Unidad 1 - Materia | F13: 11 | G13: 1. Materia. | H13: Mezclas. | I13: 1.9. Preparación de mezclas sencillas y separación de sus componentes a mano, con colador o tamiz. | J13: T4 | K13: T4-F1.2 | M13: =IF(K13="FUERA","Fuera del marco",IF(K13="N/A","Sin marco",IFERROR(INDEX(Catalogo_TIMSS!$C$5:$C$105,MATCH(K13,Catalogo_TIMSS!$A$5:$A$105,0)),"Pendiente de clasificar"))) -> Ciencias físicas | N13: =IF(K13="FUERA","Fuera del marco",IF(K13="N/A","Sin marco",IFERROR(INDEX(Catalogo_TIMSS!$F$5:$F$105,MATCH(K13,Catalogo_TIMSS!$A$5:$A$105,0)),"Pendiente de clasificar"))) -> Clasificación y propiedades de la materia y sus cambios | O13: =IF(L13="","",IFERROR(INDEX(Catalogo_TIMSS!$C$5:$C$105,MATCH(L13,Catalogo_TIMSS!$A$5:$A$105,0)),"?")) | P13: alta | Q13: Mezclas y separación de componentes con herramientas sencillas | R13: Aplicar: clasificar. Razonar: elegir un procedimiento | S13: =IFERROR(ISNUMBER(SEARCH("Conocer",$R13))/(ISNUMBER(SEARCH("Conocer",$R13))+ISNUMBER(SEARCH("Aplicar",$R13))+ISNUMBER(SEARCH("Razonar",$R13))),0) -> 0 | T13: =IFERROR(ISNUMBER(SEARCH("Aplicar",$R13))/(ISNUMBER(SEARCH("Conocer",$R13))+ISNUMBER(SEARCH("Aplicar",$R13))+ISNUMBER(SEARCH("Razonar",$R13))),0) -> 0.5 | U13: =IFERROR(ISNUMBER(SEARCH("Razonar",$R13))/(ISNUMBER(SEARCH("Conocer",$R13))+ISNUMBER(SEARCH("Aplicar",$R13))+ISNUMBER(SEARCH("Razonar",$R13))),0) -> 0.5 | V13: 2° | W13: Ciclo 2°–4°
A14: T0648-G02-CIE | B14: 2 | C14: Ciencias | D14: Matriz_Ciencias_2do_Grado_U1_U6_3.xlsx | E14: Unidad 1 - Materia | F14: 12 | G14: 1. Materia. | H14: ¿Flota o se hunde? | I14: 1.10. Predicción y comprobación de objetos que flotan o se hunden en el agua. | J14: T4 | K14: T4-F1.2 | M14: =IF(K14="FUERA","Fuera del marco",IF(K14="N/A","Sin marco",IFERROR(INDEX(Catalogo_TIMSS!$C$5:$C$105,MATCH(K14,Catalogo_TIMSS!$A$5:$A$105,0)),"Pendiente de clasificar"))) -> Ciencias físicas | N14: =IF(K14="FUERA","Fuera del marco",IF(K14="N/A","Sin marco",IFERROR(INDEX(Catalogo_TIMSS!$F$5:$F$105,MATCH(K14,Catalogo_TIMSS!$A$5:$A$105,0)),"Pendiente de clasificar"))) -> Clasificación y propiedades de la materia y sus cambios | O14: =IF(L14="","",IFERROR(INDEX(Catalogo_TIMSS!$C$5:$C$105,MATCH(L14,Catalogo_TIMSS!$A$5:$A$105,0)),"?")) | P14: media | Q14: Flotación como propiedad física para comparar y clasificar objetos | R14: Razonar: predecir y comprobar | S14: =IFERROR(ISNUMBER(SEARCH("Conocer",$R14))/(ISNUMBER(SEARCH("Conocer",$R14))+ISNUMBER(SEARCH("Aplicar",$R14))+ISNUMBER(SEARCH("Razonar",$R14))),0) -> 0 | T14: =IFERROR(ISNUMBER(SEARCH("Aplicar",$R14))/(ISNUMBER(SEARCH("Conocer",$R14))+ISNUMBER(SEARCH("Aplicar",$R14))+ISNUMBER(SEARCH("Razonar",$R14))),0) -> 0 | U14: =IFERROR(ISNUMBER(SEARCH("Razonar",$R14))/(ISNUMBER(SEARCH("Conocer",$R14))+ISNUMBER(SEARCH("Aplicar",$R14))+ISNUMBER(SEARCH("Razonar",$R14))),0) -> 1 | V14: 2° | W14: Ciclo 2°–4°
A15: T0649-G02-CIE | B15: 2 | C15: Ciencias | D15: Matriz_Ciencias_2do_Grado_U1_U6_3.xlsx | E15: Unidad 1 - Materia | F15: 13 | G15: 1. Materia. | H15: Los materiales y el ambiente. | I15: 1.11. Reutilización de materiales de desecho según sus propiedades para darles un nuevo uso. | J15: T4 | K15: T4-F1.2 | L15: T4-T1.2 | M15: =IF(K15="FUERA","Fuera del marco",IF(K15="N/A","Sin marco",IFERROR(INDEX(Catalogo_TIMSS!$C$5:$C$105,MATCH(K15,Catalogo_TIMSS!$A$5:$A$105,0)),"Pendiente de clasificar"))) -> Ciencias físicas | N15: =IF(K15="FUERA","Fuera del marco",IF(K15="N/A","Sin marco",IFERROR(INDEX(Catalogo_TIMSS!$F$5:$F$105,MATCH(K15,Catalogo_TIMSS!$A$5:$A$105,0)),"Pendiente de clasificar"))) -> Clasificación y propiedades de la materia y sus cambios | O15: =IF(L15="","",IFERROR(INDEX(Catalogo_TIMSS!$C$5:$C$105,MATCH(L15,Catalogo_TIMSS!$A$5:$A$105,0)),"?")) -> Ciencias de la Tierra | P15: media | Q15: Reutiliza desechos según sus propiedades físicas; uso responsable de recursos | R15: Aplicar: relacionar propiedades y usos. Razonar: justificar con sus palabras | S15: =IFERROR(ISNUMBER(SEARCH("Conocer",$R15))/(ISNUMBER(SEARCH("Conocer",$R15))+ISNUMBER(SEARCH("Aplicar",$R15))+ISNUMBER(SEARCH("Razonar",$R15))),0) -> 0 | T15: =IFERROR(ISNUMBER(SEARCH("Aplicar",$R15))/(ISNUMBER(SEARCH("Conocer",$R15))+ISNUMBER(SEARCH("Aplicar",$R15))+ISNUMBER(SEARCH("Razonar",$R15))),0) -> 0.5 | U15: =IFERROR(ISNUMBER(SEARCH("Razonar",$R15))/(ISNUMBER(SEARCH("Conocer",$R15))+ISNUMBER(SEARCH("Aplicar",$R15))+ISNUMBER(SEARCH("Razonar",$R15))),0) -> 0.5 | V15: 2° | W15: Ciclo 2°–4°
A16: T0650-G02-CIE | B16: 2 | C16: Ciencias | D16: Matriz_Ciencias_2do_Grado_U1_U6_3.xlsx | E16: Unidad 2 - Energía | F16: 3 | G16: 2. Energía. | H16: La energía | I16: 2.1. Observación de fenómenos donde la energía es visible. | J16: T4 | K16: T4-F2.1 | M16: =IF(K16="FUERA","Fuera del marco",IF(K16="N/A","Sin marco",IFERROR(INDEX(Catalogo_TIMSS!$C$5:$C$105,MATCH(K16,Catalogo_TIMSS!$A$5:$A$105,0)),"Pendiente de clasificar"))) -> Ciencias físicas | N16: =IF(K16="FUERA","Fuera del marco",IF(K16="N/A","Sin marco",IFERROR(INDEX(Catalogo_TIMSS!$F$5:$F$105,MATCH(K16,Catalogo_TIMSS!$A$5:$A$105,0)),"Pendiente de clasificar"))) -> Formas de energía y transferencia de energía | O16: =IF(L16="","",IFERROR(INDEX(Catalogo_TIMSS!$C$5:$C$105,MATCH(L16,Catalogo_TIMSS!$A$5:$A$105,0)),"?")) | P16: media | Q16: Reconoce la energía en fenómenos cotidianos y sus manifestaciones | R16: Conocer: identificar y dar ejemplos | S16: =IFERROR(ISNUMBER(SEARCH("Conocer",$R16))/(ISNUMBER(SEARCH("Conocer",$R16))+ISNUMBER(SEARCH("Aplicar",$R16))+ISNUMBER(SEARCH("Razonar",$R16))),0) -> 1 | T16: =IFERROR(ISNUMBER(SEARCH("Aplicar",$R16))/(ISNUMBER(SEARCH("Conocer",$R16))+ISNUMBER(SEARCH("Aplicar",$R16))+ISNUMBER(SEARCH("Razonar",$R16))),0) -> 0 | U16: =IFERROR(ISNUMBER(SEARCH("Razonar",$R16))/(ISNUMBER(SEARCH("Conocer",$R16))+ISNUMBER(SEARCH("Aplicar",$R16))+ISNUMBER(SEARCH("Razonar",$R16))),0) -> 0 | V16: 2° | W16: Ciclo 2°–4°
A17: T0651-G02-CIE | B17: 2 | C17: Ciencias | D17: Matriz_Ciencias_2do_Grado_U1_U6_3.xlsx | E17: Unidad 2 - Energía | F17: 4 | G17: 2. Energía. | H17: Formas de energía. | I17: 2.1. Experimentación con la energía mecánica, utilizando objetos de su entorno. | J17: T4 | K17: T4-F3.1 | M17: =IF(K17="FUERA","Fuera del marco",IF(K17="N/A","Sin marco",IFERROR(INDEX(Catalogo_TIMSS!$C$5:$C$105,MATCH(K17,Catalogo_TIMSS!$A$5:$A$105,0)),"Pendiente de clasificar"))) -> Ciencias físicas | N17: =IF(K17="FUERA","Fuera del marco",IF(K17="N/A","Sin marco",IFERROR(INDEX(Catalogo_TIMSS!$F$5:$F$105,MATCH(K17,Catalogo_TIMSS!$A$5:$A$105,0)),"Pendiente de clasificar"))) -> Fuerzas y movimiento | O17: =IF(L17="","",IFERROR(INDEX(Catalogo_TIMSS!$C$5:$C$105,MATCH(L17,Catalogo_TIMSS!$A$5:$A$105,0)),"?")) | P17: alta | Q17: Empujar o jalar más fuerte cambia el movimiento de objetos | R17: Aplicar: comparar. Razonar: predecir | S17: =IFERROR(ISNUMBER(SEARCH("Conocer",$R17))/(ISNUMBER(SEARCH("Conocer",$R17))+ISNUMBER(SEARCH("Aplicar",$R17))+ISNUMBER(SEARCH("Razonar",$R17))),0) -> 0 | T17: =IFERROR(ISNUMBER(SEARCH("Aplicar",$R17))/(ISNUMBER(SEARCH("Conocer",$R17))+ISNUMBER(SEARCH("Aplicar",$R17))+ISNUMBER(SEARCH("Razonar",$R17))),0) -> 0.5 | U17: =IFERROR(ISNUMBER(SEARCH("Razonar",$R17))/(ISNUMBER(SEARCH("Conocer",$R17))+ISNUMBER(SEARCH("Aplicar",$R17))+ISNUMBER(SEARCH("Razonar",$R17))),0) -> 0.5 | V17: 2° | W17: Ciclo 2°–4°
A18: T0652-G02-CIE | B18: 2 | C18: Ciencias | D18: Matriz_Ciencias_2do_Grado_U1_U6_3.xlsx | E18: Unidad 2 - Energía | F18: 5 | G18: 2. Energía. | H18: Formas de energía. | I18: 2.2. Indagación de los dispositivos que requieren electricidad y su fuente de energía. | J18: T4 | K18: T4-F2.1 | L18: T4-F2.4 | M18: =IF(K18="FUERA","Fuera del marco",IF(K18="N/A","Sin marco",IFERROR(INDEX(Catalogo_TIMSS!$C$5:$C$105,MATCH(K18,Catalogo_TIMSS!$A$5:$A$105,0)),"Pendiente de clasificar"))) -> Ciencias físicas | N18: =IF(K18="FUERA","Fuera del marco",IF(K18="N/A","Sin marco",IFERROR(INDEX(Catalogo_TIMSS!$F$5:$F$105,MATCH(K18,Catalogo_TIMSS!$A$5:$A$105,0)),"Pendiente de clasificar"))) -> Formas de energía y transferencia de energía | O18: =IF(L18="","",IFERROR(INDEX(Catalogo_TIMSS!$C$5:$C$105,MATCH(L18,Catalogo_TIMSS!$A$5:$A$105,0)),"?")) -> Ciencias físicas | P18: media | Q18: Aparatos eléctricos y sus fuentes de energía (enchufe o pilas) | R18: Aplicar: clasificar | S18: =IFERROR(ISNUMBER(SEARCH("Conocer",$R18))/(ISNUMBER(SEARCH("Conocer",$R18))+ISNUMBER(SEARCH("Aplicar",$R18))+ISNUMBER(SEARCH("Razonar",$R18))),0) -> 0 | T18: =IFERROR(ISNUMBER(SEARCH("Aplicar",$R18))/(ISNUMBER(SEARCH("Conocer",$R18))+ISNUMBER(SEARCH("Aplicar",$R18))+ISNUMBER(SEARCH("Razonar",$R18))),0) -> 1 | U18: =IFERROR(ISNUMBER(SEARCH("Razonar",$R18))/(ISNUMBER(SEARCH("Conocer",$R18))+ISNUMBER(SEARCH("Aplicar",$R18))+ISNUMBER(SEARCH("Razonar",$R18))),0) -> 0 | V18: 2° | W18: Ciclo 2°–4°
A19: T0653-G02-CIE | B19: 2 | C19: Ciencias | D19: Matriz_Ciencias_2do_Grado_U1_U6_3.xlsx | E19: Unidad 2 - Energía | F19: 6 | G19: 2. Energía. | H19: Formas de energía. | I19: 2.3. Identificación de fuentes naturales de energía eléctrica. | J19: T4 | K19: T4-F2.1 | M19: =IF(K19="FUERA","Fuera del marco",IF(K19="N/A","Sin marco",IFERROR(INDEX(Catalogo_TIMSS!$C$5:$C$105,MATCH(K19,Catalogo_TIMSS!$A$5:$A$105,0)),"Pendiente de clasificar"))) -> Ciencias físicas | N19: =IF(K19="FUERA","Fuera del marco",IF(K19="N/A","Sin marco",IFERROR(INDEX(Catalogo_TIMSS!$F$5:$F$105,MATCH(K19,Catalogo_TIMSS!$A$5:$A$105,0)),"Pendiente de clasificar"))) -> Formas de energía y transferencia de energía | O19: =IF(L19="","",IFERROR(INDEX(Catalogo_TIMSS!$C$5:$C$105,MATCH(L19,Catalogo_TIMSS!$A$5:$A$105,0)),"?")) | P19: alta | Q19: Fuentes naturales para obtener electricidad (sol, agua, geotermia) | R19: Conocer: reconocer. Aplicar: relacionar | S19: =IFERROR(ISNUMBER(SEARCH("Conocer",$R19))/(ISNUMBER(SEARCH("Conocer",$R19))+ISNUMBER(SEARCH("Aplicar",$R19))+ISNUMBER(SEARCH("Razonar",$R19))),0) -> 0.5 | T19: =IFERROR(ISNUMBER(SEARCH("Aplicar",$R19))/(ISNUMBER(SEARCH("Conocer",$R19))+ISNUMBER(SEARCH("Aplicar",$R19))+ISNUMBER(SEARCH("Razonar",$R19))),0) -> 0.5 | U19: =IFERROR(ISNUMBER(SEARCH("Razonar",$R19))/(ISNUMBER(SEARCH("Conocer",$R19))+ISNUMBER(SEARCH("Aplicar",$R19))+ISNUMBER(SEARCH("Razonar",$R19))),0) -> 0 | V19: 2° | W19: Ciclo 2°–4°
A20: T0654-G02-CIE | B20: 2 | C20: Ciencias | D20: Matriz_Ciencias_2do_Grado_U1_U6_3.xlsx | E20: Unidad 2 - Energía | F20: 7 | G20: 2. Energía. | H20: Formas de energía. | I20: 2.4. Indagación de las fuentes de energía térmica del entorno. | J20: T4 | K20: T4-F2.1 | M20: =IF(K20="FUERA","Fuera del marco",IF(K20="N/A","Sin marco",IFERROR(INDEX(Catalogo_TIMSS!$C$5:$C$105,MATCH(K20,Catalogo_TIMSS!$A$5:$A$105,0)),"Pendiente de clasificar"))) -> Ciencias físicas | N20: =IF(K20="FUERA","Fuera del marco",IF(K20="N/A","Sin marco",IFERROR(INDEX(Catalogo_TIMSS!$F$5:$F$105,MATCH(K20,Catalogo_TIMSS!$A$5:$A$105,0)),"Pendiente de clasificar"))) -> Formas de energía y transferencia de energía | O20: =IF(L20="","",IFERROR(INDEX(Catalogo_TIMSS!$C$5:$C$105,MATCH(L20,Catalogo_TIMSS!$A$5:$A$105,0)),"?")) | P20: media | Q20: Fuentes de calor del entorno y su uso seguro | R20: Conocer: identificar. Aplicar: comparar | S20: =IFERROR(ISNUMBER(SEARCH("Conocer",$R20))/(ISNUMBER(SEARCH("Conocer",$R20))+ISNUMBER(SEARCH("Aplicar",$R20))+ISNUMBER(SEARCH("Razonar",$R20))),0) -> 0.5 | T20: =IFERROR(ISNUMBER(SEARCH("Aplicar",$R20))/(ISNUMBER(SEARCH("Conocer",$R20))+ISNUMBER(SEARCH("Aplicar",$R20))+ISNUMBER(SEARCH("Razonar",$R20))),0) -> 0.5 | U20: =IFERROR(ISNUMBER(SEARCH("Razonar",$R20))/(ISNUMBER(SEARCH("Conocer",$R20))+ISNUMBER(SEARCH("Aplicar",$R20))+ISNUMBER(SEARCH("Razonar",$R20))),0) -> 0 | V20: 2° | W20: Ciclo 2°–4°
A21: T0655-G02-CIE | B21: 2 | C21: Ciencias | D21: Matriz_Ciencias_2do_Grado_U1_U6_3.xlsx | E21: Unidad 2 - Energía | F21: 8 | G21: 2. Energía. | H21: Formas de energía. | I21: 2.5. Exploración de sonidos producidos al hacer vibrar objetos del entorno (ligas, vasos con agua, tambores caseros). | J21: T4 | K21: T4-F2.2 | M21: =IF(K21="FUERA","Fuera del marco",IF(K21="N/A","Sin marco",IFERROR(INDEX(Catalogo_TIMSS!$C$5:$C$105,MATCH(K21,Catalogo_TIMSS!$A$5:$A$105,0)),"Pendiente de clasificar"))) -> Ciencias físicas | N21: =IF(K21="FUERA","Fuera del marco",IF(K21="N/A","Sin marco",IFERROR(INDEX(Catalogo_TIMSS!$F$5:$F$105,MATCH(K21,Catalogo_TIMSS!$A$5:$A$105,0)),"Pendiente de clasificar"))) -> Formas de energía y transferencia de energía | O21: =IF(L21="","",IFERROR(INDEX(Catalogo_TIMSS!$C$5:$C$105,MATCH(L21,Catalogo_TIMSS!$A$5:$A$105,0)),"?")) | P21: alta | Q21: Sonido producido por vibraciones; agudo y grave | R21: Conocer: identificar y describir. Aplicar: comparar | S21: =IFERROR(ISNUMBER(SEARCH("Conocer",$R21))/(ISNUMBER(SEARCH("Conocer",$R21))+ISNUMBER(SEARCH("Aplicar",$R21))+ISNUMBER(SEARCH("Razonar",$R21))),0) -> 0.5 | T21: =IFERROR(ISNUMBER(SEARCH("Aplicar",$R21))/(ISNUMBER(SEARCH("Conocer",$R21))+ISNUMBER(SEARCH("Aplicar",$R21))+ISNUMBER(SEARCH("Razonar",$R21))),0) -> 0.5 | U21: =IFERROR(ISNUMBER(SEARCH("Razonar",$R21))/(ISNUMBER(SEARCH("Conocer",$R21))+ISNUMBER(SEARCH("Aplicar",$R21))+ISNUMBER(SEARCH("Razonar",$R21))),0) -> 0 | V21: 2° | W21: Ciclo 2°–4°
A22: T0656-G02-CIE | B22: 2 | C22: Ciencias | D22: Matriz_Ciencias_2do_Grado_U1_U6_3.xlsx | E22: Unidad 2 - Energía | F22: 9 | G22: 2. Energía. | H22: Fuentes de energía. | I22: 2.6. Comparación de objetos colocados al sol y a la sombra para observar el efecto de la energía solar. | J22: T4 | K22: T4-F2.1 | L22: T4-F2.3 | M22: =IF(K22="FUERA","Fuera del marco",IF(K22="N/A","Sin marco",IFERROR(INDEX(Catalogo_TIMSS!$C$5:$C$105,MATCH(K22,Catalogo_TIMSS!$A$5:$A$105,0)),"Pendiente de clasificar"))) -> Ciencias físicas | N22: =IF(K22="FUERA","Fuera del marco",IF(K22="N/A","Sin marco",IFERROR(INDEX(Catalogo_TIMSS!$F$5:$F$105,MATCH(K22,Catalogo_TIMSS!$A$5:$A$105,0)),"Pendiente de clasificar"))) -> Formas de energía y transferencia de energía | O22: =IF(L22="","",IFERROR(INDEX(Catalogo_TIMSS!$C$5:$C$105,MATCH(L22,Catalogo_TIMSS!$A$5:$A$105,0)),"?")) -> Ciencias físicas | P22: media | Q22: El Sol como fuente de calor que calienta objetos | R22: Razonar: predecir y extraer conclusiones sencillas | S22: =IFERROR(ISNUMBER(SEARCH("Conocer",$R22))/(ISNUMBER(SEARCH("Conocer",$R22))+ISNUMBER(SEARCH("Aplicar",$R22))+ISNUMBER(SEARCH("Razonar",$R22))),0) -> 0 | T22: =IFERROR(ISNUMBER(SEARCH("Aplicar",$R22))/(ISNUMBER(SEARCH("Conocer",$R22))+ISNUMBER(SEARCH("Aplicar",$R22))+ISNUMBER(SEARCH("Razonar",$R22))),0) -> 0 | U22: =IFERROR(ISNUMBER(SEARCH("Razonar",$R22))/(ISNUMBER(SEARCH("Conocer",$R22))+ISNUMBER(SEARCH("Aplicar",$R22))+ISNUMBER(SEARCH("Razonar",$R22))),0) -> 1 | V22: 2° | W22: Ciclo 2°–4°
A23: T0657-G02-CIE | B23: 2 | C23: Ciencias | D23: Matriz_Ciencias_2do_Grado_U1_U6_3.xlsx | E23: Unidad 2 - Energía | F23: 10 | G23: 2. Energía. | H23: Uso responsable de la energía. | I23: 2.7. Identificación de acciones sencillas para ahorrar energía eléctrica en el hogar y la escuela. | J23: T4 | K23: T4-T1.2 | M23: =IF(K23="FUERA","Fuera del marco",IF(K23="N/A","Sin marco",IFERROR(INDEX(Catalogo_TIMSS!$C$5:$C$105,MATCH(K23,Catalogo_TIMSS!$A$5:$A$105,0)),"Pendiente de clasificar"))) -> Ciencias de la Tierra | N23: =IF(K23="FUERA","Fuera del marco",IF(K23="N/A","Sin marco",IFERROR(INDEX(Catalogo_TIMSS!$F$5:$F$105,MATCH(K23,Catalogo_TIMSS!$A$5:$A$105,0)),"Pendiente de clasificar"))) -> Características físicas, recursos e historia de la Tierra | O23: =IF(L23="","",IFERROR(INDEX(Catalogo_TIMSS!$C$5:$C$105,MATCH(L23,Catalogo_TIMSS!$A$5:$A$105,0)),"?")) | P23: media | Q23: Ahorro de energía como uso responsable de recursos | R23: Aplicar: relacionar. Razonar: justificar con sus palabras | S23: =IFERROR(ISNUMBER(SEARCH("Conocer",$R23))/(ISNUMBER(SEARCH("Conocer",$R23))+ISNUMBER(SEARCH("Aplicar",$R23))+ISNUMBER(SEARCH("Razonar",$R23))),0) -> 0 | T23: =IFERROR(ISNUMBER(SEARCH("Aplicar",$R23))/(ISNUMBER(SEARCH("Conocer",$R23))+ISNUMBER(SEARCH("Aplicar",$R23))+ISNUMBER(SEARCH("Razonar",$R23))),0) -> 0.5 | U23: =IFERROR(ISNUMBER(SEARCH("Razonar",$R23))/(ISNUMBER(SEARCH("Conocer",$R23))+ISNUMBER(SEARCH("Aplicar",$R23))+ISNUMBER(SEARCH("Razonar",$R23))),0) -> 0.5 | V23: 2° | W23: Ciclo 2°–4°
A24: T0658-G02-CIE | B24: 2 | C24: Ciencias | D24: Matriz_Ciencias_2do_Grado_U1_U6_3.xlsx | E24: Unidad 2 - Energía | F24: 11 | G24: 2. Energía. | H24: Transformaciones de la energía. | I24: 2.8. Experimentación con distintas transformaciones energéticas comunes. | J24: T4 | K24: T4-F2.4 | M24: =IF(K24="FUERA","Fuera del marco",IF(K24="N/A","Sin marco",IFERROR(INDEX(Catalogo_TIMSS!$C$5:$C$105,MATCH(K24,Catalogo_TIMSS!$A$5:$A$105,0)),"Pendiente de clasificar"))) -> Ciencias físicas | N24: =IF(K24="FUERA","Fuera del marco",IF(K24="N/A","Sin marco",IFERROR(INDEX(Catalogo_TIMSS!$F$5:$F$105,MATCH(K24,Catalogo_TIMSS!$A$5:$A$105,0)),"Pendiente de clasificar"))) -> Formas de energía y transferencia de energía | O24: =IF(L24="","",IFERROR(INDEX(Catalogo_TIMSS!$C$5:$C$105,MATCH(L24,Catalogo_TIMSS!$A$5:$A$105,0)),"?")) | P24: alta | Q24: Transformaciones de energía eléctrica en luz o movimiento | R24: Aplicar: relacionar y usar modelos sencillos (secuencias) | S24: =IFERROR(ISNUMBER(SEARCH("Conocer",$R24))/(ISNUMBER(SEARCH("Conocer",$R24))+ISNUMBER(SEARCH("Aplicar",$R24))+ISNUMBER(SEARCH("Razonar",$R24))),0) -> 0 | T24: =IFERROR(ISNUMBER(SEARCH("Aplicar",$R24))/(ISNUMBER(SEARCH("Conocer",$R24))+ISNUMBER(SEARCH("Aplicar",$R24))+ISNUMBER(SEARCH("Razonar",$R24))),0) -> 1 | U24: =IFERROR(ISNUMBER(SEARCH("Razonar",$R24))/(ISNUMBER(SEARCH("Conocer",$R24))+ISNUMBER(SEARCH("Aplicar",$R24))+ISNUMBER(SEARCH("Razonar",$R24))),0) -> 0 | V24: 2° | W24: Ciclo 2°–4°
A25: T0659-G02-CIE | B25: 2 | C25: Ciencias | D25: Matriz_Ciencias_2do_Grado_U1_U6_3.xlsx | E25: Unidad 2 - Energía | F25: 12 | G25: 2. Energía. | H25: La luz. | I25: 2.9. Registro de las diferentes fuentes de energía lumínica, naturales y artificiales. | J25: T4 | K25: T4-F2.2 | M25: =IF(K25="FUERA","Fuera del marco",IF(K25="N/A","Sin marco",IFERROR(INDEX(Catalogo_TIMSS!$C$5:$C$105,MATCH(K25,Catalogo_TIMSS!$A$5:$A$105,0)),"Pendiente de clasificar"))) -> Ciencias físicas | N25: =IF(K25="FUERA","Fuera del marco",IF(K25="N/A","Sin marco",IFERROR(INDEX(Catalogo_TIMSS!$F$5:$F$105,MATCH(K25,Catalogo_TIMSS!$A$5:$A$105,0)),"Pendiente de clasificar"))) -> Formas de energía y transferencia de energía | O25: =IF(L25="","",IFERROR(INDEX(Catalogo_TIMSS!$C$5:$C$105,MATCH(L25,Catalogo_TIMSS!$A$5:$A$105,0)),"?")) | P25: media | Q25: Fuentes de luz naturales y artificiales | R25: Aplicar: clasificar | S25: =IFERROR(ISNUMBER(SEARCH("Conocer",$R25))/(ISNUMBER(SEARCH("Conocer",$R25))+ISNUMBER(SEARCH("Aplicar",$R25))+ISNUMBER(SEARCH("Razonar",$R25))),0) -> 0 | T25: =IFERROR(ISNUMBER(SEARCH("Aplicar",$R25))/(ISNUMBER(SEARCH("Conocer",$R25))+ISNUMBER(SEARCH("Aplicar",$R25))+ISNUMBER(SEARCH("Razonar",$R25))),0) -> 1 | U25: =IFERROR(ISNUMBER(SEARCH("Razonar",$R25))/(ISNUMBER(SEARCH("Conocer",$R25))+ISNUMBER(SEARCH("Aplicar",$R25))+ISNUMBER(SEARCH("Razonar",$R25))),0) -> 0 | V25: 2° | W25: Ciclo 2°–4°
A26: T0660-G02-CIE | B26: 2 | C26: Ciencias | D26: Matriz_Ciencias_2do_Grado_U1_U6_3.xlsx | E26: Unidad 2 - Energía | F26: 13 | G26: 2. Energía. | H26: La luz. | I26: 2.10. Experimentación con colores primarios a partir de la mezcla de pinturas. | J26: T4 | K26: FUERA | M26: =IF(K26="FUERA","Fuera del marco",IF(K26="N/A","Sin marco",IFERROR(INDEX(Catalogo_TIMSS!$C$5:$C$105,MATCH(K26,Catalogo_TIMSS!$A$5:$A$105,0)),"Pendiente de clasificar"))) -> Fuera del marco | N26: =IF(K26="FUERA","Fuera del marco",IF(K26="N/A","Sin marco",IFERROR(INDEX(Catalogo_TIMSS!$F$5:$F$105,MATCH(K26,Catalogo_TIMSS!$A$5:$A$105,0)),"Pendiente de clasificar"))) -> Fuera del marco | O26: =IF(L26="","",IFERROR(INDEX(Catalogo_TIMSS!$C$5:$C$105,MATCH(L26,Catalogo_TIMSS!$A$5:$A$105,0)),"?")) | P26: baja | Q26: Mezcla de pigmentos, no óptica de la luz del marco | R26: Razonar: predecir y comprobar | S26: =IFERROR(ISNUMBER(SEARCH("Conocer",$R26))/(ISNUMBER(SEARCH("Conocer",$R26))+ISNUMBER(SEARCH("Aplicar",$R26))+ISNUMBER(SEARCH("Razonar",$R26))),0) -> 0 | T26: =IFERROR(ISNUMBER(SEARCH("Aplicar",$R26))/(ISNUMBER(SEARCH("Conocer",$R26))+ISNUMBER(SEARCH("Aplicar",$R26))+ISNUMBER(SEARCH("Razonar",$R26))),0) -> 0 | U26: =IFERROR(ISNUMBER(SEARCH("Razonar",$R26))/(ISNUMBER(SEARCH("Conocer",$R26))+ISNUMBER(SEARCH("Aplicar",$R26))+ISNUMBER(SEARCH("Razonar",$R26))),0) -> 1 | V26: 2° | W26: Ciclo 2°–4°
A27: T0661-G02-CIE | B27: 2 | C27: Ciencias | D27: Matriz_Ciencias_2do_Grado_U1_U6_3.xlsx | E27: Unidad 2 - Energía | F27: 14 | G27: 2. Energía. | H27: La luz. | I27: 2.11. Experimentación con materiales que dejan pasar la luz, la dejan pasar en parte o no la dejan pasar. | J27: T4 | K27: T4-F2.2 | L27: T4-F1.2 | M27: =IF(K27="FUERA","Fuera del marco",IF(K27="N/A","Sin marco",IFERROR(INDEX(Catalogo_TIMSS!$C$5:$C$105,MATCH(K27,Catalogo_TIMSS!$A$5:$A$105,0)),"Pendiente de clasificar"))) -> Ciencias físicas | N27: =IF(K27="FUERA","Fuera del marco",IF(K27="N/A","Sin marco",IFERROR(INDEX(Catalogo_TIMSS!$F$5:$F$105,MATCH(K27,Catalogo_TIMSS!$A$5:$A$105,0)),"Pendiente de clasificar"))) -> Formas de energía y transferencia de energía | O27: =IF(L27="","",IFERROR(INDEX(Catalogo_TIMSS!$C$5:$C$105,MATCH(L27,Catalogo_TIMSS!$A$5:$A$105,0)),"?")) -> Ciencias físicas | P27: alta | Q27: Paso de luz por materiales opacos, transparentes, translúcidos | R27: Aplicar: clasificar | S27: =IFERROR(ISNUMBER(SEARCH("Conocer",$R27))/(ISNUMBER(SEARCH("Conocer",$R27))+ISNUMBER(SEARCH("Aplicar",$R27))+ISNUMBER(SEARCH("Razonar",$R27))),0) -> 0 | T27: =IFERROR(ISNUMBER(SEARCH("Aplicar",$R27))/(ISNUMBER(SEARCH("Conocer",$R27))+ISNUMBER(SEARCH("Aplicar",$R27))+ISNUMBER(SEARCH("Razonar",$R27))),0) -> 1 | U27: =IFERROR(ISNUMBER(SEARCH("Razonar",$R27))/(ISNUMBER(SEARCH("Conocer",$R27))+ISNUMBER(SEARCH("Aplicar",$R27))+ISNUMBER(SEARCH("Razonar",$R27))),0) -> 0 | V27: 2° | W27: Ciclo 2°–4°
A28: T0662-G02-CIE | B28: 2 | C28: Ciencias | D28: Matriz_Ciencias_2do_Grado_U1_U6_3.xlsx | E28: Unidad 3 - Movimiento | F28: 3 | G28: 3. El movimiento | H28: ¿Qué es el movimiento? | I28: 3.1. Observación de objetos y seres vivos del entorno que se mueven o están en reposo. | J28: T4 | K28: T4-F3.1 | M28: =IF(K28="FUERA","Fuera del marco",IF(K28="N/A","Sin marco",IFERROR(INDEX(Catalogo_TIMSS!$C$5:$C$105,MATCH(K28,Catalogo_TIMSS!$A$5:$A$105,0)),"Pendiente de clasificar"))) -> Ciencias físicas | N28: =IF(K28="FUERA","Fuera del marco",IF(K28="N/A","Sin marco",IFERROR(INDEX(Catalogo_TIMSS!$F$5:$F$105,MATCH(K28,Catalogo_TIMSS!$A$5:$A$105,0)),"Pendiente de clasificar"))) -> Fuerzas y movimiento | O28: =IF(L28="","",IFERROR(INDEX(Catalogo_TIMSS!$C$5:$C$105,MATCH(L28,Catalogo_TIMSS!$A$5:$A$105,0)),"?")) | P28: media | Q28: Noción de movimiento como cambio de lugar | R28: Conocer: identificar y dar ejemplos | S28: =IFERROR(ISNUMBER(SEARCH("Conocer",$R28))/(ISNUMBER(SEARCH("Conocer",$R28))+ISNUMBER(SEARCH("Aplicar",$R28))+ISNUMBER(SEARCH("Razonar",$R28))),0) -> 1 | T28: =IFERROR(ISNUMBER(SEARCH("Aplicar",$R28))/(ISNUMBER(SEARCH("Conocer",$R28))+ISNUMBER(SEARCH("Aplicar",$R28))+ISNUMBER(SEARCH("Razonar",$R28))),0) -> 0 | U28: =IFERROR(ISNUMBER(SEARCH("Razonar",$R28))/(ISNUMBER(SEARCH("Conocer",$R28))+ISNUMBER(SEARCH("Aplicar",$R28))+ISNUMBER(SEARCH("Razonar",$R28))),0) -> 0 | V28: 2° | W28: Ciclo 2°–4°
A29: T0663-G02-CIE | B29: 2 | C29: Ciencias | D29: Matriz_Ciencias_2do_Grado_U1_U6_3.xlsx | E29: Unidad 3 - Movimiento | F29: 4 | G29: 3. El movimiento | H29: Las características del movimiento | I29: 3.2. Comparación de la rapidez y la dirección del movimiento de objetos y personas. | J29: T4 | K29: T4-F3.1 | M29: =IF(K29="FUERA","Fuera del marco",IF(K29="N/A","Sin marco",IFERROR(INDEX(Catalogo_TIMSS!$C$5:$C$105,MATCH(K29,Catalogo_TIMSS!$A$5:$A$105,0)),"Pendiente de clasificar"))) -> Ciencias físicas | N29: =IF(K29="FUERA","Fuera del marco",IF(K29="N/A","Sin marco",IFERROR(INDEX(Catalogo_TIMSS!$F$5:$F$105,MATCH(K29,Catalogo_TIMSS!$A$5:$A$105,0)),"Pendiente de clasificar"))) -> Fuerzas y movimiento | O29: =IF(L29="","",IFERROR(INDEX(Catalogo_TIMSS!$C$5:$C$105,MATCH(L29,Catalogo_TIMSS!$A$5:$A$105,0)),"?")) | P29: media | Q29: Rapidez y dirección del movimiento en rampas | R29: Aplicar: comparar. Razonar: predecir | S29: =IFERROR(ISNUMBER(SEARCH("Conocer",$R29))/(ISNUMBER(SEARCH("Conocer",$R29))+ISNUMBER(SEARCH("Aplicar",$R29))+ISNUMBER(SEARCH("Razonar",$R29))),0) -> 0 | T29: =IFERROR(ISNUMBER(SEARCH("Aplicar",$R29))/(ISNUMBER(SEARCH("Conocer",$R29))+ISNUMBER(SEARCH("Aplicar",$R29))+ISNUMBER(SEARCH("Razonar",$R29))),0) -> 0.5 | U29: =IFERROR(ISNUMBER(SEARCH("Razonar",$R29))/(ISNUMBER(SEARCH("Conocer",$R29))+ISNUMBER(SEARCH("Aplicar",$R29))+ISNUMBER(SEARCH("Razonar",$R29))),0) -> 0.5 | V29: 2° | W29: Ciclo 2°–4°
A30: T0664-G02-CIE | B30: 2 | C30: Ciencias | D30: Matriz_Ciencias_2do_Grado_U1_U6_3.xlsx | E30: Unidad 3 - Movimiento | F30: 5 | G30: 3. El movimiento | H30: Los tipos de movimiento | I30: 3.3. Clasificación de movimientos de objetos del entorno según el camino que siguen. | J30: T4 | K30: T4-F3.1 | M30: =IF(K30="FUERA","Fuera del marco",IF(K30="N/A","Sin marco",IFERROR(INDEX(Catalogo_TIMSS!$C$5:$C$105,MATCH(K30,Catalogo_TIMSS!$A$5:$A$105,0)),"Pendiente de clasificar"))) -> Ciencias físicas | N30: =IF(K30="FUERA","Fuera del marco",IF(K30="N/A","Sin marco",IFERROR(INDEX(Catalogo_TIMSS!$F$5:$F$105,MATCH(K30,Catalogo_TIMSS!$A$5:$A$105,0)),"Pendiente de clasificar"))) -> Fuerzas y movimiento | O30: =IF(L30="","",IFERROR(INDEX(Catalogo_TIMSS!$C$5:$C$105,MATCH(L30,Catalogo_TIMSS!$A$5:$A$105,0)),"?")) | P30: baja | Q30: Tipos de trayectoria; marco solo aborda fuerzas y movimiento | R30: Aplicar: clasificar | S30: =IFERROR(ISNUMBER(SEARCH("Conocer",$R30))/(ISNUMBER(SEARCH("Conocer",$R30))+ISNUMBER(SEARCH("Aplicar",$R30))+ISNUMBER(SEARCH("Razonar",$R30))),0) -> 0 | T30: =IFERROR(ISNUMBER(SEARCH("Aplicar",$R30))/(ISNUMBER(SEARCH("Conocer",$R30))+ISNUMBER(SEARCH("Aplicar",$R30))+ISNUMBER(SEARCH("Razonar",$R30))),0) -> 1 | U30: =IFERROR(ISNUMBER(SEARCH("Razonar",$R30))/(ISNUMBER(SEARCH("Conocer",$R30))+ISNUMBER(SEARCH("Aplicar",$R30))+ISNUMBER(SEARCH("Razonar",$R30))),0) -> 0 | V30: 2° | W30: Ciclo 2°–4°
A31: T0665-G02-CIE | B31: 2 | C31: Ciencias | D31: Matriz_Ciencias_2do_Grado_U1_U6_3.xlsx | E31: Unidad 3 - Movimiento | F31: 6 | G31: 3. El movimiento | H31: Movimiento de rotación de la Tierra. | I31: 3.4. Indagación de la percepción del día y la noche. | J31: T4 | K31: T4-T3.2 | M31: =IF(K31="FUERA","Fuera del marco",IF(K31="N/A","Sin marco",IFERROR(INDEX(Catalogo_TIMSS!$C$5:$C$105,MATCH(K31,Catalogo_TIMSS!$A$5:$A$105,0)),"Pendiente de clasificar"))) -> Ciencias de la Tierra | N31: =IF(K31="FUERA","Fuera del marco",IF(K31="N/A","Sin marco",IFERROR(INDEX(Catalogo_TIMSS!$F$5:$F$105,MATCH(K31,Catalogo_TIMSS!$A$5:$A$105,0)),"Pendiente de clasificar"))) -> La Tierra en el Sistema Solar | O31: =IF(L31="","",IFERROR(INDEX(Catalogo_TIMSS!$C$5:$C$105,MATCH(L31,Catalogo_TIMSS!$A$5:$A$105,0)),"?")) | P31: media | Q31: Diferencias entre día y noche, antesala de rotación | R31: Conocer: describir | S31: =IFERROR(ISNUMBER(SEARCH("Conocer",$R31))/(ISNUMBER(SEARCH("Conocer",$R31))+ISNUMBER(SEARCH("Aplicar",$R31))+ISNUMBER(SEARCH("Razonar",$R31))),0) -> 1 | T31: =IFERROR(ISNUMBER(SEARCH("Aplicar",$R31))/(ISNUMBER(SEARCH("Conocer",$R31))+ISNUMBER(SEARCH("Aplicar",$R31))+ISNUMBER(SEARCH("Razonar",$R31))),0) -> 0 | U31: =IFERROR(ISNUMBER(SEARCH("Razonar",$R31))/(ISNUMBER(SEARCH("Conocer",$R31))+ISNUMBER(SEARCH("Aplicar",$R31))+ISNUMBER(SEARCH("Razonar",$R31))),0) -> 0 | V31: 2° | W31: Ciclo 2°–4°
A32: T0666-G02-CIE | B32: 2 | C32: Ciencias | D32: Matriz_Ciencias_2do_Grado_U1_U6_3.xlsx | E32: Unidad 3 - Movimiento | F32: 7 | G32: 3. El movimiento | H32: Movimiento de rotación de la Tierra. | I32: 3.5. Modelación de la interacción Sol-Tierra para representar la sucesión del día y la noche por la rotación de la Tierra. | J32: T4 | K32: T4-T3.2 | M32: =IF(K32="FUERA","Fuera del marco",IF(K32="N/A","Sin marco",IFERROR(INDEX(Catalogo_TIMSS!$C$5:$C$105,MATCH(K32,Catalogo_TIMSS!$A$5:$A$105,0)),"Pendiente de clasificar"))) -> Ciencias de la Tierra | N32: =IF(K32="FUERA","Fuera del marco",IF(K32="N/A","Sin marco",IFERROR(INDEX(Catalogo_TIMSS!$F$5:$F$105,MATCH(K32,Catalogo_TIMSS!$A$5:$A$105,0)),"Pendiente de clasificar"))) -> La Tierra en el Sistema Solar | O32: =IF(L32="","",IFERROR(INDEX(Catalogo_TIMSS!$C$5:$C$105,MATCH(L32,Catalogo_TIMSS!$A$5:$A$105,0)),"?")) | P32: alta | Q32: Día y noche por rotación de la Tierra con modelo | R32: Aplicar: usar modelos sencillos | S32: =IFERROR(ISNUMBER(SEARCH("Conocer",$R32))/(ISNUMBER(SEARCH("Conocer",$R32))+ISNUMBER(SEARCH("Aplicar",$R32))+ISNUMBER(SEARCH("Razonar",$R32))),0) -> 0 | T32: =IFERROR(ISNUMBER(SEARCH("Aplicar",$R32))/(ISNUMBER(SEARCH("Conocer",$R32))+ISNUMBER(SEARCH("Aplicar",$R32))+ISNUMBER(SEARCH("Razonar",$R32))),0) -> 1 | U32: =IFERROR(ISNUMBER(SEARCH("Razonar",$R32))/(ISNUMBER(SEARCH("Conocer",$R32))+ISNUMBER(SEARCH("Aplicar",$R32))+ISNUMBER(SEARCH("Razonar",$R32))),0) -> 0 | V32: 2° | W32: Ciclo 2°–4°
A33: T0667-G02-CIE | B33: 2 | C33: Ciencias | D33: Matriz_Ciencias_2do_Grado_U1_U6_3.xlsx | E33: Unidad 3 - Movimiento | F33: 8 | G33: 3. El movimiento | H33: Movimiento de traslación de la Tierra. | I33: 3.6. Relación del movimiento de traslación de la Tierra con el calendario. | J33: T4 | K33: T4-T3.1 | M33: =IF(K33="FUERA","Fuera del marco",IF(K33="N/A","Sin marco",IFERROR(INDEX(Catalogo_TIMSS!$C$5:$C$105,MATCH(K33,Catalogo_TIMSS!$A$5:$A$105,0)),"Pendiente de clasificar"))) -> Ciencias de la Tierra | N33: =IF(K33="FUERA","Fuera del marco",IF(K33="N/A","Sin marco",IFERROR(INDEX(Catalogo_TIMSS!$F$5:$F$105,MATCH(K33,Catalogo_TIMSS!$A$5:$A$105,0)),"Pendiente de clasificar"))) -> La Tierra en el Sistema Solar | O33: =IF(L33="","",IFERROR(INDEX(Catalogo_TIMSS!$C$5:$C$105,MATCH(L33,Catalogo_TIMSS!$A$5:$A$105,0)),"?")) | P33: media | Q33: Traslación de la Tierra alrededor del Sol y el año | R33: Aplicar: relacionar | S33: =IFERROR(ISNUMBER(SEARCH("Conocer",$R33))/(ISNUMBER(SEARCH("Conocer",$R33))+ISNUMBER(SEARCH("Aplicar",$R33))+ISNUMBER(SEARCH("Razonar",$R33))),0) -> 0 | T33: =IFERROR(ISNUMBER(SEARCH("Aplicar",$R33))/(ISNUMBER(SEARCH("Conocer",$R33))+ISNUMBER(SEARCH("Aplicar",$R33))+ISNUMBER(SEARCH("Razonar",$R33))),0) -> 1 | U33: =IFERROR(ISNUMBER(SEARCH("Razonar",$R33))/(ISNUMBER(SEARCH("Conocer",$R33))+ISNUMBER(SEARCH("Aplicar",$R33))+ISNUMBER(SEARCH("Razonar",$R33))),0) -> 0 | V33: 2° | W33: Ciclo 2°–4°
A34: T0668-G02-CIE | B34: 2 | C34: Ciencias | D34: Matriz_Ciencias_2do_Grado_U1_U6_3.xlsx | E34: Unidad 3 - Movimiento | F34: 9 | G34: 3. El movimiento | H34: Movimiento de traslación de la Tierra. | I34: 3.7. Identificación de las características de las estaciones del año. | J34: T4 | K34: T4-T2.3 | L34: T4-T2.2 | M34: =IF(K34="FUERA","Fuera del marco",IF(K34="N/A","Sin marco",IFERROR(INDEX(Catalogo_TIMSS!$C$5:$C$105,MATCH(K34,Catalogo_TIMSS!$A$5:$A$105,0)),"Pendiente de clasificar"))) -> Ciencias de la Tierra | N34: =IF(K34="FUERA","Fuera del marco",IF(K34="N/A","Sin marco",IFERROR(INDEX(Catalogo_TIMSS!$F$5:$F$105,MATCH(K34,Catalogo_TIMSS!$A$5:$A$105,0)),"Pendiente de clasificar"))) -> Tiempo atmosférico y clima | O34: =IF(L34="","",IFERROR(INDEX(Catalogo_TIMSS!$C$5:$C$105,MATCH(L34,Catalogo_TIMSS!$A$5:$A$105,0)),"?")) -> Ciencias de la Tierra | P34: media | Q34: Características estacionales de temperatura y lluvia según lugar | R34: Conocer: describir. Aplicar: comparar | S34: =IFERROR(ISNUMBER(SEARCH("Conocer",$R34))/(ISNUMBER(SEARCH("Conocer",$R34))+ISNUMBER(SEARCH("Aplicar",$R34))+ISNUMBER(SEARCH("Razonar",$R34))),0) -> 0.5 | T34: =IFERROR(ISNUMBER(SEARCH("Aplicar",$R34))/(ISNUMBER(SEARCH("Conocer",$R34))+ISNUMBER(SEARCH("Aplicar",$R34))+ISNUMBER(SEARCH("Razonar",$R34))),0) -> 0.5 | U34: =IFERROR(ISNUMBER(SEARCH("Razonar",$R34))/(ISNUMBER(SEARCH("Conocer",$R34))+ISNUMBER(SEARCH("Aplicar",$R34))+ISNUMBER(SEARCH("Razonar",$R34))),0) -> 0 | V34: 2° | W34: Ciclo 2°–4°
A35: T0669-G02-CIE | B35: 2 | C35: Ciencias | D35: Matriz_Ciencias_2do_Grado_U1_U6_3.xlsx | E35: Unidad 3 - Movimiento | F35: 10 | G35: 3. El movimiento | H35: Movimiento de traslación de la Tierra. | I35: 3.8. Descripción de los fenómenos que caracterizan las estaciones del año percibidas en El Salvador. | J35: T4 | K35: T4-T2.3 | M35: =IF(K35="FUERA","Fuera del marco",IF(K35="N/A","Sin marco",IFERROR(INDEX(Catalogo_TIMSS!$C$5:$C$105,MATCH(K35,Catalogo_TIMSS!$A$5:$A$105,0)),"Pendiente de clasificar"))) -> Ciencias de la Tierra | N35: =IF(K35="FUERA","Fuera del marco",IF(K35="N/A","Sin marco",IFERROR(INDEX(Catalogo_TIMSS!$F$5:$F$105,MATCH(K35,Catalogo_TIMSS!$A$5:$A$105,0)),"Pendiente de clasificar"))) -> Tiempo atmosférico y clima | O35: =IF(L35="","",IFERROR(INDEX(Catalogo_TIMSS!$C$5:$C$105,MATCH(L35,Catalogo_TIMSS!$A$5:$A$105,0)),"?")) | P35: alta | Q35: Época seca y lluviosa: cambios estacionales de lluvia | R35: Razonar: extraer conclusiones sencillas a partir de registros | S35: =IFERROR(ISNUMBER(SEARCH("Conocer",$R35))/(ISNUMBER(SEARCH("Conocer",$R35))+ISNUMBER(SEARCH("Aplicar",$R35))+ISNUMBER(SEARCH("Razonar",$R35))),0) -> 0 | T35: =IFERROR(ISNUMBER(SEARCH("Aplicar",$R35))/(ISNUMBER(SEARCH("Conocer",$R35))+ISNUMBER(SEARCH("Aplicar",$R35))+ISNUMBER(SEARCH("Razonar",$R35))),0) -> 0 | U35: =IFERROR(ISNUMBER(SEARCH("Razonar",$R35))/(ISNUMBER(SEARCH("Conocer",$R35))+ISNUMBER(SEARCH("Aplicar",$R35))+ISNUMBER(SEARCH("Razonar",$R35))),0) -> 1 | V35: 2° | W35: Ciclo 2°–4°
A36: T0670-G02-CIE | B36: 2 | C36: Ciencias | D36: Matriz_Ciencias_2do_Grado_U1_U6_3.xlsx | E36: Unidad 4 - Seres vivos | F36: 3 | G36: 4. Seres vivos. | H36: ¿Qué es un ser vivo? | I36: 1.8. Comparación entre las características unificadoras de los seres vivos. | J36: T4 | K36: T4-V1.1 | M36: =IF(K36="FUERA","Fuera del marco",IF(K36="N/A","Sin marco",IFERROR(INDEX(Catalogo_TIMSS!$C$5:$C$105,MATCH(K36,Catalogo_TIMSS!$A$5:$A$105,0)),"Pendiente de clasificar"))) -> Ciencias de la vida | N36: =IF(K36="FUERA","Fuera del marco",IF(K36="N/A","Sin marco",IFERROR(INDEX(Catalogo_TIMSS!$F$5:$F$105,MATCH(K36,Catalogo_TIMSS!$A$5:$A$105,0)),"Pendiente de clasificar"))) -> Características y procesos vitales de los organismos | O36: =IF(L36="","",IFERROR(INDEX(Catalogo_TIMSS!$C$5:$C$105,MATCH(L36,Catalogo_TIMSS!$A$5:$A$105,0)),"?")) | P36: alta | Q36: Distingue seres vivos de objetos inertes | R36: Conocer: identificar. Aplicar: comparar | S36: =IFERROR(ISNUMBER(SEARCH("Conocer",$R36))/(ISNUMBER(SEARCH("Conocer",$R36))+ISNUMBER(SEARCH("Aplicar",$R36))+ISNUMBER(SEARCH("Razonar",$R36))),0) -> 0.5 | T36: =IFERROR(ISNUMBER(SEARCH("Aplicar",$R36))/(ISNUMBER(SEARCH("Conocer",$R36))+ISNUMBER(SEARCH("Aplicar",$R36))+ISNUMBER(SEARCH("Razonar",$R36))),0) -> 0.5 | U36: =IFERROR(ISNUMBER(SEARCH("Razonar",$R36))/(ISNUMBER(SEARCH("Conocer",$R36))+ISNUMBER(SEARCH("Aplicar",$R36))+ISNUMBER(SEARCH("Razonar",$R36))),0) -> 0 | V36: 2° | W36: Ciclo 2°–4°
A37: T0671-G02-CIE | B37: 2 | C37: Ciencias | D37: Matriz_Ciencias_2do_Grado_U1_U6_3.xlsx | E37: Unidad 4 - Seres vivos | F37: 4 | G37: 4. Seres vivos. | H37: Características de los seres vivos. | I37: 1.9. Experimentación con la forma en que los seres vivos reaccionan a lo que ocurre a su alrededor (luz, tacto, calor). | J37: T4 | K37: T4-V3.2 | M37: =IF(K37="FUERA","Fuera del marco",IF(K37="N/A","Sin marco",IFERROR(INDEX(Catalogo_TIMSS!$C$5:$C$105,MATCH(K37,Catalogo_TIMSS!$A$5:$A$105,0)),"Pendiente de clasificar"))) -> Ciencias de la vida | N37: =IF(K37="FUERA","Fuera del marco",IF(K37="N/A","Sin marco",IFERROR(INDEX(Catalogo_TIMSS!$F$5:$F$105,MATCH(K37,Catalogo_TIMSS!$A$5:$A$105,0)),"Pendiente de clasificar"))) -> Organismos, ambiente y sus interacciones | O37: =IF(L37="","",IFERROR(INDEX(Catalogo_TIMSS!$C$5:$C$105,MATCH(L37,Catalogo_TIMSS!$A$5:$A$105,0)),"?")) | P37: media | Q37: Respuesta de seres vivos a estímulos del entorno | R37: Aplicar: relacionar. Razonar: predecir | S37: =IFERROR(ISNUMBER(SEARCH("Conocer",$R37))/(ISNUMBER(SEARCH("Conocer",$R37))+ISNUMBER(SEARCH("Aplicar",$R37))+ISNUMBER(SEARCH("Razonar",$R37))),0) -> 0 | T37: =IFERROR(ISNUMBER(SEARCH("Aplicar",$R37))/(ISNUMBER(SEARCH("Conocer",$R37))+ISNUMBER(SEARCH("Aplicar",$R37))+ISNUMBER(SEARCH("Razonar",$R37))),0) -> 0.5 | U37: =IFERROR(ISNUMBER(SEARCH("Razonar",$R37))/(ISNUMBER(SEARCH("Conocer",$R37))+ISNUMBER(SEARCH("Aplicar",$R37))+ISNUMBER(SEARCH("Razonar",$R37))),0) -> 0.5 | V37: 2° | W37: Ciclo 2°–4°
A38: T0672-G02-CIE | B38: 2 | C38: Ciencias | D38: Matriz_Ciencias_2do_Grado_U1_U6_3.xlsx | E38: Unidad 4 - Seres vivos | F38: 5 | G38: 4. Seres vivos. | H38: Características de los seres vivos. | I38: 1.10. Registro con dibujos de los cambios en el crecimiento de un ser vivo. | J38: T4 | K38: T4-V2.1 | M38: =IF(K38="FUERA","Fuera del marco",IF(K38="N/A","Sin marco",IFERROR(INDEX(Catalogo_TIMSS!$C$5:$C$105,MATCH(K38,Catalogo_TIMSS!$A$5:$A$105,0)),"Pendiente de clasificar"))) -> Ciencias de la vida | N38: =IF(K38="FUERA","Fuera del marco",IF(K38="N/A","Sin marco",IFERROR(INDEX(Catalogo_TIMSS!$F$5:$F$105,MATCH(K38,Catalogo_TIMSS!$A$5:$A$105,0)),"Pendiente de clasificar"))) -> Ciclos de vida, reproducción y herencia | O38: =IF(L38="","",IFERROR(INDEX(Catalogo_TIMSS!$C$5:$C$105,MATCH(L38,Catalogo_TIMSS!$A$5:$A$105,0)),"?")) | P38: alta | Q38: Etapas de desarrollo de planta con flor (semilla a fruto) | R38: Aplicar: usar secuencias. Razonar: extraer conclusiones sencillas | S38: =IFERROR(ISNUMBER(SEARCH("Conocer",$R38))/(ISNUMBER(SEARCH("Conocer",$R38))+ISNUMBER(SEARCH("Aplicar",$R38))+ISNUMBER(SEARCH("Razonar",$R38))),0) -> 0 | T38: =IFERROR(ISNUMBER(SEARCH("Aplicar",$R38))/(ISNUMBER(SEARCH("Conocer",$R38))+ISNUMBER(SEARCH("Aplicar",$R38))+ISNUMBER(SEARCH("Razonar",$R38))),0) -> 0.5 | U38: =IFERROR(ISNUMBER(SEARCH("Razonar",$R38))/(ISNUMBER(SEARCH("Conocer",$R38))+ISNUMBER(SEARCH("Aplicar",$R38))+ISNUMBER(SEARCH("Razonar",$R38))),0) -> 0.5 | V38: 2° | W38: Ciclo 2°–4°
A39: T0673-G02-CIE | B39: 2 | C39: Ciencias | D39: Matriz_Ciencias_2do_Grado_U1_U6_3.xlsx | E39: Unidad 4 - Seres vivos | F39: 6 | G39: 4. Seres vivos. | H39: ¿Dónde se encuentran los seres vivos? | I39: 1.11. Observación de los lugares del entorno donde viven los seres vivos. | J39: T4 | K39: T4-V4.1 | L39: T4-V1.1 | M39: =IF(K39="FUERA","Fuera del marco",IF(K39="N/A","Sin marco",IFERROR(INDEX(Catalogo_TIMSS!$C$5:$C$105,MATCH(K39,Catalogo_TIMSS!$A$5:$A$105,0)),"Pendiente de clasificar"))) -> Ciencias de la vida | N39: =IF(K39="FUERA","Fuera del marco",IF(K39="N/A","Sin marco",IFERROR(INDEX(Catalogo_TIMSS!$F$5:$F$105,MATCH(K39,Catalogo_TIMSS!$A$5:$A$105,0)),"Pendiente de clasificar"))) -> Ecosistemas | O39: =IF(L39="","",IFERROR(INDEX(Catalogo_TIMSS!$C$5:$C$105,MATCH(L39,Catalogo_TIMSS!$A$5:$A$105,0)),"?")) -> Ciencias de la vida | P39: media | Q39: Relaciona seres vivos con lugares donde obtienen lo necesario | R39: Aplicar: relacionar | S39: =IFERROR(ISNUMBER(SEARCH("Conocer",$R39))/(ISNUMBER(SEARCH("Conocer",$R39))+ISNUMBER(SEARCH("Aplicar",$R39))+ISNUMBER(SEARCH("Razonar",$R39))),0) -> 0 | T39: =IFERROR(ISNUMBER(SEARCH("Aplicar",$R39))/(ISNUMBER(SEARCH("Conocer",$R39))+ISNUMBER(SEARCH("Aplicar",$R39))+ISNUMBER(SEARCH("Razonar",$R39))),0) -> 1 | U39: =IFERROR(ISNUMBER(SEARCH("Razonar",$R39))/(ISNUMBER(SEARCH("Conocer",$R39))+ISNUMBER(SEARCH("Aplicar",$R39))+ISNUMBER(SEARCH("Razonar",$R39))),0) -> 0 | V39: 2° | W39: Ciclo 2°–4°
A40: T0674-G02-CIE | B40: 2 | C40: Ciencias | D40: Matriz_Ciencias_2do_Grado_U1_U6_3.xlsx | E40: Unidad 4 - Seres vivos | F40: 7 | G40: 4. Seres vivos. | H40: ¿Cuántos tipos de organismos existen? | I40: 4.1. Observación de la variedad de seres vivos del entorno (biodiversidad). | J40: T4 | K40: T4-V1.2 | M40: =IF(K40="FUERA","Fuera del marco",IF(K40="N/A","Sin marco",IFERROR(INDEX(Catalogo_TIMSS!$C$5:$C$105,MATCH(K40,Catalogo_TIMSS!$A$5:$A$105,0)),"Pendiente de clasificar"))) -> Ciencias de la vida | N40: =IF(K40="FUERA","Fuera del marco",IF(K40="N/A","Sin marco",IFERROR(INDEX(Catalogo_TIMSS!$F$5:$F$105,MATCH(K40,Catalogo_TIMSS!$A$5:$A$105,0)),"Pendiente de clasificar"))) -> Características y procesos vitales de los organismos | O40: =IF(L40="","",IFERROR(INDEX(Catalogo_TIMSS!$C$5:$C$105,MATCH(L40,Catalogo_TIMSS!$A$5:$A$105,0)),"?")) | P40: media | Q40: Variedad de seres vivos del entorno (biodiversidad) | R40: Conocer: dar ejemplos | S40: =IFERROR(ISNUMBER(SEARCH("Conocer",$R40))/(ISNUMBER(SEARCH("Conocer",$R40))+ISNUMBER(SEARCH("Aplicar",$R40))+ISNUMBER(SEARCH("Razonar",$R40))),0) -> 1 | T40: =IFERROR(ISNUMBER(SEARCH("Aplicar",$R40))/(ISNUMBER(SEARCH("Conocer",$R40))+ISNUMBER(SEARCH("Aplicar",$R40))+ISNUMBER(SEARCH("Razonar",$R40))),0) -> 0 | U40: =IFERROR(ISNUMBER(SEARCH("Razonar",$R40))/(ISNUMBER(SEARCH("Conocer",$R40))+ISNUMBER(SEARCH("Aplicar",$R40))+ISNUMBER(SEARCH("Razonar",$R40))),0) -> 0 | V40: 2° | W40: Ciclo 2°–4°
A41: T0675-G02-CIE | B41: 2 | C41: Ciencias | D41: Matriz_Ciencias_2do_Grado_U1_U6_3.xlsx | E41: Unidad 4 - Seres vivos | F41: 8 | G41: 4. Seres vivos. | H41: ¿Cuántos tipos de organismos existen? | I41: 4.2. Clasificación de seres vivos en grupos, según sus características. | J41: T4 | K41: T4-V1.2 | M41: =IF(K41="FUERA","Fuera del marco",IF(K41="N/A","Sin marco",IFERROR(INDEX(Catalogo_TIMSS!$C$5:$C$105,MATCH(K41,Catalogo_TIMSS!$A$5:$A$105,0)),"Pendiente de clasificar"))) -> Ciencias de la vida | N41: =IF(K41="FUERA","Fuera del marco",IF(K41="N/A","Sin marco",IFERROR(INDEX(Catalogo_TIMSS!$F$5:$F$105,MATCH(K41,Catalogo_TIMSS!$A$5:$A$105,0)),"Pendiente de clasificar"))) -> Características y procesos vitales de los organismos | O41: =IF(L41="","",IFERROR(INDEX(Catalogo_TIMSS!$C$5:$C$105,MATCH(L41,Catalogo_TIMSS!$A$5:$A$105,0)),"?")) | P41: alta | Q41: Clasifica seres vivos en grupos por rasgos observables | R41: Aplicar: clasificar | S41: =IFERROR(ISNUMBER(SEARCH("Conocer",$R41))/(ISNUMBER(SEARCH("Conocer",$R41))+ISNUMBER(SEARCH("Aplicar",$R41))+ISNUMBER(SEARCH("Razonar",$R41))),0) -> 0 | T41: =IFERROR(ISNUMBER(SEARCH("Aplicar",$R41))/(ISNUMBER(SEARCH("Conocer",$R41))+ISNUMBER(SEARCH("Aplicar",$R41))+ISNUMBER(SEARCH("Razonar",$R41))),0) -> 1 | U41: =IFERROR(ISNUMBER(SEARCH("Razonar",$R41))/(ISNUMBER(SEARCH("Conocer",$R41))+ISNUMBER(SEARCH("Aplicar",$R41))+ISNUMBER(SEARCH("Razonar",$R41))),0) -> 0 | V41: 2° | W41: Ciclo 2°–4°
A42: T0676-G02-CIE | B42: 2 | C42: Ciencias | D42: Matriz_Ciencias_2do_Grado_U1_U6_3.xlsx | E42: Unidad 4 - Seres vivos | F42: 9 | G42: 4. Seres vivos. | H42: Reconociendo plantas. | I42: 4.3. Reconocimiento de las características físicas y la nutrición de las plantas. | J42: T4 | K42: T4-V1.3 | L42: T4-V1.1 | M42: =IF(K42="FUERA","Fuera del marco",IF(K42="N/A","Sin marco",IFERROR(INDEX(Catalogo_TIMSS!$C$5:$C$105,MATCH(K42,Catalogo_TIMSS!$A$5:$A$105,0)),"Pendiente de clasificar"))) -> Ciencias de la vida | N42: =IF(K42="FUERA","Fuera del marco",IF(K42="N/A","Sin marco",IFERROR(INDEX(Catalogo_TIMSS!$F$5:$F$105,MATCH(K42,Catalogo_TIMSS!$A$5:$A$105,0)),"Pendiente de clasificar"))) -> Características y procesos vitales de los organismos | O42: =IF(L42="","",IFERROR(INDEX(Catalogo_TIMSS!$C$5:$C$105,MATCH(L42,Catalogo_TIMSS!$A$5:$A$105,0)),"?")) -> Ciencias de la vida | P42: alta | Q42: Partes de la planta y lo que necesita para vivir | R42: Conocer: identificar partes. Aplicar: relacionar | S42: =IFERROR(ISNUMBER(SEARCH("Conocer",$R42))/(ISNUMBER(SEARCH("Conocer",$R42))+ISNUMBER(SEARCH("Aplicar",$R42))+ISNUMBER(SEARCH("Razonar",$R42))),0) -> 0.5 | T42: =IFERROR(ISNUMBER(SEARCH("Aplicar",$R42))/(ISNUMBER(SEARCH("Conocer",$R42))+ISNUMBER(SEARCH("Aplicar",$R42))+ISNUMBER(SEARCH("Razonar",$R42))),0) -> 0.5 | U42: =IFERROR(ISNUMBER(SEARCH("Razonar",$R42))/(ISNUMBER(SEARCH("Conocer",$R42))+ISNUMBER(SEARCH("Aplicar",$R42))+ISNUMBER(SEARCH("Razonar",$R42))),0) -> 0 | V42: 2° | W42: Ciclo 2°–4°
A43: T0677-G02-CIE | B43: 2 | C43: Ciencias | D43: Matriz_Ciencias_2do_Grado_U1_U6_3.xlsx | E43: Unidad 4 - Seres vivos | F43: 10 | G43: 4. Seres vivos. | H43: Reconociendo plantas. | I43: 4.4. Comparación entre plantas silvestres y de cultivo. | J43: T4 | K43: T4-V4.1 | M43: =IF(K43="FUERA","Fuera del marco",IF(K43="N/A","Sin marco",IFERROR(INDEX(Catalogo_TIMSS!$C$5:$C$105,MATCH(K43,Catalogo_TIMSS!$A$5:$A$105,0)),"Pendiente de clasificar"))) -> Ciencias de la vida | N43: =IF(K43="FUERA","Fuera del marco",IF(K43="N/A","Sin marco",IFERROR(INDEX(Catalogo_TIMSS!$F$5:$F$105,MATCH(K43,Catalogo_TIMSS!$A$5:$A$105,0)),"Pendiente de clasificar"))) -> Ecosistemas | O43: =IF(L43="","",IFERROR(INDEX(Catalogo_TIMSS!$C$5:$C$105,MATCH(L43,Catalogo_TIMSS!$A$5:$A$105,0)),"?")) | P43: baja | Q43: Plantas silvestres y cultivadas según dónde crecen; vínculo débil | R43: Aplicar: comparar | S43: =IFERROR(ISNUMBER(SEARCH("Conocer",$R43))/(ISNUMBER(SEARCH("Conocer",$R43))+ISNUMBER(SEARCH("Aplicar",$R43))+ISNUMBER(SEARCH("Razonar",$R43))),0) -> 0 | T43: =IFERROR(ISNUMBER(SEARCH("Aplicar",$R43))/(ISNUMBER(SEARCH("Conocer",$R43))+ISNUMBER(SEARCH("Aplicar",$R43))+ISNUMBER(SEARCH("Razonar",$R43))),0) -> 1 | U43: =IFERROR(ISNUMBER(SEARCH("Razonar",$R43))/(ISNUMBER(SEARCH("Conocer",$R43))+ISNUMBER(SEARCH("Aplicar",$R43))+ISNUMBER(SEARCH("Razonar",$R43))),0) -> 0 | V43: 2° | W43: Ciclo 2°–4°
A44: T0678-G02-CIE | B44: 2 | C44: Ciencias | D44: Matriz_Ciencias_2do_Grado_U1_U6_3.xlsx | E44: Unidad 4 - Seres vivos | F44: 11 | G44: 4. Seres vivos. | H44: Importancia de las plantas. | I44: 4.5. Identificación y registro de los productos de origen vegetal. | J44: T4 | K44: T4-T1.2 | M44: =IF(K44="FUERA","Fuera del marco",IF(K44="N/A","Sin marco",IFERROR(INDEX(Catalogo_TIMSS!$C$5:$C$105,MATCH(K44,Catalogo_TIMSS!$A$5:$A$105,0)),"Pendiente de clasificar"))) -> Ciencias de la Tierra | N44: =IF(K44="FUERA","Fuera del marco",IF(K44="N/A","Sin marco",IFERROR(INDEX(Catalogo_TIMSS!$F$5:$F$105,MATCH(K44,Catalogo_TIMSS!$A$5:$A$105,0)),"Pendiente de clasificar"))) -> Características físicas, recursos e historia de la Tierra | O44: =IF(L44="","",IFERROR(INDEX(Catalogo_TIMSS!$C$5:$C$105,MATCH(L44,Catalogo_TIMSS!$A$5:$A$105,0)),"?")) | P44: media | Q44: Plantas como recurso: productos de origen vegetal | R44: Aplicar: clasificar | S44: =IFERROR(ISNUMBER(SEARCH("Conocer",$R44))/(ISNUMBER(SEARCH("Conocer",$R44))+ISNUMBER(SEARCH("Aplicar",$R44))+ISNUMBER(SEARCH("Razonar",$R44))),0) -> 0 | T44: =IFERROR(ISNUMBER(SEARCH("Aplicar",$R44))/(ISNUMBER(SEARCH("Conocer",$R44))+ISNUMBER(SEARCH("Aplicar",$R44))+ISNUMBER(SEARCH("Razonar",$R44))),0) -> 1 | U44: =IFERROR(ISNUMBER(SEARCH("Razonar",$R44))/(ISNUMBER(SEARCH("Conocer",$R44))+ISNUMBER(SEARCH("Aplicar",$R44))+ISNUMBER(SEARCH("Razonar",$R44))),0) -> 0 | V44: 2° | W44: Ciclo 2°–4°
A45: T0679-G02-CIE | B45: 2 | C45: Ciencias | D45: Matriz_Ciencias_2do_Grado_U1_U6_3.xlsx | E45: Unidad 4 - Seres vivos | F45: 12 | G45: 4. Seres vivos. | H45: Importancia de las plantas. | I45: 4.6. Clasificación de plantas según su uso: alimenticias, ornamentales, medicinales y otros. | J45: T4 | K45: T4-T1.2 | M45: =IF(K45="FUERA","Fuera del marco",IF(K45="N/A","Sin marco",IFERROR(INDEX(Catalogo_TIMSS!$C$5:$C$105,MATCH(K45,Catalogo_TIMSS!$A$5:$A$105,0)),"Pendiente de clasificar"))) -> Ciencias de la Tierra | N45: =IF(K45="FUERA","Fuera del marco",IF(K45="N/A","Sin marco",IFERROR(INDEX(Catalogo_TIMSS!$F$5:$F$105,MATCH(K45,Catalogo_TIMSS!$A$5:$A$105,0)),"Pendiente de clasificar"))) -> Características físicas, recursos e historia de la Tierra | O45: =IF(L45="","",IFERROR(INDEX(Catalogo_TIMSS!$C$5:$C$105,MATCH(L45,Catalogo_TIMSS!$A$5:$A$105,0)),"?")) | P45: baja | Q45: Usos de plantas como recursos; clasificación utilitaria | R45: Aplicar: clasificar. Razonar: justificar | S45: =IFERROR(ISNUMBER(SEARCH("Conocer",$R45))/(ISNUMBER(SEARCH("Conocer",$R45))+ISNUMBER(SEARCH("Aplicar",$R45))+ISNUMBER(SEARCH("Razonar",$R45))),0) -> 0 | T45: =IFERROR(ISNUMBER(SEARCH("Aplicar",$R45))/(ISNUMBER(SEARCH("Conocer",$R45))+ISNUMBER(SEARCH("Aplicar",$R45))+ISNUMBER(SEARCH("Razonar",$R45))),0) -> 0.5 | U45: =IFERROR(ISNUMBER(SEARCH("Razonar",$R45))/(ISNUMBER(SEARCH("Conocer",$R45))+ISNUMBER(SEARCH("Aplicar",$R45))+ISNUMBER(SEARCH("Razonar",$R45))),0) -> 0.5 | V45: 2° | W45: Ciclo 2°–4°
A46: T0680-G02-CIE | B46: 2 | C46: Ciencias | D46: Matriz_Ciencias_2do_Grado_U1_U6_3.xlsx | E46: Unidad 4 - Seres vivos | F46: 13 | G46: 4. Seres vivos. | H46: Reconociendo animales. | I46: 4.7. Reconocimiento de las características físicas de grupos comunes de animales. | J46: T4 | K46: T4-V1.2 | M46: =IF(K46="FUERA","Fuera del marco",IF(K46="N/A","Sin marco",IFERROR(INDEX(Catalogo_TIMSS!$C$5:$C$105,MATCH(K46,Catalogo_TIMSS!$A$5:$A$105,0)),"Pendiente de clasificar"))) -> Ciencias de la vida | N46: =IF(K46="FUERA","Fuera del marco",IF(K46="N/A","Sin marco",IFERROR(INDEX(Catalogo_TIMSS!$F$5:$F$105,MATCH(K46,Catalogo_TIMSS!$A$5:$A$105,0)),"Pendiente de clasificar"))) -> Características y procesos vitales de los organismos | O46: =IF(L46="","",IFERROR(INDEX(Catalogo_TIMSS!$C$5:$C$105,MATCH(L46,Catalogo_TIMSS!$A$5:$A$105,0)),"?")) | P46: alta | Q46: Rasgos físicos de grandes grupos de animales | R46: Conocer: describir. Aplicar: clasificar | S46: =IFERROR(ISNUMBER(SEARCH("Conocer",$R46))/(ISNUMBER(SEARCH("Conocer",$R46))+ISNUMBER(SEARCH("Aplicar",$R46))+ISNUMBER(SEARCH("Razonar",$R46))),0) -> 0.5 | T46: =IFERROR(ISNUMBER(SEARCH("Aplicar",$R46))/(ISNUMBER(SEARCH("Conocer",$R46))+ISNUMBER(SEARCH("Aplicar",$R46))+ISNUMBER(SEARCH("Razonar",$R46))),0) -> 0.5 | U46: =IFERROR(ISNUMBER(SEARCH("Razonar",$R46))/(ISNUMBER(SEARCH("Conocer",$R46))+ISNUMBER(SEARCH("Aplicar",$R46))+ISNUMBER(SEARCH("Razonar",$R46))),0) -> 0 | V46: 2° | W46: Ciclo 2°–4°
A47: T0681-G02-CIE | B47: 2 | C47: Ciencias | D47: Matriz_Ciencias_2do_Grado_U1_U6_3.xlsx | E47: Unidad 4 - Seres vivos | F47: 14 | G47: 4. Seres vivos. | H47: Reconociendo animales. | I47: 4.8. Relación de las características físicas de un animal con su alimentación y su hábitat. | J47: T4 | K47: T4-V3.1 | L47: T4-V1.3 | M47: =IF(K47="FUERA","Fuera del marco",IF(K47="N/A","Sin marco",IFERROR(INDEX(Catalogo_TIMSS!$C$5:$C$105,MATCH(K47,Catalogo_TIMSS!$A$5:$A$105,0)),"Pendiente de clasificar"))) -> Ciencias de la vida | N47: =IF(K47="FUERA","Fuera del marco",IF(K47="N/A","Sin marco",IFERROR(INDEX(Catalogo_TIMSS!$F$5:$F$105,MATCH(K47,Catalogo_TIMSS!$A$5:$A$105,0)),"Pendiente de clasificar"))) -> Organismos, ambiente y sus interacciones | O47: =IF(L47="","",IFERROR(INDEX(Catalogo_TIMSS!$C$5:$C$105,MATCH(L47,Catalogo_TIMSS!$A$5:$A$105,0)),"?")) -> Ciencias de la vida | P47: alta | Q47: Rasgos físicos del animal relacionados con alimentación y hábitat | R47: Aplicar: relacionar. Razonar: justificar | S47: =IFERROR(ISNUMBER(SEARCH("Conocer",$R47))/(ISNUMBER(SEARCH("Conocer",$R47))+ISNUMBER(SEARCH("Aplicar",$R47))+ISNUMBER(SEARCH("Razonar",$R47))),0) -> 0 | T47: =IFERROR(ISNUMBER(SEARCH("Aplicar",$R47))/(ISNUMBER(SEARCH("Conocer",$R47))+ISNUMBER(SEARCH("Aplicar",$R47))+ISNUMBER(SEARCH("Razonar",$R47))),0) -> 0.5 | U47: =IFERROR(ISNUMBER(SEARCH("Razonar",$R47))/(ISNUMBER(SEARCH("Conocer",$R47))+ISNUMBER(SEARCH("Aplicar",$R47))+ISNUMBER(SEARCH("Razonar",$R47))),0) -> 0.5 | V47: 2° | W47: Ciclo 2°–4°
A48: T0682-G02-CIE | B48: 2 | C48: Ciencias | D48: Matriz_Ciencias_2do_Grado_U1_U6_3.xlsx | E48: Unidad 4 - Seres vivos | F48: 15 | G48: 4. Seres vivos. | H48: Reconociendo animales. | I48: 4.9. Clasificación de las formas de desplazamiento de los animales. | J48: T4 | K48: T4-V1.2 | M48: =IF(K48="FUERA","Fuera del marco",IF(K48="N/A","Sin marco",IFERROR(INDEX(Catalogo_TIMSS!$C$5:$C$105,MATCH(K48,Catalogo_TIMSS!$A$5:$A$105,0)),"Pendiente de clasificar"))) -> Ciencias de la vida | N48: =IF(K48="FUERA","Fuera del marco",IF(K48="N/A","Sin marco",IFERROR(INDEX(Catalogo_TIMSS!$F$5:$F$105,MATCH(K48,Catalogo_TIMSS!$A$5:$A$105,0)),"Pendiente de clasificar"))) -> Características y procesos vitales de los organismos | O48: =IF(L48="","",IFERROR(INDEX(Catalogo_TIMSS!$C$5:$C$105,MATCH(L48,Catalogo_TIMSS!$A$5:$A$105,0)),"?")) | P48: alta | Q48: Compara conductas de desplazamiento entre animales | R48: Aplicar: clasificar | S48: =IFERROR(ISNUMBER(SEARCH("Conocer",$R48))/(ISNUMBER(SEARCH("Conocer",$R48))+ISNUMBER(SEARCH("Aplicar",$R48))+ISNUMBER(SEARCH("Razonar",$R48))),0) -> 0 | T48: =IFERROR(ISNUMBER(SEARCH("Aplicar",$R48))/(ISNUMBER(SEARCH("Conocer",$R48))+ISNUMBER(SEARCH("Aplicar",$R48))+ISNUMBER(SEARCH("Razonar",$R48))),0) -> 1 | U48: =IFERROR(ISNUMBER(SEARCH("Razonar",$R48))/(ISNUMBER(SEARCH("Conocer",$R48))+ISNUMBER(SEARCH("Aplicar",$R48))+ISNUMBER(SEARCH("Razonar",$R48))),0) -> 0 | V48: 2° | W48: Ciclo 2°–4°
A49: T0683-G02-CIE | B49: 2 | C49: Ciencias | D49: Matriz_Ciencias_2do_Grado_U1_U6_3.xlsx | E49: Unidad 4 - Seres vivos | F49: 16 | G49: 4. Seres vivos. | H49: Importancia de los animales. | I49: 4.10. Identificación y registro de los productos de origen animal. | J49: T4 | K49: T4-T1.2 | M49: =IF(K49="FUERA","Fuera del marco",IF(K49="N/A","Sin marco",IFERROR(INDEX(Catalogo_TIMSS!$C$5:$C$105,MATCH(K49,Catalogo_TIMSS!$A$5:$A$105,0)),"Pendiente de clasificar"))) -> Ciencias de la Tierra | N49: =IF(K49="FUERA","Fuera del marco",IF(K49="N/A","Sin marco",IFERROR(INDEX(Catalogo_TIMSS!$F$5:$F$105,MATCH(K49,Catalogo_TIMSS!$A$5:$A$105,0)),"Pendiente de clasificar"))) -> Características físicas, recursos e historia de la Tierra | O49: =IF(L49="","",IFERROR(INDEX(Catalogo_TIMSS!$C$5:$C$105,MATCH(L49,Catalogo_TIMSS!$A$5:$A$105,0)),"?")) | P49: media | Q49: Animales como recurso: productos de origen animal | R49: Aplicar: relacionar | S49: =IFERROR(ISNUMBER(SEARCH("Conocer",$R49))/(ISNUMBER(SEARCH("Conocer",$R49))+ISNUMBER(SEARCH("Aplicar",$R49))+ISNUMBER(SEARCH("Razonar",$R49))),0) -> 0 | T49: =IFERROR(ISNUMBER(SEARCH("Aplicar",$R49))/(ISNUMBER(SEARCH("Conocer",$R49))+ISNUMBER(SEARCH("Aplicar",$R49))+ISNUMBER(SEARCH("Razonar",$R49))),0) -> 1 | U49: =IFERROR(ISNUMBER(SEARCH("Razonar",$R49))/(ISNUMBER(SEARCH("Conocer",$R49))+ISNUMBER(SEARCH("Aplicar",$R49))+ISNUMBER(SEARCH("Razonar",$R49))),0) -> 0 | V49: 2° | W49: Ciclo 2°–4°
A50: T0684-G02-CIE | B50: 2 | C50: Ciencias | D50: Matriz_Ciencias_2do_Grado_U1_U6_3.xlsx | E50: Unidad 4 - Seres vivos | F50: 17 | G50: 4. Seres vivos. | H50: Importancia de los animales. | I50: 4.11. Comparación entre animales silvestres y domésticos. | J50: T4 | K50: T4-V4.1 | M50: =IF(K50="FUERA","Fuera del marco",IF(K50="N/A","Sin marco",IFERROR(INDEX(Catalogo_TIMSS!$C$5:$C$105,MATCH(K50,Catalogo_TIMSS!$A$5:$A$105,0)),"Pendiente de clasificar"))) -> Ciencias de la vida | N50: =IF(K50="FUERA","Fuera del marco",IF(K50="N/A","Sin marco",IFERROR(INDEX(Catalogo_TIMSS!$F$5:$F$105,MATCH(K50,Catalogo_TIMSS!$A$5:$A$105,0)),"Pendiente de clasificar"))) -> Ecosistemas | O50: =IF(L50="","",IFERROR(INDEX(Catalogo_TIMSS!$C$5:$C$105,MATCH(L50,Catalogo_TIMSS!$A$5:$A$105,0)),"?")) | P50: baja | Q50: Animales silvestres y domésticos según dónde viven | R50: Aplicar: comparar | S50: =IFERROR(ISNUMBER(SEARCH("Conocer",$R50))/(ISNUMBER(SEARCH("Conocer",$R50))+ISNUMBER(SEARCH("Aplicar",$R50))+ISNUMBER(SEARCH("Razonar",$R50))),0) -> 0 | T50: =IFERROR(ISNUMBER(SEARCH("Aplicar",$R50))/(ISNUMBER(SEARCH("Conocer",$R50))+ISNUMBER(SEARCH("Aplicar",$R50))+ISNUMBER(SEARCH("Razonar",$R50))),0) -> 1 | U50: =IFERROR(ISNUMBER(SEARCH("Razonar",$R50))/(ISNUMBER(SEARCH("Conocer",$R50))+ISNUMBER(SEARCH("Aplicar",$R50))+ISNUMBER(SEARCH("Razonar",$R50))),0) -> 0 | V50: 2° | W50: Ciclo 2°–4°
A51: T0685-G02-CIE | B51: 2 | C51: Ciencias | D51: Matriz_Ciencias_2do_Grado_U1_U6_3.xlsx | E51: Unidad 4 - Seres vivos | F51: 18 | G51: 4. Seres vivos. | H51: Importancia de los animales. | I51: 4.12. Identificación de amenazas y formas de protección de los animales. | J51: T4 | K51: T4-V3.3 | M51: =IF(K51="FUERA","Fuera del marco",IF(K51="N/A","Sin marco",IFERROR(INDEX(Catalogo_TIMSS!$C$5:$C$105,MATCH(K51,Catalogo_TIMSS!$A$5:$A$105,0)),"Pendiente de clasificar"))) -> Ciencias de la vida | N51: =IF(K51="FUERA","Fuera del marco",IF(K51="N/A","Sin marco",IFERROR(INDEX(Catalogo_TIMSS!$F$5:$F$105,MATCH(K51,Catalogo_TIMSS!$A$5:$A$105,0)),"Pendiente de clasificar"))) -> Organismos, ambiente y sus interacciones | O51: =IF(L51="","",IFERROR(INDEX(Catalogo_TIMSS!$C$5:$C$105,MATCH(L51,Catalogo_TIMSS!$A$5:$A$105,0)),"?")) | P51: alta | Q51: Amenazas humanas a animales y acciones de protección | R51: Razonar: justificar con sus palabras | S51: =IFERROR(ISNUMBER(SEARCH("Conocer",$R51))/(ISNUMBER(SEARCH("Conocer",$R51))+ISNUMBER(SEARCH("Aplicar",$R51))+ISNUMBER(SEARCH("Razonar",$R51))),0) -> 0 | T51: =IFERROR(ISNUMBER(SEARCH("Aplicar",$R51))/(ISNUMBER(SEARCH("Conocer",$R51))+ISNUMBER(SEARCH("Aplicar",$R51))+ISNUMBER(SEARCH("Razonar",$R51))),0) -> 0 | U51: =IFERROR(ISNUMBER(SEARCH("Razonar",$R51))/(ISNUMBER(SEARCH("Conocer",$R51))+ISNUMBER(SEARCH("Aplicar",$R51))+ISNUMBER(SEARCH("Razonar",$R51))),0) -> 1 | V51: 2° | W51: Ciclo 2°–4°
A52: T0686-G02-CIE | B52: 2 | C52: Ciencias | D52: Matriz_Ciencias_2do_Grado_U1_U6_3.xlsx | E52: Unidad 4 - Seres vivos | F52: 19 | G52: 4. Seres vivos. | H52: Reconociendo los microorganismos. | I52: 4.13. Observación, sin abrir las bolsas, del moho que aparece en el pan (efecto de los microorganismos en los alimentos). | J52: T4 | K52: T4-V1.2 | L52: T4-V5.2 | M52: =IF(K52="FUERA","Fuera del marco",IF(K52="N/A","Sin marco",IFERROR(INDEX(Catalogo_TIMSS!$C$5:$C$105,MATCH(K52,Catalogo_TIMSS!$A$5:$A$105,0)),"Pendiente de clasificar"))) -> Ciencias de la vida | N52: =IF(K52="FUERA","Fuera del marco",IF(K52="N/A","Sin marco",IFERROR(INDEX(Catalogo_TIMSS!$F$5:$F$105,MATCH(K52,Catalogo_TIMSS!$A$5:$A$105,0)),"Pendiente de clasificar"))) -> Características y procesos vitales de los organismos | O52: =IF(L52="","",IFERROR(INDEX(Catalogo_TIMSS!$C$5:$C$105,MATCH(L52,Catalogo_TIMSS!$A$5:$A$105,0)),"?")) -> Ciencias de la vida | P52: media | Q52: Microorganismos como seres vivos; descomponen alimentos y enferman | R52: Razonar: predecir y extraer conclusiones sencillas | S52: =IFERROR(ISNUMBER(SEARCH("Conocer",$R52))/(ISNUMBER(SEARCH("Conocer",$R52))+ISNUMBER(SEARCH("Aplicar",$R52))+ISNUMBER(SEARCH("Razonar",$R52))),0) -> 0 | T52: =IFERROR(ISNUMBER(SEARCH("Aplicar",$R52))/(ISNUMBER(SEARCH("Conocer",$R52))+ISNUMBER(SEARCH("Aplicar",$R52))+ISNUMBER(SEARCH("Razonar",$R52))),0) -> 0 | U52: =IFERROR(ISNUMBER(SEARCH("Razonar",$R52))/(ISNUMBER(SEARCH("Conocer",$R52))+ISNUMBER(SEARCH("Aplicar",$R52))+ISNUMBER(SEARCH("Razonar",$R52))),0) -> 1 | V52: 2° | W52: Ciclo 2°–4°
A53: T0687-G02-CIE | B53: 2 | C53: Ciencias | D53: Matriz_Ciencias_2do_Grado_U1_U6_3.xlsx | E53: Unidad 4 - Seres vivos | F53: 20 | G53: 4. Seres vivos. | H53: Reconociendo hongos. | I53: 4.14. Reconocimiento de las características físicas y el hábitat de los hongos macroscópicos. | J53: T4 | K53: T4-V1.2 | L53: T4-V4.1 | M53: =IF(K53="FUERA","Fuera del marco",IF(K53="N/A","Sin marco",IFERROR(INDEX(Catalogo_TIMSS!$C$5:$C$105,MATCH(K53,Catalogo_TIMSS!$A$5:$A$105,0)),"Pendiente de clasificar"))) -> Ciencias de la vida | N53: =IF(K53="FUERA","Fuera del marco",IF(K53="N/A","Sin marco",IFERROR(INDEX(Catalogo_TIMSS!$F$5:$F$105,MATCH(K53,Catalogo_TIMSS!$A$5:$A$105,0)),"Pendiente de clasificar"))) -> Características y procesos vitales de los organismos | O53: =IF(L53="","",IFERROR(INDEX(Catalogo_TIMSS!$C$5:$C$105,MATCH(L53,Catalogo_TIMSS!$A$5:$A$105,0)),"?")) -> Ciencias de la vida | P53: alta | Q53: Rasgos de hongos y ambientes húmedos donde crecen | R53: Conocer: describir. Aplicar: comparar | S53: =IFERROR(ISNUMBER(SEARCH("Conocer",$R53))/(ISNUMBER(SEARCH("Conocer",$R53))+ISNUMBER(SEARCH("Aplicar",$R53))+ISNUMBER(SEARCH("Razonar",$R53))),0) -> 0.5 | T53: =IFERROR(ISNUMBER(SEARCH("Aplicar",$R53))/(ISNUMBER(SEARCH("Conocer",$R53))+ISNUMBER(SEARCH("Aplicar",$R53))+ISNUMBER(SEARCH("Razonar",$R53))),0) -> 0.5 | U53: =IFERROR(ISNUMBER(SEARCH("Razonar",$R53))/(ISNUMBER(SEARCH("Conocer",$R53))+ISNUMBER(SEARCH("Aplicar",$R53))+ISNUMBER(SEARCH("Razonar",$R53))),0) -> 0 | V53: 2° | W53: Ciclo 2°–4°
A54: T0688-G02-CIE | B54: 2 | C54: Ciencias | D54: Matriz_Ciencias_2do_Grado_U1_U6_3.xlsx | E54: Unidad 5 - Objetos técnicos | F54: 3 | G54: 5. Objetos técnicos. | H54: Equilibrio. | I54: 5.1. Construcción de balanzas. | J54: T4 | K54: FUERA | M54: =IF(K54="FUERA","Fuera del marco",IF(K54="N/A","Sin marco",IFERROR(INDEX(Catalogo_TIMSS!$C$5:$C$105,MATCH(K54,Catalogo_TIMSS!$A$5:$A$105,0)),"Pendiente de clasificar"))) -> Fuera del marco | N54: =IF(K54="FUERA","Fuera del marco",IF(K54="N/A","Sin marco",IFERROR(INDEX(Catalogo_TIMSS!$F$5:$F$105,MATCH(K54,Catalogo_TIMSS!$A$5:$A$105,0)),"Pendiente de clasificar"))) -> Fuera del marco | O54: =IF(L54="","",IFERROR(INDEX(Catalogo_TIMSS!$C$5:$C$105,MATCH(L54,Catalogo_TIMSS!$A$5:$A$105,0)),"?")) | P54: media | Q54: Construcción de objeto técnico (balanza) para comparar pesos | R54: Aplicar: usar instrumentos sencillos | S54: =IFERROR(ISNUMBER(SEARCH("Conocer",$R54))/(ISNUMBER(SEARCH("Conocer",$R54))+ISNUMBER(SEARCH("Aplicar",$R54))+ISNUMBER(SEARCH("Razonar",$R54))),0) -> 0 | T54: =IFERROR(ISNUMBER(SEARCH("Aplicar",$R54))/(ISNUMBER(SEARCH("Conocer",$R54))+ISNUMBER(SEARCH("Aplicar",$R54))+ISNUMBER(SEARCH("Razonar",$R54))),0) -> 1 | U54: =IFERROR(ISNUMBER(SEARCH("Razonar",$R54))/(ISNUMBER(SEARCH("Conocer",$R54))+ISNUMBER(SEARCH("Aplicar",$R54))+ISNUMBER(SEARCH("Razonar",$R54))),0) -> 0 | V54: 2° | W54: Ciclo 2°–4°
A55: T0689-G02-CIE | B55: 2 | C55: Ciencias | D55: Matriz_Ciencias_2do_Grado_U1_U6_3.xlsx | E55: Unidad 5 - Objetos técnicos | F55: 4 | G55: 5. Objetos técnicos. | H55: Equilibrio. | I55: 5.2. Registro de valores de magnitud empleando una balanza. | J55: T4 | K55: FUERA | M55: =IF(K55="FUERA","Fuera del marco",IF(K55="N/A","Sin marco",IFERROR(INDEX(Catalogo_TIMSS!$C$5:$C$105,MATCH(K55,Catalogo_TIMSS!$A$5:$A$105,0)),"Pendiente de clasificar"))) -> Fuera del marco | N55: =IF(K55="FUERA","Fuera del marco",IF(K55="N/A","Sin marco",IFERROR(INDEX(Catalogo_TIMSS!$F$5:$F$105,MATCH(K55,Catalogo_TIMSS!$A$5:$A$105,0)),"Pendiente de clasificar"))) -> Fuera del marco | O55: =IF(L55="","",IFERROR(INDEX(Catalogo_TIMSS!$C$5:$C$105,MATCH(L55,Catalogo_TIMSS!$A$5:$A$105,0)),"?")) | P55: alta | Q55: Estimación y medición de masa con unidades no convencionales | R55: Aplicar: medir. Razonar: estimar | S55: =IFERROR(ISNUMBER(SEARCH("Conocer",$R55))/(ISNUMBER(SEARCH("Conocer",$R55))+ISNUMBER(SEARCH("Aplicar",$R55))+ISNUMBER(SEARCH("Razonar",$R55))),0) -> 0 | T55: =IFERROR(ISNUMBER(SEARCH("Aplicar",$R55))/(ISNUMBER(SEARCH("Conocer",$R55))+ISNUMBER(SEARCH("Aplicar",$R55))+ISNUMBER(SEARCH("Razonar",$R55))),0) -> 0.5 | U55: =IFERROR(ISNUMBER(SEARCH("Razonar",$R55))/(ISNUMBER(SEARCH("Conocer",$R55))+ISNUMBER(SEARCH("Aplicar",$R55))+ISNUMBER(SEARCH("Razonar",$R55))),0) -> 0.5 | V55: 2° | W55: Ciclo 2°–4°
A56: T0690-G02-CIE | B56: 2 | C56: Ciencias | D56: Matriz_Ciencias_2do_Grado_U1_U6_3.xlsx | E56: Unidad 5 - Objetos técnicos | F56: 5 | G56: 5. Objetos técnicos. | H56: Estructuras. | I56: 5.3. Construcción de una estructura rígida: modelo de puente o torre. | J56: T4 | K56: FUERA | M56: =IF(K56="FUERA","Fuera del marco",IF(K56="N/A","Sin marco",IFERROR(INDEX(Catalogo_TIMSS!$C$5:$C$105,MATCH(K56,Catalogo_TIMSS!$A$5:$A$105,0)),"Pendiente de clasificar"))) -> Fuera del marco | N56: =IF(K56="FUERA","Fuera del marco",IF(K56="N/A","Sin marco",IFERROR(INDEX(Catalogo_TIMSS!$F$5:$F$105,MATCH(K56,Catalogo_TIMSS!$A$5:$A$105,0)),"Pendiente de clasificar"))) -> Fuera del marco | O56: =IF(L56="","",IFERROR(INDEX(Catalogo_TIMSS!$C$5:$C$105,MATCH(L56,Catalogo_TIMSS!$A$5:$A$105,0)),"?")) | P56: alta | Q56: Diseño de estructuras técnicas; sin objetivo del marco | R56: Aplicar: usar modelos | S56: =IFERROR(ISNUMBER(SEARCH("Conocer",$R56))/(ISNUMBER(SEARCH("Conocer",$R56))+ISNUMBER(SEARCH("Aplicar",$R56))+ISNUMBER(SEARCH("Razonar",$R56))),0) -> 0 | T56: =IFERROR(ISNUMBER(SEARCH("Aplicar",$R56))/(ISNUMBER(SEARCH("Conocer",$R56))+ISNUMBER(SEARCH("Aplicar",$R56))+ISNUMBER(SEARCH("Razonar",$R56))),0) -> 1 | U56: =IFERROR(ISNUMBER(SEARCH("Razonar",$R56))/(ISNUMBER(SEARCH("Conocer",$R56))+ISNUMBER(SEARCH("Aplicar",$R56))+ISNUMBER(SEARCH("Razonar",$R56))),0) -> 0 | V56: 2° | W56: Ciclo 2°–4°
A57: T0691-G02-CIE | B57: 2 | C57: Ciencias | D57: Matriz_Ciencias_2do_Grado_U1_U6_3.xlsx | E57: Unidad 5 - Objetos técnicos | F57: 6 | G57: 5. Objetos técnicos. | H57: Estructuras. | I57: 5.4. Registro de valores de la máxima resistencia que soporta una estructura. | J57: T4 | K57: FUERA | M57: =IF(K57="FUERA","Fuera del marco",IF(K57="N/A","Sin marco",IFERROR(INDEX(Catalogo_TIMSS!$C$5:$C$105,MATCH(K57,Catalogo_TIMSS!$A$5:$A$105,0)),"Pendiente de clasificar"))) -> Fuera del marco | N57: =IF(K57="FUERA","Fuera del marco",IF(K57="N/A","Sin marco",IFERROR(INDEX(Catalogo_TIMSS!$F$5:$F$105,MATCH(K57,Catalogo_TIMSS!$A$5:$A$105,0)),"Pendiente de clasificar"))) -> Fuera del marco | O57: =IF(L57="","",IFERROR(INDEX(Catalogo_TIMSS!$C$5:$C$105,MATCH(L57,Catalogo_TIMSS!$A$5:$A$105,0)),"?")) | P57: alta | Q57: Prueba de resistencia de estructura técnica construida | R57: Razonar: predecir y extraer conclusiones sencillas | S57: =IFERROR(ISNUMBER(SEARCH("Conocer",$R57))/(ISNUMBER(SEARCH("Conocer",$R57))+ISNUMBER(SEARCH("Aplicar",$R57))+ISNUMBER(SEARCH("Razonar",$R57))),0) -> 0 | T57: =IFERROR(ISNUMBER(SEARCH("Aplicar",$R57))/(ISNUMBER(SEARCH("Conocer",$R57))+ISNUMBER(SEARCH("Aplicar",$R57))+ISNUMBER(SEARCH("Razonar",$R57))),0) -> 0 | U57: =IFERROR(ISNUMBER(SEARCH("Razonar",$R57))/(ISNUMBER(SEARCH("Conocer",$R57))+ISNUMBER(SEARCH("Aplicar",$R57))+ISNUMBER(SEARCH("Razonar",$R57))),0) -> 1 | V57: 2° | W57: Ciclo 2°–4°
A58: T0692-G02-CIE | B58: 2 | C58: Ciencias | D58: Matriz_Ciencias_2do_Grado_U1_U6_3.xlsx | E58: Unidad 5 - Objetos técnicos | F58: 7 | G58: 5. Objetos técnicos. | H58: Transformaciones. | I58: 5.5. Construcción de un dispositivo transformador de energía (molinete de viento). | J58: T4 | K58: T4-F2.1 | M58: =IF(K58="FUERA","Fuera del marco",IF(K58="N/A","Sin marco",IFERROR(INDEX(Catalogo_TIMSS!$C$5:$C$105,MATCH(K58,Catalogo_TIMSS!$A$5:$A$105,0)),"Pendiente de clasificar"))) -> Ciencias físicas | N58: =IF(K58="FUERA","Fuera del marco",IF(K58="N/A","Sin marco",IFERROR(INDEX(Catalogo_TIMSS!$F$5:$F$105,MATCH(K58,Catalogo_TIMSS!$A$5:$A$105,0)),"Pendiente de clasificar"))) -> Formas de energía y transferencia de energía | O58: =IF(L58="","",IFERROR(INDEX(Catalogo_TIMSS!$C$5:$C$105,MATCH(L58,Catalogo_TIMSS!$A$5:$A$105,0)),"?")) | P58: media | Q58: Viento como fuente de energía que produce movimiento | R58: Aplicar: relacionar | S58: =IFERROR(ISNUMBER(SEARCH("Conocer",$R58))/(ISNUMBER(SEARCH("Conocer",$R58))+ISNUMBER(SEARCH("Aplicar",$R58))+ISNUMBER(SEARCH("Razonar",$R58))),0) -> 0 | T58: =IFERROR(ISNUMBER(SEARCH("Aplicar",$R58))/(ISNUMBER(SEARCH("Conocer",$R58))+ISNUMBER(SEARCH("Aplicar",$R58))+ISNUMBER(SEARCH("Razonar",$R58))),0) -> 1 | U58: =IFERROR(ISNUMBER(SEARCH("Razonar",$R58))/(ISNUMBER(SEARCH("Conocer",$R58))+ISNUMBER(SEARCH("Aplicar",$R58))+ISNUMBER(SEARCH("Razonar",$R58))),0) -> 0 | V58: 2° | W58: Ciclo 2°–4°
A59: T0693-G02-CIE | B59: 2 | C59: Ciencias | D59: Matriz_Ciencias_2do_Grado_U1_U6_3.xlsx | E59: Unidad 5 - Objetos técnicos | F59: 8 | G59: 5. Objetos técnicos. | H59: Transformaciones. | I59: 5.6. Indagación de cómo optimizar un dispositivo de transformación de energía. | J59: T4 | K59: FUERA | M59: =IF(K59="FUERA","Fuera del marco",IF(K59="N/A","Sin marco",IFERROR(INDEX(Catalogo_TIMSS!$C$5:$C$105,MATCH(K59,Catalogo_TIMSS!$A$5:$A$105,0)),"Pendiente de clasificar"))) -> Fuera del marco | N59: =IF(K59="FUERA","Fuera del marco",IF(K59="N/A","Sin marco",IFERROR(INDEX(Catalogo_TIMSS!$F$5:$F$105,MATCH(K59,Catalogo_TIMSS!$A$5:$A$105,0)),"Pendiente de clasificar"))) -> Fuera del marco | O59: =IF(L59="","",IFERROR(INDEX(Catalogo_TIMSS!$C$5:$C$105,MATCH(L59,Catalogo_TIMSS!$A$5:$A$105,0)),"?")) | P59: media | Q59: Optimización de diseño técnico de un molinete | R59: Razonar: evaluar y mejorar | S59: =IFERROR(ISNUMBER(SEARCH("Conocer",$R59))/(ISNUMBER(SEARCH("Conocer",$R59))+ISNUMBER(SEARCH("Aplicar",$R59))+ISNUMBER(SEARCH("Razonar",$R59))),0) -> 0 | T59: =IFERROR(ISNUMBER(SEARCH("Aplicar",$R59))/(ISNUMBER(SEARCH("Conocer",$R59))+ISNUMBER(SEARCH("Aplicar",$R59))+ISNUMBER(SEARCH("Razonar",$R59))),0) -> 0 | U59: =IFERROR(ISNUMBER(SEARCH("Razonar",$R59))/(ISNUMBER(SEARCH("Conocer",$R59))+ISNUMBER(SEARCH("Aplicar",$R59))+ISNUMBER(SEARCH("Razonar",$R59))),0) -> 1 | V59: 2° | W59: Ciclo 2°–4°
A60: T0694-G02-CIE | B60: 2 | C60: Ciencias | D60: Matriz_Ciencias_2do_Grado_U1_U6_3.xlsx | E60: Unidad 5 - Objetos técnicos | F60: 9 | G60: 5. Objetos técnicos. | H60: Cuidado de plantas y animales. | I60: 5.7. Registro de tareas para el cuidado de un animal. | J60: T4 | K60: T4-V1.1 | M60: =IF(K60="FUERA","Fuera del marco",IF(K60="N/A","Sin marco",IFERROR(INDEX(Catalogo_TIMSS!$C$5:$C$105,MATCH(K60,Catalogo_TIMSS!$A$5:$A$105,0)),"Pendiente de clasificar"))) -> Ciencias de la vida | N60: =IF(K60="FUERA","Fuera del marco",IF(K60="N/A","Sin marco",IFERROR(INDEX(Catalogo_TIMSS!$F$5:$F$105,MATCH(K60,Catalogo_TIMSS!$A$5:$A$105,0)),"Pendiente de clasificar"))) -> Características y procesos vitales de los organismos | O60: =IF(L60="","",IFERROR(INDEX(Catalogo_TIMSS!$C$5:$C$105,MATCH(L60,Catalogo_TIMSS!$A$5:$A$105,0)),"?")) | P60: baja | Q60: Cuidado de animal: necesidades de agua y alimento | R60: Aplicar: relacionar | S60: =IFERROR(ISNUMBER(SEARCH("Conocer",$R60))/(ISNUMBER(SEARCH("Conocer",$R60))+ISNUMBER(SEARCH("Aplicar",$R60))+ISNUMBER(SEARCH("Razonar",$R60))),0) -> 0 | T60: =IFERROR(ISNUMBER(SEARCH("Aplicar",$R60))/(ISNUMBER(SEARCH("Conocer",$R60))+ISNUMBER(SEARCH("Aplicar",$R60))+ISNUMBER(SEARCH("Razonar",$R60))),0) -> 1 | U60: =IFERROR(ISNUMBER(SEARCH("Razonar",$R60))/(ISNUMBER(SEARCH("Conocer",$R60))+ISNUMBER(SEARCH("Aplicar",$R60))+ISNUMBER(SEARCH("Razonar",$R60))),0) -> 0 | V60: 2° | W60: Ciclo 2°–4°
A61: T0695-G02-CIE | B61: 2 | C61: Ciencias | D61: Matriz_Ciencias_2do_Grado_U1_U6_3.xlsx | E61: Unidad 5 - Objetos técnicos | F61: 10 | G61: 5. Objetos técnicos. | H61: Cuidado de plantas y animales. | I61: 5.8. Construcción de una estructura para cuidar animales silvestres (bebedero o comedero de aves). | J61: T4 | K61: T4-V3.3 | M61: =IF(K61="FUERA","Fuera del marco",IF(K61="N/A","Sin marco",IFERROR(INDEX(Catalogo_TIMSS!$C$5:$C$105,MATCH(K61,Catalogo_TIMSS!$A$5:$A$105,0)),"Pendiente de clasificar"))) -> Ciencias de la vida | N61: =IF(K61="FUERA","Fuera del marco",IF(K61="N/A","Sin marco",IFERROR(INDEX(Catalogo_TIMSS!$F$5:$F$105,MATCH(K61,Catalogo_TIMSS!$A$5:$A$105,0)),"Pendiente de clasificar"))) -> Organismos, ambiente y sus interacciones | O61: =IF(L61="","",IFERROR(INDEX(Catalogo_TIMSS!$C$5:$C$105,MATCH(L61,Catalogo_TIMSS!$A$5:$A$105,0)),"?")) | P61: baja | Q61: Acción humana positiva para ayudar a animales silvestres | R61: Razonar: diseñar y evaluar | S61: =IFERROR(ISNUMBER(SEARCH("Conocer",$R61))/(ISNUMBER(SEARCH("Conocer",$R61))+ISNUMBER(SEARCH("Aplicar",$R61))+ISNUMBER(SEARCH("Razonar",$R61))),0) -> 0 | T61: =IFERROR(ISNUMBER(SEARCH("Aplicar",$R61))/(ISNUMBER(SEARCH("Conocer",$R61))+ISNUMBER(SEARCH("Aplicar",$R61))+ISNUMBER(SEARCH("Razonar",$R61))),0) -> 0 | U61: =IFERROR(ISNUMBER(SEARCH("Razonar",$R61))/(ISNUMBER(SEARCH("Conocer",$R61))+ISNUMBER(SEARCH("Aplicar",$R61))+ISNUMBER(SEARCH("Razonar",$R61))),0) -> 1 | V61: 2° | W61: Ciclo 2°–4°
A62: T0696-G02-CIE | B62: 2 | C62: Ciencias | D62: Matriz_Ciencias_2do_Grado_U1_U6_3.xlsx | E62: Unidad 5 - Objetos técnicos | F62: 11 | G62: 5. Objetos técnicos. | H62: Cuidado de plantas y animales. | I62: 5.9. Construcción y uso de terrarios. | J62: T4 | K62: T4-V1.1 | L62: T4-V4.1 | M62: =IF(K62="FUERA","Fuera del marco",IF(K62="N/A","Sin marco",IFERROR(INDEX(Catalogo_TIMSS!$C$5:$C$105,MATCH(K62,Catalogo_TIMSS!$A$5:$A$105,0)),"Pendiente de clasificar"))) -> Ciencias de la vida | N62: =IF(K62="FUERA","Fuera del marco",IF(K62="N/A","Sin marco",IFERROR(INDEX(Catalogo_TIMSS!$F$5:$F$105,MATCH(K62,Catalogo_TIMSS!$A$5:$A$105,0)),"Pendiente de clasificar"))) -> Características y procesos vitales de los organismos | O62: =IF(L62="","",IFERROR(INDEX(Catalogo_TIMSS!$C$5:$C$105,MATCH(L62,Catalogo_TIMSS!$A$5:$A$105,0)),"?")) -> Ciencias de la vida | P62: media | Q62: Terrario: necesidades de las plantas para vivir | R62: Razonar: predecir | S62: =IFERROR(ISNUMBER(SEARCH("Conocer",$R62))/(ISNUMBER(SEARCH("Conocer",$R62))+ISNUMBER(SEARCH("Aplicar",$R62))+ISNUMBER(SEARCH("Razonar",$R62))),0) -> 0 | T62: =IFERROR(ISNUMBER(SEARCH("Aplicar",$R62))/(ISNUMBER(SEARCH("Conocer",$R62))+ISNUMBER(SEARCH("Aplicar",$R62))+ISNUMBER(SEARCH("Razonar",$R62))),0) -> 0 | U62: =IFERROR(ISNUMBER(SEARCH("Razonar",$R62))/(ISNUMBER(SEARCH("Conocer",$R62))+ISNUMBER(SEARCH("Aplicar",$R62))+ISNUMBER(SEARCH("Razonar",$R62))),0) -> 1 | V62: 2° | W62: Ciclo 2°–4°
A63: T0697-G02-CIE | B63: 2 | C63: Ciencias | D63: Matriz_Ciencias_2do_Grado_U1_U6_3.xlsx | E63: Unidad 6 - Ambiente y salud | F63: 3 | G63: 6. Ambiente y salud. | H63: Peligros en la escuela y el hogar. | I63: 6.1. Reconocimiento y prevención de accidentes comunes. | J63: T4 | K63: FUERA | M63: =IF(K63="FUERA","Fuera del marco",IF(K63="N/A","Sin marco",IFERROR(INDEX(Catalogo_TIMSS!$C$5:$C$105,MATCH(K63,Catalogo_TIMSS!$A$5:$A$105,0)),"Pendiente de clasificar"))) -> Fuera del marco | N63: =IF(K63="FUERA","Fuera del marco",IF(K63="N/A","Sin marco",IFERROR(INDEX(Catalogo_TIMSS!$F$5:$F$105,MATCH(K63,Catalogo_TIMSS!$A$5:$A$105,0)),"Pendiente de clasificar"))) -> Fuera del marco | O63: =IF(L63="","",IFERROR(INDEX(Catalogo_TIMSS!$C$5:$C$105,MATCH(L63,Catalogo_TIMSS!$A$5:$A$105,0)),"?")) | P63: alta | Q63: Prevención de accidentes; no es contenido del marco | R63: Aplicar: relacionar | S63: =IFERROR(ISNUMBER(SEARCH("Conocer",$R63))/(ISNUMBER(SEARCH("Conocer",$R63))+ISNUMBER(SEARCH("Aplicar",$R63))+ISNUMBER(SEARCH("Razonar",$R63))),0) -> 0 | T63: =IFERROR(ISNUMBER(SEARCH("Aplicar",$R63))/(ISNUMBER(SEARCH("Conocer",$R63))+ISNUMBER(SEARCH("Aplicar",$R63))+ISNUMBER(SEARCH("Razonar",$R63))),0) -> 1 | U63: =IFERROR(ISNUMBER(SEARCH("Razonar",$R63))/(ISNUMBER(SEARCH("Conocer",$R63))+ISNUMBER(SEARCH("Aplicar",$R63))+ISNUMBER(SEARCH("Razonar",$R63))),0) -> 0 | V63: 2° | W63: Ciclo 2°–4°
A64: T0698-G02-CIE | B64: 2 | C64: Ciencias | D64: Matriz_Ciencias_2do_Grado_U1_U6_3.xlsx | E64: Unidad 6 - Ambiente y salud | F64: 4 | G64: 6. Ambiente y salud. | H64: Peligros en la escuela y el hogar. | I64: 6.2. Identificación de los factores de peligro en el hogar y la escuela. | J64: T4 | K64: FUERA | M64: =IF(K64="FUERA","Fuera del marco",IF(K64="N/A","Sin marco",IFERROR(INDEX(Catalogo_TIMSS!$C$5:$C$105,MATCH(K64,Catalogo_TIMSS!$A$5:$A$105,0)),"Pendiente de clasificar"))) -> Fuera del marco | N64: =IF(K64="FUERA","Fuera del marco",IF(K64="N/A","Sin marco",IFERROR(INDEX(Catalogo_TIMSS!$F$5:$F$105,MATCH(K64,Catalogo_TIMSS!$A$5:$A$105,0)),"Pendiente de clasificar"))) -> Fuera del marco | O64: =IF(L64="","",IFERROR(INDEX(Catalogo_TIMSS!$C$5:$C$105,MATCH(L64,Catalogo_TIMSS!$A$5:$A$105,0)),"?")) | P64: alta | Q64: Zonas de riesgo en hogar y escuela; prevención | R64: Aplicar: identificar y ubicar | S64: =IFERROR(ISNUMBER(SEARCH("Conocer",$R64))/(ISNUMBER(SEARCH("Conocer",$R64))+ISNUMBER(SEARCH("Aplicar",$R64))+ISNUMBER(SEARCH("Razonar",$R64))),0) -> 0 | T64: =IFERROR(ISNUMBER(SEARCH("Aplicar",$R64))/(ISNUMBER(SEARCH("Conocer",$R64))+ISNUMBER(SEARCH("Aplicar",$R64))+ISNUMBER(SEARCH("Razonar",$R64))),0) -> 1 | U64: =IFERROR(ISNUMBER(SEARCH("Razonar",$R64))/(ISNUMBER(SEARCH("Conocer",$R64))+ISNUMBER(SEARCH("Aplicar",$R64))+ISNUMBER(SEARCH("Razonar",$R64))),0) -> 0 | V64: 2° | W64: Ciclo 2°–4°
A65: T0699-G02-CIE | B65: 2 | C65: Ciencias | D65: Matriz_Ciencias_2do_Grado_U1_U6_3.xlsx | E65: Unidad 6 - Ambiente y salud | F65: 5 | G65: 6. Ambiente y salud. | H65: Amenazas naturales. | I65: 6.3. Reconocimiento de amenazas naturales comunes en El Salvador. | J65: T4 | K65: FUERA | M65: =IF(K65="FUERA","Fuera del marco",IF(K65="N/A","Sin marco",IFERROR(INDEX(Catalogo_TIMSS!$C$5:$C$105,MATCH(K65,Catalogo_TIMSS!$A$5:$A$105,0)),"Pendiente de clasificar"))) -> Fuera del marco | N65: =IF(K65="FUERA","Fuera del marco",IF(K65="N/A","Sin marco",IFERROR(INDEX(Catalogo_TIMSS!$F$5:$F$105,MATCH(K65,Catalogo_TIMSS!$A$5:$A$105,0)),"Pendiente de clasificar"))) -> Fuera del marco | O65: =IF(L65="","",IFERROR(INDEX(Catalogo_TIMSS!$C$5:$C$105,MATCH(L65,Catalogo_TIMSS!$A$5:$A$105,0)),"?")) | P65: media | Q65: Amenazas naturales y riesgo; fuera de objetivos T4 | R65: Conocer: reconocer | S65: =IFERROR(ISNUMBER(SEARCH("Conocer",$R65))/(ISNUMBER(SEARCH("Conocer",$R65))+ISNUMBER(SEARCH("Aplicar",$R65))+ISNUMBER(SEARCH("Razonar",$R65))),0) -> 1 | T65: =IFERROR(ISNUMBER(SEARCH("Aplicar",$R65))/(ISNUMBER(SEARCH("Conocer",$R65))+ISNUMBER(SEARCH("Aplicar",$R65))+ISNUMBER(SEARCH("Razonar",$R65))),0) -> 0 | U65: =IFERROR(ISNUMBER(SEARCH("Razonar",$R65))/(ISNUMBER(SEARCH("Conocer",$R65))+ISNUMBER(SEARCH("Aplicar",$R65))+ISNUMBER(SEARCH("Razonar",$R65))),0) -> 0 | V65: 2° | W65: Ciclo 2°–4°
A66: T0700-G02-CIE | B66: 2 | C66: Ciencias | D66: Matriz_Ciencias_2do_Grado_U1_U6_3.xlsx | E66: Unidad 6 - Ambiente y salud | F66: 6 | G66: 6. Ambiente y salud. | H66: Amenazas naturales. | I66: 6.4. Clasificación de las amenazas naturales comunes en El Salvador. | J66: T4 | K66: FUERA | M66: =IF(K66="FUERA","Fuera del marco",IF(K66="N/A","Sin marco",IFERROR(INDEX(Catalogo_TIMSS!$C$5:$C$105,MATCH(K66,Catalogo_TIMSS!$A$5:$A$105,0)),"Pendiente de clasificar"))) -> Fuera del marco | N66: =IF(K66="FUERA","Fuera del marco",IF(K66="N/A","Sin marco",IFERROR(INDEX(Catalogo_TIMSS!$F$5:$F$105,MATCH(K66,Catalogo_TIMSS!$A$5:$A$105,0)),"Pendiente de clasificar"))) -> Fuera del marco | O66: =IF(L66="","",IFERROR(INDEX(Catalogo_TIMSS!$C$5:$C$105,MATCH(L66,Catalogo_TIMSS!$A$5:$A$105,0)),"?")) | P66: media | Q66: Clasificación de amenazas naturales para gestión de riesgo | R66: Aplicar: clasificar | S66: =IFERROR(ISNUMBER(SEARCH("Conocer",$R66))/(ISNUMBER(SEARCH("Conocer",$R66))+ISNUMBER(SEARCH("Aplicar",$R66))+ISNUMBER(SEARCH("Razonar",$R66))),0) -> 0 | T66: =IFERROR(ISNUMBER(SEARCH("Aplicar",$R66))/(ISNUMBER(SEARCH("Conocer",$R66))+ISNUMBER(SEARCH("Aplicar",$R66))+ISNUMBER(SEARCH("Razonar",$R66))),0) -> 1 | U66: =IFERROR(ISNUMBER(SEARCH("Razonar",$R66))/(ISNUMBER(SEARCH("Conocer",$R66))+ISNUMBER(SEARCH("Aplicar",$R66))+ISNUMBER(SEARCH("Razonar",$R66))),0) -> 0 | V66: 2° | W66: Ciclo 2°–4°
A67: T0701-G02-CIE | B67: 2 | C67: Ciencias | D67: Matriz_Ciencias_2do_Grado_U1_U6_3.xlsx | E67: Unidad 6 - Ambiente y salud | F67: 7 | G67: 6. Ambiente y salud. | H67: Amenazas naturales. | I67: 6.5. Simulación de acciones a seguir durante una emergencia (sismo). | J67: T4 | K67: FUERA | M67: =IF(K67="FUERA","Fuera del marco",IF(K67="N/A","Sin marco",IFERROR(INDEX(Catalogo_TIMSS!$C$5:$C$105,MATCH(K67,Catalogo_TIMSS!$A$5:$A$105,0)),"Pendiente de clasificar"))) -> Fuera del marco | N67: =IF(K67="FUERA","Fuera del marco",IF(K67="N/A","Sin marco",IFERROR(INDEX(Catalogo_TIMSS!$F$5:$F$105,MATCH(K67,Catalogo_TIMSS!$A$5:$A$105,0)),"Pendiente de clasificar"))) -> Fuera del marco | O67: =IF(L67="","",IFERROR(INDEX(Catalogo_TIMSS!$C$5:$C$105,MATCH(L67,Catalogo_TIMSS!$A$5:$A$105,0)),"?")) | P67: alta | Q67: Simulacro de sismo; prevención de riesgos | R67: Aplicar: usar modelos (simulacro). Razonar: justificar | S67: =IFERROR(ISNUMBER(SEARCH("Conocer",$R67))/(ISNUMBER(SEARCH("Conocer",$R67))+ISNUMBER(SEARCH("Aplicar",$R67))+ISNUMBER(SEARCH("Razonar",$R67))),0) -> 0 | T67: =IFERROR(ISNUMBER(SEARCH("Aplicar",$R67))/(ISNUMBER(SEARCH("Conocer",$R67))+ISNUMBER(SEARCH("Aplicar",$R67))+ISNUMBER(SEARCH("Razonar",$R67))),0) -> 0.5 | U67: =IFERROR(ISNUMBER(SEARCH("Razonar",$R67))/(ISNUMBER(SEARCH("Conocer",$R67))+ISNUMBER(SEARCH("Aplicar",$R67))+ISNUMBER(SEARCH("Razonar",$R67))),0) -> 0.5 | V67: 2° | W67: Ciclo 2°–4°
A68: T0702-G02-CIE | B68: 2 | C68: Ciencias | D68: Matriz_Ciencias_2do_Grado_U1_U6_3.xlsx | E68: Unidad 6 - Ambiente y salud | F68: 8 | G68: 6. Ambiente y salud. | H68: Acciones humanas que transforman el entorno. | I68: 6.6. Reconocimiento de acciones humanas que transforman el entorno. | J68: T4 | K68: T4-V3.3 | M68: =IF(K68="FUERA","Fuera del marco",IF(K68="N/A","Sin marco",IFERROR(INDEX(Catalogo_TIMSS!$C$5:$C$105,MATCH(K68,Catalogo_TIMSS!$A$5:$A$105,0)),"Pendiente de clasificar"))) -> Ciencias de la vida | N68: =IF(K68="FUERA","Fuera del marco",IF(K68="N/A","Sin marco",IFERROR(INDEX(Catalogo_TIMSS!$F$5:$F$105,MATCH(K68,Catalogo_TIMSS!$A$5:$A$105,0)),"Pendiente de clasificar"))) -> Organismos, ambiente y sus interacciones | O68: =IF(L68="","",IFERROR(INDEX(Catalogo_TIMSS!$C$5:$C$105,MATCH(L68,Catalogo_TIMSS!$A$5:$A$105,0)),"?")) | P68: alta | Q68: Acciones humanas que transforman el entorno | R68: Aplicar: comparar | S68: =IFERROR(ISNUMBER(SEARCH("Conocer",$R68))/(ISNUMBER(SEARCH("Conocer",$R68))+ISNUMBER(SEARCH("Aplicar",$R68))+ISNUMBER(SEARCH("Razonar",$R68))),0) -> 0 | T68: =IFERROR(ISNUMBER(SEARCH("Aplicar",$R68))/(ISNUMBER(SEARCH("Conocer",$R68))+ISNUMBER(SEARCH("Aplicar",$R68))+ISNUMBER(SEARCH("Razonar",$R68))),0) -> 1 | U68: =IFERROR(ISNUMBER(SEARCH("Razonar",$R68))/(ISNUMBER(SEARCH("Conocer",$R68))+ISNUMBER(SEARCH("Aplicar",$R68))+ISNUMBER(SEARCH("Razonar",$R68))),0) -> 0 | V68: 2° | W68: Ciclo 2°–4°
A69: T0703-G02-CIE | B69: 2 | C69: Ciencias | D69: Matriz_Ciencias_2do_Grado_U1_U6_3.xlsx | E69: Unidad 6 - Ambiente y salud | F69: 9 | G69: 6. Ambiente y salud. | H69: Acciones humanas que transforman el entorno. | I69: 6.7. Explicación de la procedencia y descarte de los materiales. | J69: T4 | K69: T4-T1.2 | L69: T4-V3.3 | M69: =IF(K69="FUERA","Fuera del marco",IF(K69="N/A","Sin marco",IFERROR(INDEX(Catalogo_TIMSS!$C$5:$C$105,MATCH(K69,Catalogo_TIMSS!$A$5:$A$105,0)),"Pendiente de clasificar"))) -> Ciencias de la Tierra | N69: =IF(K69="FUERA","Fuera del marco",IF(K69="N/A","Sin marco",IFERROR(INDEX(Catalogo_TIMSS!$F$5:$F$105,MATCH(K69,Catalogo_TIMSS!$A$5:$A$105,0)),"Pendiente de clasificar"))) -> Características físicas, recursos e historia de la Tierra | O69: =IF(L69="","",IFERROR(INDEX(Catalogo_TIMSS!$C$5:$C$105,MATCH(L69,Catalogo_TIMSS!$A$5:$A$105,0)),"?")) -> Ciencias de la vida | P69: media | Q69: Procedencia de materiales y desecho responsable | R69: Aplicar: relacionar | S69: =IFERROR(ISNUMBER(SEARCH("Conocer",$R69))/(ISNUMBER(SEARCH("Conocer",$R69))+ISNUMBER(SEARCH("Aplicar",$R69))+ISNUMBER(SEARCH("Razonar",$R69))),0) -> 0 | T69: =IFERROR(ISNUMBER(SEARCH("Aplicar",$R69))/(ISNUMBER(SEARCH("Conocer",$R69))+ISNUMBER(SEARCH("Aplicar",$R69))+ISNUMBER(SEARCH("Razonar",$R69))),0) -> 1 | U69: =IFERROR(ISNUMBER(SEARCH("Razonar",$R69))/(ISNUMBER(SEARCH("Conocer",$R69))+ISNUMBER(SEARCH("Aplicar",$R69))+ISNUMBER(SEARCH("Razonar",$R69))),0) -> 0 | V69: 2° | W69: Ciclo 2°–4°
A70: T0704-G02-CIE | B70: 2 | C70: Ciencias | D70: Matriz_Ciencias_2do_Grado_U1_U6_3.xlsx | E70: Unidad 6 - Ambiente y salud | F70: 10 | G70: 6. Ambiente y salud. | H70: Acciones humanas que transforman el entorno. | I70: 6.8. Registro de los residuos generados en la vida diaria. | J70: T4 | K70: T4-V3.3 | L70: T4-T1.2 | M70: =IF(K70="FUERA","Fuera del marco",IF(K70="N/A","Sin marco",IFERROR(INDEX(Catalogo_TIMSS!$C$5:$C$105,MATCH(K70,Catalogo_TIMSS!$A$5:$A$105,0)),"Pendiente de clasificar"))) -> Ciencias de la vida | N70: =IF(K70="FUERA","Fuera del marco",IF(K70="N/A","Sin marco",IFERROR(INDEX(Catalogo_TIMSS!$F$5:$F$105,MATCH(K70,Catalogo_TIMSS!$A$5:$A$105,0)),"Pendiente de clasificar"))) -> Organismos, ambiente y sus interacciones | O70: =IF(L70="","",IFERROR(INDEX(Catalogo_TIMSS!$C$5:$C$105,MATCH(L70,Catalogo_TIMSS!$A$5:$A$105,0)),"?")) -> Ciencias de la Tierra | P70: media | Q70: Residuos generados y su reducción; impacto humano | R70: Razonar: extraer conclusiones sencillas | S70: =IFERROR(ISNUMBER(SEARCH("Conocer",$R70))/(ISNUMBER(SEARCH("Conocer",$R70))+ISNUMBER(SEARCH("Aplicar",$R70))+ISNUMBER(SEARCH("Razonar",$R70))),0) -> 0 | T70: =IFERROR(ISNUMBER(SEARCH("Aplicar",$R70))/(ISNUMBER(SEARCH("Conocer",$R70))+ISNUMBER(SEARCH("Aplicar",$R70))+ISNUMBER(SEARCH("Razonar",$R70))),0) -> 0 | U70: =IFERROR(ISNUMBER(SEARCH("Razonar",$R70))/(ISNUMBER(SEARCH("Conocer",$R70))+ISNUMBER(SEARCH("Aplicar",$R70))+ISNUMBER(SEARCH("Razonar",$R70))),0) -> 1 | V70: 2° | W70: Ciclo 2°–4°
A71: T0705-G02-CIE | B71: 2 | C71: Ciencias | D71: Matriz_Ciencias_2do_Grado_U1_U6_3.xlsx | E71: Unidad 6 - Ambiente y salud | F71: 11 | G71: 6. Ambiente y salud. | H71: Cuidado personal. | I71: 6.9. Relación de los hábitos higiénicos con la buena salud. | J71: T4 | K71: T4-V5.2 | M71: =IF(K71="FUERA","Fuera del marco",IF(K71="N/A","Sin marco",IFERROR(INDEX(Catalogo_TIMSS!$C$5:$C$105,MATCH(K71,Catalogo_TIMSS!$A$5:$A$105,0)),"Pendiente de clasificar"))) -> Ciencias de la vida | N71: =IF(K71="FUERA","Fuera del marco",IF(K71="N/A","Sin marco",IFERROR(INDEX(Catalogo_TIMSS!$F$5:$F$105,MATCH(K71,Catalogo_TIMSS!$A$5:$A$105,0)),"Pendiente de clasificar"))) -> Salud humana | O71: =IF(L71="","",IFERROR(INDEX(Catalogo_TIMSS!$C$5:$C$105,MATCH(L71,Catalogo_TIMSS!$A$5:$A$105,0)),"?")) | P71: alta | Q71: Higiene de manos previene transmisión de microbios | R71: Aplicar: relacionar | S71: =IFERROR(ISNUMBER(SEARCH("Conocer",$R71))/(ISNUMBER(SEARCH("Conocer",$R71))+ISNUMBER(SEARCH("Aplicar",$R71))+ISNUMBER(SEARCH("Razonar",$R71))),0) -> 0 | T71: =IFERROR(ISNUMBER(SEARCH("Aplicar",$R71))/(ISNUMBER(SEARCH("Conocer",$R71))+ISNUMBER(SEARCH("Aplicar",$R71))+ISNUMBER(SEARCH("Razonar",$R71))),0) -> 1 | U71: =IFERROR(ISNUMBER(SEARCH("Razonar",$R71))/(ISNUMBER(SEARCH("Conocer",$R71))+ISNUMBER(SEARCH("Aplicar",$R71))+ISNUMBER(SEARCH("Razonar",$R71))),0) -> 0 | V71: 2° | W71: Ciclo 2°–4°
A72: T0706-G02-CIE | B72: 2 | C72: Ciencias | D72: Matriz_Ciencias_2do_Grado_U1_U6_3.xlsx | E72: Unidad 6 - Ambiente y salud | F72: 12 | G72: 6. Ambiente y salud. | H72: Cuidado personal. | I72: 6.10. Reconocimiento de las vacunas como una forma de prevenir enfermedades. | J72: T4 | K72: T4-V5.2 | M72: =IF(K72="FUERA","Fuera del marco",IF(K72="N/A","Sin marco",IFERROR(INDEX(Catalogo_TIMSS!$C$5:$C$105,MATCH(K72,Catalogo_TIMSS!$A$5:$A$105,0)),"Pendiente de clasificar"))) -> Ciencias de la vida | N72: =IF(K72="FUERA","Fuera del marco",IF(K72="N/A","Sin marco",IFERROR(INDEX(Catalogo_TIMSS!$F$5:$F$105,MATCH(K72,Catalogo_TIMSS!$A$5:$A$105,0)),"Pendiente de clasificar"))) -> Salud humana | O72: =IF(L72="","",IFERROR(INDEX(Catalogo_TIMSS!$C$5:$C$105,MATCH(L72,Catalogo_TIMSS!$A$5:$A$105,0)),"?")) | P72: alta | Q72: Vacunas como forma de prevenir enfermedades | R72: Conocer: reconocer | S72: =IFERROR(ISNUMBER(SEARCH("Conocer",$R72))/(ISNUMBER(SEARCH("Conocer",$R72))+ISNUMBER(SEARCH("Aplicar",$R72))+ISNUMBER(SEARCH("Razonar",$R72))),0) -> 1 | T72: =IFERROR(ISNUMBER(SEARCH("Aplicar",$R72))/(ISNUMBER(SEARCH("Conocer",$R72))+ISNUMBER(SEARCH("Aplicar",$R72))+ISNUMBER(SEARCH("Razonar",$R72))),0) -> 0 | U72: =IFERROR(ISNUMBER(SEARCH("Razonar",$R72))/(ISNUMBER(SEARCH("Conocer",$R72))+ISNUMBER(SEARCH("Aplicar",$R72))+ISNUMBER(SEARCH("Razonar",$R72))),0) -> 0 | V72: 2° | W72: Ciclo 2°–4°
