Workbook

Sheet Resumen de exportación
B3: Este documento se exportó de Numbers. Cada tabla se convirtió en una hoja de cálculo de Excel. Los demás objetos de las hojas de Numbers se colocaron en distintas hojas de cálculo. Recuerda que el cálculo de fórmulas puede ser diferente en Excel.
B7: Nombre de hoja de Numbers | C7: Nombre de tabla de Numbers | D7: Nombre de hoja de cálculo de Excel
B9: Inicio
C10: Tabla 1 | D10: Inicio
B11: Resumen TIMSS y PISA
C12: Tabla 1 | D12: Resumen TIMSS y PISA
B13: Apego TIMSS y PISA
C14: Tabla 1 | D14: Apego TIMSS y PISA
B15: Presupuesto de temas
C16: Tabla 1 | D16: Presupuesto de temas
B17: TIMSS - Balance por ciclo
C18: Tabla 1 | D18: TIMSS - Balance por ciclo
B19: TIMSS - Balance por grado
C20: Tabla 1 | D20: TIMSS - Balance por grado
B21: TIMSS - Semáforo de objetivos
C22: Tabla 1 | D22: TIMSS - Semáforo de objetivos
B23: TIMSS - Conocer-Aplicar-Razonar
C24: Tabla 1 | D24: TIMSS - Conocer-Aplicar-Razonar
B25: TIMSS - Medio ambiente
C26: Tabla 1 | D26: TIMSS - Medio ambiente
B27: TIMSS - Investigación
C28: Tabla 1 | D28: TIMSS - Investigación
B29: TIMSS - Otros países
C30: Tabla 1 | D30: TIMSS - Otros países
B31: PISA - Contenidos
C32: Tabla 1 | D32: PISA - Contenidos
B33: PISA - Competencias
C34: Tabla 1 | D34: PISA - Competencias
B35: PISA - Tipos de conocimiento
C36: Tabla 1 | D36: PISA - Tipos de conocimiento
B37: PISA - Contextos
C38: Tabla 1 | D38: PISA - Contextos
B39: Datos - Temas
C40: Tabla 1 | D40: Datos - Temas
B41: Datos - Catálogo TIMSS
C42: Tabla 1 | D42: Datos - Catálogo TIMSS
B43: Datos - Catálogo PISA
C44: Tabla 1 | D44: Datos - Catálogo PISA
B45: Datos - Objetivos de países
C46: Tabla 1 | D46: Datos - Objetivos de países
B47: Datos - TIMSS 2023
C48: Tabla 1 | D48: Datos - TIMSS 2023
B49: Fuentes
C50: Tabla 1 | D50: Fuentes

Sheet Inicio
B1: Cobertura de la malla de Ciencia y Tecnología frente a TIMSS 2027 y PISA 2025 — hallazgos, cómo se construyó y cómo leerla
B2: Versión 3 (TIMSS 2027 + PISA 2025) · 2 de octubre de 2026 · Elaborado con Claude Code a partir de las mallas del equipo de Ciencias (MINED). Las versiones anteriores (TIMSS 2023) se conservan en Cobertura_TIMSS_Ciencias_SV.xlsx.
B3: {="TIMSS 2027 y PISA 2025"&" "&"BIEN · En lo acumulado la malla se parece a las pruebas: "&FIXED('Apego TIMSS y PISA'!F17*100,0)&" %"&" (TIMSS 4.°), "&FIXED('Apego TIMSS y PISA'!F18*100,0)&" %"&" (TIMSS 8.°) y "&FIXED('Apego TIMSS y PISA'!F23*100,0)&" %"&" (PISA) de apego."&" "&"OJO · TIMSS: falta Biología en 5.°, luz-sonido-electricidad en 4.° y más Razonar en 6.° y 8.°."&" "&"OJO · PISA: falta biología en 9.°, Tierra y espacio en 8.°, y enseñar a evaluar información y el porqué de la ciencia."&" "&"→ Empieza por «Resumen TIMSS y PISA» y «Presupuesto de temas». Las pestañas que empiezan con TIMSS o PISA tienen el detalle de cada prueba."} -> TIMSS 2027 y PISA 2025 BIEN · En lo acumulado la malla se parece a las pruebas: 92 % (TIMSS 4.°), 88 % (TIMSS 8.°) y 88 % (PISA) de apego. OJO · TIMSS: falta Biología en 5.°, luz-sonido-electricidad en 4.° y más Razonar en 6.° y 8.°. OJO · PISA: falta biología en 9.°, Tierra y espacio en 8.°, y enseñar a evaluar información y el porqué de la ciencia. → Empieza por «Resumen TIMSS y PISA» y «Presupuesto de temas». Las pestañas que empiezan con TIMSS o PISA tienen el detalle de cada prueba.
B5: Resumen ejecutivo (las cifras se recalculan con el libro)
B6: {="1. Apego general. En lo acumulado, la malla se parece mucho a lo que piden las pruebas: índice de apego de "&FIXED('Apego TIMSS y PISA'!F17*100,0)&" %"&" frente a TIMSS 4.° (2.°–4.°), "&FIXED('Apego TIMSS y PISA'!F18*100,0)&" %"&" frente a TIMSS 8.° (5.°–8.°) y "&FIXED('Apego TIMSS y PISA'!F23*100,0)&" %"&" frente a PISA (7.°–9.°). Cubre "&'TIMSS - Semáforo de objetivos'!D115&" de "&'TIMSS - Semáforo de objetivos'!C115&" objetivos de TIMSS 4.°, "&'TIMSS - Semáforo de objetivos'!D120&" de "&'TIMSS - Semáforo de objetivos'!C120&" de TIMSS 8.° y "&'PISA - Contenidos'!C55&" de 21 categorías de contenido de PISA. Los problemas están en el reparto entre grados y en las capas propias de PISA."} -> 1. Apego general. En lo acumulado, la malla se parece mucho a lo que piden las pruebas: índice de apego de 92 % frente a TIMSS 4.° (2.°–4.°), 88 % frente a TIMSS 8.° (5.°–8.°) y 88 % frente a PISA (7.°–9.°). Cubre 31 de 32 objetivos de TIMSS 4.°, 45 de 48 de TIMSS 8.° y 20 de 21 categorías de contenido de PISA. Los problemas están en el reparto entre grados y en las capas propias de PISA.
B7: {="2. Grados a mejorar. 5.° es el grado con menor apego ("&FIXED('Apego TIMSS y PISA'!F11*100,0)&" %"&"): le faltan unos "&FIXED('TIMSS - Balance por grado'!I21,0)&" temas de Biología del marco de 8.°, que Uruguay, Colombia y Singapur enseñan en 5.°–6.° y El Salvador recién en 6.°–7.°. En 4.° faltan unos "&FIXED('TIMSS - Balance por grado'!I17,0)&" temas de Ciencias físicas (luz, sonido, electricidad, imanes). 8.° tiene solo "&'PISA - Contenidos'!D13&" temas de Tierra y espacio y 9.° solo "&'PISA - Contenidos'!D17&" de sistemas vivos (ni célula, ni genética, ni salud humana). En 6.° y 8.° Razonar queda en "&FIXED('TIMSS - Conocer-Aplicar-Razonar'!I9*100,0)&" %"&" y "&FIXED('TIMSS - Conocer-Aplicar-Razonar'!I11*100,0)&" %"&" (meta TIMSS 30 %)."} -> 2. Grados a mejorar. 5.° es el grado con menor apego (69 %): le faltan unos 19 temas de Biología del marco de 8.°, que Uruguay, Colombia y Singapur enseñan en 5.°–6.° y El Salvador recién en 6.°–7.°. En 4.° faltan unos 13 temas de Ciencias físicas (luz, sonido, electricidad, imanes). 8.° tiene solo 6 temas de Tierra y espacio y 9.° solo 3 de sistemas vivos (ni célula, ni genética, ni salud humana). En 6.° y 8.° Razonar queda en 19 % y 21 % (meta TIMSS 30 %).
B8: {="3. Competencias PISA. La malla declara una competencia y cinco subcompetencias por tema (columnas de la propia malla). En 7.°–9.° la competencia 3, «Investigar, evaluar y usar información para decidir», llega a "&FIXED('PISA - Competencias'!H16*100,0)&" %"&" de los temas (PISA: 24–36 %); distinguir evidencia de opinión (I2), criticar argumentos (I4) y formular hipótesis (E5) casi no aparecen. La competencia 2 está sobrerrepresentada ("&FIXED('PISA - Competencias'!G16*100,0)&" %"&")."} -> 3. Competencias PISA. La malla declara una competencia y cinco subcompetencias por tema (columnas de la propia malla). En 7.°–9.° la competencia 3, «Investigar, evaluar y usar información para decidir», llega a 14 % de los temas (PISA: 24–36 %); distinguir evidencia de opinión (I2), criticar argumentos (I4) y formular hipótesis (E5) casi no aparecen. La competencia 2 está sobrerrepresentada (50 %).
B9: {="4. Conocimiento procedimental y epistémico (lo que más agrega PISA). Solo "&FIXED('PISA - Tipos de conocimiento'!G16*100,0)&" %"&" de los temas de 7.°–9.° tienen como foco el conocimiento procedimental (PISA: 27–33 %) y ninguno el epistémico (24–30 %). "&'PISA - Tipos de conocimiento'!E57&" de los 20 elementos epistémicos (modelos frente a realidad, consenso, revisión por pares, límites de la certeza) no se trabajan en ningún tema."} -> 4. Conocimiento procedimental y epistémico (lo que más agrega PISA). Solo 5 % de los temas de 7.°–9.° tienen como foco el conocimiento procedimental (PISA: 27–33 %) y ninguno el epistémico (24–30 %). 12 de los 20 elementos epistémicos (modelos frente a realidad, consenso, revisión por pares, límites de la certeza) no se trabajan en ningún tema.
B10: {="5. Contextos. "&FIXED('PISA - Contextos'!G16*100,0)&" %"&" de los temas de 7.°–9.° no sitúan la ciencia en una situación real ("&FIXED('PISA - Contextos'!G14*100,0)&" %"&" en 8.°). Cuando hay contexto, el reparto personal / local / global se parece al 1:2:1 de PISA."} -> 5. Contextos. 64 % de los temas de 7.°–9.° no sitúan la ciencia en una situación real (86 % en 8.°). Cuando hay contexto, el reparto personal / local / global se parece al 1:2:1 de PISA.
B11: {="6. Frente a otros países, El Salvador introduce "&COUNTIF('TIMSS - Otros países'!$K$5:$K$84,"El Salvador llega más tarde")&" objetivos TIMSS más tarde que la mediana, "&COUNTIF('TIMSS - Otros países'!$K$5:$K$84,"El Salvador va adelantado")&" antes y no trabaja "&COUNTIF('TIMSS - Otros países'!$K$5:$K$84,"El Salvador no llega")&" que otros sí (herencia y propiedades de la luz)."} -> 6. Frente a otros países, El Salvador introduce 24 objetivos TIMSS más tarde que la mediana, 40 antes y no trabaja 2 que otros sí (herencia y propiedades de la luz).
B13: Recomendaciones
B14: R1. Decidir el peso de PISA en 7.° y 8.° (hoja Apego TIMSS y PISA, celda E4). Sugerencia mientras se decide: PISA como guía en 7.° y 9.°, y 50/50 en 8.° si El Salvador rinde TIMSS 2027 (8.° es el grado que TIMSS evalúa).
B15: {="R2. 2.°–4.° (hoja Presupuesto de temas): fusionar temas repetidos de Biología para liberar "&FIXED('Presupuesto de temas'!J9,0)&" espacios e insertar "&FIXED('Presupuesto de temas'!G9,0)&" temas de Ciencias físicas y de la Tierra (luz, sonido, circuitos, imanes, tiempo atmosférico) y "&FIXED('Presupuesto de temas'!H9,0)&" de herencia (B2.2), sin cambiar el total."} -> R2. 2.°–4.° (hoja Presupuesto de temas): fusionar temas repetidos de Biología para liberar 13 espacios e insertar 12 temas de Ciencias físicas y de la Tierra (luz, sonido, circuitos, imanes, tiempo atmosférico) y 1 de herencia (B2.2), sin cambiar el total.
B16: R3. 5.°–8.°: el total por dominio ya está en meta; no hace falta agregar temas. Conviene REUBICAR (Presupuesto, acción «reubicar»): adelantar Biología de 7.° a 5.°, insertar luz (con una fusión de Física) y traer al ciclo los movimientos de la Tierra y la Luna (hoy en 9.°), y subir tareas de Razonar en 6.° y 8.°.
B17: {="R4. 7.°–9.° (PISA): fusionar temas de física y química que se repiten (liberan "&FIXED('Presupuesto de temas'!J20,0)&") para insertar "&FIXED('Presupuesto de temas'!G20,0)&" temas de sistemas vivos (sobre todo en 9.°: célula, salud, genética, evolución) y de Tierra y espacio (sobre todo en 8.°: universo, historia de la Tierra)."} -> R4. 7.°–9.° (PISA): fusionar temas de física y química que se repiten (liberan 33) para insertar 33 temas de sistemas vivos (sobre todo en 9.°: célula, salud, genética, evolución) y de Tierra y espacio (sobre todo en 8.°: universo, historia de la Tierra).
B18: R5. Capas PISA: en cada unidad de 7.°–9.°, al menos un tema o fase que trabaje lo epistémico (por qué se confía en un modelo o en una conclusión) y la competencia 3 (evaluar fuentes, distinguir evidencia de opinión, criticar argumentos con datos), situado en un contexto local o personal. No requiere temas nuevos: cambia la fase «Reforzar».
B19: R6. Validar antes de decidir: las clasificaciones y los candidatos del presupuesto son asistidos por IA. El equipo de Ciencias debe revisar primero los de confianza baja (columna «Decisión del equipo» en Presupuesto y outputs/revision_confianza_baja_timss2027.csv).
B21: Qué responde este libro
B22: 1. Balance: ¿el reparto de temas entre Vida / Física / Química / Tierra se parece al peso que TIMSS da a cada dominio? ¿Cuántos temas faltan o sobran para llegar a la meta?
B23: 2. Amplitud: ¿qué objetivos de contenido de TIMSS aparecen en la malla, en qué grado, con cuántos temas, y cuáles no aparecen?
B24: 3. Profundidad cognitiva: ¿la proporción Conocer / Aplicar / Razonar se parece a la de TIMSS? 4. PISA (7.°–9.°): ¿cubre los sistemas y categorías de contenido, las tres competencias y sus subcompetencias, el conocimiento procedimental y epistémico, y los contextos que PISA evalúa? 5. ¿Qué insertar y qué fusionar para acercarse a las metas sin aumentar la carga?
B26: Proceso (de dónde salen los números)
B27: Paso 1 · Extracción. Se leyeron las 11 mallas (2.° a 9.° y Física, Química, Biología de 10.° y 11.°). Cada fila con «Procedimental» es un TEMA: 1.260 en total. Se conservan archivo, hoja y fila de origen (hoja Datos - Temas, columnas D-F) para poder volver a la malla.
B28: Paso 2 · Catálogo de referencia. Objetivos de contenido de TIMSS 2027 (4.° grado: 32; 8.° grado: 48), construidos desde el PDF oficial con página citada, y TIMSS Advanced 2015 Física (23), con su dominio y el % que TIMSS asigna a cada dominio (hoja Datos - Catálogo TIMSS, celdas ámbar = valores tomados del marco y editables). Novedades 2027: áreas de Investigaciones en cada dominio y subescala de conocimiento ambiental.
B29: Paso 3 · Clasificación. Los 622 temas de 2.° a 9.° se reclasificaron contra TIMSS 2027 con agentes de IA (instrucciones fijas, un lote por grado), usando la clasificación 2023 y la tabla de equivalencias solo como referencia. Física 10.°–11.° conserva la clasificación TIMSS Advanced 2015. Un tema va a un área de Investigaciones solo si su foco es la práctica científica; si trabaja un contenido mediante indagación, la investigación va como secundaria.
B30: Paso 4 · Reglas de grado. 2.°–4.° → TIMSS 2027 4.°; 5.°–8.° → TIMSS 2027 8.°; 7.°–9.° → PISA 2025 (7.° y 8.° con los dos marcos, 9.° solo PISA); Física 10.°–11.° → TIMSS Advanced 2015. Química y Biología de Bachillerato no tienen marco de contenido.
B31: Paso 4-bis · PISA 2025. Catálogo desde el marco final (OECD 2026, cap. 2, con página). Los temas de 7.°–9.° se clasificaron con IA por categoría de contenido, tipo de conocimiento, elementos procedimentales y epistémicos, contexto, área de aplicación y demanda cognitiva. La competencia y las subcompetencias NO se clasificaron: salen de la propia malla (columnas «Competencia PISA 2025» y microhabilidades E/D/I por fase).
... B52: • 1.° grado no tiene malla, así que no entra en el ciclo 2.°–4.°.

Sheet Resumen TIMSS y PISA
A1: Resumen por grado: TIMSS 2027 (2.°–8.° y Física) arriba · PISA 2025 (7.°–9.°) abajo
A2: {="TIMSS 2027 y PISA 2025"&" "&"OJO · TIMSS (2.°–8.°): faltan "&FIXED(MAX($G$5:$G$11),0)&" temas de "&INDEX($F$5:$F$11,MATCH(MAX($G$5:$G$11),$G$5:$G$11,0))&" en "&SUBSTITUTE(INDEX($A$5:$A$11,MATCH(MAX($G$5:$G$11),$G$5:$G$11,0)),"°",".°")&", el grado más desbalanceado."&" "&"OJO · PISA (7.°–9.°): faltan "&FIXED(G25,0)&" temas de "&LOWER(F25)&" en 9.°; en 7.°–9.° sobran "&FIXED(I26,0)&" de "&LOWER(H26)&"."&" "&"● Arriba: tabla TIMSS. Abajo: tabla PISA. Al final: qué significa cada columna."} -> TIMSS 2027 y PISA 2025 OJO · TIMSS (2.°–8.°): faltan 19 temas de Biología en 5.°, el grado más desbalanceado. OJO · PISA (7.°–9.°): faltan 28 temas de sistemas vivos en 9.°; en 7.°–9.° sobran 33 de sistemas físicos. ● Arriba: tabla TIMSS. Abajo: tabla PISA. Al final: qué significa cada columna.
A3: Lo contrario de «sin objetivo en el marco» (objetivos que TIMSS evalúa y la malla NO trabaja) está en el bloque por ciclo, columna «Objetivos no cubiertos», y en rojo en TIMSS - Semáforo de objetivos. Al final de esta hoja hay una guía de cada columna.
A4: Grupo | B4: Marco de referencia | C4: Temas totales | D4: Temas de la malla SIN objetivo en el marco (la malla los tiene; TIMSS no los evalúa) | E4: % de temas sin objetivo en el marco | F4: Dominio TIMSS con MÁS temas faltantes (frente a su meta) | G4: Temas que faltan en ese dominio | H4: Dominio TIMSS con MÁS temas de sobra | I4: Temas que sobran en ese dominio | J4: Temas a AGREGAR, sin quitar ninguno, para que TODOS los dominios lleguen a su meta | K4: Dominios en meta (±tolerancia) | L4: % Razonar actual | M4: % Razonar meta
A5: 2° | B5: TIMSS 2027 4.° | C5: {=_xlfn.COUNTIFS('Datos - Temas'!$V$5:$V$1264,$A5)} -> 70 | D5: {='TIMSS - Balance por grado'!N6} -> 11 | E5: {=IF(C5=0,0,D5/C5)} -> 0.15714286 | F5: {=INDEX('TIMSS - Balance por grado'!$C$6:$C$8,MATCH(MAX('TIMSS - Balance por grado'!$I$6:$I$8),'TIMSS - Balance por grado'!$I$6:$I$8,0))} -> Ciencias de la Tierra | G5: {=ROUND(MAX('TIMSS - Balance por grado'!$I$6:$I$8),0)} -> 4 | H5: {=INDEX('TIMSS - Balance por grado'!$C$6:$C$8,MATCH(MIN('TIMSS - Balance por grado'!$I$6:$I$8),'TIMSS - Balance por grado'!$I$6:$I$8,0))} -> Ciencias físicas | I5: {=ROUND(-MIN('TIMSS - Balance por grado'!$I$6:$I$8),0)} -> 6 | J5: {='TIMSS - Balance por grado'!M9} -> 19 | K5: {=COUNTIF('TIMSS - Balance por grado'!$K$6:$K$8,"En meta")&" de "&ROWS('TIMSS - Balance por grado'!$K$6:$K$8)} -> 1 de 3 | L5: {='TIMSS - Conocer-Aplicar-Razonar'!I5} -> 0.27142857 | M5: {='TIMSS - Conocer-Aplicar-Razonar'!L5} -> 0.25
A6: 3° | B6: TIMSS 2027 4.° | C6: {=_xlfn.COUNTIFS('Datos - Temas'!$V$5:$V$1264,$A6)} -> 66 | D6: {='TIMSS - Balance por grado'!N11} -> 6 | E6: {=IF(C6=0,0,D6/C6)} -> 0.090909091 | F6: {=INDEX('TIMSS - Balance por grado'!$C$11:$C$13,MATCH(MAX('TIMSS - Balance por grado'!$I$11:$I$13),'TIMSS - Balance por grado'!$I$11:$I$13,0))} -> Ciencias de la Tierra | G6: {=ROUND(MAX('TIMSS - Balance por grado'!$I$11:$I$13),0)} -> 3 | H6: {=INDEX('TIMSS - Balance por grado'!$C$11:$C$13,MATCH(MIN('TIMSS - Balance por grado'!$I$11:$I$13),'TIMSS - Balance por grado'!$I$11:$I$13,0))} -> Biología | I6: {=ROUND(-MIN('TIMSS - Balance por grado'!$I$11:$I$13),0)} -> 5 | J6: {='TIMSS - Balance por grado'!M14} -> 12 | K6: {=COUNTIF('TIMSS - Balance por grado'!$K$11:$K$13,"En meta")&" de "&ROWS('TIMSS - Balance por grado'!$K$11:$K$13)} -> 2 de 3 | L6: {='TIMSS - Conocer-Aplicar-Razonar'!I6} -> 0.26515152 | M6: {='TIMSS - Conocer-Aplicar-Razonar'!L6} -> 0.25
A7: 4° | B7: TIMSS 2027 4.° | C7: {=_xlfn.COUNTIFS('Datos - Temas'!$V$5:$V$1264,$A7)} -> 72 | D7: {='TIMSS - Balance por grado'!N16} -> 9 | E7: {=IF(C7=0,0,D7/C7)} -> 0.125 | F7: {=INDEX('TIMSS - Balance por grado'!$C$16:$C$18,MATCH(MAX('TIMSS - Balance por grado'!$I$16:$I$18),'TIMSS - Balance por grado'!$I$16:$I$18,0))} -> Ciencias físicas | G7: {=ROUND(MAX('TIMSS - Balance por grado'!$I$16:$I$18),0)} -> 13 | H7: {=INDEX('TIMSS - Balance por grado'!$C$16:$C$18,MATCH(MIN('TIMSS - Balance por grado'!$I$16:$I$18),'TIMSS - Balance por grado'!$I$16:$I$18,0))} -> Biología | I7: {=ROUND(-MIN('TIMSS - Balance por grado'!$I$16:$I$18),0)} -> 10 | J7: {='TIMSS - Balance por grado'!M19} -> 22 | K7: {=COUNTIF('TIMSS - Balance por grado'!$K$16:$K$18,"En meta")&" de "&ROWS('TIMSS - Balance por grado'!$K$16:$K$18)} -> 0 de 3 | L7: {='TIMSS - Conocer-Aplicar-Razonar'!I7} -> 0.20138889 | M7: {='TIMSS - Conocer-Aplicar-Razonar'!L7} -> 0.25
A8: 5° | B8: TIMSS 2027 8.° | C8: {=_xlfn.COUNTIFS('Datos - Temas'!$V$5:$V$1264,$A8)} -> 72 | D8: {='TIMSS - Balance por grado'!N21} -> 11 | E8: {=IF(C8=0,0,D8/C8)} -> 0.15277778 | F8: {=INDEX('TIMSS - Balance por grado'!$C$21:$C$24,MATCH(MAX('TIMSS - Balance por grado'!$I$21:$I$24),'TIMSS - Balance por grado'!$I$21:$I$24,0))} -> Biología | G8: {=ROUND(MAX('TIMSS - Balance por grado'!$I$21:$I$24),0)} -> 19 | H8: {=INDEX('TIMSS - Balance por grado'!$C$21:$C$24,MATCH(MIN('TIMSS - Balance por grado'!$I$21:$I$24),'TIMSS - Balance por grado'!$I$21:$I$24,0))} -> Ciencias de la Tierra | I8: {=ROUND(-MIN('TIMSS - Balance por grado'!$I$21:$I$24),0)} -> 8 | J8: {='TIMSS - Balance por grado'!M25} -> 39 | K8: {=COUNTIF('TIMSS - Balance por grado'!$K$21:$K$24,"En meta")&" de "&ROWS('TIMSS - Balance por grado'!$K$21:$K$24)} -> 0 de 4 | L8: {='TIMSS - Conocer-Aplicar-Razonar'!I8} -> 0.24305556 | M8: {='TIMSS - Conocer-Aplicar-Razonar'!L8} -> 0.3
A9: 6° | B9: TIMSS 2027 8.° | C9: {=_xlfn.COUNTIFS('Datos - Temas'!$V$5:$V$1264,$A9)} -> 68 | D9: {='TIMSS - Balance por grado'!N27} -> 5 | E9: {=IF(C9=0,0,D9/C9)} -> 0.073529412 | F9: {=INDEX('TIMSS - Balance por grado'!$C$27:$C$30,MATCH(MAX('TIMSS - Balance por grado'!$I$27:$I$30),'TIMSS - Balance por grado'!$I$27:$I$30,0))} -> Ciencias de la Tierra | G9: {=ROUND(MAX('TIMSS - Balance por grado'!$I$27:$I$30),0)} -> 13 | H9: {=INDEX('TIMSS - Balance por grado'!$C$27:$C$30,MATCH(MIN('TIMSS - Balance por grado'!$I$27:$I$30),'TIMSS - Balance por grado'!$I$27:$I$30,0))} -> Física | I9: {=ROUND(-MIN('TIMSS - Balance por grado'!$I$27:$I$30),0)} -> 8 | J9: {='TIMSS - Balance por grado'!M31} -> 35 | K9: {=COUNTIF('TIMSS - Balance por grado'!$K$27:$K$30,"En meta")&" de "&ROWS('TIMSS - Balance por grado'!$K$27:$K$30)} -> 1 de 4 | L9: {='TIMSS - Conocer-Aplicar-Razonar'!I9} -> 0.19117647 | M9: {='TIMSS - Conocer-Aplicar-Razonar'!L9} -> 0.3
A10: 7° | B10: TIMSS 2027 8.° | C10: {=_xlfn.COUNTIFS('Datos - Temas'!$V$5:$V$1264,$A10)} -> 91 | D10: {='TIMSS - Balance por grado'!N33} -> 6 | E10: {=IF(C10=0,0,D10/C10)} -> 0.065934066 | F10: {=INDEX('TIMSS - Balance por grado'!$C$33:$C$36,MATCH(MAX('TIMSS - Balance por grado'!$I$33:$I$36),'TIMSS - Balance por grado'!$I$33:$I$36,0))} -> Física | G10: {=ROUND(MAX('TIMSS - Balance por grado'!$I$33:$I$36),0)} -> 19 | H10: {=INDEX('TIMSS - Balance por grado'!$C$33:$C$36,MATCH(MIN('TIMSS - Balance por grado'!$I$33:$I$36),'TIMSS - Balance por grado'!$I$33:$I$36,0))} -> Biología | I10: {=ROUND(-MIN('TIMSS - Balance por grado'!$I$33:$I$36),0)} -> 15 | J10: {='TIMSS - Balance por grado'!M37} -> 61 | K10: {=COUNTIF('TIMSS - Balance por grado'!$K$33:$K$36,"En meta")&" de "&ROWS('TIMSS - Balance por grado'!$K$33:$K$36)} -> 0 de 4 | L10: {='TIMSS - Conocer-Aplicar-Razonar'!I10} -> 0.28571429 | M10: {='TIMSS - Conocer-Aplicar-Razonar'!L10} -> 0.3
A11: 8° | B11: TIMSS 2027 8.° | C11: {=_xlfn.COUNTIFS('Datos - Temas'!$V$5:$V$1264,$A11)} -> 93 | D11: {='TIMSS - Balance por grado'!N39} -> 0 | E11: {=IF(C11=0,0,D11/C11)} -> 0 | F11: {=INDEX('TIMSS - Balance por grado'!$C$39:$C$42,MATCH(MAX('TIMSS - Balance por grado'!$I$39:$I$42),'TIMSS - Balance por grado'!$I$39:$I$42,0))} -> Ciencias de la Tierra | G11: {=ROUND(MAX('TIMSS - Balance por grado'!$I$39:$I$42),0)} -> 15 | H11: {=INDEX('TIMSS - Balance por grado'!$C$39:$C$42,MATCH(MIN('TIMSS - Balance por grado'!$I$39:$I$42),'TIMSS - Balance por grado'!$I$39:$I$42,0))} -> Física | I11: {=ROUND(-MIN('TIMSS - Balance por grado'!$I$39:$I$42),0)} -> 14 | J11: {='TIMSS - Balance por grado'!M43} -> 56 | K11: {=COUNTIF('TIMSS - Balance por grado'!$K$39:$K$42,"En meta")&" de "&ROWS('TIMSS - Balance por grado'!$K$39:$K$42)} -> 0 de 4 | L11: {='TIMSS - Conocer-Aplicar-Razonar'!I11} -> 0.20967742 | M11: {='TIMSS - Conocer-Aplicar-Razonar'!L11} -> 0.3
A12: Física 10° | B12: TIMSS Advanced 2015 Física | C12: {=_xlfn.COUNTIFS('Datos - Temas'!$V$5:$V$1264,$A12)} -> 121 | D12: {='TIMSS - Balance por grado'!N45} -> 41 | E12: {=IF(C12=0,0,D12/C12)} -> 0.33884298 | F12: {=INDEX('TIMSS - Balance por grado'!$C$45:$C$47,MATCH(MAX('TIMSS - Balance por grado'!$I$45:$I$47),'TIMSS - Balance por grado'!$I$45:$I$47,0))} -> Electricidad y magnetismo | G12: {=ROUND(MAX('TIMSS - Balance por grado'!$I$45:$I$47),0)} -> 20 | H12: {=INDEX('TIMSS - Balance por grado'!$C$45:$C$47,MATCH(MIN('TIMSS - Balance por grado'!$I$45:$I$47),'TIMSS - Balance por grado'!$I$45:$I$47,0))} -> Mecánica y termodinámica | I12: {=ROUND(-MIN('TIMSS - Balance por grado'!$I$45:$I$47),0)} -> 35 | J12: {='TIMSS - Balance por grado'!M48} -> 88 | K12: {=COUNTIF('TIMSS - Balance por grado'!$K$45:$K$47,"En meta")&" de "&ROWS('TIMSS - Balance por grado'!$K$45:$K$47)} -> 0 de 3 | L12: {='TIMSS - Conocer-Aplicar-Razonar'!I12} -> 0.48071625 | M12: {='TIMSS - Conocer-Aplicar-Razonar'!L12} -> 0.3
A13: Física 11° | B13: TIMSS Advanced 2015 Física | C13: {=_xlfn.COUNTIFS('Datos - Temas'!$V$5:$V$1264,$A13)} -> 146 | D13: {='TIMSS - Balance por grado'!N50} -> 27 | E13: {=IF(C13=0,0,D13/C13)} -> 0.18493151 | F13: {=INDEX('TIMSS - Balance por grado'!$C$50:$C$52,MATCH(MAX('TIMSS - Balance por grado'!$I$50:$I$52),'TIMSS - Balance por grado'!$I$50:$I$52,0))} -> Mecánica y termodinámica | G13: {=ROUND(MAX('TIMSS - Balance por grado'!$I$50:$I$52),0)} -> 44 | H13: {=INDEX('TIMSS - Balance por grado'!$C$50:$C$52,MATCH(MIN('TIMSS - Balance por grado'!$I$50:$I$52),'TIMSS - Balance por grado'!$I$50:$I$52,0))} -> Ondas y física atómica/nuclear | I13: {=ROUND(-MIN('TIMSS - Balance por grado'!$I$50:$I$52),0)} -> 30 | J13: {='TIMSS - Balance por grado'!M53} -> 89 | K13: {=COUNTIF('TIMSS - Balance por grado'!$K$50:$K$52,"En meta")&" de "&ROWS('TIMSS - Balance por grado'!$K$50:$K$52)} -> 0 de 3 | L13: {='TIMSS - Conocer-Aplicar-Razonar'!I13} -> 0.46575342 | M13: {='TIMSS - Conocer-Aplicar-Razonar'!L13} -> 0.3
A15: Por ciclo (comparación acumulada)
A16: Ciclo | B16: Marco de referencia | C16: Temas evaluables | D16: Dominio con mayor FALTANTE | E16: Faltan (temas) | F16: Dominio más SOBRErrepresentado | G16: Sobran (temas) | H16: Temas a agregar sin quitar | I16: Dominios en meta | J16: Objetivos TIMSS del marco | K16: Objetivos cubiertos | L16: % amplitud | M16: Objetivos del marco que la malla NO trabaja | N16: Objetivos cubiertos (2023) | O16: % amplitud (2023) | P16: Dominio con mayor FALTANTE (2023) | Q16: Cambio vs 2023 | R16: % temas ambientales (ref. ≈25 %) | S16: Temas en Investigaciones (principal)
A17: Ciclo 2°–4° | B17: TIMSS 2027 4.° | C17: {='TIMSS - Balance por ciclo'!E6} -> 182 | D17: {=INDEX('TIMSS - Balance por ciclo'!$C$6:$C$8,MATCH(MAX('TIMSS - Balance por ciclo'!$I$6:$I$8),'TIMSS - Balance por ciclo'!$I$6:$I$8,0))} -> Ciencias físicas | E17: {=ROUND(MAX('TIMSS - Balance por ciclo'!$I$6:$I$8),0)} -> 9 | F17: {=INDEX('TIMSS - Balance por ciclo'!$C$6:$C$8,MATCH(MIN('TIMSS - Balance por ciclo'!$I$6:$I$8),'TIMSS - Balance por ciclo'!$I$6:$I$8,0))} -> Biología | G17: {=ROUND(-MIN('TIMSS - Balance por ciclo'!$I$6:$I$8),0)} -> 12 | H17: {='TIMSS - Balance por ciclo'!M9} -> 29 | I17: {=COUNTIF('TIMSS - Balance por ciclo'!$K$6:$K$8,"En meta")&" de "&ROWS('TIMSS - Balance por ciclo'!$K$6:$K$8)} -> 2 de 3 | J17: {='TIMSS - Semáforo de objetivos'!C115} -> 32 | K17: {='TIMSS - Semáforo de objetivos'!D115} -> 31 | L17: {='TIMSS - Semáforo de objetivos'!E115} -> 0.96875 | M17: {='TIMSS - Semáforo de objetivos'!F115} -> 1 | N17: {='Datos - TIMSS 2023'!C110} -> 31 | O17: {='Datos - TIMSS 2023'!D110} -> 0.96875 | P17: {=INDEX('Datos - TIMSS 2023'!$C$117:$C$119,MATCH(MAX('Datos - TIMSS 2023'!$G$117:$G$119),'Datos - TIMSS 2023'!$G$117:$G$119,0))} -> Ciencias físicas | Q17: {="Cubiertos: "&N17&" de "&'Datos - TIMSS 2023'!B110&" (2023) → "&K17&" de "&J17&" (2027) · Mayor faltante: "&P17&" (2023) → "&D17&" (2027)"} -> Cubiertos: 31 de 32 (2023) → 31 de 32 (2027) · Mayor faltante: Ciencias físicas (2023) → Ciencias físicas (2027) | R17: {='TIMSS - Medio ambiente'!E16} -> 0.2967033 | S17: {='TIMSS - Investigación'!C15} -> 9
A18: Ciclo 5°–8° | B18: TIMSS 2027 8.° | C18: {='TIMSS - Balance por ciclo'!E11} -> 302 | D18: {=INDEX('TIMSS - Balance por ciclo'!$C$11:$C$14,MATCH(MAX('TIMSS - Balance por ciclo'!$I$11:$I$14),'TIMSS - Balance por ciclo'!$I$11:$I$14,0))} -> Ciencias de la Tierra | E18: {=ROUND(MAX('TIMSS - Balance por ciclo'!$I$11:$I$14),0)} -> 7 | F18: {=INDEX('TIMSS - Balance por ciclo'!$C$11:$C$14,MATCH(MIN('TIMSS - Balance por ciclo'!$I$11:$I$14),'TIMSS - Balance por ciclo'!$I$11:$I$14,0))} -> Física | G18: {=ROUND(-MIN('TIMSS - Balance por ciclo'!$I$11:$I$14),0)} -> 8 | H18: {='TIMSS - Balance por ciclo'!M15} -> 32 | I18: {=COUNTIF('TIMSS - Balance por ciclo'!$K$11:$K$14,"En meta")&" de "&ROWS('TIMSS - Balance por ciclo'!$K$11:$K$14)} -> 4 de 4 | J18: {='TIMSS - Semáforo de objetivos'!C120} -> 48 | K18: {='TIMSS - Semáforo de objetivos'!D120} -> 45 | L18: {='TIMSS - Semáforo de objetivos'!E120} -> 0.9375 | M18: {='TIMSS - Semáforo de objetivos'!F120} -> 3 | N18: {='Datos - TIMSS 2023'!C111} -> 43 | O18: {='Datos - TIMSS 2023'!D111} -> 0.93478261 | P18: {=INDEX('Datos - TIMSS 2023'!$C$121:$C$124,MATCH(MAX('Datos - TIMSS 2023'!$G$121:$G$124),'Datos - TIMSS 2023'!$G$121:$G$124,0))} -> Ciencias de la Tierra | Q18: {="Cubiertos: "&N18&" de "&'Datos - TIMSS 2023'!B111&" (2023) → "&K18&" de "&J18&" (2027) · Mayor faltante: "&P18&" (2023) → "&D18&" (2027)"} -> Cubiertos: 43 de 46 (2023) → 45 de 48 (2027) · Mayor faltante: Ciencias de la Tierra (2023) → Ciencias de la Tierra (2027) | R18: {='TIMSS - Medio ambiente'!E17} -> 0.29139073 | S18: {='TIMSS - Investigación'!C16} -> 15
A19: Física 10°–11° | B19: TIMSS Advanced 2015 Física | C19: {='TIMSS - Balance por ciclo'!E17} -> 199 | D19: {=INDEX('TIMSS - Balance por ciclo'!$C$17:$C$19,MATCH(MAX('TIMSS - Balance por ciclo'!$I$17:$I$19),'TIMSS - Balance por ciclo'!$I$17:$I$19,0))} -> Mecánica y termodinámica | E19: {=ROUND(MAX('TIMSS - Balance por ciclo'!$I$17:$I$19),0)} -> 9 | F19: {=INDEX('TIMSS - Balance por ciclo'!$C$17:$C$19,MATCH(MIN('TIMSS - Balance por ciclo'!$I$17:$I$19),'TIMSS - Balance por ciclo'!$I$17:$I$19,0))} -> Ondas y física atómica/nuclear | G19: {=ROUND(-MIN('TIMSS - Balance por ciclo'!$I$17:$I$19),0)} -> 15 | H19: {='TIMSS - Balance por ciclo'!M20} -> 46 | I19: {=COUNTIF('TIMSS - Balance por ciclo'!$K$17:$K$19,"En meta")&" de "&ROWS('TIMSS - Balance por ciclo'!$K$17:$K$19)} -> 2 de 3 | J19: {='TIMSS - Semáforo de objetivos'!C124} -> 23 | K19: {='TIMSS - Semáforo de objetivos'!D124} -> 23 | L19: {='TIMSS - Semáforo de objetivos'!E124} -> 1 | M19: {='TIMSS - Semáforo de objetivos'!F124} -> 0 | N19: {='Datos - TIMSS 2023'!C112} -> 23 | O19: {='Datos - TIMSS 2023'!D112} -> 1 | P19: {=INDEX('Datos - TIMSS 2023'!$C$131:$C$133,MATCH(MAX('Datos - TIMSS 2023'!$G$131:$G$133),'Datos - TIMSS 2023'!$G$131:$G$133,0))} -> Mecánica y termodinámica | Q19: {="Sin cambio de marco: Física sigue con TIMSS Advanced 2015"} -> Sin cambio de marco: Física sigue con TIMSS Advanced 2015 | R19: — | S19: —
A21: PISA 2025 (7.°, 8.°, 9.° y acumulado 7.°–9.°): 9.° se compara solo con PISA; 7.° y 8.° con los dos marcos (ver Apego TIMSS y PISA)
A22: Grupo | B22: Marco de referencia | C22: Temas totales | D22: Temas sin contenido PISA (la malla los tiene; PISA no los evalúa) | E22: % sin contenido PISA | F22: Sistema PISA con MÁS temas faltantes | G22: Temas que faltan | H22: Sistema PISA con MÁS temas de sobra | I22: Temas que sobran | J22: Temas a AGREGAR, sin quitar, para que todos los sistemas lleguen a su meta | K22: Sistemas en meta | L22: % competencia 3 «Investigar, evaluar y usar información» (meta 24–36 %) | M22: ÍNDICE DE APEGO PISA
A23: 7° | B23: PISA 2025 | C23: {=_xlfn.COUNTIFS('Datos - Temas'!$V$5:$V$1264,$A23,'Datos - Temas'!$AK$5:$AK$1264,"<>")} -> 91 | D23: {='PISA - Contenidos'!N6} -> 1 | E23: {=IF(C23=0,0,D23/C23)} -> 0.010989011 | F23: {=INDEX('PISA - Contenidos'!$C$6:$C$8,MATCH(MAX('PISA - Contenidos'!$I$6:$I$8),'PISA - Contenidos'!$I$6:$I$8,0))} -> Sistemas físicos | G23: {=ROUND(MAX('PISA - Contenidos'!$I$6:$I$8),0)} -> 17 | H23: {=INDEX('PISA - Contenidos'!$C$6:$C$8,MATCH(MIN('PISA - Contenidos'!$I$6:$I$8),'PISA - Contenidos'!$I$6:$I$8,0))} -> Sistemas vivos | I23: {=ROUND(-MIN('PISA - Contenidos'!$I$6:$I$8),0)} -> 18 | J23: {='PISA - Contenidos'!M9} -> 50 | K23: {=COUNTIF('PISA - Contenidos'!$K$6:$K$8,"En meta")&" de "&ROWS('PISA - Contenidos'!$K$6:$K$8)} -> 1 de 3 | L23: {='PISA - Competencias'!H13} -> 0.21978022 | M23: {='Apego TIMSS y PISA'!F20} -> 0.86155678
A24: 8° | B24: PISA 2025 | C24: {=_xlfn.COUNTIFS('Datos - Temas'!$V$5:$V$1264,$A24,'Datos - Temas'!$AK$5:$AK$1264,"<>")} -> 93 | D24: {='PISA - Contenidos'!N11} -> 5 | E24: {=IF(C24=0,0,D24/C24)} -> 0.053763441 | F24: {=INDEX('PISA - Contenidos'!$C$11:$C$13,MATCH(MAX('PISA - Contenidos'!$I$11:$I$13),'PISA - Contenidos'!$I$11:$I$13,0))} -> Sistemas de la Tierra y el espacio | G24: {=ROUND(MAX('PISA - Contenidos'!$I$11:$I$13),0)} -> 17 | H24: {=INDEX('PISA - Contenidos'!$C$11:$C$13,MATCH(MIN('PISA - Contenidos'!$I$11:$I$13),'PISA - Contenidos'!$I$11:$I$13,0))} -> Sistemas físicos | I24: {=ROUND(-MIN('PISA - Contenidos'!$I$11:$I$13),0)} -> 22 | J24: {='PISA - Contenidos'!M14} -> 63 | K24: {=COUNTIF('PISA - Contenidos'!$K$11:$K$13,"En meta")&" de "&ROWS('PISA - Contenidos'!$K$11:$K$13)} -> 0 de 3 | L24: {='PISA - Competencias'!H14} -> 0.064516129 | M24: {='Apego TIMSS y PISA'!F21} -> 0.71067204
A25: 9° | B25: PISA 2025 | C25: {=_xlfn.COUNTIFS('Datos - Temas'!$V$5:$V$1264,$A25,'Datos - Temas'!$AK$5:$AK$1264,"<>")} -> 90 | D25: {='PISA - Contenidos'!N16} -> 6 | E25: {=IF(C25=0,0,D25/C25)} -> 0.066666667 | F25: {=INDEX('PISA - Contenidos'!$C$16:$C$18,MATCH(MAX('PISA - Contenidos'!$I$16:$I$18),'PISA - Contenidos'!$I$16:$I$18,0))} -> Sistemas vivos | G25: {=ROUND(MAX('PISA - Contenidos'!$I$16:$I$18),0)} -> 28 | H25: {=INDEX('PISA - Contenidos'!$C$16:$C$18,MATCH(MIN('PISA - Contenidos'!$I$16:$I$18),'PISA - Contenidos'!$I$16:$I$18,0))} -> Sistemas físicos | I25: {=ROUND(-MIN('PISA - Contenidos'!$I$16:$I$18),0)} -> 28 | J25: {='PISA - Contenidos'!M19} -> 76 | K25: {=COUNTIF('PISA - Contenidos'!$K$16:$K$18,"En meta")&" de "&ROWS('PISA - Contenidos'!$K$16:$K$18)} -> 1 de 3 | L25: {='PISA - Competencias'!H15} -> 0.13333333 | M25: {='Apego TIMSS y PISA'!F22} -> 0.72730159
A26: Ciclo 7°–9° | B26: PISA 2025 | C26: {=_xlfn.COUNTIFS('Datos - Temas'!$AV$5:$AV$1264,$A26,'Datos - Temas'!$AK$5:$AK$1264,"<>")} -> 274 | D26: {='PISA - Contenidos'!N21} -> 12 | E26: {=IF(C26=0,0,D26/C26)} -> 0.04379562 | F26: {=INDEX('PISA - Contenidos'!$C$21:$C$23,MATCH(MAX('PISA - Contenidos'!$I$21:$I$23),'PISA - Contenidos'!$I$21:$I$23,0))} -> Sistemas de la Tierra y el espacio | G26: {=ROUND(MAX('PISA - Contenidos'!$I$21:$I$23),0)} -> 17 | H26: {=INDEX('PISA - Contenidos'!$C$21:$C$23,MATCH(MIN('PISA - Contenidos'!$I$21:$I$23),'PISA - Contenidos'!$I$21:$I$23,0))} -> Sistemas físicos | I26: {=ROUND(-MIN('PISA - Contenidos'!$I$21:$I$23),0)} -> 33 | J26: {='PISA - Contenidos'!M24} -> 90 | K26: {=COUNTIF('PISA - Contenidos'!$K$21:$K$23,"En meta")&" de "&ROWS('PISA - Contenidos'!$K$21:$K$23)} -> 0 de 3 | L26: {='PISA - Competencias'!H16} -> 0.13868613 | M26: {='Apego TIMSS y PISA'!F23} -> 0.87661579
A28: Cómo leer cada columna
A29: • Temas SIN objetivo en el marco: temas que la malla SÍ enseña pero que el marco no evalúa (p. ej. medición general, electrónica digital, gestión de riesgos). No son un error: indican cuánto de la malla va más allá de la prueba. Lo contrario —objetivos del marco que la malla NO trabaja— está en «Objetivos del marco que la malla NO trabaja».
A30: • Dominio TIMSS con MÁS temas faltantes: de los dominios de TIMSS (Biología, Química, Física, Tierra), el que más se queda por debajo del peso que TIMSS le da en la prueba. «Temas que faltan» = cuántos temas habría que pasar a ese dominio, con el mismo total de temas, para llegar a la meta.
A31: • Temas a AGREGAR sin quitar: si no se quiere quitar ningún tema, cuántos habría que SUMAR en total para que todos los dominios lleguen a su meta. Ejemplo: con 100 temas, 60 % Biología y meta 45 %, habría que llegar a 60 ÷ 0,45 ≈ 133 temas, sumando 33 en los otros dominios. Por eso suele ser una cifra alta: la alternativa realista (fusionar e insertar con el mismo total) está en la hoja Presupuesto de temas.
A32: • Dominios en meta: cuántos dominios están a ±5 puntos porcentuales de su meta (tolerancia editable en TIMSS - Balance por grado, celda H2).
A33: • ÍNDICE DE APEGO: parte del reparto de la malla que ya coincide con el del marco (100 % = igual). Detalle y escenarios TIMSS/PISA en Apego TIMSS y PISA.
A35: Cómo se calcula: Todo es fórmula sobre Temas. Balance = reparto de temas por dominio vs. metas TIMSS. Amplitud = objetivos TIMSS que aparecen. Profundidad cognitiva = Conocer/Aplicar/Razonar. Ver «Inicio» para el proceso completo.

Sheet Apego TIMSS y PISA
A1: Apego a los marcos: índice por grado y escenarios TIMSS / PISA para 7.° y 8.°
A2: {="TIMSS 2027 y PISA 2025"&" "&IF(MIN(F17,F18,F23)>=$H$4,"BIEN · ","OJO · ")&"Acumulado: TIMSS 4.° "&FIXED((F17)*100,0)&" %"&", TIMSS 8.° "&FIXED((F18)*100,0)&" %"&", PISA "&FIXED((F23)*100,0)&" %"&" de apego (alto = 85 % o más)."&" "&"OJO · Grado más flojo en TIMSS: "&SUBSTITUTE(INDEX($A$8:$A$14,MATCH(MIN($F$8:$F$14),$F$8:$F$14,0)),"°",".°")&" ("&FIXED((MIN($F$8:$F$14))*100,0)&" %"&"). En PISA: 9.° ("&FIXED((F22)*100,0)&" %"&")."&" "&"● 7.° y 8.° se miden con los dos marcos: el peso de PISA se elige en la celda E4 (hoy "&FIXED((E4)*100,0)&" %"&")."} -> TIMSS 2027 y PISA 2025 BIEN · Acumulado: TIMSS 4.° 92 %, TIMSS 8.° 88 %, PISA 88 % de apego (alto = 85 % o más). OJO · Grado más flojo en TIMSS: 5.° (69 %). En PISA: 9.° (73 %). ● 7.° y 8.° se miden con los dos marcos: el peso de PISA se elige en la celda E4 (hoy 50 %).
A4: Peso de PISA en 7.° y 8.° (0 % = solo TIMSS): | E4: 0.5 | G4: Lectura: alto desde | H4: 0.85 | I4: medio desde | J4: 0.7
A6: A · Índice de apego por grado y ciclo
A7: Grado / ciclo | B7: Marco | C7: Coincidencia de balance | D7: Coincidencia cognitiva | E7: Amplitud (ciclo) | F7: ÍNDICE DE APEGO | G7: Lectura
A8: 2° | B8: TIMSS 2027 4.° | C8: {='TIMSS - Balance por grado'!O9} -> 0.89237288 | D8: {='TIMSS - Conocer-Aplicar-Razonar'!O5} -> 0.82857143 | E8: — | F8: {=AVERAGE(C8:E8)} -> 0.86047215 | G8: {=IF(F8>=$H$4,"Alto",IF(F8>=$J$4,"Medio","Bajo: revisar"))} -> Alto
A9: 3° | B9: TIMSS 2027 4.° | C9: {='TIMSS - Balance por grado'!O14} -> 0.91666667 | D9: {='TIMSS - Conocer-Aplicar-Razonar'!O6} -> 0.86969697 | E9: — | F9: {=AVERAGE(C9:E9)} -> 0.89318182 | G9: {=IF(F9>=$H$4,"Alto",IF(F9>=$J$4,"Medio","Bajo: revisar"))} -> Alto
A10: 4° | B10: TIMSS 2027 4.° | C10: {='TIMSS - Balance por grado'!O19} -> 0.79285714 | D10: {='TIMSS - Conocer-Aplicar-Razonar'!O7} -> 0.8375 | E10: — | F10: {=AVERAGE(C10:E10)} -> 0.81517857 | G10: {=IF(F10>=$H$4,"Alto",IF(F10>=$J$4,"Medio","Bajo: revisar"))} -> Medio
A11: 5° | B11: TIMSS 2027 8.° | C11: {='TIMSS - Balance por grado'!O25} -> 0.68278689 | D11: {='TIMSS - Conocer-Aplicar-Razonar'!O8} -> 0.69027778 | E11: — | F11: {=AVERAGE(C11:E11)} -> 0.68653233 | G11: {=IF(F11>=$H$4,"Alto",IF(F11>=$J$4,"Medio","Bajo: revisar"))} -> Bajo: revisar
A12: 6° | B12: TIMSS 2027 8.° | C12: {='TIMSS - Balance por grado'!O31} -> 0.75873016 | D12: {='TIMSS - Conocer-Aplicar-Razonar'!O9} -> 0.66617647 | E12: — | F12: {=AVERAGE(C12:E12)} -> 0.71245331 | G12: {=IF(F12>=$H$4,"Alto",IF(F12>=$J$4,"Medio","Bajo: revisar"))} -> Medio
A13: 7° | B13: TIMSS 2027 8.° | C13: {='TIMSS - Balance por grado'!O37} -> 0.67941176 | D13: {='TIMSS - Conocer-Aplicar-Razonar'!O10} -> 0.83351648 | E13: — | F13: {=AVERAGE(C13:E13)} -> 0.75646412 | G13: {=IF(F13>=$H$4,"Alto",IF(F13>=$J$4,"Medio","Bajo: revisar"))} -> Medio
A14: 8° | B14: TIMSS 2027 8.° | C14: {='TIMSS - Balance por grado'!O43} -> 0.78333333 | D14: {='TIMSS - Conocer-Aplicar-Razonar'!O11} -> 0.71021505 | E14: — | F14: {=AVERAGE(C14:E14)} -> 0.74677419 | G14: {=IF(F14>=$H$4,"Alto",IF(F14>=$J$4,"Medio","Bajo: revisar"))} -> Medio
A15: Física 10° | B15: TIMSS Advanced 2015 Física | C15: {='TIMSS - Balance por grado'!O48} -> 0.5625 | D15: {='TIMSS - Conocer-Aplicar-Razonar'!O12} -> 0.76749311 | E15: — | F15: {=AVERAGE(C15:E15)} -> 0.66499656 | G15: {=IF(F15>=$H$4,"Alto",IF(F15>=$J$4,"Medio","Bajo: revisar"))} -> Bajo: revisar
A16: Física 11° | B16: TIMSS Advanced 2015 Física | C16: {='TIMSS - Balance por grado'!O53} -> 0.63361345 | D16: {='TIMSS - Conocer-Aplicar-Razonar'!O13} -> 0.79931507 | E16: — | F16: {=AVERAGE(C16:E16)} -> 0.71646426 | G16: {=IF(F16>=$H$4,"Alto",IF(F16>=$J$4,"Medio","Bajo: revisar"))} -> Medio
A17: Ciclo 2°–4° | B17: TIMSS 2027 4.° | C17: {='TIMSS - Balance por ciclo'!O9} -> 0.93351648 | D17: {=1-(ABS(_xlfn.SUMIFS('Datos - Temas'!$S$5:$S$1264,'Datos - Temas'!$W$5:$W$1264,$A17)/_xlfn.COUNTIFS('Datos - Temas'!$W$5:$W$1264,$A17)-0.35)+ABS(_xlfn.SUMIFS('Datos - Temas'!$T$5:$T$1264,'Datos - Temas'!$W$5:$W$1264,$A17)/_xlfn.COUNTIFS('Datos - Temas'!$W$5:$W$1264,$A17)-0.4)+ABS(_xlfn.SUMIFS('Datos - Temas'!$U$5:$U$1264,'Datos - Temas'!$W$5:$W$1264,$A17)/_xlfn.COUNTIFS('Datos - Temas'!$W$5:$W$1264,$A17)-0.25))/2} -> 0.85673077 | E17: {='TIMSS - Semáforo de objetivos'!E115} -> 0.96875 | F17: {=AVERAGE(C17:E17)} -> 0.91966575 | G17: {=IF(F17>=$H$4,"Alto",IF(F17>=$J$4,"Medio","Bajo: revisar"))} -> Alto
A18: Ciclo 5°–8° | B18: TIMSS 2027 8.° | C18: {='TIMSS - Balance por ciclo'!O15} -> 0.96655629 | D18: {=1-(ABS(_xlfn.SUMIFS('Datos - Temas'!$S$5:$S$1264,'Datos - Temas'!$W$5:$W$1264,$A18)/_xlfn.COUNTIFS('Datos - Temas'!$W$5:$W$1264,$A18)-0.35)+ABS(_xlfn.SUMIFS('Datos - Temas'!$T$5:$T$1264,'Datos - Temas'!$W$5:$W$1264,$A18)/_xlfn.COUNTIFS('Datos - Temas'!$W$5:$W$1264,$A18)-0.35)+ABS(_xlfn.SUMIFS('Datos - Temas'!$U$5:$U$1264,'Datos - Temas'!$W$5:$W$1264,$A18)/_xlfn.COUNTIFS('Datos - Temas'!$W$5:$W$1264,$A18)-0.3))/2} -> 0.73117284 | E18: {='TIMSS - Semáforo de objetivos'!E120} -> 0.9375 | F18: {=AVERAGE(C18:E18)} -> 0.87840971 | G18: {=IF(F18>=$H$4,"Alto",IF(F18>=$J$4,"Medio","Bajo: revisar"))} -> Alto
A19: Física 10°–11° | B19: TIMSS Advanced 2015 Física | C19: {='TIMSS - Balance por ciclo'!O20} -> 0.92286432 | D19: {=1-(ABS(_xlfn.SUMIFS('Datos - Temas'!$S$5:$S$1264,'Datos - Temas'!$W$5:$W$1264,$A19)/_xlfn.COUNTIFS('Datos - Temas'!$W$5:$W$1264,$A19)-0.3)+ABS(_xlfn.SUMIFS('Datos - Temas'!$T$5:$T$1264,'Datos - Temas'!$W$5:$W$1264,$A19)/_xlfn.COUNTIFS('Datos - Temas'!$W$5:$W$1264,$A19)-0.4)+ABS(_xlfn.SUMIFS('Datos - Temas'!$U$5:$U$1264,'Datos - Temas'!$W$5:$W$1264,$A19)/_xlfn.COUNTIFS('Datos - Temas'!$W$5:$W$1264,$A19)-0.3))/2} -> 0.78489388 | E19: {='TIMSS - Semáforo de objetivos'!E124} -> 1 | F19: {=AVERAGE(C19:E19)} -> 0.90258607 | G19: {=IF(F19>=$H$4,"Alto",IF(F19>=$J$4,"Medio","Bajo: revisar"))} -> Alto
A20: 7° · PISA | B20: PISA 2025 | C20: {='PISA - Contenidos'!O9} -> 0.80333333 | D20: {='PISA - Competencias'!L13} -> 0.91978022 | E20: — | F20: {=AVERAGE(C20:E20)} -> 0.86155678 | G20: {=IF(F20>=$H$4,"Alto",IF(F20>=$J$4,"Medio","Bajo: revisar"))} -> Alto
A21: 8° · PISA | B21: PISA 2025 | C21: {='PISA - Contenidos'!O14} -> 0.745 | D21: {='PISA - Competencias'!L14} -> 0.67634409 | E21: — | F21: {=AVERAGE(C21:E21)} -> 0.71067204 | G21: {=IF(F21>=$H$4,"Alto",IF(F21>=$J$4,"Medio","Bajo: revisar"))} -> Medio
A22: 9° · PISA | B22: PISA 2025 | C22: {='PISA - Contenidos'!O19} -> 0.66571429 | D22: {='PISA - Competencias'!L15} -> 0.78888889 | E22: — | F22: {=AVERAGE(C22:E22)} -> 0.72730159 | G22: {=IF(F22>=$H$4,"Alto",IF(F22>=$J$4,"Medio","Bajo: revisar"))} -> Medio
A23: Ciclo 7°–9° · PISA | B23: PISA 2025 | C23: {='PISA - Contenidos'!O24} -> 0.87381679 | D23: {='PISA - Competencias'!L16} -> 0.80364964 | E23: {='PISA - Contenidos'!D55} -> 0.95238095 | F23: {=AVERAGE(C23:E23)} -> 0.87661579 | G23: {=IF(F23>=$H$4,"Alto",IF(F23>=$J$4,"Medio","Bajo: revisar"))} -> Alto
A24: 7° · escenario elegido | B24: Mezcla según el peso de E4 | F24: {=(1-$E$4)*F13+$E$4*F20} -> 0.80901045 | G24: {=IF(F24>=$H$4,"Alto",IF(F24>=$J$4,"Medio","Bajo: revisar"))} -> Medio
A25: 8° · escenario elegido | B25: Mezcla según el peso de E4 | F25: {=(1-$E$4)*F14+$E$4*F21} -> 0.72872312 | G25: {=IF(F25>=$H$4,"Alto",IF(F25>=$J$4,"Medio","Bajo: revisar"))} -> Medio
A28: B · Escenarios para 7.° y 8.°: ¿cuántos temas faltan (+) o sobran (−) en cada sistema según el peso de cada marco?
A29: El eje común son los 3 sistemas de PISA. Las metas de TIMSS 8.° se agrupan igual: Sistemas físicos = Química 20 % + Física 25 %; vivos = Biología 35 %; Tierra y espacio = Ciencias de la Tierra 20 %. En cada escenario: meta = (1 − p)·TIMSS + p·PISA y % actual = (1 − p)·actual TIMSS + p·actual PISA (cada marco con su propia clasificación). Brecha (temas) = (meta − actual) × temas evaluables.
A30: Grado | B30: Sistema | C30: Meta TIMSS (agrupada) | D30: Meta PISA | E30: % actual TIMSS | F30: % actual PISA | G30: 100 % TIMSS · brecha (temas) | H30: 50 / 50 · brecha (temas) | I30: 100 % PISA · brecha (temas) | J30: Personalizado · brecha (temas) | K30: Evaluables TIMSS | L30: Evaluables PISA
A31: Peso de PISA → | G31: 0 | H31: 0.5 | I31: 1 | J31: {=$E$4} -> 0.5
A32: 7° | B32: Sistemas físicos | C32: 0.45 | D32: 0.37 | E32: {=IF(K32=0,0,(_xlfn.COUNTIFS('Datos - Temas'!$V$5:$V$1264,$A32,'Datos - Temas'!$M$5:$M$1264,"Química")+_xlfn.COUNTIFS('Datos - Temas'!$V$5:$V$1264,$A32,'Datos - Temas'!$M$5:$M$1264,"Física"))/K32)} -> 0.12941176 | F32: {=IF(L32=0,0,_xlfn.COUNTIFS('Datos - Temas'!$V$5:$V$1264,$A32,'Datos - Temas'!$AM$5:$AM$1264,$B32)/L32)} -> 0.17777778 | G32: {=((1-G$31)*C32+G$31*D32-((1-G$31)*E32+G$31*F32))*((1-G$31)*K32+G$31*L32)} -> 27.25 | H32: {=((1-H$31)*C32+H$31*D32-((1-H$31)*E32+H$31*F32))*((1-H$31)*K32+H$31*L32)} -> 22.435458 | I32: {=((1-I$31)*C32+I$31*D32-((1-I$31)*E32+I$31*F32))*((1-I$31)*K32+I$31*L32)} -> 17.3 | J32: {=((1-J$31)*C32+J$31*D32-((1-J$31)*E32+J$31*F32))*((1-J$31)*K32+J$31*L32)} -> 22.435458 | K32: {=_xlfn.COUNTIFS('Datos - Temas'!$V$5:$V$1264,$A32,'Datos - Temas'!$C$5:$C$1264,"Ciencias")-_xlfn.COUNTIFS('Datos - Temas'!$V$5:$V$1264,$A32,'Datos - Temas'!$K$5:$K$1264,"FUERA")-_xlfn.COUNTIFS('Datos - Temas'!$V$5:$V$1264,$A32,'Datos - Temas'!$K$5:$K$1264,"PENDIENTE")} -> 85 | L32: {=_xlfn.COUNTIFS('Datos - Temas'!$V$5:$V$1264,$A32,'Datos - Temas'!$AK$5:$AK$1264,"<>")-_xlfn.COUNTIFS('Datos - Temas'!$V$5:$V$1264,$A32,'Datos - Temas'!$AK$5:$AK$1264,"FUERA")} -> 90
A33: 7° | B33: Sistemas vivos | C33: 0.35 | D33: 0.37 | E33: {=IF(K33=0,0,(_xlfn.COUNTIFS('Datos - Temas'!$V$5:$V$1264,$A33,'Datos - Temas'!$M$5:$M$1264,"Biología"))/K33)} -> 0.52941176 | F33: {=IF(L33=0,0,_xlfn.COUNTIFS('Datos - Temas'!$V$5:$V$1264,$A33,'Datos - Temas'!$AM$5:$AM$1264,$B33)/L33)} -> 0.56666667 | G33: {=((1-G$31)*C33+G$31*D33-((1-G$31)*E33+G$31*F33))*((1-G$31)*K33+G$31*L33)} -> -15.25 | H33: {=((1-H$31)*C33+H$31*D33-((1-H$31)*E33+H$31*F33))*((1-H$31)*K33+H$31*L33)} -> -16.453431 | I33: {=((1-I$31)*C33+I$31*D33-((1-I$31)*E33+I$31*F33))*((1-I$31)*K33+I$31*L33)} -> -17.7 | J33: {=((1-J$31)*C33+J$31*D33-((1-J$31)*E33+J$31*F33))*((1-J$31)*K33+J$31*L33)} -> -16.453431 | K33: {=_xlfn.COUNTIFS('Datos - Temas'!$V$5:$V$1264,$A33,'Datos - Temas'!$C$5:$C$1264,"Ciencias")-_xlfn.COUNTIFS('Datos - Temas'!$V$5:$V$1264,$A33,'Datos - Temas'!$K$5:$K$1264,"FUERA")-_xlfn.COUNTIFS('Datos - Temas'!$V$5:$V$1264,$A33,'Datos - Temas'!$K$5:$K$1264,"PENDIENTE")} -> 85 | L33: {=_xlfn.COUNTIFS('Datos - Temas'!$V$5:$V$1264,$A33,'Datos - Temas'!$AK$5:$AK$1264,"<>")-_xlfn.COUNTIFS('Datos - Temas'!$V$5:$V$1264,$A33,'Datos - Temas'!$AK$5:$AK$1264,"FUERA")} -> 90
A34: 7° | B34: Sistemas de la Tierra y el espacio | C34: 0.2 | D34: 0.26 | E34: {=IF(K34=0,0,(_xlfn.COUNTIFS('Datos - Temas'!$V$5:$V$1264,$A34,'Datos - Temas'!$M$5:$M$1264,"Ciencias de la Tierra"))/K34)} -> 0.34117647 | F34: {=IF(L34=0,0,_xlfn.COUNTIFS('Datos - Temas'!$V$5:$V$1264,$A34,'Datos - Temas'!$AM$5:$AM$1264,$B34)/L34)} -> 0.25555556 | G34: {=((1-G$31)*C34+G$31*D34-((1-G$31)*E34+G$31*F34))*((1-G$31)*K34+G$31*L34)} -> -12 | H34: {=((1-H$31)*C34+H$31*D34-((1-H$31)*E34+H$31*F34))*((1-H$31)*K34+H$31*L34)} -> -5.9820261 | I34: {=((1-I$31)*C34+I$31*D34-((1-I$31)*E34+I$31*F34))*((1-I$31)*K34+I$31*L34)} -> 0.4 | J34: {=((1-J$31)*C34+J$31*D34-((1-J$31)*E34+J$31*F34))*((1-J$31)*K34+J$31*L34)} -> -5.9820261 | K34: {=_xlfn.COUNTIFS('Datos - Temas'!$V$5:$V$1264,$A34,'Datos - Temas'!$C$5:$C$1264,"Ciencias")-_xlfn.COUNTIFS('Datos - Temas'!$V$5:$V$1264,$A34,'Datos - Temas'!$K$5:$K$1264,"FUERA")-_xlfn.COUNTIFS('Datos - Temas'!$V$5:$V$1264,$A34,'Datos - Temas'!$K$5:$K$1264,"PENDIENTE")} -> 85 | L34: {=_xlfn.COUNTIFS('Datos - Temas'!$V$5:$V$1264,$A34,'Datos - Temas'!$AK$5:$AK$1264,"<>")-_xlfn.COUNTIFS('Datos - Temas'!$V$5:$V$1264,$A34,'Datos - Temas'!$AK$5:$AK$1264,"FUERA")} -> 90
B35: Coincidencia de balance | G35: {=1-(ABS((1-G$31)*C32+G$31*D32-((1-G$31)*E32+G$31*F32))+ABS((1-G$31)*C33+G$31*D33-((1-G$31)*E33+G$31*F33))+ABS((1-G$31)*C34+G$31*D34-((1-G$31)*E34+G$31*F34)))/2} -> 0.67941176 | H35: {=1-(ABS((1-H$31)*C32+H$31*D32-((1-H$31)*E32+H$31*F32))+ABS((1-H$31)*C33+H$31*D33-((1-H$31)*E33+H$31*F33))+ABS((1-H$31)*C34+H$31*D34-((1-H$31)*E34+H$31*F34)))/2} -> 0.74359477 | I35: {=1-(ABS((1-I$31)*C32+I$31*D32-((1-I$31)*E32+I$31*F32))+ABS((1-I$31)*C33+I$31*D33-((1-I$31)*E33+I$31*F33))+ABS((1-I$31)*C34+I$31*D34-((1-I$31)*E34+I$31*F34)))/2} -> 0.80333333 | J35: {=1-(ABS((1-J$31)*C32+J$31*D32-((1-J$31)*E32+J$31*F32))+ABS((1-J$31)*C33+J$31*D33-((1-J$31)*E33+J$31*F33))+ABS((1-J$31)*C34+J$31*D34-((1-J$31)*E34+J$31*F34)))/2} -> 0.74359477
B36: Índice de apego del escenario | G36: {=(1-G$31)*$F$13+G$31*$F$20} -> 0.75646412 | H36: {=(1-H$31)*$F$13+H$31*$F$20} -> 0.80901045 | I36: {=(1-I$31)*$F$13+I$31*$F$20} -> 0.86155678 | J36: {=(1-J$31)*$F$13+J$31*$F$20} -> 0.80901045
A38: 8° | B38: Sistemas físicos | C38: 0.45 | D38: 0.37 | E38: {=IF(K38=0,0,(_xlfn.COUNTIFS('Datos - Temas'!$V$5:$V$1264,$A38,'Datos - Temas'!$M$5:$M$1264,"Química")+_xlfn.COUNTIFS('Datos - Temas'!$V$5:$V$1264,$A38,'Datos - Temas'!$M$5:$M$1264,"Física"))/K38)} -> 0.66666667 | F38: {=IF(L38=0,0,_xlfn.COUNTIFS('Datos - Temas'!$V$5:$V$1264,$A38,'Datos - Temas'!$AM$5:$AM$1264,$B38)/L38)} -> 0.625 | G38: {=((1-G$31)*C38+G$31*D38-((1-G$31)*E38+G$31*F38))*((1-G$31)*K38+G$31*L38)} -> -20.15 | H38: {=((1-H$31)*C38+H$31*D38-((1-H$31)*E38+H$31*F38))*((1-H$31)*K38+H$31*L38)} -> -21.342917 | I38: {=((1-I$31)*C38+I$31*D38-((1-I$31)*E38+I$31*F38))*((1-I$31)*K38+I$31*L38)} -> -22.44 | J38: {=((1-J$31)*C38+J$31*D38-((1-J$31)*E38+J$31*F38))*((1-J$31)*K38+J$31*L38)} -> -21.342917 | K38: {=_xlfn.COUNTIFS('Datos - Temas'!$V$5:$V$1264,$A38,'Datos - Temas'!$C$5:$C$1264,"Ciencias")-_xlfn.COUNTIFS('Datos - Temas'!$V$5:$V$1264,$A38,'Datos - Temas'!$K$5:$K$1264,"FUERA")-_xlfn.COUNTIFS('Datos - Temas'!$V$5:$V$1264,$A38,'Datos - Temas'!$K$5:$K$1264,"PENDIENTE")} -> 93 | L38: {=_xlfn.COUNTIFS('Datos - Temas'!$V$5:$V$1264,$A38,'Datos - Temas'!$AK$5:$AK$1264,"<>")-_xlfn.COUNTIFS('Datos - Temas'!$V$5:$V$1264,$A38,'Datos - Temas'!$AK$5:$AK$1264,"FUERA")} -> 88
A39: 8° | B39: Sistemas vivos | C39: 0.35 | D39: 0.37 | E39: {=IF(K39=0,0,(_xlfn.COUNTIFS('Datos - Temas'!$V$5:$V$1264,$A39,'Datos - Temas'!$M$5:$M$1264,"Biología"))/K39)} -> 0.29032258 | F39: {=IF(L39=0,0,_xlfn.COUNTIFS('Datos - Temas'!$V$5:$V$1264,$A39,'Datos - Temas'!$AM$5:$AM$1264,$B39)/L39)} -> 0.30681818 | G39: {=((1-G$31)*C39+G$31*D39-((1-G$31)*E39+G$31*F39))*((1-G$31)*K39+G$31*L39)} -> 5.55 | H39: {=((1-H$31)*C39+H$31*D39-((1-H$31)*E39+H$31*F39))*((1-H$31)*K39+H$31*L39)} -> 5.5593805 | I39: {=((1-I$31)*C39+I$31*D39-((1-I$31)*E39+I$31*F39))*((1-I$31)*K39+I$31*L39)} -> 5.56 | J39: {=((1-J$31)*C39+J$31*D39-((1-J$31)*E39+J$31*F39))*((1-J$31)*K39+J$31*L39)} -> 5.5593805 | K39: {=_xlfn.COUNTIFS('Datos - Temas'!$V$5:$V$1264,$A39,'Datos - Temas'!$C$5:$C$1264,"Ciencias")-_xlfn.COUNTIFS('Datos - Temas'!$V$5:$V$1264,$A39,'Datos - Temas'!$K$5:$K$1264,"FUERA")-_xlfn.COUNTIFS('Datos - Temas'!$V$5:$V$1264,$A39,'Datos - Temas'!$K$5:$K$1264,"PENDIENTE")} -> 93 | L39: {=_xlfn.COUNTIFS('Datos - Temas'!$V$5:$V$1264,$A39,'Datos - Temas'!$AK$5:$AK$1264,"<>")-_xlfn.COUNTIFS('Datos - Temas'!$V$5:$V$1264,$A39,'Datos - Temas'!$AK$5:$AK$1264,"FUERA")} -> 88
A40: 8° | B40: Sistemas de la Tierra y el espacio | C40: 0.2 | D40: 0.26 | E40: {=IF(K40=0,0,(_xlfn.COUNTIFS('Datos - Temas'!$V$5:$V$1264,$A40,'Datos - Temas'!$M$5:$M$1264,"Ciencias de la Tierra"))/K40)} -> 0.043010753 | F40: {=IF(L40=0,0,_xlfn.COUNTIFS('Datos - Temas'!$V$5:$V$1264,$A40,'Datos - Temas'!$AM$5:$AM$1264,$B40)/L40)} -> 0.068181818 | G40: {=((1-G$31)*C40+G$31*D40-((1-G$31)*E40+G$31*F40))*((1-G$31)*K40+G$31*L40)} -> 14.6 | H40: {=((1-H$31)*C40+H$31*D40-((1-H$31)*E40+H$31*F40))*((1-H$31)*K40+H$31*L40)} -> 15.783536 | I40: {=((1-I$31)*C40+I$31*D40-((1-I$31)*E40+I$31*F40))*((1-I$31)*K40+I$31*L40)} -> 16.88 | J40: {=((1-J$31)*C40+J$31*D40-((1-J$31)*E40+J$31*F40))*((1-J$31)*K40+J$31*L40)} -> 15.783536 | K40: {=_xlfn.COUNTIFS('Datos - Temas'!$V$5:$V$1264,$A40,'Datos - Temas'!$C$5:$C$1264,"Ciencias")-_xlfn.COUNTIFS('Datos - Temas'!$V$5:$V$1264,$A40,'Datos - Temas'!$K$5:$K$1264,"FUERA")-_xlfn.COUNTIFS('Datos - Temas'!$V$5:$V$1264,$A40,'Datos - Temas'!$K$5:$K$1264,"PENDIENTE")} -> 93 | L40: {=_xlfn.COUNTIFS('Datos - Temas'!$V$5:$V$1264,$A40,'Datos - Temas'!$AK$5:$AK$1264,"<>")-_xlfn.COUNTIFS('Datos - Temas'!$V$5:$V$1264,$A40,'Datos - Temas'!$AK$5:$AK$1264,"FUERA")} -> 88
B41: Coincidencia de balance | G41: {=1-(ABS((1-G$31)*C38+G$31*D38-((1-G$31)*E38+G$31*F38))+ABS((1-G$31)*C39+G$31*D39-((1-G$31)*E39+G$31*F39))+ABS((1-G$31)*C40+G$31*D40-((1-G$31)*E40+G$31*F40)))/2} -> 0.78333333 | H41: {=1-(ABS((1-H$31)*C38+H$31*D38-((1-H$31)*E38+H$31*F38))+ABS((1-H$31)*C39+H$31*D39-((1-H$31)*E39+H$31*F39))+ABS((1-H$31)*C40+H$31*D40-((1-H$31)*E40+H$31*F40)))/2} -> 0.76416667 | I41: {=1-(ABS((1-I$31)*C38+I$31*D38-((1-I$31)*E38+I$31*F38))+ABS((1-I$31)*C39+I$31*D39-((1-I$31)*E39+I$31*F39))+ABS((1-I$31)*C40+I$31*D40-((1-I$31)*E40+I$31*F40)))/2} -> 0.745 | J41: {=1-(ABS((1-J$31)*C38+J$31*D38-((1-J$31)*E38+J$31*F38))+ABS((1-J$31)*C39+J$31*D39-((1-J$31)*E39+J$31*F39))+ABS((1-J$31)*C40+J$31*D40-((1-J$31)*E40+J$31*F40)))/2} -> 0.76416667
B42: Índice de apego del escenario | G42: {=(1-G$31)*$F$14+G$31*$F$21} -> 0.74677419 | H42: {=(1-H$31)*$F$14+H$31*$F$21} -> 0.72872312 | I42: {=(1-I$31)*$F$14+I$31*$F$21} -> 0.71067204 | J42: {=(1-J$31)*$F$14+J$31*$F$21} -> 0.72872312
A45: C · Cómo usar los escenarios (recomendación)
A46: 1. Los tres escenarios pedidos (100 % TIMSS, 50/50, 100 % PISA) están lado a lado; la columna «Personalizado» toma el peso de la celda E4, para probar cualquier mezcla (p. ej. 70 % PISA).
A47: 2. Mezclar METAS solo tiene sentido en un eje común (los 3 sistemas). Las metas cognitivas NO se mezclan: TIMSS mide Conocer/Aplicar/Razonar y PISA tres competencias distintas; por eso el escenario mezcla los ÍNDICES de apego, no las metas cognitivas.
A48: 3. 9.° ya no se compara con TIMSS (decisión del equipo): solo PISA. 5.° y 6.° siguen solo con TIMSS 8.° (que evalúa lo acumulado de 5.° a 8.°).
A49: 4. Si El Salvador participa en TIMSS 2027 (8.° grado), 8.° sigue siendo el grado evaluado por TIMSS: un 100 % PISA en 8.° dejaría de alinear justo el grado que TIMSS mide. Una mezcla 50/50 en 8.° y 70–100 % PISA en 7.° y 9.° es una opción razonable mientras se decide.
A51: Cómo se calcula: COINCIDENCIA = 1 − ½ Σ |% actual − % meta|: es la parte del reparto de la malla que ya coincide con el reparto del marco (100 % = idéntico). Se calcula para el balance de contenidos (dominios TIMSS o sistemas PISA) y para el reparto cognitivo (Conocer/Aplicar/Razonar en TIMSS; las 3 competencias en PISA). En los ciclos se agrega la AMPLITUD (% de objetivos o categorías cubiertos). ÍNDICE DE APEGO = promedio de lo disponible. 7.° y 8.° se miden con los dos marcos; qué peso dar a cada uno es una decisión de política (celda ámbar E4).

Sheet Presupuesto de temas
A1: Presupuesto de temas: qué insertar y qué fusionar para acercarse a las metas SIN aumentar el número de temas
A2: {="TIMSS 2027 (2.°–8.°) y PISA 2025 (7.°–9.°)"&" "&"● El total de temas no cambia: cada tema nuevo se paga uniendo dos temas que se repiten."&" "&"● TIMSS 2.°–4.°: "&FIXED(G9+H9,0)&" temas nuevos a cambio de "&FIXED(J9,0)&" uniones de temas repetidos. TIMSS 5.°–8.°: ya equilibrado; solo "&FIXED(G15+H15,0)&" tema nuevo (un objetivo que nadie enseña)."&" "&"● PISA 7.°–9.°: "&FIXED(G20+H20,0)&" temas nuevos de biología y Tierra a cambio de "&FIXED(J20,0)&" uniones en física y química."&" "&"→ Filtra «¿Entra en el presupuesto?» = Sí y anota tu decisión en la última columna."} -> TIMSS 2027 (2.°–8.°) y PISA 2025 (7.°–9.°) ● El total de temas no cambia: cada tema nuevo se paga uniendo dos temas que se repiten. ● TIMSS 2.°–4.°: 13 temas nuevos a cambio de 13 uniones de temas repetidos. TIMSS 5.°–8.°: ya equilibrado; solo 1 tema nuevo (un objetivo que nadie enseña). ● PISA 7.°–9.°: 33 temas nuevos de biología y Tierra a cambio de 33 uniones en física y química. → Filtra «¿Entra en el presupuesto?» = Sí y anota tu decisión en la última columna.
A3: Se trabaja por CICLO y no por grado: la meta del marco es para lo acumulado, y por grado salen brechas grandes que se compensan entre sí (p. ej. 5.°–8.°: Biología +19 en 5.° y −15 en 7.°, que se resuelve reubicando, no insertando y fusionando). 7.° y 8.° aparecen en el ciclo TIMSS 5.°–8.° y en el PISA 7.°–9.°: según el peso elegido en Apego TIMSS y PISA, seguir uno u otro bloque.
A5: Clave | B5: Ciclo | C5: Marco | D5: Área | E5: Brecha del ciclo (temas) | F5: Estado | G5: Inserciones por balance | H5: Inserciones por cobertura | I5: Temas a liberar con fusiones | J5: Temas que liberan las fusiones elegidas | K5: Saldo (insertados − liberados)
A6: 2-4|Biología | B6: Ciclo 2°–4° | C6: TIMSS 2027 4.° | D6: Biología | E6: {='TIMSS - Balance por ciclo'!I6} -> -12.1 | F6: {='TIMSS - Balance por ciclo'!K6} -> Sobran 12 temas | G6: {=IF(COUNTIF($F$6:$F$8,"En meta")=ROWS($F$6:$F$8),0,MAX(0,ROUND(E6,0)))} -> 0 | H6: {=_xlfn.COUNTIFS($B$24:$B$191,A6,$D$24:$D$191,"insertar",$E$24:$E$191,"cobertura")} -> 1 | I6: {=IF(COUNTIF($F$6:$F$8,"En meta")=ROWS($F$6:$F$8),0,MAX(0,ROUND(-E6,0)))+H6} -> 13 | J6: {=_xlfn.SUMIFS($O$24:$O$191,$B$24:$B$191,A6,$D$24:$D$191,"fusionar",$P$24:$P$191,"Sí")} -> 13 | K6: {=G6+H6-J6} -> -12
A7: 2-4|Ciencias físicas | B7: Ciclo 2°–4° | C7: TIMSS 2027 4.° | D7: Ciencias físicas | E7: {='TIMSS - Balance por ciclo'!I7} -> 8.7 | F7: {='TIMSS - Balance por ciclo'!K7} -> En meta | G7: {=IF(COUNTIF($F$6:$F$8,"En meta")=ROWS($F$6:$F$8),0,MAX(0,ROUND(E7,0)))} -> 9 | H7: {=_xlfn.COUNTIFS($B$24:$B$191,A7,$D$24:$D$191,"insertar",$E$24:$E$191,"cobertura")} -> 0 | I7: {=IF(COUNTIF($F$6:$F$8,"En meta")=ROWS($F$6:$F$8),0,MAX(0,ROUND(-E7,0)))+H7} -> 0 | J7: {=_xlfn.SUMIFS($O$24:$O$191,$B$24:$B$191,A7,$D$24:$D$191,"fusionar",$P$24:$P$191,"Sí")} -> 0 | K7: {=G7+H7-J7} -> 9
A8: 2-4|Ciencias de la Tierra | B8: Ciclo 2°–4° | C8: TIMSS 2027 4.° | D8: Ciencias de la Tierra | E8: {='TIMSS - Balance por ciclo'!I8} -> 3.4 | F8: {='TIMSS - Balance por ciclo'!K8} -> En meta | G8: {=IF(COUNTIF($F$6:$F$8,"En meta")=ROWS($F$6:$F$8),0,MAX(0,ROUND(E8,0)))} -> 3 | H8: {=_xlfn.COUNTIFS($B$24:$B$191,A8,$D$24:$D$191,"insertar",$E$24:$E$191,"cobertura")} -> 0 | I8: {=IF(COUNTIF($F$6:$F$8,"En meta")=ROWS($F$6:$F$8),0,MAX(0,ROUND(-E8,0)))+H8} -> 0 | J8: {=_xlfn.SUMIFS($O$24:$O$191,$B$24:$B$191,A8,$D$24:$D$191,"fusionar",$P$24:$P$191,"Sí")} -> 0 | K8: {=G8+H8-J8} -> 3
D9: Total Ciclo 2°–4° | G9: {=SUM(G6:G8)} -> 12 | H9: {=SUM(H6:H8)} -> 1 | I9: {=SUM(I6:I8)} -> 13 | J9: {=SUM(J6:J8)} -> 13 | K9: {=SUM(K6:K8)} -> 0
A11: 5-8|Biología | B11: Ciclo 5°–8° | C11: TIMSS 2027 8.° | D11: Biología | E11: {='TIMSS - Balance por ciclo'!I11} -> 2.7 | F11: {='TIMSS - Balance por ciclo'!K11} -> En meta | G11: {=IF(COUNTIF($F$11:$F$14,"En meta")=ROWS($F$11:$F$14),0,MAX(0,ROUND(E11,0)))} -> 0 | H11: {=_xlfn.COUNTIFS($B$24:$B$191,A11,$D$24:$D$191,"insertar",$E$24:$E$191,"cobertura")} -> 0 | I11: {=IF(COUNTIF($F$11:$F$14,"En meta")=ROWS($F$11:$F$14),0,MAX(0,ROUND(-E11,0)))+H11} -> 0 | J11: {=_xlfn.SUMIFS($O$24:$O$191,$B$24:$B$191,A11,$D$24:$D$191,"fusionar",$P$24:$P$191,"Sí")} -> 0 | K11: {=G11+H11-J11} -> 0
A12: 5-8|Química | B12: Ciclo 5°–8° | C12: TIMSS 2027 8.° | D12: Química | E12: {='TIMSS - Balance por ciclo'!I12} -> -2.6 | F12: {='TIMSS - Balance por ciclo'!K12} -> En meta | G12: {=IF(COUNTIF($F$11:$F$14,"En meta")=ROWS($F$11:$F$14),0,MAX(0,ROUND(E12,0)))} -> 0 | H12: {=_xlfn.COUNTIFS($B$24:$B$191,A12,$D$24:$D$191,"insertar",$E$24:$E$191,"cobertura")} -> 0 | I12: {=IF(COUNTIF($F$11:$F$14,"En meta")=ROWS($F$11:$F$14),0,MAX(0,ROUND(-E12,0)))+H12} -> 0 | J12: {=_xlfn.SUMIFS($O$24:$O$191,$B$24:$B$191,A12,$D$24:$D$191,"fusionar",$P$24:$P$191,"Sí")} -> 0 | K12: {=G12+H12-J12} -> 0
A13: 5-8|Física | B13: Ciclo 5°–8° | C13: TIMSS 2027 8.° | D13: Física | E13: {='TIMSS - Balance por ciclo'!I13} -> -7.5 | F13: {='TIMSS - Balance por ciclo'!K13} -> En meta | G13: {=IF(COUNTIF($F$11:$F$14,"En meta")=ROWS($F$11:$F$14),0,MAX(0,ROUND(E13,0)))} -> 0 | H13: {=_xlfn.COUNTIFS($B$24:$B$191,A13,$D$24:$D$191,"insertar",$E$24:$E$191,"cobertura")} -> 1 | I13: {=IF(COUNTIF($F$11:$F$14,"En meta")=ROWS($F$11:$F$14),0,MAX(0,ROUND(-E13,0)))+H13} -> 1 | J13: {=_xlfn.SUMIFS($O$24:$O$191,$B$24:$B$191,A13,$D$24:$D$191,"fusionar",$P$24:$P$191,"Sí")} -> 1 | K13: {=G13+H13-J13} -> 0
A14: 5-8|Ciencias de la Tierra | B14: Ciclo 5°–8° | C14: TIMSS 2027 8.° | D14: Ciencias de la Tierra | E14: {='TIMSS - Balance por ciclo'!I14} -> 7.4 | F14: {='TIMSS - Balance por ciclo'!K14} -> En meta | G14: {=IF(COUNTIF($F$11:$F$14,"En meta")=ROWS($F$11:$F$14),0,MAX(0,ROUND(E14,0)))} -> 0 | H14: {=_xlfn.COUNTIFS($B$24:$B$191,A14,$D$24:$D$191,"insertar",$E$24:$E$191,"cobertura")} -> 0 | I14: {=IF(COUNTIF($F$11:$F$14,"En meta")=ROWS($F$11:$F$14),0,MAX(0,ROUND(-E14,0)))+H14} -> 0 | J14: {=_xlfn.SUMIFS($O$24:$O$191,$B$24:$B$191,A14,$D$24:$D$191,"fusionar",$P$24:$P$191,"Sí")} -> 0 | K14: {=G14+H14-J14} -> 0
D15: Total Ciclo 5°–8° | G15: {=SUM(G11:G14)} -> 0 | H15: {=SUM(H11:H14)} -> 1 | I15: {=SUM(I11:I14)} -> 1 | J15: {=SUM(J11:J14)} -> 1 | K15: {=SUM(K11:K14)} -> 0
A17: 7-9|Sistemas físicos | B17: Ciclo 7°–9° | C17: PISA 2025 | D17: Sistemas físicos | E17: {='PISA - Contenidos'!I21} -> -33.06 | F17: {='PISA - Contenidos'!K21} -> Sobran 33 temas | G17: {=IF(COUNTIF($F$17:$F$19,"En meta")=ROWS($F$17:$F$19),0,MAX(0,ROUND(E17,0)))} -> 0 | H17: {=_xlfn.COUNTIFS($B$24:$B$191,A17,$D$24:$D$191,"insertar",$E$24:$E$191,"cobertura")} -> 0 | I17: {=IF(COUNTIF($F$17:$F$19,"En meta")=ROWS($F$17:$F$19),0,MAX(0,ROUND(-E17,0)))+H17} -> 33 | J17: {=_xlfn.SUMIFS($O$24:$O$191,$B$24:$B$191,A17,$D$24:$D$191,"fusionar",$P$24:$P$191,"Sí")} -> 33 | K17: {=G17+H17-J17} -> -33
A18: 7-9|Sistemas vivos | B18: Ciclo 7°–9° | C18: PISA 2025 | D18: Sistemas vivos | E18: {='PISA - Contenidos'!I22} -> 15.94 | F18: {='PISA - Contenidos'!K22} -> Faltan 16 temas | G18: {=IF(COUNTIF($F$17:$F$19,"En meta")=ROWS($F$17:$F$19),0,MAX(0,ROUND(E18,0)))} -> 16 | H18: {=_xlfn.COUNTIFS($B$24:$B$191,A18,$D$24:$D$191,"insertar",$E$24:$E$191,"cobertura")} -> 0 | I18: {=IF(COUNTIF($F$17:$F$19,"En meta")=ROWS($F$17:$F$19),0,MAX(0,ROUND(-E18,0)))+H18} -> 0 | J18: {=_xlfn.SUMIFS($O$24:$O$191,$B$24:$B$191,A18,$D$24:$D$191,"fusionar",$P$24:$P$191,"Sí")} -> 0 | K18: {=G18+H18-J18} -> 16
A19: 7-9|Sistemas de la Tierra y el espacio | B19: Ciclo 7°–9° | C19: PISA 2025 | D19: Sistemas de la Tierra y el espacio | E19: {='PISA - Contenidos'!I23} -> 17.12 | F19: {='PISA - Contenidos'!K23} -> Faltan 17 temas | G19: {=IF(COUNTIF($F$17:$F$19,"En meta")=ROWS($F$17:$F$19),0,MAX(0,ROUND(E19,0)))} -> 17 | H19: {=_xlfn.COUNTIFS($B$24:$B$191,A19,$D$24:$D$191,"insertar",$E$24:$E$191,"cobertura")} -> 0 | I19: {=IF(COUNTIF($F$17:$F$19,"En meta")=ROWS($F$17:$F$19),0,MAX(0,ROUND(-E19,0)))+H19} -> 0 | J19: {=_xlfn.SUMIFS($O$24:$O$191,$B$24:$B$191,A19,$D$24:$D$191,"fusionar",$P$24:$P$191,"Sí")} -> 0 | K19: {=G19+H19-J19} -> 17
D20: Total Ciclo 7°–9° | G20: {=SUM(G17:G19)} -> 33 | H20: {=SUM(H17:H19)} -> 0 | I20: {=SUM(I17:I19)} -> 33 | J20: {=SUM(J17:J19)} -> 33 | K20: {=SUM(K17:K19)} -> 0
A22: Candidatos propuestos (ordenados por ciclo, acción, área y prioridad). La columna «Decisión del equipo» es para que el equipo de Ciencias anote si acepta.
A23: ID | B23: Clave | C23: Ciclo | D23: Acción | E23: Motivo | F23: Área | G23: Prioridad | H23: Grado | I23: Unidad | J23: Temas involucrados (ID · procedimental) | K23: Objetivos del marco | L23: Propuesta | M23: Justificación | N23: Confianza | O23: Libera (temas) | P23: ¿Entra en el presupuesto? | Q23: Decisión del equipo
A24: 2-4-I20 | B24: {="2-4|"&F24} -> 2-4|Biología | C24: Ciclo 2°–4° | D24: insertar | E24: cobertura | F24: Biología | G24: 1 | H24: 3 | I24: 5. Los animales. | K24: T4_27-B2.2, T4_27-B2.1 | L24: Comparación de rasgos heredados y no heredados entre crías y progenitores, y de estrategias que favorecen la supervivencia de la descendencia (muchas semillas, cuidado de crías). | M24: B2.2 sin ningún tema en el ciclo; Uruguay lo introduce en 3.°, junto a etapas de desarrollo. | N24: alta | O24: 0 | P24: Sí (cobertura)
A25: 2-4-I13 | B25: {="2-4|"&F25} -> 2-4|Ciencias de la Tierra | C25: Ciclo 2°–4° | D25: insertar | E25: balance | F25: Ciencias de la Tierra | G25: 1 | H25: 2 | I25: 3. El movimiento | K25: T4_27-E2.1, T4_27-E5.1 | L25: Registro diario del estado del tiempo (temperatura, lluvia, nubes y viento) con símbolos y un termómetro sencillo. | M25: E2.1-A débil y E5.1 con un tema; Colombia lo introduce en 2.°. | N25: alta | O25: 0 | P25: Sí
A26: 2-4-I14 | B26: {="2-4|"&F26} -> 2-4|Ciencias de la Tierra | C26: Ciclo 2°–4° | D26: insertar | E26: balance | F26: Ciencias de la Tierra | G26: 2 | H26: 3 | I26: 2. Interacciones terrestres. | K26: T4_27-E1.2 | L26: Indagación sobre los fósiles como evidencia de seres vivos del pasado y de cambios en la superficie terrestre. | M26: E1.2-B (fósiles) sin cubrir; Uruguay lo introduce en 3.°. | N26: alta | O26: 0 | P26: Sí
A27: 2-4-I15 | B27: {="2-4|"&F27} -> 2-4|Ciencias de la Tierra | C27: Ciclo 2°–4° | D27: insertar | E27: balance | F27: Ciencias de la Tierra | G27: 3 | H27: 3 | I27: 2. Interacciones terrestres. | K27: T4_27-E5.1, T4_27-E2.1 | L27: Construcción y uso de pluviómetro, veleta y termómetro para medir y comparar variables del tiempo atmosférico. | M27: E5.1 con un solo tema; equipo citado explícitamente por TIMSS. | N27: alta | O27: 0 | P27: Sí
A28: 2-4-I16 | B28: {="2-4|"&F28} -> 2-4|Ciencias de la Tierra | C28: Ciclo 2°–4° | D28: insertar | E28: balance | F28: Ciencias de la Tierra | G28: 4 | H28: 3 | I28: 2. Interacciones terrestres. | K28: T4_27-E2.1 | L28: Reconocimiento del calentamiento global y de algunos de sus efectos en el clima y las lluvias de El Salvador. | M28: E2.1-B (calentamiento global) ausente; objetivo ambiental. | N28: alta | O28: 0 | P28: Reserva
A29: 2-4-I17 | B29: {="2-4|"&F29} -> 2-4|Ciencias de la Tierra | C29: Ciclo 2°–4° | D29: insertar | E29: balance | F29: Ciencias de la Tierra | G29: 5 | H29: 2 | I29: 6. Ambiente y salud. | K29: T4_27-E1.2 | L29: Modelación del efecto del agua y el viento sobre la arena y el suelo para explicar cómo cambia el paisaje. | M29: E1.2-A (erosión) sin tratar; Colombia lo introduce en 2.°. | N29: media | O29: 0 | P29: Reserva
A30: 2-4-I18 | B30: {="2-4|"&F30} -> 2-4|Ciencias de la Tierra | C30: Ciclo 2°–4° | D30: insertar | E30: balance | F30: Ciencias de la Tierra | G30: 6 | H30: 2 | I30: 3. El movimiento | K30: T4_27-E4.2, T4_27-P3.1 | L30: Observación y registro de la posición del Sol y del tamaño de las sombras a lo largo del día. | M30: E4.2 débil (3); patrón diario observable y sencillo para 2.°. | N30: media | O30: 0 | P30: Reserva
A31: 2-4-I19 | B31: {="2-4|"&F31} -> 2-4|Ciencias de la Tierra | C31: Ciclo 2°–4° | D31: insertar | E31: balance | F31: Ciencias de la Tierra | G31: 7 | H31: 2 | I31: 3. El movimiento | K31: T4_27-E1.1 | L31: Representación de la proporción de agua y tierra en la superficie terrestre usando un globo terráqueo, distinguiendo agua dulce y salada. | M31: E1.1-A solo en hidrosfera de 3.°; unidad de destino discutible. | N31: baja | O31: 0 | P31: Reserva
A32: 2-4-I01 | B32: {="2-4|"&F32} -> 2-4|Ciencias físicas | C32: Ciclo 2°–4° | D32: insertar | E32: balance | F32: Ciencias físicas | G32: 1 | H32: 4 | I32: 1. Máquinas y energía. | K32: T4_27-P4.1 | L32: Construcción de circuitos eléctricos sencillos con pila, cables y bombillo, comparando circuitos abiertos y cerrados y su representación en diagramas. | M32: P4.1 débil (3); circuito completo no se trabaja; 4.° tiene la mayor brecha física. | N32: alta | O32: 0 | P32: Sí
A33: 2-4-I02 | B33: {="2-4|"&F33} -> 2-4|Ciencias físicas | C33: Ciclo 2°–4° | D33: insertar | E33: balance | F33: Ciencias físicas | G33: 2 | H33: 4 | I33: 1. Máquinas y energía. | K33: T4_27-P2.2, T4_27-P1.2 | L33: Experimentación con la transferencia de calor entre objetos calientes y fríos en contacto, y con materiales conductores y aislantes térmicos de uso cotidiano. | M33: P2.2 con un solo tema; Uruguay y Colombia lo introducen antes. | N33: alta | O33: 0 | P33: Sí
A34: 2-4-I03 | B34: {="2-4|"&F34} -> 2-4|Ciencias físicas | C34: Ciclo 2°–4° | D34: insertar | E34: balance | F34: Ciencias físicas | G34: 3 | H34: 4 | I34: 1. Máquinas y energía. | K34: T4_27-P3.2 | L34: Experimentación con la propagación del sonido en el aire, el agua y los sólidos (teléfono de vasos) y la formación del eco. | M34: P3.2 con un solo tema (2.°); eco no se trabaja. | N34: alta | O34: 0 | P34: Sí
A35: 2-4-I04 | B35: {="2-4|"&F35} -> 2-4|Ciencias físicas | C35: Ciclo 2°–4° | D35: insertar | E35: balance | F35: Ciencias físicas | G35: 4 | H35: 3 | I35: 1. Medidas y fuerzas. | K35: T4_27-P4.2 | L35: Experimentación con imanes para identificar sus polos, la atracción y repulsión entre ellos y los objetos que atraen. | M35: P4.2 con un solo tema; Singapur lo introduce en 3.°; encaja con fuerzas a distancia. | N35: alta | O35: 0 | P35: Sí
... A43: 2-4-I12 | B43: {="2-4|"&F43} -> 2-4|Ciencias físicas | C43: Ciclo 2°–4° | D43: insertar | E43: balance | F43: Ciencias físicas | G43: 12 | H43: 4 | I43: 1. Máquinas y energía. | K43: T4_27-P3.1 | L43: Experimentación con la propagación de la luz a través del agua y de lentes sencillos para observar cómo se desvía. | M43: Segundo tema de luz; refracción menos central en TIMSS 4.°. | N43: baja | O43: 0 | P43: Reserva
A44: 2-4-F01 | B44: {="2-4|"&F44} -> 2-4|Biología | C44: Ciclo 2°–4° | D44: fusionar | F44: Biología | G44: 1 | H44: 4 | I44: 2. Nutrición. | J44: T0785-G04-CIE · 4.° · 2.1. Indagación sobre los conceptos de alimento y nutriente. T0786-G04-CIE · 4.° · 2.2. Clasificación de los nutrientes: macronutrientes y micronutrientes. | K44: T4_27-B5.2 | L44: Indagación sobre los conceptos de alimento y nutriente, y clasificación de macronutrientes y micronutrientes. | M44: Mismo contenido «¿Qué es un nutriente?» y mismo objetivo B5.2. | N44: alta | O44: 1 | P44: Sí
A45: 2-4-F02 | B45: {="2-4|"&F45} -> 2-4|Biología | C45: Ciclo 2°–4° | D45: fusionar | F45: Biología | G45: 2 | H45: 4 | I45: 2. Nutrición. | J45: T0790-G04-CIE · 4.° · 2.6. Clasificación de los grupos de alimentos. T0791-G04-CIE · 4.° · 2.7. Elaboración de menús según requerimientos nutricionales. | K45: T4_27-B5.2 | L45: Clasificación de los grupos de alimentos y elaboración de menús saludables según requerimientos nutricionales. | M45: Mismo contenido «Alimentación saludable»; los menús aplican los grupos. | N45: alta | O45: 1 | P45: Sí
A46: 2-4-F03 | B46: {="2-4|"&F46} -> 2-4|Biología | C46: Ciclo 2°–4° | D46: fusionar | F46: Biología | G46: 3 | H46: 4 | I46: 2. Nutrición. | J46: T0788-G04-CIE · 4.° · 2.4. Estimación de la cantidad de alimento necesaria para suplir los requerimientos nutric T0789-G04-CIE · 4.° · 2.5. Comparación del gasto y obtención de la energía contenida en la dieta diaria. | K46: T4_27-B5.2 | L46: Estimación de los requerimientos nutricionales y comparación del gasto y la obtención de energía en la dieta diaria. | M46: Ambos tratan balance energético de la dieta; B5.2 tiene 14 temas. | N46: alta | O46: 1 | P46: Sí
A47: 2-4-F04 | B47: {="2-4|"&F47} -> 2-4|Biología | C47: Ciclo 2°–4° | D47: fusionar | F47: Biología | G47: 4 | H47: 4 | I47: 5. Cuerpo humano: materia y energía. | J47: T0828-G04-CIE · 4.° · 5.1. Descripción de las funciones, la importancia y los cuidados del sistema digestivo. T0829-G04-CIE · 4.° · 5.2. Construcción de modelo del sistema digestivo. | K47: T4_27-B1.3, T4_27-B5.2 | L47: Descripción de las funciones y cuidados del sistema digestivo mediante la construcción de un modelo. | M47: Modelo y descripción del mismo sistema; B1.3 sobrerrepresentado (24). | N47: alta | O47: 1 | P47: Sí
A48: 2-4-F05 | B48: {="2-4|"&F48} -> 2-4|Biología | C48: Ciclo 2°–4° | D48: fusionar | F48: Biología | G48: 5 | H48: 4 | I48: 5. Cuerpo humano: materia y energía. | J48: T0830-G04-CIE · 4.° · 5.3. Descripción de las funciones, la importancia y los cuidados del sistema respiratorio. T0831-G04-CIE · 4.° · 5.4. Construcción de modelo del sistema respiratorio. | K48: T4_27-B1.3, T4_27-B1.4 | L48: Descripción de las funciones y cuidados del sistema respiratorio mediante la construcción de un modelo. | M48: Mismo sistema, mismo objetivo B1.3; el modelo sirve a la descripción. | N48: alta | O48: 1 | P48: Sí
A49: 2-4-F06 | B49: {="2-4|"&F49} -> 2-4|Biología | C49: Ciclo 2°–4° | D49: fusionar | F49: Biología | G49: 6 | H49: 4 | I49: 5. Cuerpo humano: materia y energía. | J49: T0835-G04-CIE · 4.° · 5.8. Uso de simulación para explicar las partes y funciones principales del sistema excret T0836-G04-CIE · 4.° · 5.9. Descripción de la importancia y los cuidados del sistema excretor. | K49: T4_27-B1.3, T4_27-B5.2 | L49: Uso de simulaciones para explicar las partes, funciones, importancia y cuidados del sistema excretor. | M49: Mismo sistema excretor; partes y cuidados se enseñan juntos. | N49: alta | O49: 1 | P49: Sí
A50: 2-4-F07 | B50: {="2-4|"&F50} -> 2-4|Biología | C50: Ciclo 2°–4° | D50: fusionar | F50: Biología | G50: 7 | H50: 4 | I50: 5. Cuerpo humano: materia y energía. | J50: T0832-G04-CIE · 4.° · 5.5. Manipulación de simulaciones para explicar la estructura y las funciones sistémicas. T0833-G04-CIE · 4.° · 5.6. Descripción del funcionamiento y los cuidados del sistema circulatorio. | K50: T4_27-B1.3, T4_27-B1.4 | L50: Manipulación de simulaciones para explicar la estructura, el funcionamiento y los cuidados del sistema circulatorio. | M50: Mismo contenido «Sistema circulatorio», mismo objetivo B1.3. | N50: alta | O50: 1 | P50: Sí
A51: 2-4-F08 | B51: {="2-4|"&F51} -> 2-4|Biología | C51: Ciclo 2°–4° | D51: fusionar | F51: Biología | G51: 8 | H51: 4 | I51: 6. Cuerpo humano: movimiento e interacciones. | J51: T0843-G04-CIE · 4.° · 6.7. Explicación de las funciones, la importancia y los cuidados del sistema nervioso. T0844-G04-CIE · 4.° · 6.8. Representación de las partes principales del sistema nervioso humano. | K51: T4_27-B1.3, T4_27-B1.4 | L51: Representación de las partes principales del sistema nervioso y explicación de sus funciones y cuidados. | M51: Partes y funciones del mismo sistema; B1.3 sobrerrepresentado. | N51: alta | O51: 1 | P51: Sí
A52: 2-4-F09 | B52: {="2-4|"&F52} -> 2-4|Biología | C52: Ciclo 2°–4° | D52: fusionar | F52: Biología | G52: 9 | H52: 4 | I52: 6. Cuerpo humano: movimiento e interacciones. | J52: T0838-G04-CIE · 4.° · 6.2. Práctica con el funcionamiento de músculos y articulaciones. T0839-G04-CIE · 4.° · 6.3. Modelación de la contracción muscular para generar movimiento. | K52: T4_27-B1.3 | L52: Práctica y modelación del funcionamiento de músculos y articulaciones para generar movimiento. | M52: Ambos modelan contracción y movimiento; mismo objetivo B1.3. | N52: media | O52: 1 | P52: Sí
A53: 2-4-F10 | B53: {="2-4|"&F53} -> 2-4|Biología | C53: Ciclo 2°–4° | D53: fusionar | F53: Biología | G53: 10 | H53: 3 | I53: 5. Los animales. | J53: T0764-G03-CIE · 3.° · 5.12. Descripción de las características morfológicas de los vertebrados. T0765-G03-CIE · 3.° · 5.13. Caracterización anatómica de los principales grupos de vertebrados. | K53: T4_27-B1.2 | L53: Descripción y caracterización anatómica de los principales grupos de vertebrados. | M53: Mismo contenido «Los vertebrados»; B1.2 tiene 18 temas. | N53: alta | O53: 1 | P53: Sí
A54: 2-4-F11 | B54: {="2-4|"&F54} -> 2-4|Biología | C54: Ciclo 2°–4° | D54: fusionar | F54: Biología | G54: 11 | H54: 3 | I54: 4. Las plantas. | J54: T0744-G03-CIE · 3.° · 4.1. Reconocimiento de los órganos presentes en las plantas con semilla. T0745-G03-CIE · 3.° · 4.2. Relación de los órganos vegetales con sus funciones. | K54: T4_27-B1.3 | L54: Reconocimiento de los órganos de las plantas con semilla y relación con sus funciones. | M54: Reconocer órganos y sus funciones es un mismo aprendizaje B1.3. | N54: alta | O54: 1 | P54: Sí
A55: 2-4-F12 | B55: {="2-4|"&F55} -> 2-4|Biología | C55: Ciclo 2°–4° | D55: fusionar | F55: Biología | G55: 12 | H55: 3 | I55: 4. Las plantas. | J55: T0748-G03-CIE · 3.° · 4.5. Comparación de la anatomía de distintas plantas con semilla y sin semilla. T0749-G03-CIE · 3.° · 4.6. Clasificación de los grupos de plantas terrestres por su anatomía. | K55: T4_27-B1.2 | L55: Comparación y clasificación de los grupos de plantas terrestres (con y sin semilla) por su anatomía. | M55: Mismo contenido «Grupos de plantas»; comparar y clasificar se solapan. | N55: alta | O55: 1 | P55: Sí
... A66: 2-4-R02 | B66: {="2-4|"&F66} -> 2-4|Ciencias físicas | C66: Ciclo 2°–4° | D66: reubicar | F66: Ciencias físicas | G66: 2 | H66: 3 | I66: 1. Medidas y fuerzas. | J66: T0651-G02-CIE · 2.° · 2.1. Experimentación con la energía mecánica, utilizando objetos de su entorno. | K66: T4_27-P5.1 | L66: Experimentación con la energía mecánica de objetos del entorno, vinculada a fuerzas y movimiento. | M66: Física sobra en 2.° y falta en 3.° (+2); encaja con fuerzas. | N66: media | O66: 0 | P66: Opcional (no cambia el total)
A67: 5-8-I01 | B67: {="5-8|"&F67} -> 5-8|Biología | C67: Ciclo 5°–8° | D67: insertar | E67: balance | F67: Biología | G67: 1 | H67: 8 | I67: 7. Anatomía y Fisiología Animal | K67: T8_27-B6.1 | L67: Indagación de las causas, formas de transmisión y prevención de enfermedades infecciosas, y del papel del sistema inmunitario, las vacunas y el uso responsable de antibióticos. | M67: B6.1 solo tiene un tema secundario; Uruguay y Colombia lo trabajan desde 6.°; cierra la unidad de sistemas. | N67: alta | O67: 0 | P67: Reserva
A68: 5-8-I02 | B68: {="5-8|"&F68} -> 5-8|Biología | C68: Ciclo 5°–8° | D68: insertar | E68: balance | F68: Biología | G68: 2 | H68: 5 | I68: 6. Ciencias de la Tierra. | K68: T8_27-B5.2 | L68: Construcción de cadenas y redes tróficas de un ecosistema local para representar el flujo de energía entre productores, consumidores y descomponedores. | M68: B5.2 débil (1 tema, en 7.°); los tres países lo introducen en 6.°; 5.° tiene la mayor brecha biológica. | N68: media | O68: 0 | P68: Reserva
A69: 5-8-I03 | B69: {="5-8|"&F69} -> 5-8|Biología | C69: Ciclo 5°–8° | D69: insertar | E69: balance | F69: Biología | G69: 3 | H69: 5 | I69: 6. Ciencias de la Tierra. | K69: T8_27-B5.3, T8_27-E2.2 | L69: Modelación de los ciclos del carbono, del oxígeno y del agua entre seres vivos, suelo y atmósfera, destacando la descomposición de la materia orgánica. | M69: B5.3 sin tema principal; Singapur lo introduce en 5.°; enlaza con el bloque de suelo de 5.°. | N69: media | O69: 0 | P69: Reserva
A70: 5-8-I04 | B70: {="5-8|"&F70} -> 5-8|Biología | C70: Ciclo 5°–8° | D70: insertar | E70: balance | F70: Biología | G70: 4 | H70: 8 | I70: 7. Anatomía y Fisiología Animal | K70: T8_27-B6.2, T8_27-B1.2 | L70: Análisis de la dieta, la actividad física y el descanso como hábitos que mantienen sanos los sistemas digestivo, circulatorio y respiratorio. | M70: B6.2 débil (2 temas, ninguno en 8.°); encaja tras sistemas digestivos y respiratorio-circulatorio. | N70: alta | O70: 0 | P70: Reserva
A71: 5-8-I05 | B71: {="5-8|"&F71} -> 5-8|Biología | C71: Ciclo 5°–8° | D71: insertar | E71: balance | F71: Biología | G71: 5 | H71: 5 | I71: 6. Ciencias de la Tierra. | K71: T8_27-B5.1, T8_27-B5.6 | L71: Comparación de ecosistemas naturales, rurales y urbanos de El Salvador a partir del cambio de cobertura y uso del suelo. | M71: B5.1 con 4 temas solo en 7.°; Colombia y Singapur lo introducen en 6.°; continúa «Usos del suelo». | N71: media | O71: 0 | P71: Reserva
A72: 5-8-I06 | B72: {="5-8|"&F72} -> 5-8|Biología | C72: Ciclo 5°–8° | D72: insertar | E72: balance | F72: Biología | G72: 6 | H72: 5 | I72: 6. Ciencias de la Tierra. | K72: T8_27-B5.5 | L72: Análisis de los factores (alimento, depredadores, enfermedades, espacio, actividad humana) que hacen variar el tamaño de una población local. | M72: B5.5 con 4 temas en 6.°–7.°; los tres países lo introducen en 6.°; suma Biología a 5.°. | N72: baja | O72: 0 | P72: Reserva
A73: 5-8-I07 | B73: {="5-8|"&F73} -> 5-8|Ciencias de la Tierra | C73: Ciclo 5°–8° | D73: insertar | E73: balance | F73: Ciencias de la Tierra | G73: 1 | H73: 8 | I73: 1. Mecánica | K73: T8_27-E4.1 | L73: Modelación de la rotación y la traslación de la Tierra para explicar el día y la noche, la duración del año y, con la inclinación del eje, las estaciones. | M73: E4.1 sin ningún tema en el ciclo; aplica el movimiento circular y de rotación de 8.°. | N73: alta | O73: 0 | P73: Reserva
A74: 5-8-I08 | B74: {="5-8|"&F74} -> 5-8|Ciencias de la Tierra | C74: Ciclo 5°–8° | D74: insertar | E74: balance | F74: Ciencias de la Tierra | G74: 2 | H74: 8 | I74: 5. Minerales | K74: T8_27-E5.1, T8_27-E1.2 | L74: Uso de lupa, escala de Mohs, brújula, GPS y libreta de campo para recolectar, medir y registrar datos de rocas y minerales del entorno. | M74: E5.1 (equipo de investigación en Tierra) sin ningún tema; encaja con la caracterización de minerales. | N74: alta | O74: 0 | P74: Reserva
A75: 5-8-I09 | B75: {="5-8|"&F75} -> 5-8|Ciencias de la Tierra | C75: Ciclo 5°–8° | D75: insertar | E75: balance | F75: Ciencias de la Tierra | G75: 3 | H75: 8 | I75: 1. Mecánica | K75: T8_27-E4.1 | L75: Modelación de las fases de la Luna, los eclipses y las mareas a partir de las posiciones relativas del Sol, la Tierra y la Luna. | M75: Completa E4.1 (0 temas); Uruguay lo trabaja desde 5.°; usa la gravitación y la rotación de 8.°. | N75: media | O75: 0 | P75: Reserva
A76: 5-8-I10 | B76: {="5-8|"&F76} -> 5-8|Ciencias de la Tierra | C76: Ciclo 5°–8° | D76: insertar | E76: balance | F76: Ciencias de la Tierra | G76: 4 | H76: 6 | I76: 1. Fluidos. | K76: T8_27-E2.1 | L76: Experimentación con la presión atmosférica y la composición del aire, relacionando su variación con la altitud en El Salvador. | M76: E2.1 débil (2 temas en 7.°); Singapur lo introduce en 5.°; aplica presión en fluidos de 6.°. | N76: alta | O76: 0 | P76: Reserva
A77: 5-8-I11 | B77: {="5-8|"&F77} -> 5-8|Ciencias de la Tierra | C77: Ciclo 5°–8° | D77: insertar | E77: balance | F77: Ciencias de la Tierra | G77: 5 | H77: 8 | I77: 1. Mecánica | K77: T8_27-E4.2, T8_27-P5.2 | L77: Relación de la gravedad con las órbitas de planetas y satélites del sistema solar a partir de datos de distancia y período orbital. | M77: E4.2 débil (2 temas, solo en 5.°); aprovecha las leyes de Newton de 8.°. | N77: media | O77: 0 | P77: Reserva
A78: 5-8-I12 | B78: {="5-8|"&F78} -> 5-8|Ciencias de la Tierra | C78: Ciclo 5°–8° | D78: insertar | E78: balance | F78: Ciencias de la Tierra | G78: 6 | H78: 6 | I78: 2. Calor y temperatura. | K78: T8_27-E2.4, T8_27-P2.2 | L78: Experimentación con la absorción de radiación por gases de efecto invernadero y su relación con el aumento de la temperatura global. | M78: E2.4 débil (3 temas en 7.°); Uruguay lo inicia en 5.°; usa la radiación térmica de 6.°. | N78: media | O78: 0 | P78: Reserva
... A84: 5-8-I18 | B84: {="5-8|"&F84} -> 5-8|Física | C84: Ciclo 5°–8° | D84: insertar | E84: cobertura | F84: Física | G84: 1 | H84: 7 | I84: 6. Ambiente y energía | K84: T8_27-P3.1, T8_27-E3.1 | L84: Experimentación con la reflexión, refracción y absorción de la luz y su aprovechamiento en concentradores y calentadores solares. | M84: P3.1 (luz) sin ningún tema en el ciclo; Uruguay lo introduce en 5.°; 7.° tiene Física subrepresentada. | N84: media | O84: 0 | P84: Sí (cobertura)
A85: 5-8-F01 | B85: {="5-8|"&F85} -> 5-8|Física | C85: Ciclo 5°–8° | D85: fusionar | F85: Física | G85: 1 | H85: 8 | I85: 1. Mecánica | J85: T1089-G08-CIE · 8.° · 1.12. Indagación del cambio del momento lineal en objetos a partir de la experimentación c T1090-G08-CIE · 8.° · 1.13. Experimentación con el cambio del momento lineal de objetos. | K85: T8_27-P5.3 | L85: Indagación y experimentación con el cambio del momento lineal de objetos a partir de la fuerza aplicada y el tiempo de interacción. | M85: Ambos temas indagan el mismo cambio de momento lineal; 8.° tiene la mayor sobrerrepresentación. | N85: alta | O85: 1 | P85: Sí
A86: 5-8-F02 | B86: {="5-8|"&F86} -> 5-8|Física | C86: Ciclo 5°–8° | D86: fusionar | F86: Física | G86: 2 | H86: 8 | I86: 3. Ondas mecánicas | J86: T1109-G08-CIE · 8.° · 3.7. Identificación experimental del tipo de onda a partir del movimiento de la fuente de T1112-G08-CIE · 8.° · 3.10. Identificación experimental del tipo de onda a partir del movimiento de la fuente de | K86: T8_27-P3.2 | L86: Identificación experimental del tipo de onda a partir del movimiento de la fuente de vibración en cuerdas y columnas de aire. | M86: Mismo procedimiento repetido para cuerdas y para columnas de aire. | N86: alta | O86: 1 | P86: Reserva
A87: 5-8-F03 | B87: {="5-8|"&F87} -> 5-8|Física | C87: Ciclo 5°–8° | D87: fusionar | F87: Física | G87: 3 | H87: 8 | I87: 3. Ondas mecánicas | J87: T1110-G08-CIE · 8.° · 3.8. Identificación experimental de las magnitudes y las condiciones que varían la frecuen T1113-G08-CIE · 8.° · 3.11. Identificación experimental de las magnitudes y las condiciones que varían la frecue | K87: T8_27-P3.2, T8_27-P6.1 | L87: Identificación experimental de las magnitudes y condiciones que varían la frecuencia o el tono del sonido en cuerdas y columnas de aire. | M87: Mismo procedimiento duplicado por fuente sonora; P3.2 conserva 4 temas. | N87: alta | O87: 1 | P87: Reserva
A88: 5-8-F04 | B88: {="5-8|"&F88} -> 5-8|Física | C88: Ciclo 5°–8° | D88: fusionar | F88: Física | G88: 4 | H88: 8 | I88: 3. Ondas mecánicas | J88: T1111-G08-CIE · 8.° · 3.9. Resolución de problemas teóricos a partir de las gráficas de desplazamiento contra po T1114-G08-CIE · 8.° · 3.12. Resolución de problemas teóricos a partir de las gráficas de presión de aire contra | K88: T8_27-P3.2 | L88: Resolución de problemas a partir de gráficas de desplazamiento y de presión de aire contra posición y tiempo en ondas transversales y longitudinales. | M88: Ambos resuelven problemas con gráficas de ondas; solo cambia el tipo de onda. | N88: alta | O88: 1 | P88: Reserva
A89: 5-8-F05 | B89: {="5-8|"&F89} -> 5-8|Física | C89: Ciclo 5°–8° | D89: fusionar | F89: Física | G89: 5 | H89: 6 | I89: 1. Fluidos. | J89: T0922-G06-CIE · 6.° · 1.4. Vinculación entre capilaridad y tensión superficial. T0923-G06-CIE · 6.° · 1.5. Demostración experimental de la capilaridad. | K89: T8_27-P1.1 | L89: Demostración experimental de la capilaridad y su vínculo con la tensión superficial. | M89: Mismo fenómeno: uno lo vincula y otro lo demuestra; 6.° tiene Física sobrerrepresentada. | N89: alta | O89: 1 | P89: Reserva
A90: 5-8-F06 | B90: {="5-8|"&F90} -> 5-8|Física | C90: Ciclo 5°–8° | D90: fusionar | F90: Física | G90: 6 | H90: 6 | I90: 1. Fluidos. | J90: T0925-G06-CIE · 6.° · 1.7. Indagación del principio de Bernoulli. T0926-G06-CIE · 6.° · 1.8. Aplicación del principio de Bernoulli. | K90: T8_27-P5.3 | L90: Indagación y aplicación del principio de Bernoulli en situaciones cotidianas. | M90: Indagar y aplicar el mismo principio caben en una secuencia de clase. | N90: alta | O90: 1 | P90: Reserva
A91: 5-8-F07 | B91: {="5-8|"&F91} -> 5-8|Física | C91: Ciclo 5°–8° | D91: fusionar | F91: Física | G91: 7 | H91: 6 | I91: 4. Interacciones químicas. | J91: T0949-G06-CIE · 6.° · 4.7. Demostración experimental macroscópica de las fuerzas intermoleculares. T0950-G06-CIE · 6.° · 4.8. Construcción del concepto de las fuerzas intermoleculares. | K91: T8_27-P1.1, T8_27-P1.2 | L91: Construcción del concepto de fuerzas intermoleculares a partir de su demostración experimental macroscópica. | M91: Mismo contenido: demostración y conceptualización de fuerzas intermoleculares. | N91: alta | O91: 1 | P91: Reserva
A92: 5-8-F08 | B92: {="5-8|"&F92} -> 5-8|Física | C92: Ciclo 5°–8° | D92: fusionar | F92: Física | G92: 8 | H92: 8 | I92: 3. Ondas mecánicas | J92: T1107-G08-CIE · 8.° · 3.5. Cálculo experimental de una altura empleando el período de oscilación de un péndulo s T1108-G08-CIE · 8.° · 3.6. Diseño de un experimento para determinar una altura empleando un péndulo simple. | K92: T8_27-P6.1 | L92: Diseño y ejecución de un experimento para calcular una altura empleando el período de oscilación de un péndulo simple. | M92: Ambos determinan una altura con el péndulo; diseñar incluye calcular. | N92: alta | O92: 1 | P92: Reserva
A93: 5-8-F09 | B93: {="5-8|"&F93} -> 5-8|Física | C93: Ciclo 5°–8° | D93: fusionar | F93: Física | G93: 9 | H93: 8 | I93: 2. Energía | J93: T1101-G08-CIE · 8.° · 2.10. Cálculo experimental de la potencia mecánica de máquinas para la obtención del momen T1102-G08-CIE · 8.° · 2.11. Resolución de problemas acerca de la potencia mecánica. | K93: T8_27-P2.1 | L93: Cálculo experimental de la potencia mecánica de máquinas y resolución de problemas de potencia. | M93: Mismo cálculo de potencia, experimental y en problemas; P2.1 tiene 21 temas. | N93: media | O93: 1 | P93: Reserva
A94: 5-8-F10 | B94: {="5-8|"&F94} -> 5-8|Física | C94: Ciclo 5°–8° | D94: fusionar | F94: Física | G94: 10 | H94: 8 | I94: 2. Energía | J94: T1098-G08-CIE · 8.° · 2.7. Experimentación con la ley de conservación de la energía mecánica. T1099-G08-CIE · 8.° · 2.8. Interpretación de las características de las gráficas de energía cinética y potencial | K94: T8_27-P2.1 | L94: Experimentación con la conservación de la energía mecánica e interpretación de las gráficas de energía cinética y potencial obtenidas. | M94: Las gráficas salen del mismo experimento de conservación. | N94: media | O94: 1 | P94: Reserva
A95: 5-8-F11 | B95: {="5-8|"&F95} -> 5-8|Física | C95: Ciclo 5°–8° | D95: fusionar | F95: Física | G95: 11 | H95: 8 | I95: 3. Ondas mecánicas | J95: T1104-G08-CIE · 8.° · 3.2. Experimentación para identificar la transformación de la energía del péndulo simple. T1105-G08-CIE · 8.° · 3.3. Interpretación de las características de las gráficas de energía del oscilador armóni | K95: T8_27-P2.1 | L95: Experimentación con la transformación de la energía del péndulo simple e interpretación de sus gráficas de energía. | M95: Mismo sistema y misma transformación energética; P2.1 sobrado. | N95: media | O95: 1 | P95: Reserva
A96: 5-8-F12 | B96: {="5-8|"&F96} -> 5-8|Física | C96: Ciclo 5°–8° | D96: fusionar | F96: Física | G96: 12 | H96: 8 | I96: 1. Mecánica | J96: T1081-G08-CIE · 8.° · 1.4. Medición de las componentes de un vector en un par de ejes perpendiculares. T1082-G08-CIE · 8.° · 1.5. Adición y sustracción de vectores por el método de las componentes rectangulares. | K96: T8_27-P5.2 | L96: Medición de las componentes rectangulares de vectores y su uso para sumarlos y restarlos. | M96: Fusión extra que paga la inserción de cobertura de luz (P3.1); mismo método de componentes. | N96: alta | O96: 1 | P96: Reserva
... A108: 5-8-R05 | B108: {="5-8|"&F108} -> 5-8|Química | C108: Ciclo 5°–8° | D108: reubicar | F108: Química | G108: 1 | H108: 7 | I108: 1. Compuestos inorgánicos | J108: T0888-G05-CIE · 5.° · 4.7. Identificación de los números de oxidación. | K108: T8_27-C1.1 | L108: Identificación de los números de oxidación, inmediatamente antes de formular y nombrar compuestos inorgánicos. | M108: Química −7 en 5.° y +8 en 7.°; la nomenclatura de 7.° requiere números de oxidación. | N108: alta | O108: 0 | P108: Opcional (no cambia el total)
A109: 7-9-I20 | B109: {="7-9|"&F109} -> 7-9|Sistemas de la Tierra y el espacio | C109: Ciclo 7°–9° | D109: insertar | E109: balance | F109: Sistemas de la Tierra y el espacio | G109: 1 | H109: 8 | I109: 8. La Tierra en el universo (nueva) | K109: PISA-T8 | L109: Indagación del origen del universo según la teoría del Big Bang y sus evidencias. | M109: PISA-T8 sin ningún tema en el ciclo. | N109: alta | O109: 0 | P109: Sí
A110: 7-9-I21 | B110: {="7-9|"&F110} -> 7-9|Sistemas de la Tierra y el espacio | C110: Ciclo 7°–9° | D110: insertar | E110: balance | F110: Sistemas de la Tierra y el espacio | G110: 2 | H110: 8 | I110: 8. La Tierra en el universo (nueva) | K110: PISA-T8, PISA-T7 | L110: Modelaje de la formación del sistema solar a partir de una nebulosa y la acreción de planetas. | M110: T8 no cubierto; formación planetaria ausente. | N110: alta | O110: 0 | P110: Sí
A111: 7-9-I22 | B111: {="7-9|"&F111} -> 7-9|Sistemas de la Tierra y el espacio | C111: Ciclo 7°–9° | D111: insertar | E111: balance | F111: Sistemas de la Tierra y el espacio | G111: 3 | H111: 8 | I111: 8. La Tierra en el universo (nueva) | K111: PISA-T8, PISA-F1 | L111: Descripción del ciclo de vida de las estrellas y del origen de los elementos químicos. | M111: T8 no cubierto; conecta con química del ciclo. | N111: alta | O111: 0 | P111: Sí
A112: 7-9-I23 | B112: {="7-9|"&F112} -> 7-9|Sistemas de la Tierra y el espacio | C112: Ciclo 7°–9° | D112: insertar | E112: balance | F112: Sistemas de la Tierra y el espacio | G112: 4 | H112: 8 | I112: 8. La Tierra en el universo (nueva) | K112: PISA-T7 | L112: Modelaje de las fases de la Luna y de los eclipses a partir de las posiciones del Sol, la Tierra y la Luna. | M112: T7 tiene solo 3 temas, todos secundarios. | N112: alta | O112: 0 | P112: Sí
A113: 7-9-I24 | B113: {="7-9|"&F113} -> 7-9|Sistemas de la Tierra y el espacio | C113: Ciclo 7°–9° | D113: insertar | E113: balance | F113: Sistemas de la Tierra y el espacio | G113: 5 | H113: 8 | I113: 8. La Tierra en el universo (nueva) | K113: PISA-T7, PISA-T3 | L113: Explicación de las estaciones a partir de la inclinación del eje y los movimientos de la Tierra. | M113: T7 débil; estaciones son contenido básico internacional. | N113: alta | O113: 0 | P113: Sí
A114: 7-9-I25 | B114: {="7-9|"&F114} -> 7-9|Sistemas de la Tierra y el espacio | C114: Ciclo 7°–9° | D114: insertar | E114: balance | F114: Sistemas de la Tierra y el espacio | G114: 6 | H114: 8 | I114: 8. La Tierra en el universo (nueva) | K114: PISA-T7 | L114: Construcción de un modelo a escala del sistema solar para comparar tamaños y distancias. | M114: T7 débil; escala del sistema solar ausente. | N114: alta | O114: 0 | P114: Sí
A115: 7-9-I26 | B115: {="7-9|"&F115} -> 7-9|Sistemas de la Tierra y el espacio | C115: Ciclo 7°–9° | D115: insertar | E115: balance | F115: Sistemas de la Tierra y el espacio | G115: 7 | H115: 8 | I115: 8. La Tierra en el universo (nueva) | K115: PISA-T7, PISA-T8 | L115: Ubicación de la Tierra en la Vía Láctea y comparación de tipos de galaxias. | M115: PISA T7 menciona galaxias; nada en el ciclo. | N115: alta | O115: 0 | P115: Sí
A116: 7-9-I27 | B116: {="7-9|"&F116} -> 7-9|Sistemas de la Tierra y el espacio | C116: Ciclo 7°–9° | D116: insertar | E116: balance | F116: Sistemas de la Tierra y el espacio | G116: 8 | H116: 8 | I116: 9. Historia de la Tierra (nueva) | K116: PISA-T6, PISA-V5 | L116: Indagación de los procesos de fosilización y de la datación relativa de estratos. | M116: T6 tiene solo 4 temas; fósiles ausentes. | N116: alta | O116: 0 | P116: Sí
A117: 7-9-I28 | B117: {="7-9|"&F117} -> 7-9|Sistemas de la Tierra y el espacio | C117: Ciclo 7°–9° | D117: insertar | E117: balance | F117: Sistemas de la Tierra y el espacio | G117: 9 | H117: 8 | I117: 9. Historia de la Tierra (nueva) | K117: PISA-T6, PISA-V5 | L117: Construcción de una línea del tiempo geológico con los principales eventos de la historia de la vida. | M117: Origen y evolución de la Tierra no trabajados. | N117: alta | O117: 0 | P117: Sí
A118: 7-9-I29 | B118: {="7-9|"&F118} -> 7-9|Sistemas de la Tierra y el espacio | C118: Ciclo 7°–9° | D118: insertar | E118: balance | F118: Sistemas de la Tierra y el espacio | G118: 10 | H118: 8 | I118: 5. Minerales | K118: PISA-T6, PISA-T1 | L118: Modelaje del ciclo de las rocas: meteorización, erosión, sedimentación y metamorfismo. | M118: Encaja en «Minerales y rocas»; refuerza T6. | N118: alta | O118: 0 | P118: Sí
A119: 7-9-I30 | B119: {="7-9|"&F119} -> 7-9|Sistemas de la Tierra y el espacio | C119: Ciclo 7°–9° | D119: insertar | E119: balance | F119: Sistemas de la Tierra y el espacio | G119: 11 | H119: 8 | I119: 9. Historia de la Tierra (nueva) | K119: PISA-T6, PISA-T2 | L119: Experimentación con la meteorización y la erosión del suelo y prácticas de conservación. | M119: Erosión solo en 9.° costero; suelo como recurso. | N119: media | O119: 0 | P119: Sí
A120: 7-9-I31 | B120: {="7-9|"&F120} -> 7-9|Sistemas de la Tierra y el espacio | C120: Ciclo 7°–9° | D120: insertar | E120: balance | F120: Sistemas de la Tierra y el espacio | G120: 12 | H120: 8 | I120: 8. La Tierra en el universo (nueva) | K120: PISA-T7, PISA-F3 | L120: Explicación del papel de la gravedad en las órbitas de planetas y satélites. | M120: T7 débil; enlaza con mecánica de 8.°. | N120: media | O120: 0 | P120: Sí
... A148: 7-9-I19 | B148: {="7-9|"&F148} -> 7-9|Sistemas vivos | C148: Ciclo 7°–9° | D148: insertar | E148: balance | F148: Sistemas vivos | G148: 19 | H148: 8 | I148: 6. Anatomía y fisiología vegetal | K148: PISA-V1, PISA-V6 | L148: Indagación de las relaciones de las plantas con microorganismos: micorrizas, bacterias fijadoras de nitrógeno y fitopatógenos. | M148: Refuerza V1 (organismos/microorganismos) dentro de la unidad vegetal. | N148: media | O148: 0 | P148: Reserva
A149: 7-9-F01 | B149: {="7-9|"&F149} -> 7-9|Sistemas físicos | C149: Ciclo 7°–9° | D149: fusionar | F149: Sistemas físicos | G149: 1 | H149: 8 | I149: 4. Estequiometría y dispersiones | J149: T1132-G08-CIE · 8.° · 4.18. Demostración de las propiedades coligativas. T1133-G08-CIE · 8.° · 4.19. Experimentación con las propiedades coligativas. | K149: PISA-F1 | L149: 4.18. Demostración y experimentación con las propiedades coligativas de las soluciones. | M149: Demostrar y experimentar la misma propiedad coligativa es una sola práctica. | N149: alta | O149: 1 | P149: Sí
A150: 7-9-F02 | B150: {="7-9|"&F150} -> 7-9|Sistemas físicos | C150: Ciclo 7°–9° | D150: fusionar | F150: Sistemas físicos | G150: 2 | H150: 8 | I150: 3. Ondas mecánicas | J150: T1109-G08-CIE · 8.° · 3.7. Identificación experimental del tipo de onda a partir del movimiento de la fuente de T1112-G08-CIE · 8.° · 3.10. Identificación experimental del tipo de onda a partir del movimiento de la fuente de | K150: PISA-F5 | L150: 3.7. Identificación experimental del tipo de onda según la fuente de vibración en cuerdas y columnas de aire. | M150: Mismo procedimiento en dos medios; se enseña comparando cuerdas y tubos. | N150: alta | O150: 1 | P150: Sí
A151: 7-9-F03 | B151: {="7-9|"&F151} -> 7-9|Sistemas físicos | C151: Ciclo 7°–9° | D151: fusionar | F151: Sistemas físicos | G151: 3 | H151: 8 | I151: 3. Ondas mecánicas | J151: T1110-G08-CIE · 8.° · 3.8. Identificación experimental de las magnitudes y las condiciones que varían la frecuen T1113-G08-CIE · 8.° · 3.11. Identificación experimental de las magnitudes y las condiciones que varían la frecue | K151: PISA-F5 | L151: 3.8. Identificación experimental de las magnitudes que varían la frecuencia o el tono del sonido en cuerdas y tubos. | M151: Misma variable (frecuencia/tono) estudiada en dos fuentes sonoras paralelas. | N151: alta | O151: 1 | P151: Sí
A152: 7-9-F04 | B152: {="7-9|"&F152} -> 7-9|Sistemas físicos | C152: Ciclo 7°–9° | D152: fusionar | F152: Sistemas físicos | G152: 4 | H152: 8 | I152: 3. Ondas mecánicas | J152: T1111-G08-CIE · 8.° · 3.9. Resolución de problemas teóricos a partir de las gráficas de desplazamiento contra po T1114-G08-CIE · 8.° · 3.12. Resolución de problemas teóricos a partir de las gráficas de presión de aire contra | K152: PISA-F5 | L152: 3.9. Resolución de problemas a partir de gráficas de desplazamiento y de presión de aire contra posición y tiempo. | M152: Ambos son problemas de lectura de gráficas de ondas. | N152: alta | O152: 1 | P152: Sí
A153: 7-9-F05 | B153: {="7-9|"&F153} -> 7-9|Sistemas físicos | C153: Ciclo 7°–9° | D153: fusionar | F153: Sistemas físicos | G153: 5 | H153: 9 | I153: 1. Mecánica de fluidos | J153: T1174-G09-CIE · 9.° · 1.4. Elaboración de una prensa hidráulica para la comprobación experimental del principio T1175-G09-CIE · 9.° · 1.5. Experimentación con el principio de multiplicación de fuerzas en una prensa hidráulic | K153: PISA-F3 | L153: 1.4. Elaboración de una prensa hidráulica y experimentación con la multiplicación de fuerzas según el principio de Pascal. | M153: Construir la prensa y experimentar con ella es la misma actividad. | N153: alta | O153: 1 | P153: Sí
A154: 7-9-F06 | B154: {="7-9|"&F154} -> 7-9|Sistemas físicos | C154: Ciclo 7°–9° | D154: fusionar | F154: Sistemas físicos | G154: 6 | H154: 9 | I154: 1. Mecánica de fluidos | J154: T1178-G09-CIE · 9.° · 1.8. Comprobación experimental del teorema de Torricelli empleando líquidos en recipientes T1179-G09-CIE · 9.° · 1.9 Cálculo de la rapidez de salida de un líquido por un orificio a partir del teorema de | K154: PISA-F3, PISA-F4 | L154: 1.8. Comprobación experimental y cálculo de la rapidez de salida de un líquido según el teorema de Torricelli. | M154: Comprobación y cálculo del mismo teorema con el mismo montaje. | N154: alta | O154: 1 | P154: Sí
A155: 7-9-F07 | B155: {="7-9|"&F155} -> 7-9|Sistemas físicos | C155: Ciclo 7°–9° | D155: fusionar | F155: Sistemas físicos | G155: 7 | H155: 9 | I155: 1. Mecánica de fluidos | J155: T1180-G09-CIE · 9.° · 1.10. Medición de magnitudes físicas que permitan calcular la viscosidad de un fluido. T1181-G09-CIE · 9.° · 1.11. Comprobación experimental de la ley de Stokes. | K155: PISA-F1, PISA-F3 | L155: 1.10. Medición de magnitudes para calcular la viscosidad y comprobación experimental de la ley de Stokes. | M155: Medir viscosidad y comprobar Stokes usan el mismo experimento. | N155: alta | O155: 1 | P155: Sí
A156: 7-9-F08 | B156: {="7-9|"&F156} -> 7-9|Sistemas físicos | C156: Ciclo 7°–9° | D156: fusionar | F156: Sistemas físicos | G156: 8 | H156: 9 | I156: 2. Calor y temperatura | J156: T1191-G09-CIE · 9.° · 2.9. Experimentación con un proceso irreversible de extracción de calor por medio de traba T1192-G09-CIE · 9.° · 2.10. Resolución de problemas acerca de la máxima eficiencia posible en una reversión parc | K156: PISA-F4 | L156: 2.9. Experimentación y resolución de problemas sobre procesos irreversibles y eficiencia máxima de máquinas térmicas. | M156: Ambos trabajan la segunda ley; experimento y cálculo se integran. | N156: alta | O156: 1 | P156: Sí
A157: 7-9-F09 | B157: {="7-9|"&F157} -> 7-9|Sistemas físicos | C157: Ciclo 7°–9° | D157: fusionar | F157: Sistemas físicos | G157: 9 | H157: 9 | I157: 2. Calor y temperatura | J157: T1183-G09-CIE · 9.° · 2.1. Experimentación con cambios de fase en sustancias puras. T1184-G09-CIE · 9.° · 2.2. Elaboración de un gráfico de temperatura versus tiempo de una sustancia a partir de d | K157: PISA-F1, PISA-F4 | L157: 2.1. Experimentación con cambios de fase y elaboración del gráfico temperatura-tiempo a partir de los datos. | M157: El gráfico se construye con los datos del mismo experimento. | N157: alta | O157: 1 | P157: Sí
A158: 7-9-F10 | B158: {="7-9|"&F158} -> 7-9|Sistemas físicos | C158: Ciclo 7°–9° | D158: fusionar | F158: Sistemas físicos | G158: 10 | H158: 9 | I158: 2. Calor y temperatura | J158: T1186-G09-CIE · 9.° · 2.4. Experimentación con procesos termodinámicos en un gas ideal. T1187-G09-CIE · 9.° · 2.5. Resolución de problemas a partir de gráficas de procesos termodinámicos. | K158: PISA-F1, PISA-F4 | L158: 2.4. Experimentación con procesos termodinámicos de un gas ideal y resolución de problemas con sus gráficas. | M158: Mismo contenido (procesos termodinámicos), experimental y gráfico. | N158: alta | O158: 1 | P158: Sí
A159: 7-9-F11 | B159: {="7-9|"&F159} -> 7-9|Sistemas físicos | C159: Ciclo 7°–9° | D159: fusionar | F159: Sistemas físicos | G159: 11 | H159: 9 | I159: 3. Equilibrio químico | J159: T1207-G09-CIE · 9.° · 3.15. Análisis de la función de las soluciones buffer. T1208-G09-CIE · 9.° · 3.16. Comprobación experimental del efecto amortiguador de pH de las soluciones buffer. T1209-G09-CIE · 9.° · 3.17. Reconocimiento de aplicaciones y ocurrencia natural de las soluciones buffer. | K159: PISA-F2 | L159: 3.15. Análisis, comprobación experimental y aplicaciones naturales de las soluciones buffer. | M159: Tres temas sobre buffer caben en una secuencia de una sesión. | N159: media | O159: 2 | P159: Sí
A160: 7-9-F12 | B160: {="7-9|"&F160} -> 7-9|Sistemas físicos | C160: Ciclo 7°–9° | D160: fusionar | F160: Sistemas físicos | G160: 12 | H160: 9 | I160: 3. Equilibrio químico | J160: T1200-G09-CIE · 9.° · 3.8. Indagación del concepto y las características de ácidos y bases. T1201-G09-CIE · 9.° · 3.9. Identificación de ácidos y bases según las teorías de Arrhenius, Bronsted-Lowry y Lew | K160: PISA-F2 | L160: 3.8. Indagación del concepto de ácidos y bases según las teorías de Arrhenius, Brønsted-Lowry y Lewis. | M160: Concepto y teorías ácido-base se enseñan juntos. | N160: alta | O160: 1 | P160: Sí
... A191: 7-9-R04 | B191: {="7-9|"&F191} -> 7-9|Sistemas vivos | C191: Ciclo 7°–9° | D191: reubicar | F191: Sistemas vivos | G191: 4 | H191: 9 | I191: 9. Salud humana (nueva) | J191: T1013-G07-CIE · 7.° · 2.15. Descripción del proceso de resistencia bacteriana ante un antibiótico. | K191: PISA-V5, PISA-V1 | L191: 2.15. Descripción del proceso de resistencia bacteriana ante un antibiótico. | M191: Resistencia a antibióticos enlaza microorganismos y salud en 9.°. | N191: media | O191: 0 | P191: Opcional (no cambia el total)
A193: Cómo se calcula: El «presupuesto» es el número de temas de cada ciclo, que se mantiene. Se FUSIONAN temas que se repiten en el área que sobra (libera espacio) y se INSERTAN temas en el área que falta (usa ese espacio). CUÁNTOS: fórmula sobre la brecha del ciclo (TIMSS - Balance por ciclo y PISA - Contenidos; si el área está «En meta» no se toca). CUÁLES: candidatos propuestos por IA leyendo los temas, en orden de prioridad; «Entra» = está dentro de los N necesarios. Inserción por COBERTURA = objetivo que nadie trabaja, aunque su área sobre: siempre entra y se paga con una fusión extra de la misma área. REUBICAR = mover un tema de grado dentro del ciclo (no cambia el total; equilibra grados y adelanta lo que otros países enseñan antes).

Sheet TIMSS - Balance por ciclo
A1: Balance de contenidos por ciclo (comparación acumulada, la más fiel a TIMSS)
A2: Tolerancia para considerar «en meta» (± puntos porcentuales): | H2: 0.05
A3: {="TIMSS 2027"&" "&IF(COUNTIF($K$6:$K$8,"En meta")=ROWS($K$6:$K$8),"BIEN · ","OJO · ")&"TIMSS 4.° (2.°–4.°): "&IF(COUNTIF($K$6:$K$8,"En meta")=ROWS($K$6:$K$8),"los "&ROWS($K$6:$K$8)&" dominios están en meta.","faltan "&FIXED(MAX($I$6:$I$8),0)&" temas de "&INDEX($C$6:$C$8,MATCH(MAX($I$6:$I$8),$I$6:$I$8,0))&" y sobran "&FIXED(-MIN($I$6:$I$8),0)&" de "&INDEX($C$6:$C$8,MATCH(MIN($I$6:$I$8),$I$6:$I$8,0))&".")&" "&IF(COUNTIF($K$11:$K$14,"En meta")=ROWS($K$11:$K$14),"BIEN · ","OJO · ")&"TIMSS 8.° (5.°–8.°): "&IF(COUNTIF($K$11:$K$14,"En meta")=ROWS($K$11:$K$14),"los "&ROWS($K$11:$K$14)&" dominios están en meta.","faltan "&FIXED(MAX($I$11:$I$14),0)&" temas de "&INDEX($C$11:$C$14,MATCH(MAX($I$11:$I$14),$I$11:$I$14,0))&" y sobran "&FIXED(-MIN($I$11:$I$14),0)&" de "&INDEX($C$11:$C$14,MATCH(MIN($I$11:$I$14),$I$11:$I$14,0))&".")&" "&IF(COUNTIF($K$17:$K$19,"En meta")=ROWS($K$17:$K$19),"BIEN · ","OJO · ")&"TIMSS Advanced (Física 10.°–11.°): "&IF(COUNTIF($K$17:$K$19,"En meta")=ROWS($K$17:$K$19),"los "&ROWS($K$17:$K$19)&" dominios están en meta.","faltan "&FIXED(MAX($I$17:$I$19),0)&" temas de "&INDEX($C$17:$C$19,MATCH(MAX($I$17:$I$19),$I$17:$I$19,0))&" y sobran "&FIXED(-MIN($I$17:$I$19),0)&" de "&INDEX($C$17:$C$19,MATCH(MIN($I$17:$I$19),$I$17:$I$19,0))&".")&" "&"→ Esta es la comparación más justa: TIMSS evalúa lo acumulado, no cada grado. PISA: hoja «PISA - Contenidos»."} -> TIMSS 2027 OJO · TIMSS 4.° (2.°–4.°): faltan 9 temas de Ciencias físicas y sobran 12 de Biología. BIEN · TIMSS 8.° (5.°–8.°): los 4 dominios están en meta. OJO · TIMSS Advanced (Física 10.°–11.°): faltan 9 temas de Mecánica y termodinámica y sobran 15 de Ondas y física atómica/nuclear. → Esta es la comparación más justa: TIMSS evalúa lo acumulado, no cada grado. PISA: hoja «PISA - Contenidos».
A5: Grupo | B5: Marco de referencia | C5: Dominio | D5: Temas actuales en el dominio | E5: Temas evaluables del grupo (sin «fuera») | F5: % actual | G5: Meta TIMSS (%) | H5: Temas esperados según meta | I5: Brecha (temas): + faltan / − sobran | J5: Brecha (pp) | K5: Estado | L5: Escala para cumplir sin quitar temas (total evaluables) | M5: Temas a AGREGAR para llegar a la meta sin quitar | N5: Temas «fuera del marco» del grupo | O5: Desvío |actual − meta| (fila) · COINCIDENCIA con la meta (fila total)
A6: Ciclo 2°–4° | B6: TIMSS 2027 4.° | C6: Biología | D6: {=_xlfn.COUNTIFS('Datos - Temas'!$W$5:$W$1264,$A6,'Datos - Temas'!$M$5:$M$1264,$C6)} -> 94 | E6: {=_xlfn.COUNTIFS('Datos - Temas'!$W$5:$W$1264,$A6)-_xlfn.COUNTIFS('Datos - Temas'!$W$5:$W$1264,$A6,'Datos - Temas'!$K$5:$K$1264,"FUERA")-_xlfn.COUNTIFS('Datos - Temas'!$W$5:$W$1264,$A6,'Datos - Temas'!$K$5:$K$1264,"PENDIENTE")} -> 182 | F6: {=IF(E6=0,0,D6/E6)} -> 0.51648352 | G6: 0.45 | H6: {=G6*E6} -> 81.9 | I6: {=H6-D6} -> -12.1 | J6: {=(G6-F6)*100} -> -6.6483516 | K6: {=IF(ABS(G6-F6)<=$H$2,"En meta",IF(I6>0,"Faltan "&FIXED(I6,0)&" temas","Sobran "&FIXED(-I6,0)&" temas"))} -> Sobran 12 temas | L6: {=MAX(D6/G6,D7/G7,D8/G8)} -> 208.88889 | M6: {=MAX(0,ROUNDUP(G6*L6-D6,0))} -> 1 | N6: {=_xlfn.COUNTIFS('Datos - Temas'!$W$5:$W$1264,$A6,'Datos - Temas'!$K$5:$K$1264,"FUERA")} -> 26 | O6: {=ABS(F6-G6)} -> 0.066483516
A7: Ciclo 2°–4° | B7: TIMSS 2027 4.° | C7: Ciencias físicas | D7: {=_xlfn.COUNTIFS('Datos - Temas'!$W$5:$W$1264,$A7,'Datos - Temas'!$M$5:$M$1264,$C7)} -> 55 | E7: {=_xlfn.COUNTIFS('Datos - Temas'!$W$5:$W$1264,$A7)-_xlfn.COUNTIFS('Datos - Temas'!$W$5:$W$1264,$A7,'Datos - Temas'!$K$5:$K$1264,"FUERA")-_xlfn.COUNTIFS('Datos - Temas'!$W$5:$W$1264,$A7,'Datos - Temas'!$K$5:$K$1264,"PENDIENTE")} -> 182 | F7: {=IF(E7=0,0,D7/E7)} -> 0.3021978 | G7: 0.35 | H7: {=G7*E7} -> 63.7 | I7: {=H7-D7} -> 8.7 | J7: {=(G7-F7)*100} -> 4.7802198 | K7: {=IF(ABS(G7-F7)<=$H$2,"En meta",IF(I7>0,"Faltan "&FIXED(I7,0)&" temas","Sobran "&FIXED(-I7,0)&" temas"))} -> En meta | L7: {=MAX(D6/G6,D7/G7,D8/G8)} -> 208.88889 | M7: {=MAX(0,ROUNDUP(G7*L7-D7,0))} -> 19 | N7: {=_xlfn.COUNTIFS('Datos - Temas'!$W$5:$W$1264,$A7,'Datos - Temas'!$K$5:$K$1264,"FUERA")} -> 26 | O7: {=ABS(F7-G7)} -> 0.047802198
A8: Ciclo 2°–4° | B8: TIMSS 2027 4.° | C8: Ciencias de la Tierra | D8: {=_xlfn.COUNTIFS('Datos - Temas'!$W$5:$W$1264,$A8,'Datos - Temas'!$M$5:$M$1264,$C8)} -> 33 | E8: {=_xlfn.COUNTIFS('Datos - Temas'!$W$5:$W$1264,$A8)-_xlfn.COUNTIFS('Datos - Temas'!$W$5:$W$1264,$A8,'Datos - Temas'!$K$5:$K$1264,"FUERA")-_xlfn.COUNTIFS('Datos - Temas'!$W$5:$W$1264,$A8,'Datos - Temas'!$K$5:$K$1264,"PENDIENTE")} -> 182 | F8: {=IF(E8=0,0,D8/E8)} -> 0.18131868 | G8: 0.2 | H8: {=G8*E8} -> 36.4 | I8: {=H8-D8} -> 3.4 | J8: {=(G8-F8)*100} -> 1.8681319 | K8: {=IF(ABS(G8-F8)<=$H$2,"En meta",IF(I8>0,"Faltan "&FIXED(I8,0)&" temas","Sobran "&FIXED(-I8,0)&" temas"))} -> En meta | L8: {=MAX(D6/G6,D7/G7,D8/G8)} -> 208.88889 | M8: {=MAX(0,ROUNDUP(G8*L8-D8,0))} -> 9 | N8: {=_xlfn.COUNTIFS('Datos - Temas'!$W$5:$W$1264,$A8,'Datos - Temas'!$K$5:$K$1264,"FUERA")} -> 26 | O8: {=ABS(F8-G8)} -> 0.018681319
C9: Total del grupo | D9: {=SUM(D6:D8)} -> 182 | G9: {=SUM(G6:G8)} -> 1 | M9: {=SUM(M6:M8)} -> 29 | O9: {=1-SUM(O6:O8)/2} -> 0.93351648
A11: Ciclo 5°–8° | B11: TIMSS 2027 8.° | C11: Biología | D11: {=_xlfn.COUNTIFS('Datos - Temas'!$W$5:$W$1264,$A11,'Datos - Temas'!$M$5:$M$1264,$C11)} -> 103 | E11: {=_xlfn.COUNTIFS('Datos - Temas'!$W$5:$W$1264,$A11)-_xlfn.COUNTIFS('Datos - Temas'!$W$5:$W$1264,$A11,'Datos - Temas'!$K$5:$K$1264,"FUERA")-_xlfn.COUNTIFS('Datos - Temas'!$W$5:$W$1264,$A11,'Datos - Temas'!$K$5:$K$1264,"PENDIENTE")} -> 302 | F11: {=IF(E11=0,0,D11/E11)} -> 0.3410596 | G11: 0.35 | H11: {=G11*E11} -> 105.7 | I11: {=H11-D11} -> 2.7 | J11: {=(G11-F11)*100} -> 0.89403974 | K11: {=IF(ABS(G11-F11)<=$H$2,"En meta",IF(I11>0,"Faltan "&FIXED(I11,0)&" temas","Sobran "&FIXED(-I11,0)&" temas"))} -> En meta | L11: {=MAX(D11/G11,D12/G12,D13/G13,D14/G14)} -> 332 | M11: {=MAX(0,ROUNDUP(G11*L11-D11,0))} -> 14 | N11: {=_xlfn.COUNTIFS('Datos - Temas'!$W$5:$W$1264,$A11,'Datos - Temas'!$K$5:$K$1264,"FUERA")} -> 22 | O11: {=ABS(F11-G11)} -> 0.0089403974
A12: Ciclo 5°–8° | B12: TIMSS 2027 8.° | C12: Química | D12: {=_xlfn.COUNTIFS('Datos - Temas'!$W$5:$W$1264,$A12,'Datos - Temas'!$M$5:$M$1264,$C12)} -> 63 | E12: {=_xlfn.COUNTIFS('Datos - Temas'!$W$5:$W$1264,$A12)-_xlfn.COUNTIFS('Datos - Temas'!$W$5:$W$1264,$A12,'Datos - Temas'!$K$5:$K$1264,"FUERA")-_xlfn.COUNTIFS('Datos - Temas'!$W$5:$W$1264,$A12,'Datos - Temas'!$K$5:$K$1264,"PENDIENTE")} -> 302 | F12: {=IF(E12=0,0,D12/E12)} -> 0.20860927 | G12: 0.2 | H12: {=G12*E12} -> 60.4 | I12: {=H12-D12} -> -2.6 | J12: {=(G12-F12)*100} -> -0.86092715 | K12: {=IF(ABS(G12-F12)<=$H$2,"En meta",IF(I12>0,"Faltan "&FIXED(I12,0)&" temas","Sobran "&FIXED(-I12,0)&" temas"))} -> En meta | L12: {=MAX(D11/G11,D12/G12,D13/G13,D14/G14)} -> 332 | M12: {=MAX(0,ROUNDUP(G12*L12-D12,0))} -> 4 | N12: {=_xlfn.COUNTIFS('Datos - Temas'!$W$5:$W$1264,$A12,'Datos - Temas'!$K$5:$K$1264,"FUERA")} -> 22 | O12: {=ABS(F12-G12)} -> 0.0086092715
A13: Ciclo 5°–8° | B13: TIMSS 2027 8.° | C13: Física | D13: {=_xlfn.COUNTIFS('Datos - Temas'!$W$5:$W$1264,$A13,'Datos - Temas'!$M$5:$M$1264,$C13)} -> 83 | E13: {=_xlfn.COUNTIFS('Datos - Temas'!$W$5:$W$1264,$A13)-_xlfn.COUNTIFS('Datos - Temas'!$W$5:$W$1264,$A13,'Datos - Temas'!$K$5:$K$1264,"FUERA")-_xlfn.COUNTIFS('Datos - Temas'!$W$5:$W$1264,$A13,'Datos - Temas'!$K$5:$K$1264,"PENDIENTE")} -> 302 | F13: {=IF(E13=0,0,D13/E13)} -> 0.27483444 | G13: 0.25 | H13: {=G13*E13} -> 75.5 | I13: {=H13-D13} -> -7.5 | J13: {=(G13-F13)*100} -> -2.4834437 | K13: {=IF(ABS(G13-F13)<=$H$2,"En meta",IF(I13>0,"Faltan "&FIXED(I13,0)&" temas","Sobran "&FIXED(-I13,0)&" temas"))} -> En meta | L13: {=MAX(D11/G11,D12/G12,D13/G13,D14/G14)} -> 332 | M13: {=MAX(0,ROUNDUP(G13*L13-D13,0))} -> 0 | N13: {=_xlfn.COUNTIFS('Datos - Temas'!$W$5:$W$1264,$A13,'Datos - Temas'!$K$5:$K$1264,"FUERA")} -> 22 | O13: {=ABS(F13-G13)} -> 0.024834437
A14: Ciclo 5°–8° | B14: TIMSS 2027 8.° | C14: Ciencias de la Tierra | D14: {=_xlfn.COUNTIFS('Datos - Temas'!$W$5:$W$1264,$A14,'Datos - Temas'!$M$5:$M$1264,$C14)} -> 53 | E14: {=_xlfn.COUNTIFS('Datos - Temas'!$W$5:$W$1264,$A14)-_xlfn.COUNTIFS('Datos - Temas'!$W$5:$W$1264,$A14,'Datos - Temas'!$K$5:$K$1264,"FUERA")-_xlfn.COUNTIFS('Datos - Temas'!$W$5:$W$1264,$A14,'Datos - Temas'!$K$5:$K$1264,"PENDIENTE")} -> 302 | F14: {=IF(E14=0,0,D14/E14)} -> 0.17549669 | G14: 0.2 | H14: {=G14*E14} -> 60.4 | I14: {=H14-D14} -> 7.4 | J14: {=(G14-F14)*100} -> 2.4503311 | K14: {=IF(ABS(G14-F14)<=$H$2,"En meta",IF(I14>0,"Faltan "&FIXED(I14,0)&" temas","Sobran "&FIXED(-I14,0)&" temas"))} -> En meta | L14: {=MAX(D11/G11,D12/G12,D13/G13,D14/G14)} -> 332 | M14: {=MAX(0,ROUNDUP(G14*L14-D14,0))} -> 14 | N14: {=_xlfn.COUNTIFS('Datos - Temas'!$W$5:$W$1264,$A14,'Datos - Temas'!$K$5:$K$1264,"FUERA")} -> 22 | O14: {=ABS(F14-G14)} -> 0.024503311
C15: Total del grupo | D15: {=SUM(D11:D14)} -> 302 | G15: {=SUM(G11:G14)} -> 1 | M15: {=SUM(M11:M14)} -> 32 | O15: {=1-SUM(O11:O14)/2} -> 0.96655629
A17: Física 10°–11° | B17: TIMSS Advanced 2015 Física | C17: Mecánica y termodinámica | D17: {=_xlfn.COUNTIFS('Datos - Temas'!$W$5:$W$1264,$A17,'Datos - Temas'!$M$5:$M$1264,$C17)} -> 71 | E17: {=_xlfn.COUNTIFS('Datos - Temas'!$W$5:$W$1264,$A17)-_xlfn.COUNTIFS('Datos - Temas'!$W$5:$W$1264,$A17,'Datos - Temas'!$K$5:$K$1264,"FUERA")-_xlfn.COUNTIFS('Datos - Temas'!$W$5:$W$1264,$A17,'Datos - Temas'!$K$5:$K$1264,"PENDIENTE")} -> 199 | F17: {=IF(E17=0,0,D17/E17)} -> 0.35678392 | G17: 0.4 | H17: {=G17*E17} -> 79.6 | I17: {=H17-D17} -> 8.6 | J17: {=(G17-F17)*100} -> 4.321608 | K17: {=IF(ABS(G17-F17)<=$H$2,"En meta",IF(I17>0,"Faltan "&FIXED(I17,0)&" temas","Sobran "&FIXED(-I17,0)&" temas"))} -> En meta | L17: {=MAX(D17/G17,D18/G18,D19/G19)} -> 242.85714 | M17: {=MAX(0,ROUNDUP(G17*L17-D17,0))} -> 27 | N17: {=_xlfn.COUNTIFS('Datos - Temas'!$W$5:$W$1264,$A17,'Datos - Temas'!$K$5:$K$1264,"FUERA")} -> 68 | O17: {=ABS(F17-G17)} -> 0.04321608
A18: Física 10°–11° | B18: TIMSS Advanced 2015 Física | C18: Electricidad y magnetismo | D18: {=_xlfn.COUNTIFS('Datos - Temas'!$W$5:$W$1264,$A18,'Datos - Temas'!$M$5:$M$1264,$C18)} -> 43 | E18: {=_xlfn.COUNTIFS('Datos - Temas'!$W$5:$W$1264,$A18)-_xlfn.COUNTIFS('Datos - Temas'!$W$5:$W$1264,$A18,'Datos - Temas'!$K$5:$K$1264,"FUERA")-_xlfn.COUNTIFS('Datos - Temas'!$W$5:$W$1264,$A18,'Datos - Temas'!$K$5:$K$1264,"PENDIENTE")} -> 199 | F18: {=IF(E18=0,0,D18/E18)} -> 0.2160804 | G18: 0.25 | H18: {=G18*E18} -> 49.75 | I18: {=H18-D18} -> 6.75 | J18: {=(G18-F18)*100} -> 3.3919598 | K18: {=IF(ABS(G18-F18)<=$H$2,"En meta",IF(I18>0,"Faltan "&FIXED(I18,0)&" temas","Sobran "&FIXED(-I18,0)&" temas"))} -> En meta | L18: {=MAX(D17/G17,D18/G18,D19/G19)} -> 242.85714 | M18: {=MAX(0,ROUNDUP(G18*L18-D18,0))} -> 18 | N18: {=_xlfn.COUNTIFS('Datos - Temas'!$W$5:$W$1264,$A18,'Datos - Temas'!$K$5:$K$1264,"FUERA")} -> 68 | O18: {=ABS(F18-G18)} -> 0.033919598
A19: Física 10°–11° | B19: TIMSS Advanced 2015 Física | C19: Ondas y física atómica/nuclear | D19: {=_xlfn.COUNTIFS('Datos - Temas'!$W$5:$W$1264,$A19,'Datos - Temas'!$M$5:$M$1264,$C19)} -> 85 | E19: {=_xlfn.COUNTIFS('Datos - Temas'!$W$5:$W$1264,$A19)-_xlfn.COUNTIFS('Datos - Temas'!$W$5:$W$1264,$A19,'Datos - Temas'!$K$5:$K$1264,"FUERA")-_xlfn.COUNTIFS('Datos - Temas'!$W$5:$W$1264,$A19,'Datos - Temas'!$K$5:$K$1264,"PENDIENTE")} -> 199 | F19: {=IF(E19=0,0,D19/E19)} -> 0.42713568 | G19: 0.35 | H19: {=G19*E19} -> 69.65 | I19: {=H19-D19} -> -15.35 | J19: {=(G19-F19)*100} -> -7.7135678 | K19: {=IF(ABS(G19-F19)<=$H$2,"En meta",IF(I19>0,"Faltan "&FIXED(I19,0)&" temas","Sobran "&FIXED(-I19,0)&" temas"))} -> Sobran 15 temas | L19: {=MAX(D17/G17,D18/G18,D19/G19)} -> 242.85714 | M19: {=MAX(0,ROUNDUP(G19*L19-D19,0))} -> 1 | N19: {=_xlfn.COUNTIFS('Datos - Temas'!$W$5:$W$1264,$A19,'Datos - Temas'!$K$5:$K$1264,"FUERA")} -> 68 | O19: {=ABS(F19-G19)} -> 0.077135678
C20: Total del grupo | D20: {=SUM(D17:D19)} -> 199 | G20: {=SUM(G17:G19)} -> 1 | M20: {=SUM(M17:M19)} -> 46 | O20: {=1-SUM(O17:O19)/2} -> 0.92286432
A22: Cómo se calcula: TIMSS 4.° evalúa lo aprendido hasta 4.° grado → se compara con el acumulado de 2.° a 4.° (1.° grado no tiene malla). TIMSS 8.° evalúa lo aprendido hasta 8.° → acumulado de 5.° a 8.°. 9.° se muestra contra TIMSS 8.° solo como referencia. Física de Bachillerato se compara con TIMSS Advanced 2015 (Física). Química y Biología de Bachillerato no tienen marco TIMSS de contenido.

Sheet TIMSS - Balance por grado
A1: Balance de contenidos por grado frente a las metas de TIMSS
A2: Tolerancia para considerar «en meta» (± puntos porcentuales): | H2: 0.05
A3: {="TIMSS 2027"&" "&"● 2.°–8.°: la mayor falta es "&FIXED(MAX($I$6:$I$43),0)&" temas de "&INDEX($C$6:$C$43,MATCH(MAX($I$6:$I$43),$I$6:$I$43,0))&" en "&SUBSTITUTE(INDEX($A$6:$A$43,MATCH(MAX($I$6:$I$43),$I$6:$I$43,0)),"°",".°")&"; la mayor sobra, "&FIXED(-MIN($I$6:$I$43),0)&" de "&INDEX($C$6:$C$43,MATCH(MIN($I$6:$I$43),$I$6:$I$43,0))&" en "&SUBSTITUTE(INDEX($A$6:$A$43,MATCH(MIN($I$6:$I$43),$I$6:$I$43,0)),"°",".°")&"."&" "&"● Por grado las brechas se compensan entre grados: decide con «TIMSS - Balance por ciclo»."} -> TIMSS 2027 ● 2.°–8.°: la mayor falta es 19 temas de Biología en 5.°; la mayor sobra, 15 de Biología en 7.°. ● Por grado las brechas se compensan entre grados: decide con «TIMSS - Balance por ciclo».
A5: Grupo | B5: Marco de referencia | C5: Dominio | D5: Temas actuales en el dominio | E5: Temas evaluables del grupo (sin «fuera») | F5: % actual | G5: Meta TIMSS (%) | H5: Temas esperados según meta | I5: Brecha (temas): + faltan / − sobran | J5: Brecha (pp) | K5: Estado | L5: Escala para cumplir sin quitar temas (total evaluables) | M5: Temas a AGREGAR para llegar a la meta sin quitar | N5: Temas «fuera del marco» del grupo | O5: Desvío |actual − meta| (fila) · COINCIDENCIA con la meta (fila total)
A6: 2° | B6: TIMSS 2027 4.° | C6: Biología | D6: {=_xlfn.COUNTIFS('Datos - Temas'!$V$5:$V$1264,$A6,'Datos - Temas'!$M$5:$M$1264,$C6)} -> 24 | E6: {=_xlfn.COUNTIFS('Datos - Temas'!$V$5:$V$1264,$A6)-_xlfn.COUNTIFS('Datos - Temas'!$V$5:$V$1264,$A6,'Datos - Temas'!$K$5:$K$1264,"FUERA")-_xlfn.COUNTIFS('Datos - Temas'!$V$5:$V$1264,$A6,'Datos - Temas'!$K$5:$K$1264,"PENDIENTE")} -> 59 | F6: {=IF(E6=0,0,D6/E6)} -> 0.40677966 | G6: 0.45 | H6: {=G6*E6} -> 26.55 | I6: {=H6-D6} -> 2.55 | J6: {=(G6-F6)*100} -> 4.3220339 | K6: {=IF(ABS(G6-F6)<=$H$2,"En meta",IF(I6>0,"Faltan "&FIXED(I6,0)&" temas","Sobran "&FIXED(-I6,0)&" temas"))} -> En meta | L6: {=MAX(D6/G6,D7/G7,D8/G8)} -> 77.142857 | M6: {=MAX(0,ROUNDUP(G6*L6-D6,0))} -> 11 | N6: {=_xlfn.COUNTIFS('Datos - Temas'!$V$5:$V$1264,$A6,'Datos - Temas'!$K$5:$K$1264,"FUERA")} -> 11 | O6: {=ABS(F6-G6)} -> 0.043220339
A7: 2° | B7: TIMSS 2027 4.° | C7: Ciencias físicas | D7: {=_xlfn.COUNTIFS('Datos - Temas'!$V$5:$V$1264,$A7,'Datos - Temas'!$M$5:$M$1264,$C7)} -> 27 | E7: {=_xlfn.COUNTIFS('Datos - Temas'!$V$5:$V$1264,$A7)-_xlfn.COUNTIFS('Datos - Temas'!$V$5:$V$1264,$A7,'Datos - Temas'!$K$5:$K$1264,"FUERA")-_xlfn.COUNTIFS('Datos - Temas'!$V$5:$V$1264,$A7,'Datos - Temas'!$K$5:$K$1264,"PENDIENTE")} -> 59 | F7: {=IF(E7=0,0,D7/E7)} -> 0.45762712 | G7: 0.35 | H7: {=G7*E7} -> 20.65 | I7: {=H7-D7} -> -6.35 | J7: {=(G7-F7)*100} -> -10.762712 | K7: {=IF(ABS(G7-F7)<=$H$2,"En meta",IF(I7>0,"Faltan "&FIXED(I7,0)&" temas","Sobran "&FIXED(-I7,0)&" temas"))} -> Sobran 6 temas | L7: {=MAX(D6/G6,D7/G7,D8/G8)} -> 77.142857 | M7: {=MAX(0,ROUNDUP(G7*L7-D7,0))} -> 0 | N7: {=_xlfn.COUNTIFS('Datos - Temas'!$V$5:$V$1264,$A7,'Datos - Temas'!$K$5:$K$1264,"FUERA")} -> 11 | O7: {=ABS(F7-G7)} -> 0.10762712
A8: 2° | B8: TIMSS 2027 4.° | C8: Ciencias de la Tierra | D8: {=_xlfn.COUNTIFS('Datos - Temas'!$V$5:$V$1264,$A8,'Datos - Temas'!$M$5:$M$1264,$C8)} -> 8 | E8: {=_xlfn.COUNTIFS('Datos - Temas'!$V$5:$V$1264,$A8)-_xlfn.COUNTIFS('Datos - Temas'!$V$5:$V$1264,$A8,'Datos - Temas'!$K$5:$K$1264,"FUERA")-_xlfn.COUNTIFS('Datos - Temas'!$V$5:$V$1264,$A8,'Datos - Temas'!$K$5:$K$1264,"PENDIENTE")} -> 59 | F8: {=IF(E8=0,0,D8/E8)} -> 0.13559322 | G8: 0.2 | H8: {=G8*E8} -> 11.8 | I8: {=H8-D8} -> 3.8 | J8: {=(G8-F8)*100} -> 6.440678 | K8: {=IF(ABS(G8-F8)<=$H$2,"En meta",IF(I8>0,"Faltan "&FIXED(I8,0)&" temas","Sobran "&FIXED(-I8,0)&" temas"))} -> Faltan 4 temas | L8: {=MAX(D6/G6,D7/G7,D8/G8)} -> 77.142857 | M8: {=MAX(0,ROUNDUP(G8*L8-D8,0))} -> 8 | N8: {=_xlfn.COUNTIFS('Datos - Temas'!$V$5:$V$1264,$A8,'Datos - Temas'!$K$5:$K$1264,"FUERA")} -> 11 | O8: {=ABS(F8-G8)} -> 0.06440678
C9: Total del grupo | D9: {=SUM(D6:D8)} -> 59 | G9: {=SUM(G6:G8)} -> 1 | M9: {=SUM(M6:M8)} -> 19 | O9: {=1-SUM(O6:O8)/2} -> 0.89237288
A11: 3° | B11: TIMSS 2027 4.° | C11: Biología | D11: {=_xlfn.COUNTIFS('Datos - Temas'!$V$5:$V$1264,$A11,'Datos - Temas'!$M$5:$M$1264,$C11)} -> 32 | E11: {=_xlfn.COUNTIFS('Datos - Temas'!$V$5:$V$1264,$A11)-_xlfn.COUNTIFS('Datos - Temas'!$V$5:$V$1264,$A11,'Datos - Temas'!$K$5:$K$1264,"FUERA")-_xlfn.COUNTIFS('Datos - Temas'!$V$5:$V$1264,$A11,'Datos - Temas'!$K$5:$K$1264,"PENDIENTE")} -> 60 | F11: {=IF(E11=0,0,D11/E11)} -> 0.53333333 | G11: 0.45 | H11: {=G11*E11} -> 27 | I11: {=H11-D11} -> -5 | J11: {=(G11-F11)*100} -> -8.3333333 | K11: {=IF(ABS(G11-F11)<=$H$2,"En meta",IF(I11>0,"Faltan "&FIXED(I11,0)&" temas","Sobran "&FIXED(-I11,0)&" temas"))} -> Sobran 5 temas | L11: {=MAX(D11/G11,D12/G12,D13/G13)} -> 71.111111 | M11: {=MAX(0,ROUNDUP(G11*L11-D11,0))} -> 0 | N11: {=_xlfn.COUNTIFS('Datos - Temas'!$V$5:$V$1264,$A11,'Datos - Temas'!$K$5:$K$1264,"FUERA")} -> 6 | O11: {=ABS(F11-G11)} -> 0.083333333
A12: 3° | B12: TIMSS 2027 4.° | C12: Ciencias físicas | D12: {=_xlfn.COUNTIFS('Datos - Temas'!$V$5:$V$1264,$A12,'Datos - Temas'!$M$5:$M$1264,$C12)} -> 19 | E12: {=_xlfn.COUNTIFS('Datos - Temas'!$V$5:$V$1264,$A12)-_xlfn.COUNTIFS('Datos - Temas'!$V$5:$V$1264,$A12,'Datos - Temas'!$K$5:$K$1264,"FUERA")-_xlfn.COUNTIFS('Datos - Temas'!$V$5:$V$1264,$A12,'Datos - Temas'!$K$5:$K$1264,"PENDIENTE")} -> 60 | F12: {=IF(E12=0,0,D12/E12)} -> 0.31666667 | G12: 0.35 | H12: {=G12*E12} -> 21 | I12: {=H12-D12} -> 2 | J12: {=(G12-F12)*100} -> 3.3333333 | K12: {=IF(ABS(G12-F12)<=$H$2,"En meta",IF(I12>0,"Faltan "&FIXED(I12,0)&" temas","Sobran "&FIXED(-I12,0)&" temas"))} -> En meta | L12: {=MAX(D11/G11,D12/G12,D13/G13)} -> 71.111111 | M12: {=MAX(0,ROUNDUP(G12*L12-D12,0))} -> 6 | N12: {=_xlfn.COUNTIFS('Datos - Temas'!$V$5:$V$1264,$A12,'Datos - Temas'!$K$5:$K$1264,"FUERA")} -> 6 | O12: {=ABS(F12-G12)} -> 0.033333333
A13: 3° | B13: TIMSS 2027 4.° | C13: Ciencias de la Tierra | D13: {=_xlfn.COUNTIFS('Datos - Temas'!$V$5:$V$1264,$A13,'Datos - Temas'!$M$5:$M$1264,$C13)} -> 9 | E13: {=_xlfn.COUNTIFS('Datos - Temas'!$V$5:$V$1264,$A13)-_xlfn.COUNTIFS('Datos - Temas'!$V$5:$V$1264,$A13,'Datos - Temas'!$K$5:$K$1264,"FUERA")-_xlfn.COUNTIFS('Datos - Temas'!$V$5:$V$1264,$A13,'Datos - Temas'!$K$5:$K$1264,"PENDIENTE")} -> 60 | F13: {=IF(E13=0,0,D13/E13)} -> 0.15 | G13: 0.2 | H13: {=G13*E13} -> 12 | I13: {=H13-D13} -> 3 | J13: {=(G13-F13)*100} -> 5 | K13: {=IF(ABS(G13-F13)<=$H$2,"En meta",IF(I13>0,"Faltan "&FIXED(I13,0)&" temas","Sobran "&FIXED(-I13,0)&" temas"))} -> En meta | L13: {=MAX(D11/G11,D12/G12,D13/G13)} -> 71.111111 | M13: {=MAX(0,ROUNDUP(G13*L13-D13,0))} -> 6 | N13: {=_xlfn.COUNTIFS('Datos - Temas'!$V$5:$V$1264,$A13,'Datos - Temas'!$K$5:$K$1264,"FUERA")} -> 6 | O13: {=ABS(F13-G13)} -> 0.05
C14: Total del grupo | D14: {=SUM(D11:D13)} -> 60 | G14: {=SUM(G11:G13)} -> 1 | M14: {=SUM(M11:M13)} -> 12 | O14: {=1-SUM(O11:O13)/2} -> 0.91666667
A16: 4° | B16: TIMSS 2027 4.° | C16: Biología | D16: {=_xlfn.COUNTIFS('Datos - Temas'!$V$5:$V$1264,$A16,'Datos - Temas'!$M$5:$M$1264,$C16)} -> 38 | E16: {=_xlfn.COUNTIFS('Datos - Temas'!$V$5:$V$1264,$A16)-_xlfn.COUNTIFS('Datos - Temas'!$V$5:$V$1264,$A16,'Datos - Temas'!$K$5:$K$1264,"FUERA")-_xlfn.COUNTIFS('Datos - Temas'!$V$5:$V$1264,$A16,'Datos - Temas'!$K$5:$K$1264,"PENDIENTE")} -> 63 | F16: {=IF(E16=0,0,D16/E16)} -> 0.6031746 | G16: 0.45 | H16: {=G16*E16} -> 28.35 | I16: {=H16-D16} -> -9.65 | J16: {=(G16-F16)*100} -> -15.31746 | K16: {=IF(ABS(G16-F16)<=$H$2,"En meta",IF(I16>0,"Faltan "&FIXED(I16,0)&" temas","Sobran "&FIXED(-I16,0)&" temas"))} -> Sobran 10 temas | L16: {=MAX(D16/G16,D17/G17,D18/G18)} -> 84.444444 | M16: {=MAX(0,ROUNDUP(G16*L16-D16,0))} -> 0 | N16: {=_xlfn.COUNTIFS('Datos - Temas'!$V$5:$V$1264,$A16,'Datos - Temas'!$K$5:$K$1264,"FUERA")} -> 9 | O16: {=ABS(F16-G16)} -> 0.1531746
A17: 4° | B17: TIMSS 2027 4.° | C17: Ciencias físicas | D17: {=_xlfn.COUNTIFS('Datos - Temas'!$V$5:$V$1264,$A17,'Datos - Temas'!$M$5:$M$1264,$C17)} -> 9 | E17: {=_xlfn.COUNTIFS('Datos - Temas'!$V$5:$V$1264,$A17)-_xlfn.COUNTIFS('Datos - Temas'!$V$5:$V$1264,$A17,'Datos - Temas'!$K$5:$K$1264,"FUERA")-_xlfn.COUNTIFS('Datos - Temas'!$V$5:$V$1264,$A17,'Datos - Temas'!$K$5:$K$1264,"PENDIENTE")} -> 63 | F17: {=IF(E17=0,0,D17/E17)} -> 0.14285714 | G17: 0.35 | H17: {=G17*E17} -> 22.05 | I17: {=H17-D17} -> 13.05 | J17: {=(G17-F17)*100} -> 20.714286 | K17: {=IF(ABS(G17-F17)<=$H$2,"En meta",IF(I17>0,"Faltan "&FIXED(I17,0)&" temas","Sobran "&FIXED(-I17,0)&" temas"))} -> Faltan 13 temas | L17: {=MAX(D16/G16,D17/G17,D18/G18)} -> 84.444444 | M17: {=MAX(0,ROUNDUP(G17*L17-D17,0))} -> 21 | N17: {=_xlfn.COUNTIFS('Datos - Temas'!$V$5:$V$1264,$A17,'Datos - Temas'!$K$5:$K$1264,"FUERA")} -> 9 | O17: {=ABS(F17-G17)} -> 0.20714286
A18: 4° | B18: TIMSS 2027 4.° | C18: Ciencias de la Tierra | D18: {=_xlfn.COUNTIFS('Datos - Temas'!$V$5:$V$1264,$A18,'Datos - Temas'!$M$5:$M$1264,$C18)} -> 16 | E18: {=_xlfn.COUNTIFS('Datos - Temas'!$V$5:$V$1264,$A18)-_xlfn.COUNTIFS('Datos - Temas'!$V$5:$V$1264,$A18,'Datos - Temas'!$K$5:$K$1264,"FUERA")-_xlfn.COUNTIFS('Datos - Temas'!$V$5:$V$1264,$A18,'Datos - Temas'!$K$5:$K$1264,"PENDIENTE")} -> 63 | F18: {=IF(E18=0,0,D18/E18)} -> 0.25396825 | G18: 0.2 | H18: {=G18*E18} -> 12.6 | I18: {=H18-D18} -> -3.4 | J18: {=(G18-F18)*100} -> -5.3968254 | K18: {=IF(ABS(G18-F18)<=$H$2,"En meta",IF(I18>0,"Faltan "&FIXED(I18,0)&" temas","Sobran "&FIXED(-I18,0)&" temas"))} -> Sobran 3 temas | L18: {=MAX(D16/G16,D17/G17,D18/G18)} -> 84.444444 | M18: {=MAX(0,ROUNDUP(G18*L18-D18,0))} -> 1 | N18: {=_xlfn.COUNTIFS('Datos - Temas'!$V$5:$V$1264,$A18,'Datos - Temas'!$K$5:$K$1264,"FUERA")} -> 9 | O18: {=ABS(F18-G18)} -> 0.053968254
C19: Total del grupo | D19: {=SUM(D16:D18)} -> 63 | G19: {=SUM(G16:G18)} -> 1 | M19: {=SUM(M16:M18)} -> 22 | O19: {=1-SUM(O16:O18)/2} -> 0.79285714
A21: 5° | B21: TIMSS 2027 8.° | C21: Biología | D21: {=_xlfn.COUNTIFS('Datos - Temas'!$V$5:$V$1264,$A21,'Datos - Temas'!$M$5:$M$1264,$C21)} -> 2 | E21: {=_xlfn.COUNTIFS('Datos - Temas'!$V$5:$V$1264,$A21)-_xlfn.COUNTIFS('Datos - Temas'!$V$5:$V$1264,$A21,'Datos - Temas'!$K$5:$K$1264,"FUERA")-_xlfn.COUNTIFS('Datos - Temas'!$V$5:$V$1264,$A21,'Datos - Temas'!$K$5:$K$1264,"PENDIENTE")} -> 61 | F21: {=IF(E21=0,0,D21/E21)} -> 0.032786885 | G21: 0.35 | H21: {=G21*E21} -> 21.35 | I21: {=H21-D21} -> 19.35 | J21: {=(G21-F21)*100} -> 31.721311 | K21: {=IF(ABS(G21-F21)<=$H$2,"En meta",IF(I21>0,"Faltan "&FIXED(I21,0)&" temas","Sobran "&FIXED(-I21,0)&" temas"))} -> Faltan 19 temas | L21: {=MAX(D21/G21,D22/G22,D23/G23,D24/G24)} -> 100 | M21: {=MAX(0,ROUNDUP(G21*L21-D21,0))} -> 33 | N21: {=_xlfn.COUNTIFS('Datos - Temas'!$V$5:$V$1264,$A21,'Datos - Temas'!$K$5:$K$1264,"FUERA")} -> 11 | O21: {=ABS(F21-G21)} -> 0.31721311
A22: 5° | B22: TIMSS 2027 8.° | C22: Química | D22: {=_xlfn.COUNTIFS('Datos - Temas'!$V$5:$V$1264,$A22,'Datos - Temas'!$M$5:$M$1264,$C22)} -> 19 | E22: {=_xlfn.COUNTIFS('Datos - Temas'!$V$5:$V$1264,$A22)-_xlfn.COUNTIFS('Datos - Temas'!$V$5:$V$1264,$A22,'Datos - Temas'!$K$5:$K$1264,"FUERA")-_xlfn.COUNTIFS('Datos - Temas'!$V$5:$V$1264,$A22,'Datos - Temas'!$K$5:$K$1264,"PENDIENTE")} -> 61 | F22: {=IF(E22=0,0,D22/E22)} -> 0.31147541 | G22: 0.2 | H22: {=G22*E22} -> 12.2 | I22: {=H22-D22} -> -6.8 | J22: {=(G22-F22)*100} -> -11.147541 | K22: {=IF(ABS(G22-F22)<=$H$2,"En meta",IF(I22>0,"Faltan "&FIXED(I22,0)&" temas","Sobran "&FIXED(-I22,0)&" temas"))} -> Sobran 7 temas | L22: {=MAX(D21/G21,D22/G22,D23/G23,D24/G24)} -> 100 | M22: {=MAX(0,ROUNDUP(G22*L22-D22,0))} -> 1 | N22: {=_xlfn.COUNTIFS('Datos - Temas'!$V$5:$V$1264,$A22,'Datos - Temas'!$K$5:$K$1264,"FUERA")} -> 11 | O22: {=ABS(F22-G22)} -> 0.11147541
A23: 5° | B23: TIMSS 2027 8.° | C23: Física | D23: {=_xlfn.COUNTIFS('Datos - Temas'!$V$5:$V$1264,$A23,'Datos - Temas'!$M$5:$M$1264,$C23)} -> 20 | E23: {=_xlfn.COUNTIFS('Datos - Temas'!$V$5:$V$1264,$A23)-_xlfn.COUNTIFS('Datos - Temas'!$V$5:$V$1264,$A23,'Datos - Temas'!$K$5:$K$1264,"FUERA")-_xlfn.COUNTIFS('Datos - Temas'!$V$5:$V$1264,$A23,'Datos - Temas'!$K$5:$K$1264,"PENDIENTE")} -> 61 | F23: {=IF(E23=0,0,D23/E23)} -> 0.32786885 | G23: 0.25 | H23: {=G23*E23} -> 15.25 | I23: {=H23-D23} -> -4.75 | J23: {=(G23-F23)*100} -> -7.7868852 | K23: {=IF(ABS(G23-F23)<=$H$2,"En meta",IF(I23>0,"Faltan "&FIXED(I23,0)&" temas","Sobran "&FIXED(-I23,0)&" temas"))} -> Sobran 5 temas | L23: {=MAX(D21/G21,D22/G22,D23/G23,D24/G24)} -> 100 | M23: {=MAX(0,ROUNDUP(G23*L23-D23,0))} -> 5 | N23: {=_xlfn.COUNTIFS('Datos - Temas'!$V$5:$V$1264,$A23,'Datos - Temas'!$K$5:$K$1264,"FUERA")} -> 11 | O23: {=ABS(F23-G23)} -> 0.077868852
A24: 5° | B24: TIMSS 2027 8.° | C24: Ciencias de la Tierra | D24: {=_xlfn.COUNTIFS('Datos - Temas'!$V$5:$V$1264,$A24,'Datos - Temas'!$M$5:$M$1264,$C24)} -> 20 | E24: {=_xlfn.COUNTIFS('Datos - Temas'!$V$5:$V$1264,$A24)-_xlfn.COUNTIFS('Datos - Temas'!$V$5:$V$1264,$A24,'Datos - Temas'!$K$5:$K$1264,"FUERA")-_xlfn.COUNTIFS('Datos - Temas'!$V$5:$V$1264,$A24,'Datos - Temas'!$K$5:$K$1264,"PENDIENTE")} -> 61 | F24: {=IF(E24=0,0,D24/E24)} -> 0.32786885 | G24: 0.2 | H24: {=G24*E24} -> 12.2 | I24: {=H24-D24} -> -7.8 | J24: {=(G24-F24)*100} -> -12.786885 | K24: {=IF(ABS(G24-F24)<=$H$2,"En meta",IF(I24>0,"Faltan "&FIXED(I24,0)&" temas","Sobran "&FIXED(-I24,0)&" temas"))} -> Sobran 8 temas | L24: {=MAX(D21/G21,D22/G22,D23/G23,D24/G24)} -> 100 | M24: {=MAX(0,ROUNDUP(G24*L24-D24,0))} -> 0 | N24: {=_xlfn.COUNTIFS('Datos - Temas'!$V$5:$V$1264,$A24,'Datos - Temas'!$K$5:$K$1264,"FUERA")} -> 11 | O24: {=ABS(F24-G24)} -> 0.12786885
C25: Total del grupo | D25: {=SUM(D21:D24)} -> 61 | G25: {=SUM(G21:G24)} -> 1 | M25: {=SUM(M21:M24)} -> 39 | O25: {=1-SUM(O21:O24)/2} -> 0.68278689
A27: 6° | B27: TIMSS 2027 8.° | C27: Biología | D27: {=_xlfn.COUNTIFS('Datos - Temas'!$V$5:$V$1264,$A27,'Datos - Temas'!$M$5:$M$1264,$C27)} -> 29 | E27: {=_xlfn.COUNTIFS('Datos - Temas'!$V$5:$V$1264,$A27)-_xlfn.COUNTIFS('Datos - Temas'!$V$5:$V$1264,$A27,'Datos - Temas'!$K$5:$K$1264,"FUERA")-_xlfn.COUNTIFS('Datos - Temas'!$V$5:$V$1264,$A27,'Datos - Temas'!$K$5:$K$1264,"PENDIENTE")} -> 63 | F27: {=IF(E27=0,0,D27/E27)} -> 0.46031746 | G27: 0.35 | H27: {=G27*E27} -> 22.05 | I27: {=H27-D27} -> -6.95 | J27: {=(G27-F27)*100} -> -11.031746 | K27: {=IF(ABS(G27-F27)<=$H$2,"En meta",IF(I27>0,"Faltan "&FIXED(I27,0)&" temas","Sobran "&FIXED(-I27,0)&" temas"))} -> Sobran 7 temas | L27: {=MAX(D27/G27,D28/G28,D29/G29,D30/G30)} -> 96 | M27: {=MAX(0,ROUNDUP(G27*L27-D27,0))} -> 5 | N27: {=_xlfn.COUNTIFS('Datos - Temas'!$V$5:$V$1264,$A27,'Datos - Temas'!$K$5:$K$1264,"FUERA")} -> 5 | O27: {=ABS(F27-G27)} -> 0.11031746
A28: 6° | B28: TIMSS 2027 8.° | C28: Química | D28: {=_xlfn.COUNTIFS('Datos - Temas'!$V$5:$V$1264,$A28,'Datos - Temas'!$M$5:$M$1264,$C28)} -> 10 | E28: {=_xlfn.COUNTIFS('Datos - Temas'!$V$5:$V$1264,$A28)-_xlfn.COUNTIFS('Datos - Temas'!$V$5:$V$1264,$A28,'Datos - Temas'!$K$5:$K$1264,"FUERA")-_xlfn.COUNTIFS('Datos - Temas'!$V$5:$V$1264,$A28,'Datos - Temas'!$K$5:$K$1264,"PENDIENTE")} -> 63 | F28: {=IF(E28=0,0,D28/E28)} -> 0.15873016 | G28: 0.2 | H28: {=G28*E28} -> 12.6 | I28: {=H28-D28} -> 2.6 | J28: {=(G28-F28)*100} -> 4.1269841 | K28: {=IF(ABS(G28-F28)<=$H$2,"En meta",IF(I28>0,"Faltan "&FIXED(I28,0)&" temas","Sobran "&FIXED(-I28,0)&" temas"))} -> En meta | L28: {=MAX(D27/G27,D28/G28,D29/G29,D30/G30)} -> 96 | M28: {=MAX(0,ROUNDUP(G28*L28-D28,0))} -> 10 | N28: {=_xlfn.COUNTIFS('Datos - Temas'!$V$5:$V$1264,$A28,'Datos - Temas'!$K$5:$K$1264,"FUERA")} -> 5 | O28: {=ABS(F28-G28)} -> 0.041269841
A29: 6° | B29: TIMSS 2027 8.° | C29: Física | D29: {=_xlfn.COUNTIFS('Datos - Temas'!$V$5:$V$1264,$A29,'Datos - Temas'!$M$5:$M$1264,$C29)} -> 24 | E29: {=_xlfn.COUNTIFS('Datos - Temas'!$V$5:$V$1264,$A29)-_xlfn.COUNTIFS('Datos - Temas'!$V$5:$V$1264,$A29,'Datos - Temas'!$K$5:$K$1264,"FUERA")-_xlfn.COUNTIFS('Datos - Temas'!$V$5:$V$1264,$A29,'Datos - Temas'!$K$5:$K$1264,"PENDIENTE")} -> 63 | F29: {=IF(E29=0,0,D29/E29)} -> 0.38095238 | G29: 0.25 | H29: {=G29*E29} -> 15.75 | I29: {=H29-D29} -> -8.25 | J29: {=(G29-F29)*100} -> -13.095238 | K29: {=IF(ABS(G29-F29)<=$H$2,"En meta",IF(I29>0,"Faltan "&FIXED(I29,0)&" temas","Sobran "&FIXED(-I29,0)&" temas"))} -> Sobran 8 temas | L29: {=MAX(D27/G27,D28/G28,D29/G29,D30/G30)} -> 96 | M29: {=MAX(0,ROUNDUP(G29*L29-D29,0))} -> 0 | N29: {=_xlfn.COUNTIFS('Datos - Temas'!$V$5:$V$1264,$A29,'Datos - Temas'!$K$5:$K$1264,"FUERA")} -> 5 | O29: {=ABS(F29-G29)} -> 0.13095238
A30: 6° | B30: TIMSS 2027 8.° | C30: Ciencias de la Tierra | D30: {=_xlfn.COUNTIFS('Datos - Temas'!$V$5:$V$1264,$A30,'Datos - Temas'!$M$5:$M$1264,$C30)} -> 0 | E30: {=_xlfn.COUNTIFS('Datos - Temas'!$V$5:$V$1264,$A30)-_xlfn.COUNTIFS('Datos - Temas'!$V$5:$V$1264,$A30,'Datos - Temas'!$K$5:$K$1264,"FUERA")-_xlfn.COUNTIFS('Datos - Temas'!$V$5:$V$1264,$A30,'Datos - Temas'!$K$5:$K$1264,"PENDIENTE")} -> 63 | F30: {=IF(E30=0,0,D30/E30)} -> 0 | G30: 0.2 | H30: {=G30*E30} -> 12.6 | I30: {=H30-D30} -> 12.6 | J30: {=(G30-F30)*100} -> 20 | K30: {=IF(ABS(G30-F30)<=$H$2,"En meta",IF(I30>0,"Faltan "&FIXED(I30,0)&" temas","Sobran "&FIXED(-I30,0)&" temas"))} -> Faltan 13 temas | L30: {=MAX(D27/G27,D28/G28,D29/G29,D30/G30)} -> 96 | M30: {=MAX(0,ROUNDUP(G30*L30-D30,0))} -> 20 | N30: {=_xlfn.COUNTIFS('Datos - Temas'!$V$5:$V$1264,$A30,'Datos - Temas'!$K$5:$K$1264,"FUERA")} -> 5 | O30: {=ABS(F30-G30)} -> 0.2
C31: Total del grupo | D31: {=SUM(D27:D30)} -> 63 | G31: {=SUM(G27:G30)} -> 1 | M31: {=SUM(M27:M30)} -> 35 | O31: {=1-SUM(O27:O30)/2} -> 0.75873016
A33: 7° | B33: TIMSS 2027 8.° | C33: Biología | D33: {=_xlfn.COUNTIFS('Datos - Temas'!$V$5:$V$1264,$A33,'Datos - Temas'!$M$5:$M$1264,$C33)} -> 45 | E33: {=_xlfn.COUNTIFS('Datos - Temas'!$V$5:$V$1264,$A33)-_xlfn.COUNTIFS('Datos - Temas'!$V$5:$V$1264,$A33,'Datos - Temas'!$K$5:$K$1264,"FUERA")-_xlfn.COUNTIFS('Datos - Temas'!$V$5:$V$1264,$A33,'Datos - Temas'!$K$5:$K$1264,"PENDIENTE")} -> 85 | F33: {=IF(E33=0,0,D33/E33)} -> 0.52941176 | G33: 0.35 | H33: {=G33*E33} -> 29.75 | I33: {=H33-D33} -> -15.25 | J33: {=(G33-F33)*100} -> -17.941176 | K33: {=IF(ABS(G33-F33)<=$H$2,"En meta",IF(I33>0,"Faltan "&FIXED(I33,0)&" temas","Sobran "&FIXED(-I33,0)&" temas"))} -> Sobran 15 temas | L33: {=MAX(D33/G33,D34/G34,D35/G35,D36/G36)} -> 145 | M33: {=MAX(0,ROUNDUP(G33*L33-D33,0))} -> 6 | N33: {=_xlfn.COUNTIFS('Datos - Temas'!$V$5:$V$1264,$A33,'Datos - Temas'!$K$5:$K$1264,"FUERA")} -> 6 | O33: {=ABS(F33-G33)} -> 0.17941176
A34: 7° | B34: TIMSS 2027 8.° | C34: Química | D34: {=_xlfn.COUNTIFS('Datos - Temas'!$V$5:$V$1264,$A34,'Datos - Temas'!$M$5:$M$1264,$C34)} -> 9 | E34: {=_xlfn.COUNTIFS('Datos - Temas'!$V$5:$V$1264,$A34)-_xlfn.COUNTIFS('Datos - Temas'!$V$5:$V$1264,$A34,'Datos - Temas'!$K$5:$K$1264,"FUERA")-_xlfn.COUNTIFS('Datos - Temas'!$V$5:$V$1264,$A34,'Datos - Temas'!$K$5:$K$1264,"PENDIENTE")} -> 85 | F34: {=IF(E34=0,0,D34/E34)} -> 0.10588235 | G34: 0.2 | H34: {=G34*E34} -> 17 | I34: {=H34-D34} -> 8 | J34: {=(G34-F34)*100} -> 9.4117647 | K34: {=IF(ABS(G34-F34)<=$H$2,"En meta",IF(I34>0,"Faltan "&FIXED(I34,0)&" temas","Sobran "&FIXED(-I34,0)&" temas"))} -> Faltan 8 temas | L34: {=MAX(D33/G33,D34/G34,D35/G35,D36/G36)} -> 145 | M34: {=MAX(0,ROUNDUP(G34*L34-D34,0))} -> 20 | N34: {=_xlfn.COUNTIFS('Datos - Temas'!$V$5:$V$1264,$A34,'Datos - Temas'!$K$5:$K$1264,"FUERA")} -> 6 | O34: {=ABS(F34-G34)} -> 0.094117647
A35: 7° | B35: TIMSS 2027 8.° | C35: Física | D35: {=_xlfn.COUNTIFS('Datos - Temas'!$V$5:$V$1264,$A35,'Datos - Temas'!$M$5:$M$1264,$C35)} -> 2 | E35: {=_xlfn.COUNTIFS('Datos - Temas'!$V$5:$V$1264,$A35)-_xlfn.COUNTIFS('Datos - Temas'!$V$5:$V$1264,$A35,'Datos - Temas'!$K$5:$K$1264,"FUERA")-_xlfn.COUNTIFS('Datos - Temas'!$V$5:$V$1264,$A35,'Datos - Temas'!$K$5:$K$1264,"PENDIENTE")} -> 85 | F35: {=IF(E35=0,0,D35/E35)} -> 0.023529412 | G35: 0.25 | H35: {=G35*E35} -> 21.25 | I35: {=H35-D35} -> 19.25 | J35: {=(G35-F35)*100} -> 22.647059 | K35: {=IF(ABS(G35-F35)<=$H$2,"En meta",IF(I35>0,"Faltan "&FIXED(I35,0)&" temas","Sobran "&FIXED(-I35,0)&" temas"))} -> Faltan 19 temas | L35: {=MAX(D33/G33,D34/G34,D35/G35,D36/G36)} -> 145 | M35: {=MAX(0,ROUNDUP(G35*L35-D35,0))} -> 35 | N35: {=_xlfn.COUNTIFS('Datos - Temas'!$V$5:$V$1264,$A35,'Datos - Temas'!$K$5:$K$1264,"FUERA")} -> 6 | O35: {=ABS(F35-G35)} -> 0.22647059
A36: 7° | B36: TIMSS 2027 8.° | C36: Ciencias de la Tierra | D36: {=_xlfn.COUNTIFS('Datos - Temas'!$V$5:$V$1264,$A36,'Datos - Temas'!$M$5:$M$1264,$C36)} -> 29 | E36: {=_xlfn.COUNTIFS('Datos - Temas'!$V$5:$V$1264,$A36)-_xlfn.COUNTIFS('Datos - Temas'!$V$5:$V$1264,$A36,'Datos - Temas'!$K$5:$K$1264,"FUERA")-_xlfn.COUNTIFS('Datos - Temas'!$V$5:$V$1264,$A36,'Datos - Temas'!$K$5:$K$1264,"PENDIENTE")} -> 85 | F36: {=IF(E36=0,0,D36/E36)} -> 0.34117647 | G36: 0.2 | H36: {=G36*E36} -> 17 | I36: {=H36-D36} -> -12 | J36: {=(G36-F36)*100} -> -14.117647 | K36: {=IF(ABS(G36-F36)<=$H$2,"En meta",IF(I36>0,"Faltan "&FIXED(I36,0)&" temas","Sobran "&FIXED(-I36,0)&" temas"))} -> Sobran 12 temas | L36: {=MAX(D33/G33,D34/G34,D35/G35,D36/G36)} -> 145 | M36: {=MAX(0,ROUNDUP(G36*L36-D36,0))} -> 0 | N36: {=_xlfn.COUNTIFS('Datos - Temas'!$V$5:$V$1264,$A36,'Datos - Temas'!$K$5:$K$1264,"FUERA")} -> 6 | O36: {=ABS(F36-G36)} -> 0.14117647
C37: Total del grupo | D37: {=SUM(D33:D36)} -> 85 | G37: {=SUM(G33:G36)} -> 1 | M37: {=SUM(M33:M36)} -> 61 | O37: {=1-SUM(O33:O36)/2} -> 0.67941176
A39: 8° | B39: TIMSS 2027 8.° | C39: Biología | D39: {=_xlfn.COUNTIFS('Datos - Temas'!$V$5:$V$1264,$A39,'Datos - Temas'!$M$5:$M$1264,$C39)} -> 27 | E39: {=_xlfn.COUNTIFS('Datos - Temas'!$V$5:$V$1264,$A39)-_xlfn.COUNTIFS('Datos - Temas'!$V$5:$V$1264,$A39,'Datos - Temas'!$K$5:$K$1264,"FUERA")-_xlfn.COUNTIFS('Datos - Temas'!$V$5:$V$1264,$A39,'Datos - Temas'!$K$5:$K$1264,"PENDIENTE")} -> 93 | F39: {=IF(E39=0,0,D39/E39)} -> 0.29032258 | G39: 0.35 | H39: {=G39*E39} -> 32.55 | I39: {=H39-D39} -> 5.55 | J39: {=(G39-F39)*100} -> 5.9677419 | K39: {=IF(ABS(G39-F39)<=$H$2,"En meta",IF(I39>0,"Faltan "&FIXED(I39,0)&" temas","Sobran "&FIXED(-I39,0)&" temas"))} -> Faltan 6 temas | L39: {=MAX(D39/G39,D40/G40,D41/G41,D42/G42)} -> 148 | M39: {=MAX(0,ROUNDUP(G39*L39-D39,0))} -> 25 | N39: {=_xlfn.COUNTIFS('Datos - Temas'!$V$5:$V$1264,$A39,'Datos - Temas'!$K$5:$K$1264,"FUERA")} -> 0 | O39: {=ABS(F39-G39)} -> 0.059677419
A40: 8° | B40: TIMSS 2027 8.° | C40: Química | D40: {=_xlfn.COUNTIFS('Datos - Temas'!$V$5:$V$1264,$A40,'Datos - Temas'!$M$5:$M$1264,$C40)} -> 25 | E40: {=_xlfn.COUNTIFS('Datos - Temas'!$V$5:$V$1264,$A40)-_xlfn.COUNTIFS('Datos - Temas'!$V$5:$V$1264,$A40,'Datos - Temas'!$K$5:$K$1264,"FUERA")-_xlfn.COUNTIFS('Datos - Temas'!$V$5:$V$1264,$A40,'Datos - Temas'!$K$5:$K$1264,"PENDIENTE")} -> 93 | F40: {=IF(E40=0,0,D40/E40)} -> 0.2688172 | G40: 0.2 | H40: {=G40*E40} -> 18.6 | I40: {=H40-D40} -> -6.4 | J40: {=(G40-F40)*100} -> -6.8817204 | K40: {=IF(ABS(G40-F40)<=$H$2,"En meta",IF(I40>0,"Faltan "&FIXED(I40,0)&" temas","Sobran "&FIXED(-I40,0)&" temas"))} -> Sobran 6 temas | L40: {=MAX(D39/G39,D40/G40,D41/G41,D42/G42)} -> 148 | M40: {=MAX(0,ROUNDUP(G40*L40-D40,0))} -> 5 | N40: {=_xlfn.COUNTIFS('Datos - Temas'!$V$5:$V$1264,$A40,'Datos - Temas'!$K$5:$K$1264,"FUERA")} -> 0 | O40: {=ABS(F40-G40)} -> 0.068817204
A41: 8° | B41: TIMSS 2027 8.° | C41: Física | D41: {=_xlfn.COUNTIFS('Datos - Temas'!$V$5:$V$1264,$A41,'Datos - Temas'!$M$5:$M$1264,$C41)} -> 37 | E41: {=_xlfn.COUNTIFS('Datos - Temas'!$V$5:$V$1264,$A41)-_xlfn.COUNTIFS('Datos - Temas'!$V$5:$V$1264,$A41,'Datos - Temas'!$K$5:$K$1264,"FUERA")-_xlfn.COUNTIFS('Datos - Temas'!$V$5:$V$1264,$A41,'Datos - Temas'!$K$5:$K$1264,"PENDIENTE")} -> 93 | F41: {=IF(E41=0,0,D41/E41)} -> 0.39784946 | G41: 0.25 | H41: {=G41*E41} -> 23.25 | I41: {=H41-D41} -> -13.75 | J41: {=(G41-F41)*100} -> -14.784946 | K41: {=IF(ABS(G41-F41)<=$H$2,"En meta",IF(I41>0,"Faltan "&FIXED(I41,0)&" temas","Sobran "&FIXED(-I41,0)&" temas"))} -> Sobran 14 temas | L41: {=MAX(D39/G39,D40/G40,D41/G41,D42/G42)} -> 148 | M41: {=MAX(0,ROUNDUP(G41*L41-D41,0))} -> 0 | N41: {=_xlfn.COUNTIFS('Datos - Temas'!$V$5:$V$1264,$A41,'Datos - Temas'!$K$5:$K$1264,"FUERA")} -> 0 | O41: {=ABS(F41-G41)} -> 0.14784946
A42: 8° | B42: TIMSS 2027 8.° | C42: Ciencias de la Tierra | D42: {=_xlfn.COUNTIFS('Datos - Temas'!$V$5:$V$1264,$A42,'Datos - Temas'!$M$5:$M$1264,$C42)} -> 4 | E42: {=_xlfn.COUNTIFS('Datos - Temas'!$V$5:$V$1264,$A42)-_xlfn.COUNTIFS('Datos - Temas'!$V$5:$V$1264,$A42,'Datos - Temas'!$K$5:$K$1264,"FUERA")-_xlfn.COUNTIFS('Datos - Temas'!$V$5:$V$1264,$A42,'Datos - Temas'!$K$5:$K$1264,"PENDIENTE")} -> 93 | F42: {=IF(E42=0,0,D42/E42)} -> 0.043010753 | G42: 0.2 | H42: {=G42*E42} -> 18.6 | I42: {=H42-D42} -> 14.6 | J42: {=(G42-F42)*100} -> 15.698925 | K42: {=IF(ABS(G42-F42)<=$H$2,"En meta",IF(I42>0,"Faltan "&FIXED(I42,0)&" temas","Sobran "&FIXED(-I42,0)&" temas"))} -> Faltan 15 temas | L42: {=MAX(D39/G39,D40/G40,D41/G41,D42/G42)} -> 148 | M42: {=MAX(0,ROUNDUP(G42*L42-D42,0))} -> 26 | N42: {=_xlfn.COUNTIFS('Datos - Temas'!$V$5:$V$1264,$A42,'Datos - Temas'!$K$5:$K$1264,"FUERA")} -> 0 | O42: {=ABS(F42-G42)} -> 0.15698925
C43: Total del grupo | D43: {=SUM(D39:D42)} -> 93 | G43: {=SUM(G39:G42)} -> 1 | M43: {=SUM(M39:M42)} -> 56 | O43: {=1-SUM(O39:O42)/2} -> 0.78333333
A45: Física 10° | B45: TIMSS Advanced 2015 Física | C45: Mecánica y termodinámica | D45: {=_xlfn.COUNTIFS('Datos - Temas'!$V$5:$V$1264,$A45,'Datos - Temas'!$M$5:$M$1264,$C45)} -> 67 | E45: {=_xlfn.COUNTIFS('Datos - Temas'!$V$5:$V$1264,$A45)-_xlfn.COUNTIFS('Datos - Temas'!$V$5:$V$1264,$A45,'Datos - Temas'!$K$5:$K$1264,"FUERA")-_xlfn.COUNTIFS('Datos - Temas'!$V$5:$V$1264,$A45,'Datos - Temas'!$K$5:$K$1264,"PENDIENTE")} -> 80 | F45: {=IF(E45=0,0,D45/E45)} -> 0.8375 | G45: 0.4 | H45: {=G45*E45} -> 32 | I45: {=H45-D45} -> -35 | J45: {=(G45-F45)*100} -> -43.75 | K45: {=IF(ABS(G45-F45)<=$H$2,"En meta",IF(I45>0,"Faltan "&FIXED(I45,0)&" temas","Sobran "&FIXED(-I45,0)&" temas"))} -> Sobran 35 temas | L45: {=MAX(D45/G45,D46/G46,D47/G47)} -> 167.5 | M45: {=MAX(0,ROUNDUP(G45*L45-D45,0))} -> 0 | N45: {=_xlfn.COUNTIFS('Datos - Temas'!$V$5:$V$1264,$A45,'Datos - Temas'!$K$5:$K$1264,"FUERA")} -> 41 | O45: {=ABS(F45-G45)} -> 0.4375
A46: Física 10° | B46: TIMSS Advanced 2015 Física | C46: Electricidad y magnetismo | D46: {=_xlfn.COUNTIFS('Datos - Temas'!$V$5:$V$1264,$A46,'Datos - Temas'!$M$5:$M$1264,$C46)} -> 0 | E46: {=_xlfn.COUNTIFS('Datos - Temas'!$V$5:$V$1264,$A46)-_xlfn.COUNTIFS('Datos - Temas'!$V$5:$V$1264,$A46,'Datos - Temas'!$K$5:$K$1264,"FUERA")-_xlfn.COUNTIFS('Datos - Temas'!$V$5:$V$1264,$A46,'Datos - Temas'!$K$5:$K$1264,"PENDIENTE")} -> 80 | F46: {=IF(E46=0,0,D46/E46)} -> 0 | G46: 0.25 | H46: {=G46*E46} -> 20 | I46: {=H46-D46} -> 20 | J46: {=(G46-F46)*100} -> 25 | K46: {=IF(ABS(G46-F46)<=$H$2,"En meta",IF(I46>0,"Faltan "&FIXED(I46,0)&" temas","Sobran "&FIXED(-I46,0)&" temas"))} -> Faltan 20 temas | L46: {=MAX(D45/G45,D46/G46,D47/G47)} -> 167.5 | M46: {=MAX(0,ROUNDUP(G46*L46-D46,0))} -> 42 | N46: {=_xlfn.COUNTIFS('Datos - Temas'!$V$5:$V$1264,$A46,'Datos - Temas'!$K$5:$K$1264,"FUERA")} -> 41 | O46: {=ABS(F46-G46)} -> 0.25
A47: Física 10° | B47: TIMSS Advanced 2015 Física | C47: Ondas y física atómica/nuclear | D47: {=_xlfn.COUNTIFS('Datos - Temas'!$V$5:$V$1264,$A47,'Datos - Temas'!$M$5:$M$1264,$C47)} -> 13 | E47: {=_xlfn.COUNTIFS('Datos - Temas'!$V$5:$V$1264,$A47)-_xlfn.COUNTIFS('Datos - Temas'!$V$5:$V$1264,$A47,'Datos - Temas'!$K$5:$K$1264,"FUERA")-_xlfn.COUNTIFS('Datos - Temas'!$V$5:$V$1264,$A47,'Datos - Temas'!$K$5:$K$1264,"PENDIENTE")} -> 80 | F47: {=IF(E47=0,0,D47/E47)} -> 0.1625 | G47: 0.35 | H47: {=G47*E47} -> 28 | I47: {=H47-D47} -> 15 | J47: {=(G47-F47)*100} -> 18.75 | K47: {=IF(ABS(G47-F47)<=$H$2,"En meta",IF(I47>0,"Faltan "&FIXED(I47,0)&" temas","Sobran "&FIXED(-I47,0)&" temas"))} -> Faltan 15 temas | L47: {=MAX(D45/G45,D46/G46,D47/G47)} -> 167.5 | M47: {=MAX(0,ROUNDUP(G47*L47-D47,0))} -> 46 | N47: {=_xlfn.COUNTIFS('Datos - Temas'!$V$5:$V$1264,$A47,'Datos - Temas'!$K$5:$K$1264,"FUERA")} -> 41 | O47: {=ABS(F47-G47)} -> 0.1875
C48: Total del grupo | D48: {=SUM(D45:D47)} -> 80 | G48: {=SUM(G45:G47)} -> 1 | M48: {=SUM(M45:M47)} -> 88 | O48: {=1-SUM(O45:O47)/2} -> 0.5625
A50: Física 11° | B50: TIMSS Advanced 2015 Física | C50: Mecánica y termodinámica | D50: {=_xlfn.COUNTIFS('Datos - Temas'!$V$5:$V$1264,$A50,'Datos - Temas'!$M$5:$M$1264,$C50)} -> 4 | E50: {=_xlfn.COUNTIFS('Datos - Temas'!$V$5:$V$1264,$A50)-_xlfn.COUNTIFS('Datos - Temas'!$V$5:$V$1264,$A50,'Datos - Temas'!$K$5:$K$1264,"FUERA")-_xlfn.COUNTIFS('Datos - Temas'!$V$5:$V$1264,$A50,'Datos - Temas'!$K$5:$K$1264,"PENDIENTE")} -> 119 | F50: {=IF(E50=0,0,D50/E50)} -> 0.033613445 | G50: 0.4 | H50: {=G50*E50} -> 47.6 | I50: {=H50-D50} -> 43.6 | J50: {=(G50-F50)*100} -> 36.638655 | K50: {=IF(ABS(G50-F50)<=$H$2,"En meta",IF(I50>0,"Faltan "&FIXED(I50,0)&" temas","Sobran "&FIXED(-I50,0)&" temas"))} -> Faltan 44 temas | L50: {=MAX(D50/G50,D51/G51,D52/G52)} -> 205.71429 | M50: {=MAX(0,ROUNDUP(G50*L50-D50,0))} -> 79 | N50: {=_xlfn.COUNTIFS('Datos - Temas'!$V$5:$V$1264,$A50,'Datos - Temas'!$K$5:$K$1264,"FUERA")} -> 27 | O50: {=ABS(F50-G50)} -> 0.36638655
A51: Física 11° | B51: TIMSS Advanced 2015 Física | C51: Electricidad y magnetismo | D51: {=_xlfn.COUNTIFS('Datos - Temas'!$V$5:$V$1264,$A51,'Datos - Temas'!$M$5:$M$1264,$C51)} -> 43 | E51: {=_xlfn.COUNTIFS('Datos - Temas'!$V$5:$V$1264,$A51)-_xlfn.COUNTIFS('Datos - Temas'!$V$5:$V$1264,$A51,'Datos - Temas'!$K$5:$K$1264,"FUERA")-_xlfn.COUNTIFS('Datos - Temas'!$V$5:$V$1264,$A51,'Datos - Temas'!$K$5:$K$1264,"PENDIENTE")} -> 119 | F51: {=IF(E51=0,0,D51/E51)} -> 0.36134454 | G51: 0.25 | H51: {=G51*E51} -> 29.75 | I51: {=H51-D51} -> -13.25 | J51: {=(G51-F51)*100} -> -11.134454 | K51: {=IF(ABS(G51-F51)<=$H$2,"En meta",IF(I51>0,"Faltan "&FIXED(I51,0)&" temas","Sobran "&FIXED(-I51,0)&" temas"))} -> Sobran 13 temas | L51: {=MAX(D50/G50,D51/G51,D52/G52)} -> 205.71429 | M51: {=MAX(0,ROUNDUP(G51*L51-D51,0))} -> 9 | N51: {=_xlfn.COUNTIFS('Datos - Temas'!$V$5:$V$1264,$A51,'Datos - Temas'!$K$5:$K$1264,"FUERA")} -> 27 | O51: {=ABS(F51-G51)} -> 0.11134454
A52: Física 11° | B52: TIMSS Advanced 2015 Física | C52: Ondas y física atómica/nuclear | D52: {=_xlfn.COUNTIFS('Datos - Temas'!$V$5:$V$1264,$A52,'Datos - Temas'!$M$5:$M$1264,$C52)} -> 72 | E52: {=_xlfn.COUNTIFS('Datos - Temas'!$V$5:$V$1264,$A52)-_xlfn.COUNTIFS('Datos - Temas'!$V$5:$V$1264,$A52,'Datos - Temas'!$K$5:$K$1264,"FUERA")-_xlfn.COUNTIFS('Datos - Temas'!$V$5:$V$1264,$A52,'Datos - Temas'!$K$5:$K$1264,"PENDIENTE")} -> 119 | F52: {=IF(E52=0,0,D52/E52)} -> 0.60504202 | G52: 0.35 | H52: {=G52*E52} -> 41.65 | I52: {=H52-D52} -> -30.35 | J52: {=(G52-F52)*100} -> -25.504202 | K52: {=IF(ABS(G52-F52)<=$H$2,"En meta",IF(I52>0,"Faltan "&FIXED(I52,0)&" temas","Sobran "&FIXED(-I52,0)&" temas"))} -> Sobran 30 temas | L52: {=MAX(D50/G50,D51/G51,D52/G52)} -> 205.71429 | M52: {=MAX(0,ROUNDUP(G52*L52-D52,0))} -> 1 | N52: {=_xlfn.COUNTIFS('Datos - Temas'!$V$5:$V$1264,$A52,'Datos - Temas'!$K$5:$K$1264,"FUERA")} -> 27 | O52: {=ABS(F52-G52)} -> 0.25504202
C53: Total del grupo | D53: {=SUM(D50:D52)} -> 119 | G53: {=SUM(G50:G52)} -> 1 | M53: {=SUM(M50:M52)} -> 89 | O53: {=1-SUM(O50:O52)/2} -> 0.63361345
A55: Cómo se calcula: Cómo leerlo: «% actual» = temas del dominio ÷ temas evaluables del grado (se excluyen los «fuera del marco»). «Brecha (temas)» = meta × evaluables − actuales: positivo = faltan temas en ese dominio si se redistribuye la misma carga; negativo = sobran. «Temas a AGREGAR» = cuántos temas habría que sumar a cada dominio para cumplir todas las metas SIN quitar ninguno (la escala la fija el dominio más sobrerrepresentado). Ojo: TIMSS fija pesos para la prueba acumulada (4.° y 8.°); aplicarlos a cada grado es una aproximación. La hoja TIMSS - Balance por ciclo hace la comparación acumulada.

Sheet TIMSS - Semáforo de objetivos
A1: Amplitud: ¿qué objetivos TIMSS cubre la malla y en qué grado?
A2: {="TIMSS 2027 (2.°–8.°) y TIMSS Advanced (Física)"&" "&IF(COUNTIF($R$5:$R$107,"No cubierto")=0,"BIEN · ","OJO · ")&"Rojo: "&COUNTIF($R$5:$R$107,"No cubierto")&" objetivos de TIMSS sin ningún tema. Amarillo: "&COUNTIF($R$5:$R$107,"Débil (1 tema)")&" con un solo tema."&" "&"● Cubiertos: "&COUNTIF($Q$5:$Q$107,"Sí")&" de "&ROWS($Q$5:$Q$107)&" objetivos. «N/A» = ese grado no lo evalúa ese TIMSS (no es un problema)."&" "&"→ Filtra «Estado» por rojo o amarillo; la última columna dice qué hacer. Lo de PISA está en «PISA - Contenidos»."} -> TIMSS 2027 (2.°–8.°) y TIMSS Advanced (Física) OJO · Rojo: 4 objetivos de TIMSS sin ningún tema. Amarillo: 7 con un solo tema. ● Cubiertos: 99 de 103 objetivos. «N/A» = ese grado no lo evalúa ese TIMSS (no es un problema). → Filtra «Estado» por rojo o amarillo; la última columna dice qué hacer. Lo de PISA está en «PISA - Contenidos».
A4: Código | B4: Marco | C4: Dominio | D4: Área temática | E4: Objetivo | F4: 2° | G4: 3° | H4: 4° | I4: 5° | J4: 6° | K4: 7° | L4: 8° | M4: Física 10° | N4: Física 11° | O4: Total temas en su ciclo | P4: Como principal (todos los grados) | Q4: Estado en su ciclo (semáforo) | R4: Primer grado donde aparece (en su ciclo) | S4: Qué hacer · dónde aparece hoy
A5: T4_27-B1.1 | B5: T4_27 | C5: Biología | D5: Características y procesos vitales de los organismos | E5: Diferencias entre seres vivos y no vivos, y lo que los seres vivos necesitan para vivir | F5: {=_xlfn.COUNTIFS('Datos - Temas'!$V$5:$V$1264,F$4,'Datos - Temas'!$K$5:$K$1264,$A5)+_xlfn.COUNTIFS('Datos - Temas'!$V$5:$V$1264,F$4,'Datos - Temas'!$L$5:$L$1264,$A5)} -> 5 | G5: {=_xlfn.COUNTIFS('Datos - Temas'!$V$5:$V$1264,G$4,'Datos - Temas'!$K$5:$K$1264,$A5)+_xlfn.COUNTIFS('Datos - Temas'!$V$5:$V$1264,G$4,'Datos - Temas'!$L$5:$L$1264,$A5)} -> 5 | H5: {=_xlfn.COUNTIFS('Datos - Temas'!$V$5:$V$1264,H$4,'Datos - Temas'!$K$5:$K$1264,$A5)+_xlfn.COUNTIFS('Datos - Temas'!$V$5:$V$1264,H$4,'Datos - Temas'!$L$5:$L$1264,$A5)} -> 3 | I5: N/A | J5: N/A | K5: N/A | L5: N/A | M5: N/A | N5: N/A | O5: 13 | P5: {=_xlfn.COUNTIFS('Datos - Temas'!$K$5:$K$1264,$A5)} -> 9 | Q5: {=IF(O5>0,"Sí","No")} -> Sí | R5: {=IF(O5=0,"No cubierto",IF(O5=1,"Débil (1 tema)",IF(O5<=3,"Básica (2–3)","Sólida (4+)")))} -> Sólida (4+) | S5: {=_xlfn.IFERROR(INDEX($F$4:$H$4,MATCH(TRUE,INDEX(F5:H5>0,0),0)),"—")} -> 2° | T5: Hoy: 2° U4 (3); 2° U5 (2); 3° U2 (1); 3° U3 (1); 3° U5 (1); 3° U6 (2); 4° U2 (1); 4° U3 (2)
A6: T4_27-B1.2 | B6: T4_27 | C6: Biología | D6: Características y procesos vitales de los organismos | E6: Rasgos físicos y de conducta de los grandes grupos de seres vivos | F6: {=_xlfn.COUNTIFS('Datos - Temas'!$V$5:$V$1264,F$4,'Datos - Temas'!$K$5:$K$1264,$A6)+_xlfn.COUNTIFS('Datos - Temas'!$V$5:$V$1264,F$4,'Datos - Temas'!$L$5:$L$1264,$A6)} -> 5 | G6: {=_xlfn.COUNTIFS('Datos - Temas'!$V$5:$V$1264,G$4,'Datos - Temas'!$K$5:$K$1264,$A6)+_xlfn.COUNTIFS('Datos - Temas'!$V$5:$V$1264,G$4,'Datos - Temas'!$L$5:$L$1264,$A6)} -> 13 | H6: {=_xlfn.COUNTIFS('Datos - Temas'!$V$5:$V$1264,H$4,'Datos - Temas'!$K$5:$K$1264,$A6)+_xlfn.COUNTIFS('Datos - Temas'!$V$5:$V$1264,H$4,'Datos - Temas'!$L$5:$L$1264,$A6)} -> 0 | I6: N/A | J6: N/A | K6: N/A | L6: N/A | M6: N/A | N6: N/A | O6: 18 | P6: {=_xlfn.COUNTIFS('Datos - Temas'!$K$5:$K$1264,$A6)} -> 17 | Q6: {=IF(O6>0,"Sí","No")} -> Sí | R6: {=IF(O6=0,"No cubierto",IF(O6=1,"Débil (1 tema)",IF(O6<=3,"Básica (2–3)","Sólida (4+)")))} -> Sólida (4+) | S6: {=_xlfn.IFERROR(INDEX($F$4:$H$4,MATCH(TRUE,INDEX(F6:H6>0,0),0)),"—")} -> 2° | T6: Hoy: 2° U4 (5); 3° U4 (3); 3° U5 (9); 3° U6 (1)
A7: T4_27-B1.3 | B7: T4_27 | C7: Biología | D7: Características y procesos vitales de los organismos | E7: Funciones de las estructuras principales de animales y plantas | F7: {=_xlfn.COUNTIFS('Datos - Temas'!$V$5:$V$1264,F$4,'Datos - Temas'!$K$5:$K$1264,$A7)+_xlfn.COUNTIFS('Datos - Temas'!$V$5:$V$1264,F$4,'Datos - Temas'!$L$5:$L$1264,$A7)} -> 1 | G7: {=_xlfn.COUNTIFS('Datos - Temas'!$V$5:$V$1264,G$4,'Datos - Temas'!$K$5:$K$1264,$A7)+_xlfn.COUNTIFS('Datos - Temas'!$V$5:$V$1264,G$4,'Datos - Temas'!$L$5:$L$1264,$A7)} -> 5 | H7: {=_xlfn.COUNTIFS('Datos - Temas'!$V$5:$V$1264,H$4,'Datos - Temas'!$K$5:$K$1264,$A7)+_xlfn.COUNTIFS('Datos - Temas'!$V$5:$V$1264,H$4,'Datos - Temas'!$L$5:$L$1264,$A7)} -> 18 | I7: N/A | J7: N/A | K7: N/A | L7: N/A | M7: N/A | N7: N/A | O7: 24 | P7: {=_xlfn.COUNTIFS('Datos - Temas'!$K$5:$K$1264,$A7)} -> 23 | Q7: {=IF(O7>0,"Sí","No")} -> Sí | R7: {=IF(O7=0,"No cubierto",IF(O7=1,"Débil (1 tema)",IF(O7<=3,"Básica (2–3)","Sólida (4+)")))} -> Sólida (4+) | S7: {=_xlfn.IFERROR(INDEX($F$4:$H$4,MATCH(TRUE,INDEX(F7:H7>0,0),0)),"—")} -> 2° | T7: Hoy: 2° U4 (1); 3° U4 (4); 3° U5 (1); 4° U5 (9); 4° U6 (9)
A8: T4_27-B1.4 | B8: T4_27 | C8: Biología | D8: Características y procesos vitales de los organismos | E8: Obtención de alimento y respuesta de los seres vivos a cambios externos | F8: {=_xlfn.COUNTIFS('Datos - Temas'!$V$5:$V$1264,F$4,'Datos - Temas'!$K$5:$K$1264,$A8)+_xlfn.COUNTIFS('Datos - Temas'!$V$5:$V$1264,F$4,'Datos - Temas'!$L$5:$L$1264,$A8)} -> 2 | G8: {=_xlfn.COUNTIFS('Datos - Temas'!$V$5:$V$1264,G$4,'Datos - Temas'!$K$5:$K$1264,$A8)+_xlfn.COUNTIFS('Datos - Temas'!$V$5:$V$1264,G$4,'Datos - Temas'!$L$5:$L$1264,$A8)} -> 5 | H8: {=_xlfn.COUNTIFS('Datos - Temas'!$V$5:$V$1264,H$4,'Datos - Temas'!$K$5:$K$1264,$A8)+_xlfn.COUNTIFS('Datos - Temas'!$V$5:$V$1264,H$4,'Datos - Temas'!$L$5:$L$1264,$A8)} -> 3 | I8: N/A | J8: N/A | K8: N/A | L8: N/A | M8: N/A | N8: N/A | O8: 10 | P8: {=_xlfn.COUNTIFS('Datos - Temas'!$K$5:$K$1264,$A8)} -> 5 | Q8: {=IF(O8>0,"Sí","No")} -> Sí | R8: {=IF(O8=0,"No cubierto",IF(O8=1,"Débil (1 tema)",IF(O8<=3,"Básica (2–3)","Sólida (4+)")))} -> Sólida (4+) | S8: {=_xlfn.IFERROR(INDEX($F$4:$H$4,MATCH(TRUE,INDEX(F8:H8>0,0),0)),"—")} -> 2° | T8: Hoy: 2° U4 (2); 3° U4 (3); 3° U5 (2); 4° U5 (2); 4° U6 (1)
A9: T4_27-B2.1 | B9: T4_27 | C9: Biología | D9: Ciclos de vida, reproducción y herencia | E9: Etapas y diferencias de los ciclos de vida de plantas y animales comunes | F9: {=_xlfn.COUNTIFS('Datos - Temas'!$V$5:$V$1264,F$4,'Datos - Temas'!$K$5:$K$1264,$A9)+_xlfn.COUNTIFS('Datos - Temas'!$V$5:$V$1264,F$4,'Datos - Temas'!$L$5:$L$1264,$A9)} -> 1 | G9: {=_xlfn.COUNTIFS('Datos - Temas'!$V$5:$V$1264,G$4,'Datos - Temas'!$K$5:$K$1264,$A9)+_xlfn.COUNTIFS('Datos - Temas'!$V$5:$V$1264,G$4,'Datos - Temas'!$L$5:$L$1264,$A9)} -> 1 | H9: {=_xlfn.COUNTIFS('Datos - Temas'!$V$5:$V$1264,H$4,'Datos - Temas'!$K$5:$K$1264,$A9)+_xlfn.COUNTIFS('Datos - Temas'!$V$5:$V$1264,H$4,'Datos - Temas'!$L$5:$L$1264,$A9)} -> 0 | I9: N/A | J9: N/A | K9: N/A | L9: N/A | M9: N/A | N9: N/A | O9: 2 | P9: {=_xlfn.COUNTIFS('Datos - Temas'!$K$5:$K$1264,$A9)} -> 2 | Q9: {=IF(O9>0,"Sí","No")} -> Sí | R9: {=IF(O9=0,"No cubierto",IF(O9=1,"Débil (1 tema)",IF(O9<=3,"Básica (2–3)","Sólida (4+)")))} -> Básica (2–3) | S9: {=_xlfn.IFERROR(INDEX($F$4:$H$4,MATCH(TRUE,INDEX(F9:H9>0,0),0)),"—")} -> 2° | T9: Hoy: 2° U4 (1); 3° U5 (1) · Propuesta 2-4-I20 (Presupuesto): 3.° · Comparación de rasgos heredados y no heredados entre crías y progenitores, y de estrategias que favorecen la supervivencia de la descendencia (muchas semillas, cuidado de crías).
A10: T4_27-B2.2 | B10: T4_27 | C10: Biología | D10: Ciclos de vida, reproducción y herencia | E10: Herencia y estrategias de reproducción | F10: {=_xlfn.COUNTIFS('Datos - Temas'!$V$5:$V$1264,F$4,'Datos - Temas'!$K$5:$K$1264,$A10)+_xlfn.COUNTIFS('Datos - Temas'!$V$5:$V$1264,F$4,'Datos - Temas'!$L$5:$L$1264,$A10)} -> 0 | G10: {=_xlfn.COUNTIFS('Datos - Temas'!$V$5:$V$1264,G$4,'Datos - Temas'!$K$5:$K$1264,$A10)+_xlfn.COUNTIFS('Datos - Temas'!$V$5:$V$1264,G$4,'Datos - Temas'!$L$5:$L$1264,$A10)} -> 0 | H10: {=_xlfn.COUNTIFS('Datos - Temas'!$V$5:$V$1264,H$4,'Datos - Temas'!$K$5:$K$1264,$A10)+_xlfn.COUNTIFS('Datos - Temas'!$V$5:$V$1264,H$4,'Datos - Temas'!$L$5:$L$1264,$A10)} -> 0 | I10: N/A | J10: N/A | K10: N/A | L10: N/A | M10: N/A | N10: N/A | O10: 0 | P10: {=_xlfn.COUNTIFS('Datos - Temas'!$K$5:$K$1264,$A10)} -> 0 | Q10: {=IF(O10>0,"Sí","No")} -> No | R10: {=IF(O10=0,"No cubierto",IF(O10=1,"Débil (1 tema)",IF(O10<=3,"Básica (2–3)","Sólida (4+)")))} -> No cubierto | S10: {=_xlfn.IFERROR(INDEX($F$4:$H$4,MATCH(TRUE,INDEX(F10:H10>0,0),0)),"—")} -> — | T10: Hoy: ningún tema de 2.°–9.° lo trabaja. · Propuesta 2-4-I20 (Presupuesto): 3.° · Comparación de rasgos heredados y no heredados entre crías y progenitores, y de estrategias que favorecen la supervivencia de la descendencia (muchas semillas, cuidado de crías).
A11: T4_27-B3.1 | B11: T4_27 | C11: Biología | D11: Diversidad y adaptación | E11: Rasgos físicos y conductas que ayudan a sobrevivir en el ambiente | F11: {=_xlfn.COUNTIFS('Datos - Temas'!$V$5:$V$1264,F$4,'Datos - Temas'!$K$5:$K$1264,$A11)+_xlfn.COUNTIFS('Datos - Temas'!$V$5:$V$1264,F$4,'Datos - Temas'!$L$5:$L$1264,$A11)} -> 2 | G11: {=_xlfn.COUNTIFS('Datos - Temas'!$V$5:$V$1264,G$4,'Datos - Temas'!$K$5:$K$1264,$A11)+_xlfn.COUNTIFS('Datos - Temas'!$V$5:$V$1264,G$4,'Datos - Temas'!$L$5:$L$1264,$A11)} -> 0 | H11: {=_xlfn.COUNTIFS('Datos - Temas'!$V$5:$V$1264,H$4,'Datos - Temas'!$K$5:$K$1264,$A11)+_xlfn.COUNTIFS('Datos - Temas'!$V$5:$V$1264,H$4,'Datos - Temas'!$L$5:$L$1264,$A11)} -> 0 | I11: N/A | J11: N/A | K11: N/A | L11: N/A | M11: N/A | N11: N/A | O11: 2 | P11: {=_xlfn.COUNTIFS('Datos - Temas'!$K$5:$K$1264,$A11)} -> 1 | Q11: {=IF(O11>0,"Sí","No")} -> Sí | R11: {=IF(O11=0,"No cubierto",IF(O11=1,"Débil (1 tema)",IF(O11<=3,"Básica (2–3)","Sólida (4+)")))} -> Básica (2–3) | S11: {=_xlfn.IFERROR(INDEX($F$4:$H$4,MATCH(TRUE,INDEX(F11:H11>0,0),0)),"—")} -> 2° | T11: Hoy: 2° U4 (2)
A12: T4_27-B4.1 | B12: T4_27 | C12: Biología | D12: Ecosistemas | E12: Ecosistemas comunes | F12: {=_xlfn.COUNTIFS('Datos - Temas'!$V$5:$V$1264,F$4,'Datos - Temas'!$K$5:$K$1264,$A12)+_xlfn.COUNTIFS('Datos - Temas'!$V$5:$V$1264,F$4,'Datos - Temas'!$L$5:$L$1264,$A12)} -> 3 | G12: {=_xlfn.COUNTIFS('Datos - Temas'!$V$5:$V$1264,G$4,'Datos - Temas'!$K$5:$K$1264,$A12)+_xlfn.COUNTIFS('Datos - Temas'!$V$5:$V$1264,G$4,'Datos - Temas'!$L$5:$L$1264,$A12)} -> 0 | H12: {=_xlfn.COUNTIFS('Datos - Temas'!$V$5:$V$1264,H$4,'Datos - Temas'!$K$5:$K$1264,$A12)+_xlfn.COUNTIFS('Datos - Temas'!$V$5:$V$1264,H$4,'Datos - Temas'!$L$5:$L$1264,$A12)} -> 5 | I12: N/A | J12: N/A | K12: N/A | L12: N/A | M12: N/A | N12: N/A | O12: 8 | P12: {=_xlfn.COUNTIFS('Datos - Temas'!$K$5:$K$1264,$A12)} -> 7 | Q12: {=IF(O12>0,"Sí","No")} -> Sí | R12: {=IF(O12=0,"No cubierto",IF(O12=1,"Débil (1 tema)",IF(O12<=3,"Básica (2–3)","Sólida (4+)")))} -> Sólida (4+) | S12: {=_xlfn.IFERROR(INDEX($F$4:$H$4,MATCH(TRUE,INDEX(F12:H12>0,0),0)),"—")} -> 2° | T12: Hoy: 2° U4 (3); 4° U3 (5)
A13: T4_27-B4.2 | B13: T4_27 | C13: Biología | D13: Ecosistemas | E13: Relaciones en los ecosistemas | F13: {=_xlfn.COUNTIFS('Datos - Temas'!$V$5:$V$1264,F$4,'Datos - Temas'!$K$5:$K$1264,$A13)+_xlfn.COUNTIFS('Datos - Temas'!$V$5:$V$1264,F$4,'Datos - Temas'!$L$5:$L$1264,$A13)} -> 0 | G13: {=_xlfn.COUNTIFS('Datos - Temas'!$V$5:$V$1264,G$4,'Datos - Temas'!$K$5:$K$1264,$A13)+_xlfn.COUNTIFS('Datos - Temas'!$V$5:$V$1264,G$4,'Datos - Temas'!$L$5:$L$1264,$A13)} -> 1 | H13: {=_xlfn.COUNTIFS('Datos - Temas'!$V$5:$V$1264,H$4,'Datos - Temas'!$K$5:$K$1264,$A13)+_xlfn.COUNTIFS('Datos - Temas'!$V$5:$V$1264,H$4,'Datos - Temas'!$L$5:$L$1264,$A13)} -> 4 | I13: N/A | J13: N/A | K13: N/A | L13: N/A | M13: N/A | N13: N/A | O13: 5 | P13: {=_xlfn.COUNTIFS('Datos - Temas'!$K$5:$K$1264,$A13)} -> 4 | Q13: {=IF(O13>0,"Sí","No")} -> Sí | R13: {=IF(O13=0,"No cubierto",IF(O13=1,"Débil (1 tema)",IF(O13<=3,"Básica (2–3)","Sólida (4+)")))} -> Sólida (4+) | S13: {=_xlfn.IFERROR(INDEX($F$4:$H$4,MATCH(TRUE,INDEX(F13:H13>0,0),0)),"—")} -> 3° | T13: Hoy: 3° U6 (1); 4° U3 (4)
A14: T4_27-B4.3 | B14: T4_27 | C14: Biología | D14: Ecosistemas | E14: Impacto humano en los ecosistemas | F14: {=_xlfn.COUNTIFS('Datos - Temas'!$V$5:$V$1264,F$4,'Datos - Temas'!$K$5:$K$1264,$A14)+_xlfn.COUNTIFS('Datos - Temas'!$V$5:$V$1264,F$4,'Datos - Temas'!$L$5:$L$1264,$A14)} -> 5 | G14: {=_xlfn.COUNTIFS('Datos - Temas'!$V$5:$V$1264,G$4,'Datos - Temas'!$K$5:$K$1264,$A14)+_xlfn.COUNTIFS('Datos - Temas'!$V$5:$V$1264,G$4,'Datos - Temas'!$L$5:$L$1264,$A14)} -> 1 | H14: {=_xlfn.COUNTIFS('Datos - Temas'!$V$5:$V$1264,H$4,'Datos - Temas'!$K$5:$K$1264,$A14)+_xlfn.COUNTIFS('Datos - Temas'!$V$5:$V$1264,H$4,'Datos - Temas'!$L$5:$L$1264,$A14)} -> 0 | I14: N/A | J14: N/A | K14: N/A | L14: N/A | M14: N/A | N14: N/A | O14: 6 | P14: {=_xlfn.COUNTIFS('Datos - Temas'!$K$5:$K$1264,$A14)} -> 4 | Q14: {=IF(O14>0,"Sí","No")} -> Sí | R14: {=IF(O14=0,"No cubierto",IF(O14=1,"Débil (1 tema)",IF(O14<=3,"Básica (2–3)","Sólida (4+)")))} -> Sólida (4+) | S14: {=_xlfn.IFERROR(INDEX($F$4:$H$4,MATCH(TRUE,INDEX(F14:H14>0,0),0)),"—")} -> 2° | T14: Hoy: 2° U4 (1); 2° U5 (1); 2° U6 (3); 3° U3 (1)
A15: T4_27-B5.1 | B15: T4_27 | C15: Biología | D15: Salud humana | E15: Transmisión y prevención de enfermedades | F15: {=_xlfn.COUNTIFS('Datos - Temas'!$V$5:$V$1264,F$4,'Datos - Temas'!$K$5:$K$1264,$A15)+_xlfn.COUNTIFS('Datos - Temas'!$V$5:$V$1264,F$4,'Datos - Temas'!$L$5:$L$1264,$A15)} -> 3 | G15: {=_xlfn.COUNTIFS('Datos - Temas'!$V$5:$V$1264,G$4,'Datos - Temas'!$K$5:$K$1264,$A15)+_xlfn.COUNTIFS('Datos - Temas'!$V$5:$V$1264,G$4,'Datos - Temas'!$L$5:$L$1264,$A15)} -> 5 | H15: {=_xlfn.COUNTIFS('Datos - Temas'!$V$5:$V$1264,H$4,'Datos - Temas'!$K$5:$K$1264,$A15)+_xlfn.COUNTIFS('Datos - Temas'!$V$5:$V$1264,H$4,'Datos - Temas'!$L$5:$L$1264,$A15)} -> 1 | I15: N/A | J15: N/A | K15: N/A | L15: N/A | M15: N/A | N15: N/A | O15: 9 | P15: {=_xlfn.COUNTIFS('Datos - Temas'!$K$5:$K$1264,$A15)} -> 8 | Q15: {=IF(O15>0,"Sí","No")} -> Sí | R15: {=IF(O15=0,"No cubierto",IF(O15=1,"Débil (1 tema)",IF(O15<=3,"Básica (2–3)","Sólida (4+)")))} -> Sólida (4+) | S15: {=_xlfn.IFERROR(INDEX($F$4:$H$4,MATCH(TRUE,INDEX(F15:H15>0,0),0)),"—")} -> 2° | T15: Hoy: 2° U6 (3); 3° U6 (5); 4° U2 (1)
A16: T4_27-B5.2 | B16: T4_27 | C16: Biología | D16: Salud humana | E16: Hábitos para mantener una buena salud | F16: {=_xlfn.COUNTIFS('Datos - Temas'!$V$5:$V$1264,F$4,'Datos - Temas'!$K$5:$K$1264,$A16)+_xlfn.COUNTIFS('Datos - Temas'!$V$5:$V$1264,F$4,'Datos - Temas'!$L$5:$L$1264,$A16)} -> 1 | G16: {=_xlfn.COUNTIFS('Datos - Temas'!$V$5:$V$1264,G$4,'Datos - Temas'!$K$5:$K$1264,$A16)+_xlfn.COUNTIFS('Datos - Temas'!$V$5:$V$1264,G$4,'Datos - Temas'!$L$5:$L$1264,$A16)} -> 0 | H16: {=_xlfn.COUNTIFS('Datos - Temas'!$V$5:$V$1264,H$4,'Datos - Temas'!$K$5:$K$1264,$A16)+_xlfn.COUNTIFS('Datos - Temas'!$V$5:$V$1264,H$4,'Datos - Temas'!$L$5:$L$1264,$A16)} -> 13 | I16: N/A | J16: N/A | K16: N/A | L16: N/A | M16: N/A | N16: N/A | O16: 14 | P16: {=_xlfn.COUNTIFS('Datos - Temas'!$K$5:$K$1264,$A16)} -> 12 | Q16: {=IF(O16>0,"Sí","No")} -> Sí | R16: {=IF(O16=0,"No cubierto",IF(O16=1,"Débil (1 tema)",IF(O16<=3,"Básica (2–3)","Sólida (4+)")))} -> Sólida (4+) | S16: {=_xlfn.IFERROR(INDEX($F$4:$H$4,MATCH(TRUE,INDEX(F16:H16>0,0),0)),"—")} -> 2° | T16: Hoy: 2° U6 (1); 4° U2 (10); 4° U5 (2); 4° U6 (1)
... A36: T4_27-E5.1 | B36: T4_27 | C36: Ciencias de la Tierra | D36: Investigaciones en ciencias de la Tierra | E36: Uso de equipo en investigaciones de ciencias de la Tierra | F36: {=_xlfn.COUNTIFS('Datos - Temas'!$V$5:$V$1264,F$4,'Datos - Temas'!$K$5:$K$1264,$A36)+_xlfn.COUNTIFS('Datos - Temas'!$V$5:$V$1264,F$4,'Datos - Temas'!$L$5:$L$1264,$A36)} -> 0 | G36: {=_xlfn.COUNTIFS('Datos - Temas'!$V$5:$V$1264,G$4,'Datos - Temas'!$K$5:$K$1264,$A36)+_xlfn.COUNTIFS('Datos - Temas'!$V$5:$V$1264,G$4,'Datos - Temas'!$L$5:$L$1264,$A36)} -> 0 | H36: {=_xlfn.COUNTIFS('Datos - Temas'!$V$5:$V$1264,H$4,'Datos - Temas'!$K$5:$K$1264,$A36)+_xlfn.COUNTIFS('Datos - Temas'!$V$5:$V$1264,H$4,'Datos - Temas'!$L$5:$L$1264,$A36)} -> 1 | I36: N/A | J36: N/A | K36: N/A | L36: N/A | M36: N/A | N36: N/A | O36: 1 | P36: {=_xlfn.COUNTIFS('Datos - Temas'!$K$5:$K$1264,$A36)} -> 0 | Q36: {=IF(O36>0,"Sí","No")} -> Sí | R36: {=IF(O36=0,"No cubierto",IF(O36=1,"Débil (1 tema)",IF(O36<=3,"Básica (2–3)","Sólida (4+)")))} -> Débil (1 tema) | S36: {=_xlfn.IFERROR(INDEX($F$4:$H$4,MATCH(TRUE,INDEX(F36:H36>0,0),0)),"—")} -> 4° | T36: Hoy: 4° U4 (1) · Propuesta 2-4-I13 (Presupuesto): 2.° · Registro diario del estado del tiempo (temperatura, lluvia, nubes y viento) con símbolos y un termómetro sencillo.
A37: T8_27-B1.1 | B37: T8_27 | C37: Biología | D37: Características y procesos vitales de los organismos | E37: Diferencias entre los grandes grupos taxonómicos | F37: N/A | G37: N/A | H37: N/A | I37: {=_xlfn.COUNTIFS('Datos - Temas'!$V$5:$V$1264,I$4,'Datos - Temas'!$K$5:$K$1264,$A37)+_xlfn.COUNTIFS('Datos - Temas'!$V$5:$V$1264,I$4,'Datos - Temas'!$L$5:$L$1264,$A37)} -> 0 | J37: {=_xlfn.COUNTIFS('Datos - Temas'!$V$5:$V$1264,J$4,'Datos - Temas'!$K$5:$K$1264,$A37)+_xlfn.COUNTIFS('Datos - Temas'!$V$5:$V$1264,J$4,'Datos - Temas'!$L$5:$L$1264,$A37)} -> 1 | K37: {=_xlfn.COUNTIFS('Datos - Temas'!$V$5:$V$1264,K$4,'Datos - Temas'!$K$5:$K$1264,$A37)+_xlfn.COUNTIFS('Datos - Temas'!$V$5:$V$1264,K$4,'Datos - Temas'!$L$5:$L$1264,$A37)} -> 11 | L37: {=_xlfn.COUNTIFS('Datos - Temas'!$V$5:$V$1264,L$4,'Datos - Temas'!$K$5:$K$1264,$A37)+_xlfn.COUNTIFS('Datos - Temas'!$V$5:$V$1264,L$4,'Datos - Temas'!$L$5:$L$1264,$A37)} -> 0 | M37: N/A | N37: N/A | O37: 12 | P37: {=_xlfn.COUNTIFS('Datos - Temas'!$K$5:$K$1264,$A37)} -> 9 | Q37: {=IF(O37>0,"Sí","No")} -> Sí | R37: {=IF(O37=0,"No cubierto",IF(O37=1,"Débil (1 tema)",IF(O37<=3,"Básica (2–3)","Sólida (4+)")))} -> Sólida (4+) | S37: {=_xlfn.IFERROR(INDEX($I$4:$L$4,MATCH(TRUE,INDEX(I37:L37>0,0),0)),"—")} -> 6° | T37: Hoy: 6° U5 (1); 7° U3 (11)
A38: T8_27-B1.2 | B38: T8_27 | C38: Biología | D38: Características y procesos vitales de los organismos | E38: Estructura y función de los principales sistemas de órganos | F38: N/A | G38: N/A | H38: N/A | I38: {=_xlfn.COUNTIFS('Datos - Temas'!$V$5:$V$1264,I$4,'Datos - Temas'!$K$5:$K$1264,$A38)+_xlfn.COUNTIFS('Datos - Temas'!$V$5:$V$1264,I$4,'Datos - Temas'!$L$5:$L$1264,$A38)} -> 0 | J38: {=_xlfn.COUNTIFS('Datos - Temas'!$V$5:$V$1264,J$4,'Datos - Temas'!$K$5:$K$1264,$A38)+_xlfn.COUNTIFS('Datos - Temas'!$V$5:$V$1264,J$4,'Datos - Temas'!$L$5:$L$1264,$A38)} -> 1 | K38: {=_xlfn.COUNTIFS('Datos - Temas'!$V$5:$V$1264,K$4,'Datos - Temas'!$K$5:$K$1264,$A38)+_xlfn.COUNTIFS('Datos - Temas'!$V$5:$V$1264,K$4,'Datos - Temas'!$L$5:$L$1264,$A38)} -> 0 | L38: {=_xlfn.COUNTIFS('Datos - Temas'!$V$5:$V$1264,L$4,'Datos - Temas'!$K$5:$K$1264,$A38)+_xlfn.COUNTIFS('Datos - Temas'!$V$5:$V$1264,L$4,'Datos - Temas'!$L$5:$L$1264,$A38)} -> 14 | M38: N/A | N38: N/A | O38: 15 | P38: {=_xlfn.COUNTIFS('Datos - Temas'!$K$5:$K$1264,$A38)} -> 14 | Q38: {=IF(O38>0,"Sí","No")} -> Sí | R38: {=IF(O38=0,"No cubierto",IF(O38=1,"Débil (1 tema)",IF(O38<=3,"Básica (2–3)","Sólida (4+)")))} -> Sólida (4+) | S38: {=_xlfn.IFERROR(INDEX($I$4:$L$4,MATCH(TRUE,INDEX(I38:L38>0,0),0)),"—")} -> 6° | T38: Hoy: 6° U5 (1); 8° U6 (2); 8° U7 (12) · Propuesta 5-8-I04 (Presupuesto): 8.° · Análisis de la dieta, la actividad física y el descanso como hábitos que mantienen sanos los sistemas digestivo, circulatorio y respiratorio.
A39: T8_27-B1.3 | B39: T8_27 | C39: Biología | D39: Características y procesos vitales de los organismos | E39: Procesos fisiológicos en plantas y animales | F39: N/A | G39: N/A | H39: N/A | I39: {=_xlfn.COUNTIFS('Datos - Temas'!$V$5:$V$1264,I$4,'Datos - Temas'!$K$5:$K$1264,$A39)+_xlfn.COUNTIFS('Datos - Temas'!$V$5:$V$1264,I$4,'Datos - Temas'!$L$5:$L$1264,$A39)} -> 0 | J39: {=_xlfn.COUNTIFS('Datos - Temas'!$V$5:$V$1264,J$4,'Datos - Temas'!$K$5:$K$1264,$A39)+_xlfn.COUNTIFS('Datos - Temas'!$V$5:$V$1264,J$4,'Datos - Temas'!$L$5:$L$1264,$A39)} -> 6 | K39: {=_xlfn.COUNTIFS('Datos - Temas'!$V$5:$V$1264,K$4,'Datos - Temas'!$K$5:$K$1264,$A39)+_xlfn.COUNTIFS('Datos - Temas'!$V$5:$V$1264,K$4,'Datos - Temas'!$L$5:$L$1264,$A39)} -> 0 | L39: {=_xlfn.COUNTIFS('Datos - Temas'!$V$5:$V$1264,L$4,'Datos - Temas'!$K$5:$K$1264,$A39)+_xlfn.COUNTIFS('Datos - Temas'!$V$5:$V$1264,L$4,'Datos - Temas'!$L$5:$L$1264,$A39)} -> 6 | M39: N/A | N39: N/A | O39: 12 | P39: {=_xlfn.COUNTIFS('Datos - Temas'!$K$5:$K$1264,$A39)} -> 7 | Q39: {=IF(O39>0,"Sí","No")} -> Sí | R39: {=IF(O39=0,"No cubierto",IF(O39=1,"Débil (1 tema)",IF(O39<=3,"Básica (2–3)","Sólida (4+)")))} -> Sólida (4+) | S39: {=_xlfn.IFERROR(INDEX($I$4:$L$4,MATCH(TRUE,INDEX(I39:L39>0,0),0)),"—")} -> 6° | T39: Hoy: 6° U5 (6); 8° U6 (3); 8° U7 (3)
A40: T8_27-B2.1 | B40: T8_27 | C40: Biología | D40: Las células y sus funciones | E40: Estructura y funciones de la célula | F40: N/A | G40: N/A | H40: N/A | I40: {=_xlfn.COUNTIFS('Datos - Temas'!$V$5:$V$1264,I$4,'Datos - Temas'!$K$5:$K$1264,$A40)+_xlfn.COUNTIFS('Datos - Temas'!$V$5:$V$1264,I$4,'Datos - Temas'!$L$5:$L$1264,$A40)} -> 0 | J40: {=_xlfn.COUNTIFS('Datos - Temas'!$V$5:$V$1264,J$4,'Datos - Temas'!$K$5:$K$1264,$A40)+_xlfn.COUNTIFS('Datos - Temas'!$V$5:$V$1264,J$4,'Datos - Temas'!$L$5:$L$1264,$A40)} -> 18 | K40: {=_xlfn.COUNTIFS('Datos - Temas'!$V$5:$V$1264,K$4,'Datos - Temas'!$K$5:$K$1264,$A40)+_xlfn.COUNTIFS('Datos - Temas'!$V$5:$V$1264,K$4,'Datos - Temas'!$L$5:$L$1264,$A40)} -> 1 | L40: {=_xlfn.COUNTIFS('Datos - Temas'!$V$5:$V$1264,L$4,'Datos - Temas'!$K$5:$K$1264,$A40)+_xlfn.COUNTIFS('Datos - Temas'!$V$5:$V$1264,L$4,'Datos - Temas'!$L$5:$L$1264,$A40)} -> 9 | M40: N/A | N40: N/A | O40: 28 | P40: {=_xlfn.COUNTIFS('Datos - Temas'!$K$5:$K$1264,$A40)} -> 25 | Q40: {=IF(O40>0,"Sí","No")} -> Sí | R40: {=IF(O40=0,"No cubierto",IF(O40=1,"Débil (1 tema)",IF(O40<=3,"Básica (2–3)","Sólida (4+)")))} -> Sólida (4+) | S40: {=_xlfn.IFERROR(INDEX($I$4:$L$4,MATCH(TRUE,INDEX(I40:L40>0,0),0)),"—")} -> 6° | T40: Hoy: 6° U5 (14); 6° U6 (4); 7° U2 (1); 8° U6 (6); 8° U7 (3)
A41: T8_27-B3.1 | B41: T8_27 | C41: Biología | D41: Ciclos de vida, reproducción y herencia | E41: Reproducción sexual y herencia en plantas y animales | F41: N/A | G41: N/A | H41: N/A | I41: {=_xlfn.COUNTIFS('Datos - Temas'!$V$5:$V$1264,I$4,'Datos - Temas'!$K$5:$K$1264,$A41)+_xlfn.COUNTIFS('Datos - Temas'!$V$5:$V$1264,I$4,'Datos - Temas'!$L$5:$L$1264,$A41)} -> 0 | J41: {=_xlfn.COUNTIFS('Datos - Temas'!$V$5:$V$1264,J$4,'Datos - Temas'!$K$5:$K$1264,$A41)+_xlfn.COUNTIFS('Datos - Temas'!$V$5:$V$1264,J$4,'Datos - Temas'!$L$5:$L$1264,$A41)} -> 6 | K41: {=_xlfn.COUNTIFS('Datos - Temas'!$V$5:$V$1264,K$4,'Datos - Temas'!$K$5:$K$1264,$A41)+_xlfn.COUNTIFS('Datos - Temas'!$V$5:$V$1264,K$4,'Datos - Temas'!$L$5:$L$1264,$A41)} -> 14 | L41: {=_xlfn.COUNTIFS('Datos - Temas'!$V$5:$V$1264,L$4,'Datos - Temas'!$K$5:$K$1264,$A41)+_xlfn.COUNTIFS('Datos - Temas'!$V$5:$V$1264,L$4,'Datos - Temas'!$L$5:$L$1264,$A41)} -> 0 | M41: N/A | N41: N/A | O41: 20 | P41: {=_xlfn.COUNTIFS('Datos - Temas'!$K$5:$K$1264,$A41)} -> 18 | Q41: {=IF(O41>0,"Sí","No")} -> Sí | R41: {=IF(O41=0,"No cubierto",IF(O41=1,"Débil (1 tema)",IF(O41<=3,"Básica (2–3)","Sólida (4+)")))} -> Sólida (4+) | S41: {=_xlfn.IFERROR(INDEX($I$4:$L$4,MATCH(TRUE,INDEX(I41:L41>0,0),0)),"—")} -> 6° | T41: Hoy: 6° U6 (6); 7° U2 (14)
A42: T8_27-B4.1 | B42: T8_27 | C42: Biología | D42: Diversidad, adaptación y selección natural | E42: La variación como base de la selección natural | F42: N/A | G42: N/A | H42: N/A | I42: {=_xlfn.COUNTIFS('Datos - Temas'!$V$5:$V$1264,I$4,'Datos - Temas'!$K$5:$K$1264,$A42)+_xlfn.COUNTIFS('Datos - Temas'!$V$5:$V$1264,I$4,'Datos - Temas'!$L$5:$L$1264,$A42)} -> 1 | J42: {=_xlfn.COUNTIFS('Datos - Temas'!$V$5:$V$1264,J$4,'Datos - Temas'!$K$5:$K$1264,$A42)+_xlfn.COUNTIFS('Datos - Temas'!$V$5:$V$1264,J$4,'Datos - Temas'!$L$5:$L$1264,$A42)} -> 0 | K42: {=_xlfn.COUNTIFS('Datos - Temas'!$V$5:$V$1264,K$4,'Datos - Temas'!$K$5:$K$1264,$A42)+_xlfn.COUNTIFS('Datos - Temas'!$V$5:$V$1264,K$4,'Datos - Temas'!$L$5:$L$1264,$A42)} -> 7 | L42: {=_xlfn.COUNTIFS('Datos - Temas'!$V$5:$V$1264,L$4,'Datos - Temas'!$K$5:$K$1264,$A42)+_xlfn.COUNTIFS('Datos - Temas'!$V$5:$V$1264,L$4,'Datos - Temas'!$L$5:$L$1264,$A42)} -> 0 | M42: N/A | N42: N/A | O42: 8 | P42: {=_xlfn.COUNTIFS('Datos - Temas'!$K$5:$K$1264,$A42)} -> 5 | Q42: {=IF(O42>0,"Sí","No")} -> Sí | R42: {=IF(O42=0,"No cubierto",IF(O42=1,"Débil (1 tema)",IF(O42<=3,"Básica (2–3)","Sólida (4+)")))} -> Sólida (4+) | S42: {=_xlfn.IFERROR(INDEX($I$4:$L$4,MATCH(TRUE,INDEX(I42:L42>0,0),0)),"—")} -> 5° | T42: Hoy: 5° U6 (1); 7° U2 (6); 7° U3 (1)
A43: T8_27-B4.2 | B43: T8_27 | C43: Biología | D43: Diversidad, adaptación y selección natural | E43: Evidencias del cambio de la vida en la Tierra | F43: N/A | G43: N/A | H43: N/A | I43: {=_xlfn.COUNTIFS('Datos - Temas'!$V$5:$V$1264,I$4,'Datos - Temas'!$K$5:$K$1264,$A43)+_xlfn.COUNTIFS('Datos - Temas'!$V$5:$V$1264,I$4,'Datos - Temas'!$L$5:$L$1264,$A43)} -> 3 | J43: {=_xlfn.COUNTIFS('Datos - Temas'!$V$5:$V$1264,J$4,'Datos - Temas'!$K$5:$K$1264,$A43)+_xlfn.COUNTIFS('Datos - Temas'!$V$5:$V$1264,J$4,'Datos - Temas'!$L$5:$L$1264,$A43)} -> 0 | K43: {=_xlfn.COUNTIFS('Datos - Temas'!$V$5:$V$1264,K$4,'Datos - Temas'!$K$5:$K$1264,$A43)+_xlfn.COUNTIFS('Datos - Temas'!$V$5:$V$1264,K$4,'Datos - Temas'!$L$5:$L$1264,$A43)} -> 2 | L43: {=_xlfn.COUNTIFS('Datos - Temas'!$V$5:$V$1264,L$4,'Datos - Temas'!$K$5:$K$1264,$A43)+_xlfn.COUNTIFS('Datos - Temas'!$V$5:$V$1264,L$4,'Datos - Temas'!$L$5:$L$1264,$A43)} -> 0 | M43: N/A | N43: N/A | O43: 5 | P43: {=_xlfn.COUNTIFS('Datos - Temas'!$K$5:$K$1264,$A43)} -> 4 | Q43: {=IF(O43>0,"Sí","No")} -> Sí | R43: {=IF(O43=0,"No cubierto",IF(O43=1,"Débil (1 tema)",IF(O43<=3,"Básica (2–3)","Sólida (4+)")))} -> Sólida (4+) | S43: {=_xlfn.IFERROR(INDEX($I$4:$L$4,MATCH(TRUE,INDEX(I43:L43>0,0),0)),"—")} -> 5° | T43: Hoy: 5° U6 (3); 7° U3 (2)
A44: T8_27-B5.1 | B44: T8_27 | C44: Biología | D44: Ecosistemas | E44: Ecosistemas naturales, urbanos y rurales | F44: N/A | G44: N/A | H44: N/A | I44: {=_xlfn.COUNTIFS('Datos - Temas'!$V$5:$V$1264,I$4,'Datos - Temas'!$K$5:$K$1264,$A44)+_xlfn.COUNTIFS('Datos - Temas'!$V$5:$V$1264,I$4,'Datos - Temas'!$L$5:$L$1264,$A44)} -> 0 | J44: {=_xlfn.COUNTIFS('Datos - Temas'!$V$5:$V$1264,J$4,'Datos - Temas'!$K$5:$K$1264,$A44)+_xlfn.COUNTIFS('Datos - Temas'!$V$5:$V$1264,J$4,'Datos - Temas'!$L$5:$L$1264,$A44)} -> 0 | K44: {=_xlfn.COUNTIFS('Datos - Temas'!$V$5:$V$1264,K$4,'Datos - Temas'!$K$5:$K$1264,$A44)+_xlfn.COUNTIFS('Datos - Temas'!$V$5:$V$1264,K$4,'Datos - Temas'!$L$5:$L$1264,$A44)} -> 4 | L44: {=_xlfn.COUNTIFS('Datos - Temas'!$V$5:$V$1264,L$4,'Datos - Temas'!$K$5:$K$1264,$A44)+_xlfn.COUNTIFS('Datos - Temas'!$V$5:$V$1264,L$4,'Datos - Temas'!$L$5:$L$1264,$A44)} -> 0 | M44: N/A | N44: N/A | O44: 4 | P44: {=_xlfn.COUNTIFS('Datos - Temas'!$K$5:$K$1264,$A44)} -> 4 | Q44: {=IF(O44>0,"Sí","No")} -> Sí | R44: {=IF(O44=0,"No cubierto",IF(O44=1,"Débil (1 tema)",IF(O44<=3,"Básica (2–3)","Sólida (4+)")))} -> Sólida (4+) | S44: {=_xlfn.IFERROR(INDEX($I$4:$L$4,MATCH(TRUE,INDEX(I44:L44>0,0),0)),"—")} -> 7° | T44: Hoy: 7° U3 (1); 7° U4 (3); 9° U4 (2) · Propuesta 5-8-I05 (Presupuesto): 5.° · Comparación de ecosistemas naturales, rurales y urbanos de El Salvador a partir del cambio de cobertura y uso del suelo.
A45: T8_27-B5.2 | B45: T8_27 | C45: Biología | D45: Ecosistemas | E45: Flujo de energía en los ecosistemas | F45: N/A | G45: N/A | H45: N/A | I45: {=_xlfn.COUNTIFS('Datos - Temas'!$V$5:$V$1264,I$4,'Datos - Temas'!$K$5:$K$1264,$A45)+_xlfn.COUNTIFS('Datos - Temas'!$V$5:$V$1264,I$4,'Datos - Temas'!$L$5:$L$1264,$A45)} -> 0 | J45: {=_xlfn.COUNTIFS('Datos - Temas'!$V$5:$V$1264,J$4,'Datos - Temas'!$K$5:$K$1264,$A45)+_xlfn.COUNTIFS('Datos - Temas'!$V$5:$V$1264,J$4,'Datos - Temas'!$L$5:$L$1264,$A45)} -> 0 | K45: {=_xlfn.COUNTIFS('Datos - Temas'!$V$5:$V$1264,K$4,'Datos - Temas'!$K$5:$K$1264,$A45)+_xlfn.COUNTIFS('Datos - Temas'!$V$5:$V$1264,K$4,'Datos - Temas'!$L$5:$L$1264,$A45)} -> 1 | L45: {=_xlfn.COUNTIFS('Datos - Temas'!$V$5:$V$1264,L$4,'Datos - Temas'!$K$5:$K$1264,$A45)+_xlfn.COUNTIFS('Datos - Temas'!$V$5:$V$1264,L$4,'Datos - Temas'!$L$5:$L$1264,$A45)} -> 0 | M45: N/A | N45: N/A | O45: 1 | P45: {=_xlfn.COUNTIFS('Datos - Temas'!$K$5:$K$1264,$A45)} -> 1 | Q45: {=IF(O45>0,"Sí","No")} -> Sí | R45: {=IF(O45=0,"No cubierto",IF(O45=1,"Débil (1 tema)",IF(O45<=3,"Básica (2–3)","Sólida (4+)")))} -> Débil (1 tema) | S45: {=_xlfn.IFERROR(INDEX($I$4:$L$4,MATCH(TRUE,INDEX(I45:L45>0,0),0)),"—")} -> 7° | T45: Hoy: 7° U4 (1) · Propuesta 5-8-I02 (Presupuesto): 5.° · Construcción de cadenas y redes tróficas de un ecosistema local para representar el flujo de energía entre productores, consumidores y descomponedores.
A46: T8_27-B5.3 | B46: T8_27 | C46: Biología | D46: Ecosistemas | E46: Ciclos del agua, el oxígeno y el carbono en los ecosistemas | F46: N/A | G46: N/A | H46: N/A | I46: {=_xlfn.COUNTIFS('Datos - Temas'!$V$5:$V$1264,I$4,'Datos - Temas'!$K$5:$K$1264,$A46)+_xlfn.COUNTIFS('Datos - Temas'!$V$5:$V$1264,I$4,'Datos - Temas'!$L$5:$L$1264,$A46)} -> 0 | J46: {=_xlfn.COUNTIFS('Datos - Temas'!$V$5:$V$1264,J$4,'Datos - Temas'!$K$5:$K$1264,$A46)+_xlfn.COUNTIFS('Datos - Temas'!$V$5:$V$1264,J$4,'Datos - Temas'!$L$5:$L$1264,$A46)} -> 0 | K46: {=_xlfn.COUNTIFS('Datos - Temas'!$V$5:$V$1264,K$4,'Datos - Temas'!$K$5:$K$1264,$A46)+_xlfn.COUNTIFS('Datos - Temas'!$V$5:$V$1264,K$4,'Datos - Temas'!$L$5:$L$1264,$A46)} -> 1 | L46: {=_xlfn.COUNTIFS('Datos - Temas'!$V$5:$V$1264,L$4,'Datos - Temas'!$K$5:$K$1264,$A46)+_xlfn.COUNTIFS('Datos - Temas'!$V$5:$V$1264,L$4,'Datos - Temas'!$L$5:$L$1264,$A46)} -> 0 | M46: N/A | N46: N/A | O46: 1 | P46: {=_xlfn.COUNTIFS('Datos - Temas'!$K$5:$K$1264,$A46)} -> 0 | Q46: {=IF(O46>0,"Sí","No")} -> Sí | R46: {=IF(O46=0,"No cubierto",IF(O46=1,"Débil (1 tema)",IF(O46<=3,"Básica (2–3)","Sólida (4+)")))} -> Débil (1 tema) | S46: {=_xlfn.IFERROR(INDEX($I$4:$L$4,MATCH(TRUE,INDEX(I46:L46>0,0),0)),"—")} -> 7° | T46: Hoy: 7° U4 (1) · Propuesta 5-8-I03 (Presupuesto): 5.° · Modelación de los ciclos del carbono, del oxígeno y del agua entre seres vivos, suelo y atmósfera, destacando la descomposición de la materia orgánica.
A47: T8_27-B5.4 | B47: T8_27 | C47: Biología | D47: Ecosistemas | E47: Relaciones en los ecosistemas | F47: N/A | G47: N/A | H47: N/A | I47: {=_xlfn.COUNTIFS('Datos - Temas'!$V$5:$V$1264,I$4,'Datos - Temas'!$K$5:$K$1264,$A47)+_xlfn.COUNTIFS('Datos - Temas'!$V$5:$V$1264,I$4,'Datos - Temas'!$L$5:$L$1264,$A47)} -> 0 | J47: {=_xlfn.COUNTIFS('Datos - Temas'!$V$5:$V$1264,J$4,'Datos - Temas'!$K$5:$K$1264,$A47)+_xlfn.COUNTIFS('Datos - Temas'!$V$5:$V$1264,J$4,'Datos - Temas'!$L$5:$L$1264,$A47)} -> 0 | K47: {=_xlfn.COUNTIFS('Datos - Temas'!$V$5:$V$1264,K$4,'Datos - Temas'!$K$5:$K$1264,$A47)+_xlfn.COUNTIFS('Datos - Temas'!$V$5:$V$1264,K$4,'Datos - Temas'!$L$5:$L$1264,$A47)} -> 3 | L47: {=_xlfn.COUNTIFS('Datos - Temas'!$V$5:$V$1264,L$4,'Datos - Temas'!$K$5:$K$1264,$A47)+_xlfn.COUNTIFS('Datos - Temas'!$V$5:$V$1264,L$4,'Datos - Temas'!$L$5:$L$1264,$A47)} -> 0 | M47: N/A | N47: N/A | O47: 3 | P47: {=_xlfn.COUNTIFS('Datos - Temas'!$K$5:$K$1264,$A47)} -> 4 | Q47: {=IF(O47>0,"Sí","No")} -> Sí | R47: {=IF(O47=0,"No cubierto",IF(O47=1,"Débil (1 tema)",IF(O47<=3,"Básica (2–3)","Sólida (4+)")))} -> Básica (2–3) | S47: {=_xlfn.IFERROR(INDEX($I$4:$L$4,MATCH(TRUE,INDEX(I47:L47>0,0),0)),"—")} -> 7° | T47: Hoy: 7° U4 (3); 9° U4 (1)
A48: T8_27-B5.5 | B48: T8_27 | C48: Biología | D48: Ecosistemas | E48: Factores que afectan el tamaño de las poblaciones | F48: N/A | G48: N/A | H48: N/A | I48: {=_xlfn.COUNTIFS('Datos - Temas'!$V$5:$V$1264,I$4,'Datos - Temas'!$K$5:$K$1264,$A48)+_xlfn.COUNTIFS('Datos - Temas'!$V$5:$V$1264,I$4,'Datos - Temas'!$L$5:$L$1264,$A48)} -> 0 | J48: {=_xlfn.COUNTIFS('Datos - Temas'!$V$5:$V$1264,J$4,'Datos - Temas'!$K$5:$K$1264,$A48)+_xlfn.COUNTIFS('Datos - Temas'!$V$5:$V$1264,J$4,'Datos - Temas'!$L$5:$L$1264,$A48)} -> 1 | K48: {=_xlfn.COUNTIFS('Datos - Temas'!$V$5:$V$1264,K$4,'Datos - Temas'!$K$5:$K$1264,$A48)+_xlfn.COUNTIFS('Datos - Temas'!$V$5:$V$1264,K$4,'Datos - Temas'!$L$5:$L$1264,$A48)} -> 3 | L48: {=_xlfn.COUNTIFS('Datos - Temas'!$V$5:$V$1264,L$4,'Datos - Temas'!$K$5:$K$1264,$A48)+_xlfn.COUNTIFS('Datos - Temas'!$V$5:$V$1264,L$4,'Datos - Temas'!$L$5:$L$1264,$A48)} -> 0 | M48: N/A | N48: N/A | O48: 4 | P48: {=_xlfn.COUNTIFS('Datos - Temas'!$K$5:$K$1264,$A48)} -> 4 | Q48: {=IF(O48>0,"Sí","No")} -> Sí | R48: {=IF(O48=0,"No cubierto",IF(O48=1,"Débil (1 tema)",IF(O48<=3,"Básica (2–3)","Sólida (4+)")))} -> Sólida (4+) | S48: {=_xlfn.IFERROR(INDEX($I$4:$L$4,MATCH(TRUE,INDEX(I48:L48>0,0),0)),"—")} -> 6° | T48: Hoy: 6° U5 (1); 7° U4 (3) · Propuesta 5-8-I06 (Presupuesto): 5.° · Análisis de los factores (alimento, depredadores, enfermedades, espacio, actividad humana) que hacen variar el tamaño de una población local.
... A84: T8_27-E5.1 | B84: T8_27 | C84: Ciencias de la Tierra | D84: Investigaciones en ciencias de la Tierra | E84: Equipo usado en investigaciones de ciencias de la Tierra | F84: N/A | G84: N/A | H84: N/A | I84: {=_xlfn.COUNTIFS('Datos - Temas'!$V$5:$V$1264,I$4,'Datos - Temas'!$K$5:$K$1264,$A84)+_xlfn.COUNTIFS('Datos - Temas'!$V$5:$V$1264,I$4,'Datos - Temas'!$L$5:$L$1264,$A84)} -> 0 | J84: {=_xlfn.COUNTIFS('Datos - Temas'!$V$5:$V$1264,J$4,'Datos - Temas'!$K$5:$K$1264,$A84)+_xlfn.COUNTIFS('Datos - Temas'!$V$5:$V$1264,J$4,'Datos - Temas'!$L$5:$L$1264,$A84)} -> 0 | K84: {=_xlfn.COUNTIFS('Datos - Temas'!$V$5:$V$1264,K$4,'Datos - Temas'!$K$5:$K$1264,$A84)+_xlfn.COUNTIFS('Datos - Temas'!$V$5:$V$1264,K$4,'Datos - Temas'!$L$5:$L$1264,$A84)} -> 0 | L84: {=_xlfn.COUNTIFS('Datos - Temas'!$V$5:$V$1264,L$4,'Datos - Temas'!$K$5:$K$1264,$A84)+_xlfn.COUNTIFS('Datos - Temas'!$V$5:$V$1264,L$4,'Datos - Temas'!$L$5:$L$1264,$A84)} -> 0 | M84: N/A | N84: N/A | O84: 0 | P84: {=_xlfn.COUNTIFS('Datos - Temas'!$K$5:$K$1264,$A84)} -> 0 | Q84: {=IF(O84>0,"Sí","No")} -> No | R84: {=IF(O84=0,"No cubierto",IF(O84=1,"Débil (1 tema)",IF(O84<=3,"Básica (2–3)","Sólida (4+)")))} -> No cubierto | S84: {=_xlfn.IFERROR(INDEX($I$4:$L$4,MATCH(TRUE,INDEX(I84:L84>0,0),0)),"—")} -> — | T84: Hoy: 9° U7 (1) · Propuesta 5-8-I08 (Presupuesto): 8.° · Uso de lupa, escala de Mohs, brújula, GPS y libreta de campo para recolectar, medir y registrar datos de rocas y minerales del entorno.
A85: TA-M1.1 | B85: TA | C85: Mecánica y termodinámica | D85: Fuerzas y movimiento | E85: Cinemática y leyes de Newton | F85: N/A | G85: N/A | H85: N/A | I85: N/A | J85: N/A | K85: N/A | L85: N/A | M85: {=_xlfn.COUNTIFS('Datos - Temas'!$V$5:$V$1264,M$4,'Datos - Temas'!$K$5:$K$1264,$A85)+_xlfn.COUNTIFS('Datos - Temas'!$V$5:$V$1264,M$4,'Datos - Temas'!$L$5:$L$1264,$A85)} -> 18 | N85: {=_xlfn.COUNTIFS('Datos - Temas'!$V$5:$V$1264,N$4,'Datos - Temas'!$K$5:$K$1264,$A85)+_xlfn.COUNTIFS('Datos - Temas'!$V$5:$V$1264,N$4,'Datos - Temas'!$L$5:$L$1264,$A85)} -> 0 | O85: 18 | P85: {=_xlfn.COUNTIFS('Datos - Temas'!$K$5:$K$1264,$A85)} -> 16 | Q85: {=IF(O85>0,"Sí","No")} -> Sí | R85: {=IF(O85=0,"No cubierto",IF(O85=1,"Débil (1 tema)",IF(O85<=3,"Básica (2–3)","Sólida (4+)")))} -> Sólida (4+) | S85: {=_xlfn.IFERROR(INDEX($M$4:$N$4,MATCH(TRUE,INDEX(M85:N85>0,0),0)),"—")} -> Física 10° | T85: Hoy: Física 10° U3 (7); Física 10° U4 (4); Física 10° U5 (7)
A86: TA-M1.2 | B86: TA | C86: Mecánica y termodinámica | D86: Fuerzas y movimiento | E86: Fuerzas sobre cuerpos y sus efectos | F86: N/A | G86: N/A | H86: N/A | I86: N/A | J86: N/A | K86: N/A | L86: N/A | M86: {=_xlfn.COUNTIFS('Datos - Temas'!$V$5:$V$1264,M$4,'Datos - Temas'!$K$5:$K$1264,$A86)+_xlfn.COUNTIFS('Datos - Temas'!$V$5:$V$1264,M$4,'Datos - Temas'!$L$5:$L$1264,$A86)} -> 10 | N86: {=_xlfn.COUNTIFS('Datos - Temas'!$V$5:$V$1264,N$4,'Datos - Temas'!$K$5:$K$1264,$A86)+_xlfn.COUNTIFS('Datos - Temas'!$V$5:$V$1264,N$4,'Datos - Temas'!$L$5:$L$1264,$A86)} -> 1 | O86: 11 | P86: {=_xlfn.COUNTIFS('Datos - Temas'!$K$5:$K$1264,$A86)} -> 8 | Q86: {=IF(O86>0,"Sí","No")} -> Sí | R86: {=IF(O86=0,"No cubierto",IF(O86=1,"Débil (1 tema)",IF(O86<=3,"Básica (2–3)","Sólida (4+)")))} -> Sólida (4+) | S86: {=_xlfn.IFERROR(INDEX($M$4:$N$4,MATCH(TRUE,INDEX(M86:N86>0,0),0)),"—")} -> Física 10° | T86: Hoy: Física 10° U10 (1); Física 10° U5 (7); Física 10° U6 (1); Física 10° U7 (1); Física 11° U1 (1)
A87: TA-M1.3 | B87: TA | C87: Mecánica y termodinámica | D87: Fuerzas y movimiento | E87: Movimiento circular: fuerza y aceleración centrípeta | F87: N/A | G87: N/A | H87: N/A | I87: N/A | J87: N/A | K87: N/A | L87: N/A | M87: {=_xlfn.COUNTIFS('Datos - Temas'!$V$5:$V$1264,M$4,'Datos - Temas'!$K$5:$K$1264,$A87)+_xlfn.COUNTIFS('Datos - Temas'!$V$5:$V$1264,M$4,'Datos - Temas'!$L$5:$L$1264,$A87)} -> 8 | N87: {=_xlfn.COUNTIFS('Datos - Temas'!$V$5:$V$1264,N$4,'Datos - Temas'!$K$5:$K$1264,$A87)+_xlfn.COUNTIFS('Datos - Temas'!$V$5:$V$1264,N$4,'Datos - Temas'!$L$5:$L$1264,$A87)} -> 1 | O87: 9 | P87: {=_xlfn.COUNTIFS('Datos - Temas'!$K$5:$K$1264,$A87)} -> 7 | Q87: {=IF(O87>0,"Sí","No")} -> Sí | R87: {=IF(O87=0,"No cubierto",IF(O87=1,"Débil (1 tema)",IF(O87<=3,"Básica (2–3)","Sólida (4+)")))} -> Sólida (4+) | S87: {=_xlfn.IFERROR(INDEX($M$4:$N$4,MATCH(TRUE,INDEX(M87:N87>0,0),0)),"—")} -> Física 10° | T87: Hoy: Física 10° U6 (7); Física 10° U9 (1); Física 11° U10 (1)
A88: TA-M1.4 | B88: TA | C88: Mecánica y termodinámica | D88: Fuerzas y movimiento | E88: Ley de gravitación y movimiento de cuerpos celestes | F88: N/A | G88: N/A | H88: N/A | I88: N/A | J88: N/A | K88: N/A | L88: N/A | M88: {=_xlfn.COUNTIFS('Datos - Temas'!$V$5:$V$1264,M$4,'Datos - Temas'!$K$5:$K$1264,$A88)+_xlfn.COUNTIFS('Datos - Temas'!$V$5:$V$1264,M$4,'Datos - Temas'!$L$5:$L$1264,$A88)} -> 3 | N88: {=_xlfn.COUNTIFS('Datos - Temas'!$V$5:$V$1264,N$4,'Datos - Temas'!$K$5:$K$1264,$A88)+_xlfn.COUNTIFS('Datos - Temas'!$V$5:$V$1264,N$4,'Datos - Temas'!$L$5:$L$1264,$A88)} -> 2 | O88: 5 | P88: {=_xlfn.COUNTIFS('Datos - Temas'!$K$5:$K$1264,$A88)} -> 4 | Q88: {=IF(O88>0,"Sí","No")} -> Sí | R88: {=IF(O88=0,"No cubierto",IF(O88=1,"Débil (1 tema)",IF(O88<=3,"Básica (2–3)","Sólida (4+)")))} -> Sólida (4+) | S88: {=_xlfn.IFERROR(INDEX($M$4:$N$4,MATCH(TRUE,INDEX(M88:N88>0,0),0)),"—")} -> Física 10° | T88: Hoy: Física 10° U5 (1); Física 10° U6 (2); Física 11° U22 (2)
A89: TA-M2.1 | B89: TA | C89: Mecánica y termodinámica | D89: Leyes de conservación | E89: Conservación de la energía mecánica | F89: N/A | G89: N/A | H89: N/A | I89: N/A | J89: N/A | K89: N/A | L89: N/A | M89: {=_xlfn.COUNTIFS('Datos - Temas'!$V$5:$V$1264,M$4,'Datos - Temas'!$K$5:$K$1264,$A89)+_xlfn.COUNTIFS('Datos - Temas'!$V$5:$V$1264,M$4,'Datos - Temas'!$L$5:$L$1264,$A89)} -> 11 | N89: {=_xlfn.COUNTIFS('Datos - Temas'!$V$5:$V$1264,N$4,'Datos - Temas'!$K$5:$K$1264,$A89)+_xlfn.COUNTIFS('Datos - Temas'!$V$5:$V$1264,N$4,'Datos - Temas'!$L$5:$L$1264,$A89)} -> 2 | O89: 13 | P89: {=_xlfn.COUNTIFS('Datos - Temas'!$K$5:$K$1264,$A89)} -> 11 | Q89: {=IF(O89>0,"Sí","No")} -> Sí | R89: {=IF(O89=0,"No cubierto",IF(O89=1,"Débil (1 tema)",IF(O89<=3,"Básica (2–3)","Sólida (4+)")))} -> Sólida (4+) | S89: {=_xlfn.IFERROR(INDEX($M$4:$N$4,MATCH(TRUE,INDEX(M89:N89>0,0),0)),"—")} -> Física 10° | T89: Hoy: Física 10° U10 (1); Física 10° U7 (9); Física 10° U8 (1); Física 11° U1 (1); Física 11° U8 (1)
A90: TA-M2.2 | B90: TA | C90: Mecánica y termodinámica | D90: Leyes de conservación | E90: Conservación del momento lineal en choques | F90: N/A | G90: N/A | H90: N/A | I90: N/A | J90: N/A | K90: N/A | L90: N/A | M90: {=_xlfn.COUNTIFS('Datos - Temas'!$V$5:$V$1264,M$4,'Datos - Temas'!$K$5:$K$1264,$A90)+_xlfn.COUNTIFS('Datos - Temas'!$V$5:$V$1264,M$4,'Datos - Temas'!$L$5:$L$1264,$A90)} -> 5 | N90: {=_xlfn.COUNTIFS('Datos - Temas'!$V$5:$V$1264,N$4,'Datos - Temas'!$K$5:$K$1264,$A90)+_xlfn.COUNTIFS('Datos - Temas'!$V$5:$V$1264,N$4,'Datos - Temas'!$L$5:$L$1264,$A90)} -> 1 | O90: 6 | P90: {=_xlfn.COUNTIFS('Datos - Temas'!$K$5:$K$1264,$A90)} -> 5 | Q90: {=IF(O90>0,"Sí","No")} -> Sí | R90: {=IF(O90=0,"No cubierto",IF(O90=1,"Débil (1 tema)",IF(O90<=3,"Básica (2–3)","Sólida (4+)")))} -> Sólida (4+) | S90: {=_xlfn.IFERROR(INDEX($M$4:$N$4,MATCH(TRUE,INDEX(M90:N90>0,0),0)),"—")} -> Física 10° | T90: Hoy: Física 10° U8 (5); Física 11° U15 (1)
A91: TA-M2.3 | B91: TA | C91: Mecánica y termodinámica | D91: Leyes de conservación | E91: Primera ley de la termodinámica | F91: N/A | G91: N/A | H91: N/A | I91: N/A | J91: N/A | K91: N/A | L91: N/A | M91: {=_xlfn.COUNTIFS('Datos - Temas'!$V$5:$V$1264,M$4,'Datos - Temas'!$K$5:$K$1264,$A91)+_xlfn.COUNTIFS('Datos - Temas'!$V$5:$V$1264,M$4,'Datos - Temas'!$L$5:$L$1264,$A91)} -> 8 | N91: {=_xlfn.COUNTIFS('Datos - Temas'!$V$5:$V$1264,N$4,'Datos - Temas'!$K$5:$K$1264,$A91)+_xlfn.COUNTIFS('Datos - Temas'!$V$5:$V$1264,N$4,'Datos - Temas'!$L$5:$L$1264,$A91)} -> 0 | O91: 8 | P91: {=_xlfn.COUNTIFS('Datos - Temas'!$K$5:$K$1264,$A91)} -> 7 | Q91: {=IF(O91>0,"Sí","No")} -> Sí | R91: {=IF(O91=0,"No cubierto",IF(O91=1,"Débil (1 tema)",IF(O91<=3,"Básica (2–3)","Sólida (4+)")))} -> Sólida (4+) | S91: {=_xlfn.IFERROR(INDEX($M$4:$N$4,MATCH(TRUE,INDEX(M91:N91>0,0),0)),"—")} -> Física 10° | T91: Hoy: Física 10° U12 (1); Física 10° U15 (7)
A92: TA-M3.1 | B92: TA | C92: Mecánica y termodinámica | D92: Calor y temperatura | E92: Mecanismos de transferencia de calor; capacidad calorífica y equilibrio térmico | F92: N/A | G92: N/A | H92: N/A | I92: N/A | J92: N/A | K92: N/A | L92: N/A | M92: {=_xlfn.COUNTIFS('Datos - Temas'!$V$5:$V$1264,M$4,'Datos - Temas'!$K$5:$K$1264,$A92)+_xlfn.COUNTIFS('Datos - Temas'!$V$5:$V$1264,M$4,'Datos - Temas'!$L$5:$L$1264,$A92)} -> 10 | N92: {=_xlfn.COUNTIFS('Datos - Temas'!$V$5:$V$1264,N$4,'Datos - Temas'!$K$5:$K$1264,$A92)+_xlfn.COUNTIFS('Datos - Temas'!$V$5:$V$1264,N$4,'Datos - Temas'!$L$5:$L$1264,$A92)} -> 0 | O92: 10 | P92: {=_xlfn.COUNTIFS('Datos - Temas'!$K$5:$K$1264,$A92)} -> 8 | Q92: {=IF(O92>0,"Sí","No")} -> Sí | R92: {=IF(O92=0,"No cubierto",IF(O92=1,"Débil (1 tema)",IF(O92<=3,"Básica (2–3)","Sólida (4+)")))} -> Sólida (4+) | S92: {=_xlfn.IFERROR(INDEX($M$4:$N$4,MATCH(TRUE,INDEX(M92:N92>0,0),0)),"—")} -> Física 10° | T92: Hoy: Física 10° U12 (4); Física 10° U13 (4); Física 10° U15 (2)
A93: TA-M3.2 | B93: TA | C93: Mecánica y termodinámica | D93: Calor y temperatura | E93: Dilatación térmica; ley del gas ideal y sus límites | F93: N/A | G93: N/A | H93: N/A | I93: N/A | J93: N/A | K93: N/A | L93: N/A | M93: {=_xlfn.COUNTIFS('Datos - Temas'!$V$5:$V$1264,M$4,'Datos - Temas'!$K$5:$K$1264,$A93)+_xlfn.COUNTIFS('Datos - Temas'!$V$5:$V$1264,M$4,'Datos - Temas'!$L$5:$L$1264,$A93)} -> 7 | N93: {=_xlfn.COUNTIFS('Datos - Temas'!$V$5:$V$1264,N$4,'Datos - Temas'!$K$5:$K$1264,$A93)+_xlfn.COUNTIFS('Datos - Temas'!$V$5:$V$1264,N$4,'Datos - Temas'!$L$5:$L$1264,$A93)} -> 0 | O93: 7 | P93: {=_xlfn.COUNTIFS('Datos - Temas'!$K$5:$K$1264,$A93)} -> 5 | Q93: {=IF(O93>0,"Sí","No")} -> Sí | R93: {=IF(O93=0,"No cubierto",IF(O93=1,"Débil (1 tema)",IF(O93<=3,"Básica (2–3)","Sólida (4+)")))} -> Sólida (4+) | S93: {=_xlfn.IFERROR(INDEX($M$4:$N$4,MATCH(TRUE,INDEX(M93:N93>0,0),0)),"—")} -> Física 10° | T93: Hoy: Física 10° U12 (3); Física 10° U14 (2); Física 10° U15 (2)
A94: TA-E1.1 | B94: TA | C94: Electricidad y magnetismo | D94: Electricidad y circuitos | E94: Ley de Coulomb | F94: N/A | G94: N/A | H94: N/A | I94: N/A | J94: N/A | K94: N/A | L94: N/A | M94: {=_xlfn.COUNTIFS('Datos - Temas'!$V$5:$V$1264,M$4,'Datos - Temas'!$K$5:$K$1264,$A94)+_xlfn.COUNTIFS('Datos - Temas'!$V$5:$V$1264,M$4,'Datos - Temas'!$L$5:$L$1264,$A94)} -> 0 | N94: {=_xlfn.COUNTIFS('Datos - Temas'!$V$5:$V$1264,N$4,'Datos - Temas'!$K$5:$K$1264,$A94)+_xlfn.COUNTIFS('Datos - Temas'!$V$5:$V$1264,N$4,'Datos - Temas'!$L$5:$L$1264,$A94)} -> 7 | O94: 7 | P94: {=_xlfn.COUNTIFS('Datos - Temas'!$K$5:$K$1264,$A94)} -> 5 | Q94: {=IF(O94>0,"Sí","No")} -> Sí | R94: {=IF(O94=0,"No cubierto",IF(O94=1,"Débil (1 tema)",IF(O94<=3,"Básica (2–3)","Sólida (4+)")))} -> Sólida (4+) | S94: {=_xlfn.IFERROR(INDEX($M$4:$N$4,MATCH(TRUE,INDEX(M94:N94>0,0),0)),"—")} -> Física 11° | T94: Hoy: Física 11° U6 (5); Física 11° U7 (1); Física 11° U8 (1)
A95: TA-E1.2 | B95: TA | C95: Electricidad y magnetismo | D95: Electricidad y circuitos | E95: Fuerza y trayectoria de cargas en campos eléctricos | F95: N/A | G95: N/A | H95: N/A | I95: N/A | J95: N/A | K95: N/A | L95: N/A | M95: {=_xlfn.COUNTIFS('Datos - Temas'!$V$5:$V$1264,M$4,'Datos - Temas'!$K$5:$K$1264,$A95)+_xlfn.COUNTIFS('Datos - Temas'!$V$5:$V$1264,M$4,'Datos - Temas'!$L$5:$L$1264,$A95)} -> 0 | N95: {=_xlfn.COUNTIFS('Datos - Temas'!$V$5:$V$1264,N$4,'Datos - Temas'!$K$5:$K$1264,$A95)+_xlfn.COUNTIFS('Datos - Temas'!$V$5:$V$1264,N$4,'Datos - Temas'!$L$5:$L$1264,$A95)} -> 11 | O95: 11 | P95: {=_xlfn.COUNTIFS('Datos - Temas'!$K$5:$K$1264,$A95)} -> 10 | Q95: {=IF(O95>0,"Sí","No")} -> Sí | R95: {=IF(O95=0,"No cubierto",IF(O95=1,"Débil (1 tema)",IF(O95<=3,"Básica (2–3)","Sólida (4+)")))} -> Sólida (4+) | S95: {=_xlfn.IFERROR(INDEX($M$4:$N$4,MATCH(TRUE,INDEX(M95:N95>0,0),0)),"—")} -> Física 11° | T95: Hoy: Física 11° U12 (1); Física 11° U7 (5); Física 11° U8 (5)
A96: TA-E1.3 | B96: TA | C96: Electricidad y magnetismo | D96: Electricidad y circuitos | E96: Circuitos: leyes de Ohm y Joule | F96: N/A | G96: N/A | H96: N/A | I96: N/A | J96: N/A | K96: N/A | L96: N/A | M96: {=_xlfn.COUNTIFS('Datos - Temas'!$V$5:$V$1264,M$4,'Datos - Temas'!$K$5:$K$1264,$A96)+_xlfn.COUNTIFS('Datos - Temas'!$V$5:$V$1264,M$4,'Datos - Temas'!$L$5:$L$1264,$A96)} -> 0 | N96: {=_xlfn.COUNTIFS('Datos - Temas'!$V$5:$V$1264,N$4,'Datos - Temas'!$K$5:$K$1264,$A96)+_xlfn.COUNTIFS('Datos - Temas'!$V$5:$V$1264,N$4,'Datos - Temas'!$L$5:$L$1264,$A96)} -> 15 | O96: 15 | P96: {=_xlfn.COUNTIFS('Datos - Temas'!$K$5:$K$1264,$A96)} -> 14 | Q96: {=IF(O96>0,"Sí","No")} -> Sí | R96: {=IF(O96=0,"No cubierto",IF(O96=1,"Débil (1 tema)",IF(O96<=3,"Básica (2–3)","Sólida (4+)")))} -> Sólida (4+) | S96: {=_xlfn.IFERROR(INDEX($M$4:$N$4,MATCH(TRUE,INDEX(M96:N96>0,0),0)),"—")} -> Física 11° | T96: Hoy: Física 11° U13 (2); Física 11° U9 (13)
... A107: TA-O2.4 | B107: TA | C107: Ondas y física atómica/nuclear | D107: Física atómica y nuclear | E107: Equivalencia masa-energía | F107: N/A | G107: N/A | H107: N/A | I107: N/A | J107: N/A | K107: N/A | L107: N/A | M107: {=_xlfn.COUNTIFS('Datos - Temas'!$V$5:$V$1264,M$4,'Datos - Temas'!$K$5:$K$1264,$A107)+_xlfn.COUNTIFS('Datos - Temas'!$V$5:$V$1264,M$4,'Datos - Temas'!$L$5:$L$1264,$A107)} -> 0 | N107: {=_xlfn.COUNTIFS('Datos - Temas'!$V$5:$V$1264,N$4,'Datos - Temas'!$K$5:$K$1264,$A107)+_xlfn.COUNTIFS('Datos - Temas'!$V$5:$V$1264,N$4,'Datos - Temas'!$L$5:$L$1264,$A107)} -> 4 | O107: 4 | P107: {=_xlfn.COUNTIFS('Datos - Temas'!$K$5:$K$1264,$A107)} -> 2 | Q107: {=IF(O107>0,"Sí","No")} -> Sí | R107: {=IF(O107=0,"No cubierto",IF(O107=1,"Débil (1 tema)",IF(O107<=3,"Básica (2–3)","Sólida (4+)")))} -> Sólida (4+) | S107: {=_xlfn.IFERROR(INDEX($M$4:$N$4,MATCH(TRUE,INDEX(M107:N107>0,0),0)),"—")} -> Física 11° | T107: Hoy: Física 11° U19 (1); Física 11° U20 (1); Física 11° U23 (2)
A110: Resumen de amplitud por marco y dominio
A111: Marco | B111: Dominio | C111: Objetivos en el marco | D111: Objetivos cubiertos | E111: % cubierto | F111: Objetivos no cubiertos | G111: Objetivos débiles (1 tema)
A112: T4_27 | B112: Biología | C112: {=_xlfn.COUNTIFS($B$5:$B$107,$A112,$C$5:$C$107,$B112)} -> 13 | D112: {=_xlfn.COUNTIFS($B$5:$B$107,$A112,$C$5:$C$107,$B112,$Q$5:$Q$107,"Sí")} -> 12 | E112: {=IF(C112=0,0,D112/C112)} -> 0.92307692 | F112: {=C112-D112} -> 1 | G112: {=_xlfn.COUNTIFS($B$5:$B$107,$A112,$C$5:$C$107,$B112,$R$5:$R$107,"Débil (1 tema)")} -> 0
A113: T4_27 | B113: Ciencias físicas | C113: {=_xlfn.COUNTIFS($B$5:$B$107,$A113,$C$5:$C$107,$B113)} -> 12 | D113: {=_xlfn.COUNTIFS($B$5:$B$107,$A113,$C$5:$C$107,$B113,$Q$5:$Q$107,"Sí")} -> 12 | E113: {=IF(C113=0,0,D113/C113)} -> 1 | F113: {=C113-D113} -> 0 | G113: {=_xlfn.COUNTIFS($B$5:$B$107,$A113,$C$5:$C$107,$B113,$R$5:$R$107,"Débil (1 tema)")} -> 3
A114: T4_27 | B114: Ciencias de la Tierra | C114: {=_xlfn.COUNTIFS($B$5:$B$107,$A114,$C$5:$C$107,$B114)} -> 7 | D114: {=_xlfn.COUNTIFS($B$5:$B$107,$A114,$C$5:$C$107,$B114,$Q$5:$Q$107,"Sí")} -> 7 | E114: {=IF(C114=0,0,D114/C114)} -> 1 | F114: {=C114-D114} -> 0 | G114: {=_xlfn.COUNTIFS($B$5:$B$107,$A114,$C$5:$C$107,$B114,$R$5:$R$107,"Débil (1 tema)")} -> 1
A115: T4_27 | B115: (todos) | C115: {=_xlfn.COUNTIFS($B$5:$B$107,$A115,$C$5:$C$107,"*")} -> 32 | D115: {=_xlfn.COUNTIFS($B$5:$B$107,$A115,$C$5:$C$107,"*",$Q$5:$Q$107,"Sí")} -> 31 | E115: {=IF(C115=0,0,D115/C115)} -> 0.96875 | F115: {=C115-D115} -> 1 | G115: {=_xlfn.COUNTIFS($B$5:$B$107,$A115,$C$5:$C$107,"*",$R$5:$R$107,"Débil (1 tema)")} -> 4
A116: T8_27 | B116: Biología | C116: {=_xlfn.COUNTIFS($B$5:$B$107,$A116,$C$5:$C$107,$B116)} -> 16 | D116: {=_xlfn.COUNTIFS($B$5:$B$107,$A116,$C$5:$C$107,$B116,$Q$5:$Q$107,"Sí")} -> 16 | E116: {=IF(C116=0,0,D116/C116)} -> 1 | F116: {=C116-D116} -> 0 | G116: {=_xlfn.COUNTIFS($B$5:$B$107,$A116,$C$5:$C$107,$B116,$R$5:$R$107,"Débil (1 tema)")} -> 3
A117: T8_27 | B117: Química | C117: {=_xlfn.COUNTIFS($B$5:$B$107,$A117,$C$5:$C$107,$B117)} -> 9 | D117: {=_xlfn.COUNTIFS($B$5:$B$107,$A117,$C$5:$C$107,$B117,$Q$5:$Q$107,"Sí")} -> 9 | E117: {=IF(C117=0,0,D117/C117)} -> 1 | F117: {=C117-D117} -> 0 | G117: {=_xlfn.COUNTIFS($B$5:$B$107,$A117,$C$5:$C$107,$B117,$R$5:$R$107,"Débil (1 tema)")} -> 0
A118: T8_27 | B118: Física | C118: {=_xlfn.COUNTIFS($B$5:$B$107,$A118,$C$5:$C$107,$B118)} -> 12 | D118: {=_xlfn.COUNTIFS($B$5:$B$107,$A118,$C$5:$C$107,$B118,$Q$5:$Q$107,"Sí")} -> 11 | E118: {=IF(C118=0,0,D118/C118)} -> 0.91666667 | F118: {=C118-D118} -> 1 | G118: {=_xlfn.COUNTIFS($B$5:$B$107,$A118,$C$5:$C$107,$B118,$R$5:$R$107,"Débil (1 tema)")} -> 0
A119: T8_27 | B119: Ciencias de la Tierra | C119: {=_xlfn.COUNTIFS($B$5:$B$107,$A119,$C$5:$C$107,$B119)} -> 11 | D119: {=_xlfn.COUNTIFS($B$5:$B$107,$A119,$C$5:$C$107,$B119,$Q$5:$Q$107,"Sí")} -> 9 | E119: {=IF(C119=0,0,D119/C119)} -> 0.81818182 | F119: {=C119-D119} -> 2 | G119: {=_xlfn.COUNTIFS($B$5:$B$107,$A119,$C$5:$C$107,$B119,$R$5:$R$107,"Débil (1 tema)")} -> 0
A120: T8_27 | B120: (todos) | C120: {=_xlfn.COUNTIFS($B$5:$B$107,$A120,$C$5:$C$107,"*")} -> 48 | D120: {=_xlfn.COUNTIFS($B$5:$B$107,$A120,$C$5:$C$107,"*",$Q$5:$Q$107,"Sí")} -> 45 | E120: {=IF(C120=0,0,D120/C120)} -> 0.9375 | F120: {=C120-D120} -> 3 | G120: {=_xlfn.COUNTIFS($B$5:$B$107,$A120,$C$5:$C$107,"*",$R$5:$R$107,"Débil (1 tema)")} -> 3
A121: TA | B121: Mecánica y termodinámica | C121: {=_xlfn.COUNTIFS($B$5:$B$107,$A121,$C$5:$C$107,$B121)} -> 9 | D121: {=_xlfn.COUNTIFS($B$5:$B$107,$A121,$C$5:$C$107,$B121,$Q$5:$Q$107,"Sí")} -> 9 | E121: {=IF(C121=0,0,D121/C121)} -> 1 | F121: {=C121-D121} -> 0 | G121: {=_xlfn.COUNTIFS($B$5:$B$107,$A121,$C$5:$C$107,$B121,$R$5:$R$107,"Débil (1 tema)")} -> 0
A122: TA | B122: Electricidad y magnetismo | C122: {=_xlfn.COUNTIFS($B$5:$B$107,$A122,$C$5:$C$107,$B122)} -> 6 | D122: {=_xlfn.COUNTIFS($B$5:$B$107,$A122,$C$5:$C$107,$B122,$Q$5:$Q$107,"Sí")} -> 6 | E122: {=IF(C122=0,0,D122/C122)} -> 1 | F122: {=C122-D122} -> 0 | G122: {=_xlfn.COUNTIFS($B$5:$B$107,$A122,$C$5:$C$107,$B122,$R$5:$R$107,"Débil (1 tema)")} -> 0
A123: TA | B123: Ondas y física atómica/nuclear | C123: {=_xlfn.COUNTIFS($B$5:$B$107,$A123,$C$5:$C$107,$B123)} -> 8 | D123: {=_xlfn.COUNTIFS($B$5:$B$107,$A123,$C$5:$C$107,$B123,$Q$5:$Q$107,"Sí")} -> 8 | E123: {=IF(C123=0,0,D123/C123)} -> 1 | F123: {=C123-D123} -> 0 | G123: {=_xlfn.COUNTIFS($B$5:$B$107,$A123,$C$5:$C$107,$B123,$R$5:$R$107,"Débil (1 tema)")} -> 0
A124: TA | B124: (todos) | C124: {=_xlfn.COUNTIFS($B$5:$B$107,$A124,$C$5:$C$107,"*")} -> 23 | D124: {=_xlfn.COUNTIFS($B$5:$B$107,$A124,$C$5:$C$107,"*",$Q$5:$Q$107,"Sí")} -> 23 | E124: {=IF(C124=0,0,D124/C124)} -> 1 | F124: {=C124-D124} -> 0 | G124: {=_xlfn.COUNTIFS($B$5:$B$107,$A124,$C$5:$C$107,"*",$R$5:$R$107,"Débil (1 tema)")} -> 0
